Workbook

Sheet Summary
G5: Week Ending | H5: =TODAY() -> 45968
B8: To. | C8: RACHEL GAO, PHIL HARDIE and MALCOLM PUGH,
B9: From. | C9: MALCOLM COHEN, SABINA BATHURST, GREG HUTCHENSON and CRISTINA CIMPOESU
B10: cc. | C10: PETER MORDEN, LAURA OWEN, PERRY LINCH, HOWARD ROSEN, TOM HURLEY, SHANIE HENDERSON, CARA DYETT, CHERYL MASON, JOSEPH MANNU, WILLIAM SPENCER, ELIZABETH TAYLOR, SEAN COLLINS, RUTH SHAVE, GRAEME NOOT,
B12: Ref. | C12: New Lettings Progress
B14: Sections | G14: No. Of Deals | H14: Total Rental Value/Year
B16: A | C16: (i) New deals in solicitors hands | G16: =COUNTIFS('Letting Progress'!$D5:$D72, "NL", 'Letting Progress'!$Q5:$Q72, "No") -> 6 | H16: =SUMIFS('Letting Progress'!$I5:$I72, 'Letting Progress'!$Q5:$Q72, "no", 'Letting Progress'!$D5:$D72, "NL") -> 385381
C18: (ii) Deals in Solicitors’ Hands: Temporary Lettings | G18: =COUNTIFS('Letting Progress'!$D5:$D72, "TL", 'Letting Progress'!$Q5:$Q72, "No") -> 0 | H18: =SUMIFS('Letting Progress'!$I5:$I72, 'Letting Progress'!$Q5:$Q72, "no", 'Letting Progress'!$D5:$D72, "TL") -> 0
C20: (iii) Lease Renewals - Agreed Rental Uplift | G20: =COUNTIFS('Letting Progress'!$D5:$D72, "LR", 'Letting Progress'!$Q5:$Q72, "No") -> 6 | H20: =SUMIFS('Letting Progress'!$K5:$K72, 'Letting Progress'!$Q5:$Q72, "no", 'Letting Progress'!$D5:$D72, "LR") -> 117492
C21: TOTAL (EXCLUDING DEAD DUCKS) | G21: =SUM(G16:G20) -> 12 | H21: =SUM(H16:H20) -> 502873
B23: B | C23: (i) Deals completed this week | G23: =SUM(COUNTIF('Letting Progress'!$Q$5:$Q$14,"Yes")) -> 1 | H23: =SUM(SUMIF('Letting Progress'!$Q$5:$Q$34,"Yes",'Letting Progress'!$K$5:$K$34)) -> 335016
C25: (ii) Total deals complete 1st Jan to date
D27: New Lets | G27: =MAX(Income!$5:$5) -> 41 | H27: =Income!AX14 -> 5510541
D28: Temporary Lets | G28: =MAX(Income!$6:$6) -> 3 | H28: =Income!AX15 -> 48300
C29: Lease Renewals (Rental Uplift) | G29: =MAX(Income!$7:$7) -> 24 | H29: =Income!AX16 -> 487239.5
F30: Total | G30: =SUM(G27:G29) -> 68 | H30: =SUM(H27:H29) -> 6046080.5
C32: (iii) Dead Ducks | G32: ='Dead Ducks'!$E7 -> 0 | H32: =SUM('Dead Ducks'!$F10:$F12) -> 0
A41: Malcolm Cohen

Sheet Letting Progress
J1: LETTING PROGRESS
N2: Week Ending: | O2: =TODAY() -> 45968
A4: No. | B4: Address | C4: Floor | D4: Type of Letting | E4: Area to be Demised sq ft | F4: Date Solicitors Instructed | G4: Name of Tenant | H4: Lease Terms | I4: New Rent | J4: Existing Rent | K4: Rental Uplift | L4: Average psf (NEW) | M4: Average psf (OLD) | N4: ERV psf | O4: Solicitors for Tenant | P4: Solicitor | Q4: Completed | R4: Action | S4: Surveyor
A5: {=_xlfn.SEQUENCE(COUNTIF(B:B,"?*"))} -> 1 | B5: 9 Little Portland St | C5: Ground and Basement | D5: LR | E5: 747 | F5: 45327 | G5: Order Line Limited | H5: 4 years | I5: 45000 | J5: 45000 | K5: =I5-J5 -> 0 | L5: =I5/E5 -> 60.240964 | M5: =J5/E5 -> 60.240964 | N5: =I5/E5 -> 60.240964 | O5: Tenant acting on their behalf. | P5: SH | Q5: No | R5: Tenant lease renewal is on hold while the landlord prepares a retail strategy with KLM. Existing tenants may no longer meet the requirements under the new strategy. 26.09.25 | S5: CD
A6: 2 | B6: 56 Great Titchfield Street | C6: Whole | D6: LR | E6: 2692 | F6: 45665 | G6: Morplan Ltd | H6: 5 years from 01/02.2025 with 4 weeks rent free period | I6: 97996 | J6: 104500 | K6: =I6-J6 -> -6504 | L6: =I6/E6 -> 36.402675 | M6: =J6/E6 -> 38.818722 | N6: =I6/E6 -> 36.402675 | O6: Glovers Solicitors | P6: SH | Q6: No | R6: Tenant's AML checks have ceen ompleted. The tenant is based in France and is now awaiting confirmation that they have completed the Statutory Declaration for the 1st-3rd Floor, 58 Great Titchfield Street, before proceeding with the lease of the protected tenancies. 29/10/25b | S6: CD
A7: 3 | B7: 58 Great Titchfield Street | C7: Ground and Basement | D7: LR | E7: 1172 | F7: 45665 | G7: Morplan Ltd | H7: 5 years from 01/02.2025 with 4 weeks rent free period | I7: 43393.5 | J7: 41000 | K7: =I7-J7 -> 2393.5 | L7: =I7/E7 -> 37.025171 | M7: =J7/E7 -> 34.982935 | N7: =I7/E7 -> 37.025171 | O7: Glovers Solicitors | P7: SH | Q7: No | R7: Tenant's AML checks have completed. Tenant is based in France and now awaiting confirmation that tenant has completed the Statutory Declaration on the 1st-3rd Floor 58 Great Titchfield Street, before completing the lease of the protected tenancies. 29/10/25 | S7: CD
A8: 4 | B8: Floors, 58 Great Titchfield Street | C8: 1st 2nd & 3rd | D8: LR | E8: 1159 | F8: 45665 | G8: Morplan Ltd | H8: 5 year from 01/02.25 with 4 weeks rent free period | I8: 58610.5 | J8: 61575 | K8: =I8-J8 -> -2964.5 | L8: =I8/E8 -> 50.569888 | M8: =J8/E8 -> 53.127696 | N8: =I8/E8 -> 50.569888 | O8: Glovers Solicitors | P8: SH | Q8: No | R8: Tenant's AML checks have completed. Tenant is based in France and is now awaiting confirmation that the tenant has completed the Statutory Declaration in France. 29/10/25 | S8: CD
A9: 5 | B9: 4 Winsley Street | C9: Ground and Basement | D9: LR | E9: 7079 | F9: 45642 | G9: VNK Limited | H9: 10-year renewal from 28 Sep 2027, Rent £499,600, Rent Review 5th Year. | I9: 499600 | J9: 425033 | K9: =I9-J9 -> 74567 | L9: =I9/E9 -> 70.57494 | M9: =J9/E9 -> 60.04139 | N9: =I9/E9 -> 70.57494 | O9: Memery Crystal | P9: Wedlake Bell | Q9: No | R9: Draft documents in the agreed-upon format to reflect the existing lease. Target completion for Jan 2026. AML Passed. JM is happy with the Licence to Alter docs. Awaiting bank consent. 09/05/2025. Breach of planning application. Awaiting resolution from the tenant. The lease will be completed once the breach is rectified on 13/06/2025. The tenant has agreed to rectify the breach, and completion is expected in Q4. | S9: JM
A10: 6 | B10: 36-38 Mortimer Street, Radiant House | C10: 2nd | D10: NL | E10: 1255 | F10: 45846 | G10: Arya Douge Ltd | H10: 5 years with t/b 3rd year | I10: 74000 | J10: 0 | K10: =I10-J10 -> 74000 | L10: =I10/E10 -> 58.964143 | M10: =J10/E10 -> 0 | N10: =I10/E10 -> 58.964143 | O10: TBC | P10: SH | Q10: No | R10: Draft Documents in final form. Lease plans are being amended. Works are close to completion. 03/10/2025 | S10: WS / ET
A11: 7 | B11: Circus House | C11: 2nd & 3rd | D11: NL | E11: 4653 | F11: 45877 | G11: New Era Cap Company | H11: 10 years with t/b 5th year | I11: 335016 | J11: 0 | K11: =I11-J11 -> 335016 | L11: =I11/E11 -> 72 | M11: =J11/E11 -> 0 | N11: =I11/E11 -> 72 | O11: TBC | P11: SH | Q11: Yes | R11: Stephenson Harwood has answered all the queries raised by the tenant's solicitors and has returned all documents to them. 30/10/2025 - ET has instructed Hot Water Works, which will deliver an electrified and degassed floor, allowing EPC B to be achieved. These are likely to be completed just after the lease does, but a side letter will be required, and Stephen Laud will deal with this. Completion is expected by either Friday, 31 October, or early next week. | S11: ET
A12: 8 | B12: Circus House, 21 Great Titchfield Street | C12: Ground Floor, (West) | D12: NL | E12: 1946 | F12: 45869 | G12: Lege Aetis Ltd | H12: 15 years with t/b 10th yr on 6 months notice | I12: 118500 | J12: 0 | K12: =I12-J12 -> 118500 | L12: =I12/E12 -> 60.894142 | M12: =J12/E12 -> 0 | N12: =I12/E12 -> 60.894142 | O12: SA Law | P12: SH | Q12: No | R12: Tenant's solicitors to get back to Stephenson Harwood with their comments on the legal documents shortly. 10/10/2025: 30/10/2025 Lege Atris team undertaking surveys and investigations into how drainage provision can be delivered for use as dentists surgery. | S12: ET
A13: 9 | B13: 158 Oxford Street | C13: Ground Floor | D13: LR | E13: 1690 | F13: 45905 | G13: VF Northern Europe (T/A Timberland) | H13: 10 Years Leae. TOB Year 5. 3m RF. £615 Zone A (Gross) / £600 Zone A (Net) | I13: 550000 | J13: 500000 | K13: =I13-J13 -> 50000 | L13: =I13/E13 -> 325.44379 | M13: =J13/E13 -> 295.85799 | N13: =I13/E13 -> 325.44379 | O13: TBC | P13: SH | Q13: No | R13: SH to circulate first draft to to tenant. Lease to commence on 19 January 2026. | S13: JM
A14: 10 | B14: Golderbrock House | C14: 1st Floor (Rear) | D14: NL | E14: 533 | F14: 45904 | G14: NMHL Ltd (T/A Natalino) | H14: 5 year lease T/o break end of yr 2. | I14: 28889 | J14: 0 | K14: =I14-J14 -> 28889 | L14: =I14/E14 -> 54.20075 | M14: =J14/E14 -> 0 | N14: =I14/E14 -> 54.20075 | O14: TBC | P14: SH | Q14: No | R14: Draft documents with the other side. Tenant pack sent to SH. 03/10/2025 | S14: WS
A15: 11 | B15: 85 Mortimer Street | C15: 1st-3rd floors | D15: NL | E15: 1248 | F15: 45918 | G15: Sindhu Immigration Services | H15: 5 years with a mutail break at the end of the 3rd year | I15: 68640 | J15: 0 | K15: =I15-J15 -> 68640 | L15: =I15/E15 -> 55 | M15: =J15/E15 -> 0 | N15: =I15/E15 -> 55 | O15: TBC | P15: SH | Q15: No | R15: Fee Quote accepted, tenant pack being put together. ARES Works is now underway. 10/10/2025 Stephenson Harwood requested further details from Langham, and Elizabeth Taylor provided them over the course of the week. 30/10/2025 - each side's solicitors dealing. | S15: WS / ET
A16: 12 | B16: 53 Great Portland Street | C16: Kiosk | D16: NL | E16: 60 | F16: 45916 | G16: Mr Yogesh Brahmbhatt | H16: 5 Years With break at end of 3rd &4th Year | I16: 13500 | J16: 0 | K16: =I16-J16 -> 13500 | L16: =I16/E16 -> 225 | M16: =J16/E16 -> 0 | N16: =J16/E16 -> 0 | O16: Markand & Co Solicitors LLP | P16: SH | Q16: No | R16: Draft documents still with tenant to review. SH have chased. 15/10/2025 | S16: WS
A17: 13 | B17: 15/16 Margaret Street | C17: 3rd floor | D17: NL | E17: 1129 | F17: 45954 | G17: Termgrid Limited | H17: 5 years with tenant break 3rd year | I17: 81852 | J17: 0 | K17: =I17-J17 -> 81852 | L17: =I17/E17 -> 72.499557 | M17: =J17/E17 -> 0 | N17: 66.5 | O17: TBC | P17: SH | Q17: NO | R17: Stephenson Harwood instructed. Pack being put together. 29/10/2025 | S17: WS
A18: 14 | K18: =I18-J18 -> 0 | L18: =I18/E18 -> #DIV/0! | M18: =J18/E18 -> #DIV/0!
J19: 0 | K19: =I19-J19 -> 0 | L19: =I19/E19 -> #DIV/0! | M19: =J19/E19 -> #DIV/0!

Sheet Dead Ducks
B1: B | E1: LETTING PROGRESS
E2: Dead Ducks
G4: Week Ending | H4: =Summary!#REF! -> #REF!
B7: No. of 'dead ducks' this week: | E7: =COUNT(F10:F12) -> 0
B9: No. | C9: Address | D9: Company | E9: Lease Terms | F9: Rent | G9: Rent psf | H9: Reason | I9: Surveyor
B10: 1
B11: 2
B12: 3
B15: END
C24: Address | D24: Company | E24: Lease Terms | F24: Rent | G24: Rent psf | H24: Reason | I24: Surveyor
C25: 15/16 Margaret Street Basement 2,161sq.ft | D25: Canis (marylebone)Ltd | E25: 5 Years With M/B year 3 | F25: 55000 | G25: 25 | H25: It was felt this was not the right operator with the refurbishedunits above | I25: TH
C26: 67 Wells street, Welbeck House | D26: World Chess | E26: 5 years T/O break at end of 3yr | F26: 150000 | G26: 45 | H26: Shifting focus to online operations due to uncertain | I26: YS
C27: Great Titchfield House, 14-18 Great Titchfield Street | D27: True Green Capital | E27: 5 yr lease | F27: 135456 | G27: 68 | H27: Tenant looking t ostay put during economic uncertantiy. | I27: YS
C28: 2nd Floor, 14-18 Great Titchfield Street, | D28: Infront Sports & Media UK Ltd | E28: 3 year lease | F28: 152250 | G28: 78.56 | H28: Tenant has found alternative accomadation in a different area. | I28: YS
C29: 47-50 Margaret Street | D29: 77 Diamonds | E29: 5 years T/O break at end of 3yr | F29: 155496 | G29: 62 | H29: Tenant believed that buildin common parts were too much of security threat depsite proposed improvements | I29: SH
C30: 47-50 Margaret Street 4th Floor East | D30: Dolor Medical Supplies | E30: 5years with mutual break in year 3 | F30: 39387 | G30: 57 | H30: Isses relating to plannign change of use delayed deal too long | I30: SH

Sheet Viewing Schedule
C1: Viewing Schedule
F2: Week Ending | G2: =TODAY() -> 45968
A4: No. | B4: Date | C4: Address | D4: Floor/Suite | E4: Potential Tenant | F4: Agent/Broker | G4: Proposed Terms | H4: Remarks | I4: Agent
A5: 1 | B5: 45964 | C5: Moray House | D5: 1st floor (2 suites) | E5: Media Tech agony | F5: LEM | G5: NYD | H5: 1st inspection with London director. 2nd inspection to be arranged for US director to inspect. | I5: MAC
A6: 2 | B6: 45964 | C6: 75/77 Margaret Street | D6: entire 2nd floor Front & rear) | E6: Media Tech agency | F6: LEM | G6: NYD | H6: 1st inspection with London director. 2nd inspection to be arranged for US director to inspect. | I6: MAC
A7: 3 | B7: 45964 | C7: 30 Market Place | D7: 3rd floor | E7: Tech company | F7: ECP | G7: NYD | H7: 1st inspection. Waiting for update report from our agent. | I7: MAC
A8: 4 | B8: 45964 | C8: 15/16 Margaret Street | D8: 3rd floor | E8: Termgrid Limited | F8: RIB | G8: See letting progress | H8: Inspection by their design team | I8: MAC
A9: 5 | B9: 45964 | C9: 9 Little Portland House | D9: Ground floor & Basement | E9: Fabrique (Bakery) | F9: KLM | G9: NYD | H9: 1st Inspection. Awaiting feedback. | I9: KLM
A10: 6 | B10: 45965 | C10: 22-23 Eastcastle Street | D10: 3rd Floor (East) | E10: Media 15 | F10: N/A | G10: NYD | H10: Liked unit but didn't like the metal wall as couldn't understand what it was for and don't want to wait for works to be done. | I10: SB
A11: 7 | B11: 45965 | C11: 47-50 Margaret Street | D11: 3rd Floor (West) | E11: Media 15 | F11: N/A | G11: NYD | H11: Didn't like the unit as no kitchenette and they didn't want the hassle of having to put one in. | I11: SB
A12: 8 | B12: 45965 | C12: 51-53 Margaret Street | D12: 1st Floor (West) | E12: Media 15 | F12: N/A | G12: NYD | H12: They liked the unit a lot, but I didn't like that it had no fridge or blinds (which I mentioned we could supply if needed). | I12: SB
A13: 9 | B13: 45966 | C13: 32-36 Great Portland Street | D13: 1st Floor | E13: Orphalan UK | F13: LEM | G13: NYD | H13: 1st Inspection. Like unit but has no meeting rooms and they don't want to put them in. | I13: SB
A14: 11 | B14: 45966 | C14: 47-50 Margaret Street | D14: 3rd East | E14: Wal G | F14: LDG | G14: £63 psf /5 yr lease | H14: Several inspections. Offer made and we are running cash flows between this offer and another offer made by Binocular Productions. | I14: MAC
A15: 12 | B15: 45966 | C15: 47-50 Margaret Street | D15: 3rd Floor (East) | E15: Orphalan UK | F15: LEM | G15: NYD | H15: 1st Inspection. Really liked this unit due to it's glass partioned meeting rooms but the unit is about to go under offer to someone else. | I15: SB
B16: 45966 | C16: 19-21 Great Portland Street | D16: 3rd Floor | E16: Orphalan UK | F16: LEM | G16: NYD | H16: 1st Inspection. Liked unit and the meeting rooms. Will look at plan and come back to us. | I16: SB
B17: 45967 | C17: 51/53 Eastcastle Street | D17: Ground floor & Basement | E17: Passyunk Avenue | F17: OVH | G17: NYD | H17: 1st inspection. They appeared to like the site and felt that it would work well as a competitive socialising venue. | I17: MAC
A18: 13 | B18: 45967 | C18: Moray House | D18: 1st floor (2 suites) | E18: TGR1.618 Limited | F18: LEM | G18: NYD | H18: 1st inspection. Did not like the configuration. | I18: MAC
A19: 14 | B19: 45967 | C19: 75/77 Margaret Street | D19: entire 2nd floor Front & rear) | E19: TGR1.618 Limited | F19: LEM | G19: NYD | H19: 1st inspection. Liked the configuration and has requested further info. | I19: MAC
A20: 15 | B20: 45967 | C20: 23-25 Eastcastle Street | D20: 2nd & 3rd floors | E20: Unknown | F20: Bluebook | G20: NYD | H20: 1st Inspection. Awaiting feedback | I20: BB
A21: 16 | B21: 45967 | C21: 32-36 Great Portland Street | D21: 3rd & 4th Floors | E21: Lonic | F21: Bluebook | G21: NYD | H21: 1st Inspection. Awaiting feedback | I21: BB
A22: 17 | B22: 45967 | C22: 51 Great Portland Street | D22: 3rd Floor | E22: CLYX | F22: LEM | G22: NYD | H22: 1st Inspection. Awaiting feedback. | I22: SB
A23: 18 | B23: 45967 | C23: 53 Great Portland Street | D23: 1st Floor | E23: CLYX | F23: LEM | G23: NYD | H23: 1st Inspection. Awaiting feedback. | I23: SB
A24: 19 | B24: 45967 | C24: 53 Great Portland Street | D24: 3rd Floor | E24: CLYX | F24: LEM | G24: NYD | H24: 1st Inspection. Awaiting feedback. | I24: SB
A25: 20 | B25: 45967 | C25: 47-50 Margaret Street | D25: 3rd Floor (West) | E25: CLYX | F25: LEM | G25: NYD | H25: 1st Inspection. Awaiting feedback although clearly liked this one the best due to having a lift. Will need to look at finances. | I25: SB
A26: 21 | B26: 45967 | C26: 39 Great Portland Street | D26: Ground floor & Basement | E26: SCRT | F26: KLM | G26: NYD | H26: 1st Inspection. Awaiting feedback | I26: KLM
A27: 22 | B27: 45967 | C27: 41 Great Portland Street | D27: Whole Building | E27: SCRT | F27: KLM | G27: NYD | H27: 1st Inspection. Awaiting feedback | I27: KLM
A28: 23 | B28: 45968 | C28: 75/77 Margaret Street | D28: entire 2nd floor Front & rear) | E28: Wal G | F28: LEM | G28: NYD | H28: 1st viewing. We have blown them out the 47/50 Margaret Street =3rd floor deal to go with another party. Looking at alternative options | I28: MAC
A29: 24 | B29: 45968 | C29: 32/36 Great Portland Street | D29: 1st floor | E29: Wal G | F29: LEM | G29: NYD | H29: See above comment. | I29: MAC
... A37: 32 | B37: 45968 | C37: 42-48 Great Portland Street | D37: 5th Floor | E37: Media.Work | F37: LEM | G37: NYD | H37: 1st Inspection. Awaiting feedback | I37: SB
A38: 33
A39: 34
A40: 35
A41: 36
A42: 37
A43: 38
A44: 39
A45: 40
A46: 41
A47: 42
A48: 43
A49: 44
... A69: 64
C104: Princess House | D104: 1st, 2nd & 3rd floors | E104: Convene | F104: LEM | G104: NYD | H104: 2nd inspection. Very interested in taking 2 floors. Board meeting on Wednesday to discuss the next steps. | I104: MAC
C105: Circus House | D105: Ground Floor | E105: The Graphical Tree | F105: N/A | G105: NYD | H105: 1st Inspection. Knows unit is under offer but wanted to see it anyway. | I105: SB
C106: Welbeck House | D106: Ground & Basement Floor | E106: The Graphical Tree | F106: N/A | G106: NYD | H106: 1st Inspection, not keen as floor plan wouldn't work | I106: SB
C107: 15-16 Margaret Street | D107: 3rd Floor | E107: Agent led -TBC | F107: Workplace | G107: NYD | H107: 1st Inspection, not keen as didn't like layout. | I107: SB
C108: 47-50 Margaret Street | D108: 3rd Floor (East) | E108: Agent led -TBC | F108: LDG | G108: NYD | H108: 1st Inspection, awaiting feedback from our agent | I108: SB
C109: 6-10 Great Portland St | D109: 4th Floor | E109: Ortus Energy | F109: N/A | G109: NYD | H109: 1st Inspection, liked unit but felt it was slightly too small | I109: SB
C110: 30 Market Place | D110: 3rd floor | E110: New ERA | F110: Edward Charles | G110: NYD | H110: 1st inspection. Looking at a fitted option. | I110: MAC
C111: 30 Market Place | D111: 3rd floor | E111: Duo Lingo | F111: Edward Charles | G111: NYD | H111: 1st inspection. Positive inspection with their agent and will want to carry out another inspection. Tenant represented by Savills. | I111: MAC
C112: 22-25 Eastcastle Street | D112: 2nd Floor | E112: TBC | F112: Ian Scott | G112: NYD | H112: 1st Inspection. Waiting for the feedback from our agent. | I112: SB
C113: 19-21 Great Portland Streeet | D113: 2nd Floor | E113: Agent led -TBC | F113: LDG | G113: NYD | H113: 1st Inspection, awaiting feedback from our agent | I113: SB
C114: 23-25 Eastcastle St | D114: 6th Floor | E114: Scott Free | F114: N/A | G114: NYD | H114: 1st Inspection, liked unit but wants to instruct an agent on their behalf to negotiatie | I114: SB
C115: Princess House | D115: 1st, 2nd & 3rd floors | E115: Brave Corp | F115: LEM | G115: NYD | H115: 1st inspection. Very interested in leasing all the vacant space. Another inspection is being arranged next week for their design team. Initial layout plans prepared. | I115: MAC
... C217: 85 Mortimer Street | D217: 1-3rd Floor | E217: DMR Film | F217: N/A | G217: NYD | H217: 1st Inspection, interested in a short term let only. | I217: SB
B218: 45762 | C218: 51 Great Portland Street | D218: 1st Floor | E218: Tommy Graham / Art Gallery | F218: RIB | H218: HOTs agreed - waiting for Langham to send out draft lease
B219: 45805 | C219: 63/64 Margaret Street | D219: 4th Floor (East) | E219: Mukil Menon / Logistic Centre | F219: RIB | G219: NYD | H219: They liked the space however after consideration they would prefer a ground floor presence
B220: 45810 | C220: 51 Great Portland Street | D220: 1st Floor | E220: Andrea Puccio / Art Gallery | F220: RIB | G220: NYD | H220: Unit was too small and would prefer a lift if upper floors
B221: 45812 | C221: 51-53 Margaret Street | D221: 4th Floor (West) | E221: Craig Whitehead / Contractors | F221: RIB | G221: NYD | H221: Unit was out of price range and prefered another option viewed
B222: 45827 | C222: 15-16 Margaret Street | D222: Whole | E222: Film Post Production Co | F222: RIB | G222: NYD | H222: Floor arrangement floor by floor was not feasible following further review, focus is now on self contained space
B223: 45831 | C223: 21 Little Portland Street | D223: 1st Floor | E223: Azime Hunt | F223: RIB | G223: NYD | H223: Agent representing a number of turkish clinics. Unit was disregarded due their prefernce of Mayfair of Fitzrovia
B224: 45849 | C224: 15-16 Margaret Street | D224: 4th & 5th Floor | E224: Scott Free - Film production Co | F224: RIB | G224: NYD | H224: Inspected both floors, suggesting the location and configuration works well. Decision makers are currently away on AL. MM due to catchup next week on their return
B225: 45866 | C225: 15-16 MS & 21 LPS | D225: 3rd | E225: Golf Traveller | F225: RIB | G225: NYD | H225: Ideally they want a managed space but they are lookign at tradtional and liek the look of 15-16 MS (3rd)
B226: 45867 | C226: 15-16 MS & 21 LPS | D226: 1st at LPS & 3rd at 15-16 | E226: Pictorum | F226: RIB | G226: NYD | H226: Small family office (advisory in art & Private Investment). They like the look of 21 LPS & 3rd Floor 15-16 MS. chased for viewing times.
B227: 45868 | C227: 15-16 Margaret Street | D227: 3rd | E227: Levi RE - EV Charging Co | F227: RIB | G227: NYD | H227: Details being considered by the agents client - they're looking for a 1 year break date. Viewings expected next week
B228: 45868 | C228: 15-16 MS & 21 LPS | D228: All | E228: Auriga | F228: RIB | G228: NYD | H228: Tech co. looking for new office space. No floor of particular ibetrest but hopefully out vieiwng all available next week.
B229: 45869 | C229: 15/16 Margaret Street | D229: 4th or 5th | E229: https://eckuity.com/about-us/ | F229: RIB | G229: NYD | H229: Eckuity Capital is a proactive investor in healthcare, and they work with their portfolio companies to create value across multiple aspects of company growth. They have enquired into 15-16 Margaret Street and I hope to view with them next week.
B230: 45874 | C230: 63-64 Margaret Street | D230: 4th Floor (East) | E230: Production Co | F230: RIB | G230: NYD | H230: Looking for circa 800-1000 Sq. Ft in Fitzrovia. Currently building a shortlist of options to potentially view in September once thier directors have returned from overseas.
... B235: 45883 | C235: 15-16 Margaret Street | D235: 4th & 5th Floor | E235: Financial Tech | F235: RIB | G235: NYD | H235: Tech investment bank Looking for 600-1000 sq ft in Fitzrovia with a meeting room. Both 3rd, 4th and 5th floors are being considered for viewings
B236: 45889 | C236: Great Titchfield House | D236: 4th Floor | E236: Unknown | F236: Workplace+ | G236: NYD | H236: 1st Inspection, awaiting feedback. | I236: SB
B237: 45890 | C237: 53 Eastcastle Street | D237: Ground & Basement | E237: Italian Restuarant | F237: One Voice | G237: NYD | H237: 1st Inspection, awaiting feedback. | I237: SB
B238: 45890 | C238: 23-25 Eastcastle Steet | D238: 6th Floor | E238: Public Pictures | F238: N/A | G238: NYD | H238: 1st Inspection, but loved all the light and the unit -said it was the best they had seen to date but they would want glass in windows replaced. | I238: SB
B239: 45890 | C239: 15-16 Margaret Street | D239: 4th Floor | E239: Public Pictures | F239: N/A | G239: NYD | H239: 1st Inspection, Liked unit but didn't like that it didn't have a meeting room | I239: SB
B240: 45890 | C240: 30 Market Place | D240: 3rd Floor | E240: Ascot Lloyds | F240: Carter Jonas | G240: NYD | H240: 1st Inspection, meeting rooms not in line with their current branding but think they could make it work. | I240: SB
B241: 46255 | C241: 19-21 Great Portland Street | D241: 2nd & 3rd Floors | E241: Unknown | F241: LDG | G241: NYD | H241: 1st Inspection, awaiting feedback. | I241: SB
B242: 46255 | C242: 63-64 Margaret Street | D242: 3rd Floor | E242: Public Pictures | F242: N/A | G242: NYD | H242: 1st Inspection, Liked the unit but work might not be done in time. | I242: SB
B243: 45820 | C243: 19-21 Great Portland Street | D243: 2nd & 3rd Floors | E243: Property Company | F243: LDG | G243: NYD | H243: Liked the space but couldn't get the requested info in time so decided to proceed on something else
B244: 45820 | C244: 47-50 Margaret Street | D244: 3rd Floor | E244: Technology | F244: LDG | G244: NYD | H244: Tech co. Preferred 19-21 GPS but they don't need to give notice until August so won't be moving until next year. They were basically on a fact finding tour looking at trad, managed and serviced.
B245: 45820 | C245: 19-21 Great Portland Street | D245: 3rd Floor | E245: Technology | F245: LDG | G245: NYD | H245: Tech co. Preferred 19-21 GPS but they don't need to give notice until August so won't be moving until next year. They were basically on a fact finding tour looking at trad, managed and serviced.
B246: 45827 | C246: 47-50 Margaret Street | D246: 3rd Floor | E246: Lemon Pepper Holdings / Restaurants | F246: LDG | G246: NYD | H246: UO on a self-contained building of 5,500 sq.ft. with window frontage. Too Small
B247: 45827 | C247: 19-21 Great Portland Street | D247: 3rd Floor | E247: Lemon Pepper Holdings / Restaurants | F247: LDG | G247: NYD | H247: UO on a self-contained building of 5,500 sq.ft. with window frontage. Too corporated and preferred something more industrial and fitted with audio suites.
B248: 45847 | C248: 19-21 Great Portland Street | D248: 2nd & 3rd Floors | E248: The Production Lens / Film & Media | F248: LDG | G248: NYD | H248: Liked the space but made an unrealistic offer for a 12 month term
B249: 45849 | C249: 47-50 Margaret Street | D249: 3rd Floor | E249: Creative & Media | F249: LDG | G249: NYD | H249: Second Viewd. Whilst they liked the space, the focus is on smaller premises due to day-to-day use of the premises.
B250: 45859 | C250: 19-21 Great Portland Street | D250: 2nd & 3rd Floors | E250: Aries Global / Software Company | F250: LDG | G250: NYD | H250: Did not feel the quality met their requirements.
B251: 45859 | C251: 47-50 Margaret Street | D251: 3rd Floor | E251: Aries Global / Software Company | F251: LDG | G251: NYD | H251: Did not feel the quality met their requirements.
B252: 45860 | C252: 47-50 Margaret Street | D252: 3rd Floor | E252: Unknown | F252: LDG | G252: NYD | H252: Originally liked how bright the space was and was confident they could fit 20-22 people in the space. Asked about a managed solution which we're providing quotes for. Agent has subsequently not been able to follow up with his client.
B253: 45876 | C253: 47-50 Margaret Street | D253: 3rd Floor | E253: Banking & Finance | F253: LDG | G253: NYD | H253: Layout doesn't work for them, they have clients coming in often and don't want them to walk past the whole team to get to meeting rooms. They also felt the main working space was too tight for them
B254: 45881 | C254: 19-21 Great Portland Street | D254: 2nd & 3rd Floors | E254: TBC | F254: LDG | G254: NYD | H254: Visit seemed positive, preferred layout of the 3rd floor but decision maker is away for summer. Considering and will revert once the director is back in September. Second Viewing booked in
B255: 45890 | C255: 19-21 Great Portland Street | D255: 2nd & 3rd Floors | E255: Undisclosed Prop Co. | F255: LDG | G255: NYD | H255: Felt the quality of the fit-out did not meet their aspirations and were not fans of the suspended ceiling. Was complimentary of the level of natural light, even on a grey day.
B256: 45895 | C256: 23-25 Eastcastle Street | D256: Ground & Basement | E256: Nonamebargames | F256: OneVoice | G256: NYD | H256: 1st Inpection. Will look at plans but believes it may be too small as ideally looking for 10,000sqft on one floor. | I256: SB
B257: 45895 | C257: 19-21 Great Portland Street | D257: 2nd & 3rd Floors | E257: Consultancy Firm | F257: LDG | G257: NYD | H257: Neutral viewing. Currently has 3,000 - 3,500 sq.ft. and isn't looking to downsize but they don't seem to have the budget for larger so they are focussing on the third floor. I have sent them 47-50 Margaret Street too to also consider. Will want unfurnished
B258: 45897 | C258: 30 Market Place | D258: 3rd Floor | E258: Undisclosed | F258: Edward Charles | G258: NYD | H258: 4-5k. Cat A or Fully Fitted. Occupation Q4 2025. Viewing 28/08. Positive feedback - need 3 x private offices.
B259: 45897 | C259: 30 Market Place | D259: 3rd Floor | E259: Ascot Lloyd | F259: Carter Jonas | G259: NYD | H259: 2nd Inspection. Brought space planners with them so hopeful they will proceed. | I259: SB
B260: 45897 | C260: 51 Margaret Street | D260: 2nd Floor | E260: David Wej / Menswear | F260: N/A | G260: NYD | H260: 1st Inspection. Liked size but needs to be on ground or first floor to due deliveries of clothing. | I260: SB
B261: 45897 | C261: 20 Margaret Street | D261: 1st Floor | E261: David Wej / Menswear | F261: N/A | G261: NYD | H261: 1st Inspection. Liked unit and have sent him details along with some other cheaper options. | I261: SB
B262: 45898 | C262: 55 Eastcastle Street | D262: Ground & Basement | E262: Ayodele Ayeni / Dentist | F262: N/A | G262: NYD | H262: 1st Inspection. Size would work but preferred location of 9 Little Portland Street -which they were going to view later and will get back to me | I262: SB
B263: 45902 | C263: 9 Little Portland Street | D263: 1st Floor | E263: David Wej | F263: N/A | G263: NYD | H263: 2nd Inspection, likes unit but doesn't have to move until January so will wait if any ground floor units become available. | I263: SB
B264: 45903 | C264: 6-10 Great Portland Street | D264: 4th Floor | E264: Dmitri Savchenko | F264: N/A | G264: NYD | H264: 1st Inspection. | I264: SB
B265: 45903 | C265: 23-25 Eastcastle Street | D265: 6th Floor | E265: Public Pictures | F265: N/A | G265: 3 year term, wants rolling break on anniversary of the lease | H265: 2nd Inspection, likes the unit but wants windows replaced and rolling break clause as they are new. | I265: SB
B266: 45903 | C266: 19-21 Great Portland Street | D266: 2nd & 3rd Floor | E266: Unknown | F266: LDG | G266: NYD | H266: 1st Inspection. Awaiting agent feedback
...

Sheet Income
B3: Total Number of Deals | F3: Actual | G3: Actual | H3: Actual | I3: Actual | J3: Actual | K3: Actual | L3: Actual | M3: Actual | N3: Actual | O3: Actual | P3: Actual | Q3: Actual | R3: Actual | S3: Actual | T3: Actual | U3: Actual | V3: Actual | W3: Actual | X3: Actual | Y3: Actual | Z3: Actual | AA3: Actual | AB3: Actual | AC3: Actual | AD3: Actual | AE3: Actual | AF3: Actual | AG3: Actual | AH3: Actual | AI3: Actual | AJ3: Actual | AK3: Actual | AL3: Actual | AM3: Actual | AN3: Actual | AO3: Actual | AP3: Actual | AQ3: Actual | AR3: Actual | AS3: Actual | AT3: Actual | AU3: Actual | AV3: Actual | AW3: Actual | AX3: Running
F4: 45660 | G4: =F4+7 -> 45667 | H4: =G4+7 -> 45674 | I4: =H4+7 -> 45681 | J4: =I4+7 -> 45688 | K4: =J4+7 -> 45695 | L4: =K4+7 -> 45702 | M4: =L4+7 -> 45709 | N4: =M4+7 -> 45716 | ... AK4: =AJ4+7 -> 45877 | AL4: 45884 | AM4: =AL4+7 -> 45891 | AN4: =AM4+7 -> 45898 | AO4: =AN4+7 -> 45905 | AP4: =AO4+7 -> 45912 | AQ4: =AP4+7 -> 45919 | AR4: =AQ4+7 -> 45926 | AS4: =AR4+7 -> 45933 | AT4: =AS4+7 -> 45940 | ... AX4: =AW4+7 -> 45968
B5: Permanent Lets | F5: 0 | G5: 4 | H5: 4 | I5: 5 | J5: 7 | K5: 7 | L5: 10 | M5: 12 | N5: 15 | O5: 15 | P5: 15 | Q5: 16 | R5: 17 | S5: 18 | T5: 18 | U5: 19 | V5: 20 | W5: 20 | X5: 20 | Y5: 21 | Z5: 21 | AA5: 23 | AB5: 23 | AC5: 23 | AD5: 24 | AE5: 25 | AF5: 25 | AG5: 25 | AH5: 27 | AI5: 27 | AJ5: 27 | AK5: 27 | AL5: 29 | AM5: 31 | AN5: 31 | AO5: 32 | AP5: 32 | AQ5: 34 | AR5: 34 | AS5: 34 | AT5: 35 | AU5: 35 | AV5: 36 | AW5: 40 | AX5: =AW5 + COUNTIFS('Letting Progress'!$D5:$D72, "NL", 'Letting Progress'!$Q5:$Q72, "Yes") -> 41
B6: Temporary Lets | F6: 0 | G6: 0 | H6: 0 | I6: 1 | J6: 2 | K6: 2 | L6: 2 | M6: 2 | N6: 2 | O6: 2 | P6: 2 | Q6: 2 | R6: 2 | S6: 2 | T6: 2 | U6: 2 | V6: =U6 + COUNTIFS('Letting Progress'!$D5:$D72, "TL", 'Letting Progress'!$Q5:$Q72, "Yes") -> 2 | W6: 2 | X6: 2 | Y6: 2 | Z6: 2 | AA6: 2 | AB6: 2 | AC6: 2 | AD6: 2 | AE6: 2 | AF6: 2 | AG6: 2 | AH6: 2 | AI6: 2 | AJ6: 2 | AK6: 2 | AL6: 2 | AM6: 2 | AN6: 2 | AO6: 2 | AP6: 2 | AQ6: 3 | AR6: 3 | AS6: 3 | AT6: 3 | AU6: 3 | AV6: 3 | AW6: 3 | AX6: =AW6 + COUNTIFS('Letting Progress'!$D6:$D72, "STL", 'Letting Progress'!$Q6:$Q72, "Yes") -> 3
B7: Lease Renewals (Rental Uplift) | F7: 0 | G7: 1 | H7: 2 | I7: 2 | J7: 2 | K7: 3 | L7: 4 | M7: 4 | N7: 4 | O7: 4 | P7: 4 | Q7: 4 | R7: 4 | S7: 4 | T7: 5 | U7: 8 | V7: 8 | W7: 11 | X7: 11 | Y7: 12 | Z7: 14 | AA7: 14 | AB7: 14 | AC7: 14 | AD7: 14 | AE7: 14 | AF7: 14 | AG7: 14 | AH7: 15 | AI7: 17 | AJ7: 17 | AK7: 17 | AL7: 18 | AM7: 18 | AN7: 19 | AO7: 19 | AP7: 21 | AQ7: 23 | AR7: 23 | AS7: 24 | AT7: 24 | AU7: 24 | AV7: 24 | AW7: 24 | AX7: =AW7 + COUNTIFS('Letting Progress'!$D7:$D72, "LR", 'Letting Progress'!$Q7:$Q72, "Yes") -> 24
B8: Total | F8: =SUM(F5:F7) -> 0 | G8: =SUM(G5:G7) -> 5 | H8: =SUM(H5:H7) -> 6 | I8: =SUM(I5:I7) -> 8 | J8: =SUM(J5:J7) -> 11 | K8: =SUM(K5:K7) -> 12 | L8: =SUM(L5:L7) -> 16 | M8: =SUM(M5:M7) -> 18 | ... AX8: =SUM(AX5:AX7) -> 68
B11: Total Rental Value/Year | F11: Actual | G11: Actual | H11: Actual | I11: Actual | J11: Actual | K11: Actual | L11: Actual | M11: Actual | N11: Actual | O11: Actual | P11: Actual | Q11: Actual | R11: Actual | S11: Actual | T11: Actual | U11: Actual | V11: Actual | W11: Actual | X11: Actual | Y11: Actual | Z11: Actual | AA11: Actual | AB11: Actual | AC11: Actual | AD11: Actual | AE11: Actual | AF11: Actual | AG11: Actual | AH11: Actual | AI11: Actual | AJ11: Actual | AK11: Actual | AL11: Actual | AM11: Actual | AN11: Actual | AO11: Actual | AP11: Actual | AQ11: Actual | AR11: Actual | AS11: Actual | AT11: Actual | AU11: Actual | AV11: Actual | AW11: Actual | AX11: Running
F12: 45660 | G12: =F12+7 -> 45667 | H12: =G12+7 -> 45674 | I12: =H12+7 -> 45681 | J12: =I12+7 -> 45688 | K12: =J12+7 -> 45695 | L12: =K12+7 -> 45702 | M12: =L12+7 -> 45709 | N12: =M12+7 -> 45716 | ... AK12: =AJ12+7 -> 45877 | AL12: 45884 | AM12: =AL12+7 -> 45891 | AN12: =AM12+7 -> 45898 | AO12: =AN12+7 -> 45905 | AP12: =AO12+7 -> 45912 | AQ12: =AP12+7 -> 45919 | AR12: =AQ12+7 -> 45926 | AS12: =AR12+7 -> 45933 | AT12: =AS12+7 -> 45940 | ... AX12: =AW12+7 -> 45968
B14: Permanent Lets | F14: 0 | G14: 332971 | H14: 332971 | I14: 332971 | J14: 592971 | K14: 592971 | L14: 1005040 | M14: 1725040 | N14: 2145480 | O14: 2145480 | P14: 2145480 | Q14: 2273480 | R14: 2273480 | S14: 2453480 | T14: 2453480 | U14: 2539930 | V14: 2568537 | W14: 2568537 | X14: 2568537 | Y14: 2929787 | Z14: 2929787 | AA14: 3865787 | AB14: 3865787 | AC14: 3865787 | AD14: 3920787 | AE14: 4011387 | AF14: 4011387 | AG14: 4011387 | AH14: 4295347 | AI14: 4295347 | AJ14: 4295347 | AK14: 4295347 | AL14: 4365347 | AM14: 4365347 | AN14: 4435347 | AO14: 4435347 | AP14: 4435347 | AQ14: 4519072 | AR14: 4519072 | AS14: 4519072 | AT14: 4625857 | AU14: 4625857 | AV14: 4735857 | AW14: 5175525 | AX14: =AW14 + SUMIFS('Letting Progress'!$K5:$K74, 'Letting Progress'!$D5:$D74, "NL", 'Letting Progress'!$Q5:$Q74, "Yes") -> 5510541
B15: Temporary Lets | F15: 0 | G15: 0 | H15: 0 | I15: 0 | J15: 48300 | K15: 48300 | L15: 48300 | M15: 48300 | N15: 48300 | O15: 48300 | P15: 48300 | Q15: 48300 | R15: 48300 | S15: 48300 | T15: 48300 | U15: 48300 | V15: 48300 | W15: 48300 | X15: 48300 | Y15: 48300 | Z15: 48300 | AA15: 48300 | AB15: 48300 | AC15: 48300 | AD15: 48300 | AE15: 48300 | AF15: 48300 | AG15: 48300 | AH15: 48300 | AI15: 48300 | AJ15: 48300 | AK15: 48300 | AL15: 48300 | AM15: 48300 | AN15: 48300 | AO15: 48300 | AP15: 48300 | AQ15: 48300 | AR15: 48300 | AS15: 48300 | AT15: 48300 | AU15: 48300 | AV15: 48300 | AW15: 48300 | AX15: =AW15 + SUMIFS('Letting Progress'!$K5:$K72, 'Letting Progress'!$D5:$D72, "TL", 'Letting Progress'!$Q5:$Q72, "Yes") -> 48300
B16: Lease Renewals (Rental Uplift) | F16: 0 | G16: 130000 | H16: 130000 | I16: =H16+SUMIF('Letting Progress'!$Q5:$Q14, "Yes",'Letting Progress'!$K5:$K9) -> 465016 | J16: 130000 | K16: 130000 | L16: 137848 | M16: 137848 | N16: 137848 | O16: 137848 | P16: 137848 | Q16: 137848 | R16: 137848 | S16: 137848 | T16: 138298 | U16: 139600 | V16: 139600 | W16: 153100 | X16: 153100 | Y16: 155100 | Z16: 156000 | AA16: 156000 | AB16: 156000 | AC16: 156000 | AD16: 156000 | AE16: 156000 | AF16: 156000 | AG16: 156000 | AH16: 376000 | AI16: 376000 | AJ16: 376000 | AK16: 390100 | AL16: 390100 | AM16: 390100 | AN16: 398560 | AO16: 454882 | AP16: 473402 | AQ16: 487239.5 | AR16: 487239.5 | AS16: 487239.5 | AT16: 487239.5 | AU16: 487239.5 | AV16: 487239.5 | AW16: 487239.5 | AX16: =AW16 + SUMIFS('Letting Progress'!$K5:$K77, 'Letting Progress'!$D5:$D77, "LR", 'Letting Progress'!$Q5:$Q77, "Yes") -> 487239.5
B17: Total | F17: =SUM(F14:F16) -> 0 | G17: =SUM(G14:G16) -> 462971 | H17: =SUM(H14:H16) -> 462971 | I17: =SUM(I14:I16) -> 797987 | J17: =SUM(J14:J16) -> 771271 | K17: =SUM(K14:K16) -> 771271 | L17: =SUM(L14:L16) -> 1191188 | M17: =SUM(M14:M16) -> 1911188 | ... AX17: =SUM(AX14:AX16) -> 6046080.5

Sheet Completed Deals
B2: Completed Deals
B5: New Lettings
B6: Address | C6: Address | D6: Floor | E6: Type of Letting | F6: Area to be Demised sq ft | G6: Date Solicitors Instructed | H6: Name of Tenant | I6: Lease Terms | J6: New Rent | K6: Existing Rent | L6: Rental Uplift | M6: Average psf (NEW) | N6: Average psf (OLD) | O6: ERV psf | P6: Solicitors for Tenant | Q6: Solicitor | R6: Completed | S6: Action | T6: Surveyor | U6: Actual
B7: 1 | C7: 22-25 Eastcastle Street | D7: 1st floor East 1,050 sq ft | G7: 45499 | H7: Peter Alexander UK Limited | I7: 5 years with a t/b 3rd year | J7: 61425 | K7: 55700 | L7: =J7-K7 -> 5725 | M7: 58.5 | P7: TBC | Q7: TBC | R7: Yes | S7: COMPLETED | T7: SH | U7: 45555
B8: 2 | C8: 20 Margaret Street | D8: 5th Floor 750 sq ft | G8: 45538 | H8: Moods beauty Limited | I8: 2 years | J8: 41250 | K8: 39200 | L8: =J8-K8 -> 2050 | M8: 55 | P8: Withers LLP | Q8: SH | R8: Yes | S8: COMPLETED | T8: YS | U8: 45555
B9: 3 | C9: Moray House, 23-35 Great Titchfield Street | D9: 6th floor Flat 2 bed | G9: 45541 | H9: Mr Marc Versteegh & William Alex Mikael Antell | I9: 1 year | J9: 42000 | K9: 26496 | M9: 72.41 | P9: NA | Q9: NA | R9: Yes | S9: COMPLETED | T9: CM | U9: 45548
B10: 4 | C10: 63-64 Margaret Street | D10: 1st Floor West 688 sq ft | G10: 45510 | H10: Staybrook Capital Limited | I10: 3 years t/b 2nd year | J10: 47250 | K10: 35000 | M10: 68.67 | P10: TBC | Q10: SH | R10: Yes | S10: Completed | T10: CM | U10: 45562
B11: 5 | C11: Portland House, 4 Great Portland Street | D11: Ground floor and Basement , East, 5,667 sq ft | G11: 45464 | H11: Future Maxx Limited | I11: 15 years with a landord break at the end of the 8th year for redevolpement | J11: 300000 | K11: 255000 | M11: 53 | P11: Fladgates | Q11: SH | R11: Yes | S11: Draft lease being prepared Rent agreed is yr1 £300,000 yr2 £300,000; yr3 £305,000 yr4 £310,000; yr5 £320,000 | T11: SH | U11: 45569
B12: 6 | C12: 3-4 Bywell Place | D12: Ground Floor and Basement 1,167 sq ft | G12: 45274 | H12: Solo60 Ltd | I12: 5 years with landlord break (conditional on noise complaints) | J12: 46800 | K12: 37700 | M12: 40.48 | P12: TBC | Q12: SH | R12: Yes | T12: TH | U12: 45575
B13: 7 | C13: Moray House | D13: Ground Floor (A & B) 1,452 sq ft | G13: 45499 | H13: Media lab Group Limited | I13: For a term to expiring 15/03/28 | J13: 117500 | K13: 115000 | M13: 68 | P13: TBC | Q13: SH | R13: Yes | S13: Completed | T13: TH | U13: 45590
B14: 8 | C14: 51-53 Margaret Street | D14: 3rd Floor (west) 504 sq ft | G14: 45562 | H14: Reishi Clinic Ltd | I14: 5 year lease t/b 2nd yr | J14: 28050 | K14: 26500 | M14: 55 | P14: TBC | Q14: SH | R14: Yes | S14: Completed - Not completed. | T14: SH | U14: 45591
B15: 9 | C15: 146-148 Oxford Street | D15: Ground Floor and Basement 3,348 sq ft | G15: 45303 | H15: Holland & Barrett Retail Limited | I15: 10 years with t/b 6th year | J15: 520000 | K15: 522500 | M15: 160 | P15: In House | Q15: SH | R15: Yes | S15: Exchanged | T15: JM | U15: Completion 08/11/2024
B16: 10 | C16: 27-28 Eastcastle Street | D16: 3rd Floor 665 sq ft | G16: 45534 | H16: Principle Estate Management Limited | I16: 5 year lease with a t/b 2 years & 6 months | J16: 41875 | K16: 36600 | M16: 62.5 | P16: TBC | Q16: SH | R16: YES | S16: Completed. | T16: SH | U16: 45618
B17: 11 | C17: 23-25 Eastcastle Street | D17: 2nd Floor (East) 1,124 sq ft | G17: 45581 | H17: Cord Technologies Ltd | I17: Co-terminus with current lease on 1st Floor West (Expiring 08/06/26 | J17: 71875 | K17: 60400 | M17: 63.95 | P17: Stephenson's LLP | Q17: SH | R17: Yes | S17: Completed | T17: SH | U17: 45618
B18: 12 | C18: Golderbrock House, 15/19 Great Titchfield Street | D18: 1st Floor Front 1,335 sq ft | G18: 45427 | H18: Space Workplace Limited | I18: 5 years with a tb 3rd year | J18: 80400 | K18: 73700 | M18: 60 | P18: BPE | Q18: SH | R18: Yes | S18: Completed 29/11/2024 | T18: TH | U18: 45624
B19: 13 | C19: Portland House, 4 Great Portland Street | D19: 5th Floor (West) 1,528 sq ft | G19: 45539 | H19: Rios Design Studio Limited | I19: 5 year lease with a t/b 3rd year | J19: 108680 | K19: N/A | M19: 71.5 | P19: In House | Q19: SH | R19: YES | S19: Completed 26/11/2024 | T19: SH | U19: 45621
B20: 14 | C20: Flat 1, 2 Little Portland Street | D20: 1st Floor (1 bed / 420 sq ft) | G20: n/a | H20: Miss Julia Tressler | I20: 1 Year | J20: 25200 | K20: 27000 | M20: 58.65 | P20: n/a | Q20: n/a | R20: Yes | S20: Completed. 12/12/2024 | T20: CM | U20: 45639
B21: 9 | C21: 20 Great Portland street | D21: 2 Margaret Court 265sq.ft | G21: 45583 | H21: Express Alteration and Tailoring Limited | I21: 5 year lease | J21: 18000 | K21: 11700 | M21: 68 | P21: TBC | Q21: SH | R21: YES | S21: Solicitors instructed. Tenant made additional requests for lease documents. 12/12/2024 | T21: YS | U21: 45646
B22: 2025 | C22: 2025 | D22: 2025 | G22: 2025 | H22: 2025 | I22: 2025 | J22: 2025 | K22: 2025 | M22: 2025 | P22: 2025 | Q22: 2025 | R22: 2025 | S22: 2025 | T22: 2025 | U22: 2025
B23: 1 | C23: Portland House, 4 Great Portland Street | D23: 4th Floor, (East) 1,957sq.ft | E23: NL | G23: 45540 | H23: Racoon Media Services Ltd | I23: 5 years lease with a break option in year 3 on | J23: 114253 | K23: 115800 | L23: =J23-K23 -> -1547 | M23: 58.38 | P23: SMB London | Q23: SH | R23: Yes | S23: Completed | T23: SH | U23: 45667
B24: 2 | C24: Portland House, 4 Great Portland Street | D24: 4th Floor, (West) 1,548sq.ft | E24: NL | G24: 45540 | H24: Racoon Media Services Ltd | I24: 5 years lease with a break option in year 3 on 6 months notice. Rent free period of 3 months & 16 days | J24: 90090 | K24: 90100 | L24: =J24-K24 -> -10 | M24: 58.19 | P24: SMB London | Q24: SH | R24: Yes | S24: Completed | T24: SH | U24: 45667
B25: 3 | C25: Portland House, 4 Great Portland Street | D25: 6th Floor, (West) 1,253sq.ft | E25: NL | G25: 45540 | H25: Directors Cut Films West Ltd | I25: 5 year lease with a break option in year 3 on 6 months & 16 days. | J25: 66700 | K25: 66.7 | L25: =J25-K25 -> 66633.3 | M25: 53.23 | P25: Ronald Fletcher Baker | Q25: SH | R25: Yes | S25: Completed | T25: SH | U25: 45667
B26: 4 | C26: 6-10 Great Portland Street | D26: 5th Floor - 995sq.ft | E26: NL | G26: 45540 | H26: Racoon Media Services Ltd | I26: 5 year lease with a break option in year 3 on 6 months & 16 days. | J26: 61928 | K26: 61200 | L26: =J26-K26 -> 728 | M26: 62.24 | P26: SMB London | Q26: SH | R26: Yes | S26: Completed | T26: SH | U26: 45667
B27: 5 | C27: 47-50 Margaret Street | D27: 4th Floor (West) 390sq.ft | E27: NL | G27: 45593 | H27: Sen Yoga Ltd | I27: 5 years with t/b year 3 | J27: 21060 | K27: 19500 | L27: =J27-K27 -> 1560 | M27: 54 | P27: Lisa's Law LLP | Q27: SH | R27: Yes | S27: Completed | T27: SH | U27: 45681
B28: 6 | C28: Moray House | D28: Ground Floor Centre 1,949sq.ft | E28: NL | G28: 45590 | H28: H Illume Limited T/A LAPO | I28: 10 years | J28: 118000 | K28: 91000 | L28: =J28-K28 -> 27000 | M28: 60.5 | P28: TBC | Q28: SH | R28: YES | S28: Compled | T28: TH | U28: 45687
B29: 7 | C29: Store Room A, 50 Eastcastle Street | D29: Basement 454 sq ft | E29: NL | G29: 45670 | H29: Hope 93 Ltd | I29: 4 Years 7 Months / TB on 28/08/27 / RR on 28/08/27 | J29: 12000 | K29: 10000 | L29: =J29-K29 -> 2000 | M29: =55000/2161 -> 25.45118 | P29: SH | Q29: SH | R29: YES | S29: Completed 28th 27/01 | T29: JM | U29: 45684
B30: 8 | C30: 51 Great Portland Street | D30: 2nd Floor 325sq.ft | E30: NL | G30: 45593 | H30: Learn Lab Language School Ltd | I30: 2 years with t/b yr 1 (Inclusive deal) | J30: 22069 | K30: 17100 | L30: =J30-K30 -> 4969 | M30: 56 | P30: TBC | Q30: SH | R30: YES | S30: Completed 11/02/2025 | T30: YS | U30: 45702
B31: 9 | C31: 50 Eastcastle Street | D31: Suite 398 416sq.ft | E31: NL | G31: 45635 | H31: Pixi Beauty | I31: Co terminus with lease at 395 13/11/2027 | J31: 15000 | K31: 23900 | L31: =J31-K31 -> -8900 | M31: 36 | P31: Inhouse | Q31: SH | R31: YES | S31: Awaiting for completion documents from Pixi. Internal Red Tape and time difference is the given reason for the delay. 24/01/2025 | T31: JM | U31: 45702
B32: 10 | C32: 6/10 Great Portland Street | D32: Basement, Ground & Mezz 4,958 sq ft | E32: NL | G32: 45646 | H32: PrettyLittleThing.com Limited | I32: 5 years with t/b year 3 | J32: 375000 | K32: 337100 | L32: =J32-K32 -> 37900 | M32: 75.63 | P32: Pannone Corporate LLP | Q32: SH | R32: YES | S32: Completed 11/02/2025.14.02.25 | T32: SH | U32: 45702
B33: 11 | C33: 93 Mortimer Street / 43 Gt Portland Street | D33: Whole Building 10,112 sq ft | E33: NL | G33: 45464 | H33: Kamel Lazaar Foundation | I33: 15 years with t/b 6th & 10th years | J33: 700000 | K33: 750000 | L33: =J33-K33 -> -50000 | M33: 71 | P33: TBC | Q33: SH | R33: YES | S33: Completed 20/02/2025 | T33: YS | U33: 45709
B34: 12 | C34: Golderbrock House, 15/19 Great Titchfield Street | D34: Ground Floor Rear 325 sq ft | E34: NL | G34: 45625 | H34: Arlettie | I34: 3 years | J34: 20000 | K34: 17073 | L34: =J34-K34 -> 2927 | M34: 61.54 | P34: Wedlake Bell | Q34: SH | R34: YES | S34: Due to complete 20/21 Feb. 20/02/25 | T34: TH | U34: 45709
B35: 13 | C35: Princess House, 50 Eastcastle Street | D35: Suite 375 797 sq.ft | E35: NL | G35: 45678 | H35: Jewells Retail Limited | I35: A term to expire on 07/03/26 | J35: 59583 | K35: 45800 | L35: =J35-K35 -> 13783 | M35: 58.5 | P35: Inhouse | Q35: Wallace | R35: Yes | S35: all inclusive deal completed 25/02/2025 | T35: JM | U35: 45716
B36: 14 | C36: Princess House, 50 Eastcastle Street | D36: Suite 380 480 sq.ft | E36: NL | G36: 45678 | H36: Jewells Retail Limited | I36: A term to expire on 07/03/26 | J36: 35857 | K36: 27600 | L36: =J36-K36 -> 8257 | M36: 58.5 | P36: Inhouse | Q36: Wallace | R36: Yes | S36: all inclusive deal completed 25/02/2025 | T36: JM | U36: 45716
B37: 15 | C37: 23-25 Eastcastle Street | D37: Ground Floor and Basement 6,092 sq ft | E37: NL | G37: 45510 | H37: Sisters Grimm Limited | I37: 5 years with a t/b 3rd year | J37: 325000 | K37: 225000 | L37: =J37-K37 -> 100000 | M37: 56.32 | P37: TBC | Q37: SH | R37: Yes | S37: Completed. 28.02.25 | T37: SH | U37: 45716
B38: 16 | C38: 22 Eastcastle Street | D38: Ground Floor 2,333 sq ft | E38: NL | G38: 45553 | H38: Top Bridal Ltd | I38: 5 year Lease t/b 3rd year | J38: 128000 | K38: 110000 | L38: =J38-K38 -> 18000 | M38: =J38/2333 -> 54.864981 | P38: TBC | Q38: SH | R38: YES | S38: Completion 20.03.25 | T38: SH | U38: 45736
B39: 17 | C39: 65 Margaret Street | D39: 5th Floor 350 sq ft | E39: NL | G39: 45674 | H39: Mercury Creations Limited | I39: 5 years with t/b year 3 | J39: 19950 | K39: 17500 | L39: =J39-K39 -> 2450 | M39: 57 | P39: Inhouse | Q39: SH | R39: Yes | S39: COMPLETED | T39: CM | U39: 45744
B40: 18 | C40: 1 Great Titchfield street | D40: Whole Building 1,425 sq ft | E40: NL | G40: 45624 | H40: Tikkas | I40: 10 years | J40: 90000 | K40: 90000 | L40: =J40-K40 -> 0 | M40: 63 | P40: Optima Law Solicitors | Q40: SH | R40: Yes | S40: Engrossments all signed. Awaiting completion money - 28/03/2025 | T40: YS | U40: 45749
B41: 19 | C41: Golderbrock House, 15/19 Great Titchfield Street | D41: 4th Floor 1,330 sq.ft. | E41: NL | G41: 45700 | H41: Autonomous UK Ltd | I41: 5 year lease with t/b year 3 | J41: 86450 | K41: 78200 | L41: =J41-K41 -> 8250 | M41: 65 | P41: Clarke Wilmott | Q41: SH | R41: Yes | S41: Completed 15/04/2025 | T41: TH | U41: 45762
B42: 20 | C42: Priness House, 50 Eastcastle Street | D42: Suite 350, 3rd Floor 489 sq ft | E42: NL | G42: 45744 | H42: Jewells Retail Ltd | I42: A term to expire on 07/03/2026 | J42: 28607 | K42: 28100 | L42: =J42-K42 -> 507 | M42: 58.5 | P42: TBC | Q42: Wallace | R42: Yes | S42: Completed 23/04/2025 | T42: JM | U42: 45770
B43: 21 | C43: 30 Market Place | D43: 4th Floor 4,250 sq.ft | E43: NL | G43: 45733 | H43: Ascot Lloyd | I43: 10 year lease T/0 Break 5yr | J43: 361250 | K43: 358600 | L43: =J43-K43 -> 2650 | M43: =J43/4250 -> 85 | P43: Murrell Associates | Q43: SH | R43: YES | S43: Completed 09/05/2025 | T43: YS | U43: 45791
B44: 22 | C44: 142-144 Oxford Street | D44: Basement, Ground & 1st Floor 5,200 sq ft | E44: NL | G44: 45527 | H44: 02 (Telefonica) | I44: 10 year lease with t/b 5th year | J44: 705000 | K44: 616000 | L44: =J44-K44 -> 89000 | M44: 135 | P44: Shoosmiths | Q44: SH | R44: YES | S44: Completed | T44: JM | U44: 45807
B45: 23 | C45: Moray House, 23-35 Great Titchfield Street | D45: 2nd Floor (East) 3,300 sq.ft | E45: NL | G45: 45709 | H45: InPost UK Ltd | I45: A Term to expire on 25/01/2029 | J45: 231000 | K45: 193000 | L45: =J45-K45 -> 38000 | M45: 70 | P45: TBC | Q45: SH | R45: YES | S45: COMPLETED | T45: TH | U45: 45807
B46: 24 | C46: Kenilworth House, 79-80 Margaret Street | D46: Basement (East) 1,519 sq ft | E46: NL | G46: 45772 | H46: Jewells Retail Ltd | I46: 12 month short form lease | J46: 55000 | K46: 53600 | L46: =J46-K46 -> 1400 | M46: 36.2 | P46: In House | Q46: SH | R46: Yes | S46: In solicitors hands. Final draft lease issued and being reviewed. Tenant is on a licence to occupy in the interim. 23.05.2025. Still awaiting tenant signed docs expected on 16/06/25 to report completion next week 13/06/25 | T46: JM | U46: 45834
B47: 25 | C47: Kenilworth House, 79-80 Margaret Street | D47: Ground (East) 1,525 sq.ft. | E47: NL | G47: 45699 | H47: Lualdi UK | I47: 5 year Lease | J47: 90600 | K47: 90600 | L47: =J47-K47 -> 0 | M47: 59 | P47: TBC | Q47: Wallace | R47: Yes | S47: Final iteration of lease docs out for final approval. Co-terminus surrender and new lease to start 16th June. Tenant in Gilmoora temporarily to facilitate 50 ECS development. 09.05.2025. Engrossments have been circulated. Now targeting completion W/C 16th. 13/06/2025. Delayed again completion set for 01/08/25 tenant is waiting for materials for fit out to arrive from italy. Nowat gilmoora house in the interim 20/06/2025. | T47: JM | U47: 45835
B48: 26 | C48: 51/53 Margaret Street | D48: Ground and Basement | E48: NL | F48: 1922 | G48: 45702 | H48: Fred Bakery Limited | I48: 15 years with mutual break in 10th year | J48: 132000 | K48: 0 | L48: =J48-K48 -> 132000 | M48: 69 | N48: 126000 | O48: =100000/F48 -> 52.029136 | P48: Finance Law | Q48: SH | R48: Yes | S48: Completed.. 11.07.25 | T48: SH | U48: 45849
B49: 27 | C49: 47-50 Margaret Street | D49: 2nd | E49: NL | F49: 2610 | G49: 45805 | H49: Fitzrovia IT Ltd | I49: 7 years With T/o Break end of 5yr | J49: 151960 | K49: 0 | L49: =J49-K49 -> 151960 | M49: 58 | N49: 169700 | O49: =169700/F49 -> 65.019157 | P49: Spencer West | Q49: SH | R49: Yes | S49: Completed.. 11.07.25 | T49: SH | U49: 45849
B50: 28 | C50: 65 Margaret Street | D50: 2nd Floor | E50: NL | F50: 375 | G50: 45859 | H50: Olga Mantsiou | I50: 3 year lease | J50: 21000 | M50: 56 | P50: n/a | Q50: SH | R50: No | S50: Completed | T50: CM | U50: 45891
B51: 29 | C51: 15/16 Margaret Street | D51: Basement | E51: NL | F51: 2160 | G51: 45786 | H51: The Ludorum Club | I51: 10 years with t/b 5th year | J51: 70000 | K51: 0 | L51: =J51-K51 -> 70000 | M51: =J51/F51 -> 32.407407 | N51: 53800 | O51: =54000/F51 -> 25 | P51: TBC | Q51: SH | R51: yes | S51: completed | T51: WS | U51: 45887
B52: 30 | C52: 51 Great Portland Street | D52: 1st Floor | E52: NL | F52: 325 | G52: 45862 | H52: Pale Horse Gallery Ltd | I52: 3 year Lease | J52: 17000 | K52: 0 | L52: =J52-K52 -> 17000 | M52: =J52/F52 -> 52.307692 | N52: =K52/F52 -> 0 | O52: 52.3 | P52: TBC | Q52: SH | R52: YES | S52: Completed 05/09/2025 | T52: WS | U52: 45905
B53: 31 | C53: 21 Little Portland Street | D53: 1st | E53: NL | F53: 1282 | G53: 45841 | H53: Ltde Limited | I53: 5 years with t/b 3rd year | J53: 83000 | K53: 0 | L53: =J53-K53 -> 83000 | M53: =J53/F53 -> 64.74259 | N53: =K53/F53 -> 0 | O53: =70500/F53 -> 54.9922 | P53: TBC | Q53: SH | R53: Yes | S53: Lease documents close to final form. Side letter for Landlord works being drafted on common part works. 05/09/2025 | T53: WS | U53: 45919
B54: 32 | C54: 3/4A Little Portland Street | D54: Part 2nd | E54: NL | F54: 1659 | G54: 45842 | H54: Media lab Group Limited | I54: 5 years with t/b 15/03/28 | J54: 106785 | K54: 0 | L54: =J54-K54 -> 106785 | M54: =J54/F54 -> 64.367089 | N54: =K54/F54 -> 0 | O54: =J54/F54 -> 64.367089 | P54: Lanyon Bowdler | Q54: SH | R54: Yes | S54: Lease completed. 09/10/25 | T54: CD | U54: 45940
C55: 15/16 Margaret Street | D55: 1st | E55: NL | F55: 1606 | G55: 45845 | H55: Whispering Smith Ltd | I55: 5 years with t/b 3rd year | J55: 110000 | K55: 0 | L55: =J55-K55 -> 110000 | M55: =J55/F55 -> 68.493151 | N55: =K55/F55 -> 0 | O55: =J55/F55 -> 68.493151 | P55: TBC | Q55: SH | R55: YES | S55: Completed 21/10/2025 | T55: WS | U55: 45954
C56: 19-21 Great Portland Street | D56: 2nd Floor | E56: NL | F56: 2847 | G56: 45889 | H56: Doctor Care Anywhere | I56: 3 year term | J56: 193596 | K56: 68 | L56: =J56-K56 -> 193528 | M56: =J56/F56 -> 68 | N56: =K56/F56 -> 0.023884791 | O56: =J56/F56 -> 68 | P56: TBC | Q56: SH | R56: Yes | S56: Lease completed 29th October 2025. | T56: CD | U56: 45961
C57: 67-81 Mortimer Street | D57: 3rd ( E) | E57: NL | F57: 1371 | G57: 45806 | H57: Feel Films Limited | I57: 5 years with t/b 3rd year | J57: 85002 | K57: 0 | L57: =J57-K57 -> 85002 | M57: =J57/F57 -> 62 | N57: =K57/F57 -> 0 | O57: =J57/F57 -> 62 | P57: tbc | Q57: SH | R57: Yes | S57: Engrossments issued for signing. 15/10/2025 | T57: WS / ET | U57: 45961
C58: 67-81 Mortimer Street | D58: 3rd ( W) | E58: NL | F58: 1204 | G58: 45806 | H58: Feel Films Limited | I58: 5 years with t/b 3rd year | J58: 74648 | K58: 0 | L58: =J58-K58 -> 74648 | M58: =J58/F58 -> 62 | N58: =K58/F58 -> 0 | O58: =J58/F58 -> 62 | P58: TBC | Q58: SH | R58: Yes | S58: Engrossments issued for signing. 15/10/2025 | T58: WS / ET | U58: 45961
C59: 67-81 Mortimer Street | D59: 2nd ( E) | E59: NL | F59: 1395 | G59: 45806 | H59: Feel Films Limited | I59: 5 years with t/b 3rd year | J59: 86490 | K59: 0 | L59: =J59-K59 -> 86490 | M59: =J59/F59 -> 62 | N59: =K59/F59 -> 0 | O59: =J59/F59 -> 62 | P59: TBC | Q59: SH | R59: Yes | S59: Engrossments issued for signing. 15/10/2025 | T59: WS / ET | U59: 45961
B62: Renewals
C63: Address | F63: Area to be Demised sq ft | G63: Date Solicitors Instructed | H63: Name of Tenant | I63: Lease Terms | J63: New Rent | K63: Existing Rent | L63: Rental Uplift | M63: Average psf (NEW) | N63: Average psf (OLD) | O63: ERV psf | P63: Solicitors for Tenant | Q63: Solicitor | R63: Completed | S63: Action | T63: Surveyor | U63: Actual
B64: 1 | C64: Basement (rear) Golderbrock House | D64: 525 | G64: 45386 | H64: Soho Sonic Ltd | I64: 5 year lease from 27/05/24 | J64: 16000 | K64: =J64-M64 -> 2000 | M64: 14000 | P64: =M64/D64 -> 26.666667 | R64: Yes | S64: Completed | T64: TH | U64: 45541
B65: 2 | C65: 3rd Floor, 26 Eastcastle Street, London, W1 | D65: 480 | G65: 45507 | H65: Alistair Park | I65: 5 years from 06/09/24 | J65: 26000 | K65: =J65-M65 -> 80 | M65: 25920 | P65: =M65/D65 -> 54 | R65: Yes | S65: Completed. | T65: SH | U65: 45562
B66: 3 | C66: 2nd Floor (West/North) 17/18 Margaret Street | D66: 1220 | G66: 45416 | H66: Smiggle UK Limited | I66: 5 year lease from 26/05/24 | J66: 70200 | K66: =J66-M66 -> 10200 | M66: 60000 | P66: =M66/D66 -> 49.180328 | R66: Yes | S66: Completed | T66: TH | U66: 45583
B67: 4 | C67: Ground floor (west) 17/18 Maragret Street | D67: 1485 | G67: 45499 | H67: Yamaha Music Europe GmbH | I67: 5 year lease with T/B 20/08/24 | J67: 90000 | K67: 3127 | M67: 86873 | P67: 58.5 | Q67: 78000 | R67: Yes | S67: Completed | T67: TH | U67: 45583
B68: 5 | C68: 67-81 Mortimer Street (2nd floor West) | D68: 1395 | G68: 45509 | H68: Tappei Education Division | I68: Tenant break anytime after 29/06/2025 subject to 3 months notice | J68: 79200 | K68: 0 | M68: 79200 | P68: =M68/D68 -> 56.774194 | Q68: 54.98 | R68: Yes | S68: Completed | T68: YS | U68: 45583
B69: 6 | C69: Penthouse, 39 Great Portland Street | D69: 1180 | G69: n/a | H69: Ciss & Moser | I69: 1 year, no break | J69: 65000 | K69: =J69-M69 -> 0 | M69: 65000 | P69: 55.08 | Q69: 52 | R69: YES | S69: COMPLETED | T69: CM | U69: 45590
B70: 7 | C70: Gilmoora House, 57-61 Mortimer Street (Part Gnd - 5th Floors) | D70: 20993 | G70: 45554 | H70: Gilmoora House Limited | I70: 5 years, no break | J70: 1000000 | K70: =J70-M70 -> 0 | M70: 1000000 | P70: 47.63 | Q70: 80.4 | R70: YES | S70: COMPLETED | T70: CM | U70: 45590
B71: 8 | C71: 156-162 Oxford Street | D71: 3030 | G71: 45529 | H71: Dune Group Ltd | I71: 10 years from 22/02/2025 | J71: 500000 | K71: =J71-M71 -> 245000 | M71: 255000 | P71: =M71/D71 -> 84.158416 | Q71: 140 | R71: Yes | S71: Completed | T71: JM | U71: 45604
B72: 9 | C72: 2nd Floor (Front), 25 Margaret Street | D72: 170 | G72: 45544 | H72: Tara Harrison | I72: 5 Years from 06/12/24 | J72: 9400 | K72: =J72-M72 -> 475 | M72: 8925 | P72: =M72/D72 -> 52.5 | R72: Yes | S72: Completed | T72: CM | U72: 45605
B73: 10 | C73: 1st Floor, 50 Great Portland Street | D73: 552 | G73: 45544 | H73: Fresh Film Productions Ltd | I73: 5 Years from 13/10/24 | J73: 33000 | K73: =J73-M73 -> 3000 | M73: 30000 | P73: =M73/D73 -> 54.347826 | R73: YES | S73: COMPLETED | T73: CM | U73: 45614
B74: 11 | C74: Kiosk | D74: 85 | G74: 45498 | H74: The Prudential Assurance Company | I74: 1 Year | J74: 68250 | K74: =J74-M74 -> 3250 | M74: 65000 | P74: =M74/D74 -> 764.70588 | Q74: 764.71 | R74: YES | S74: COMPLETED | T74: JM | U74: 45614
B75: 12 | C75: Basement, 25 Margaret Street | D75: 424 | G75: 45544 | H75: Mr Kram Ddin Saraj (trading as K Tailoring) | I75: 5 years no break. | J75: 11872 | K75: =J75-M75 -> 1272 | M75: 10600 | P75: 25 | Q75: 27.5 | R75: Yes | S75: COMPLETED | T75: CM | U75: 45618
B76: 13 | C76: 4th Floor, (East), 52/53 Margaret Street | D76: 582 | G76: 45585 | H76: MDB SARL | I76: 2 years from 18/11/24 | J76: 42282 | K76: =J76-M76 -> 5202 | M76: 37080 | P76: 63.71 | Q76: 58.41 | R76: Yes | S76: COMPLETED | T76: SH | U76: 45618
B77: 14 | C77: 20 Margaret Street (ground and Basement) | D77: 1973 | G77: 45442 | H77: Outform EMEA Ltd | I77: 5 years, breaks in 2nd & 3rd year | J77: 103000 | K77: =J77-M77 -> 0 | M77: 103000 | P77: =M77/D77 -> 52.204764 | Q77: =94417/D77 -> 47.854536 | R77: YES | S77: Lease Completed 12/12/2024. | T77: YS | U77: 45639
B78: 15 | C78: 16/20 Hallam Street, London W1 | D78: 23500 | G78: 45614 | H78: Astor Court Hotel | I78: 10 year lease from 25/12/2024 rent review in 5th year at a ccommencing rent of £600,000 pax | J78: 660000 | K78: =J78-M78 -> 141809 | M78: 518191 | P78: =M78/D78 -> 22.050681 | Q78: 39.98 | R78: YES | S78: Lease Completed 13/12/2024. | T78: YS | U78: 45639
B79: 16 | C79: Ground floor/basement Radiant House 36-38 Mortimer Street | D79: 3452 | G79: 45551 | H79: Europride Ltd | I79: 3 year lease with T/B 17/02/26 | J79: 138440 | K79: =J79-M79 -> 16440 | M79: 122000 | P79: =M79/D79 -> 35.341831 | Q79: 109600 | R79: YES | S79: Completed (20/12/24) | T79: TH | U79: 45646
B80: 17 | C80: Ground Floor, (West), Portland House, 4 Great Portland Street, London, W1 | D80: 2103 | G80: 45553 | H80: Costa Limited | I80: 15 years from 12.01.25 with a mutual break option in year 10. Rent review to be 5 yearly. | J80: 220000 | K80: =J80-M80 -> 35000 | M80: 185000 | P80: 88 | Q80: 83 | R80: YES | S80: completed on 20/12/24. | T80: SH | U80: 45647
B81: 2025 | C81: 2025 | D81: 2025 | G81: 2025 | H81: 2025 | I81: 2025 | J81: 2025 | K81: 2025 | M81: 2025 | P81: 2025 | Q81: 2025 | R81: 2025 | S81: 2025 | T81: 2025 | U81: 2025
B82: 1 | C82: 142-144 Oxford Street | D82: Ground & Basement | E82: LR | F82: 5200 | G82: 45643 | H82: Cool Britannia Retail Ltd | I82: 1 Year with 1 month rolling mutual break option from day 1. | J82: 383908 | K82: 253908 | L82: =J82-K82 -> 130000 | M82: =J82/F82 -> 73.828462 | N82: =K82/F82 -> 48.828462 | O82: 122 | P82: Unrepresented | Q82: SH | R82: Yes | S82: Completed 06/01/2025 | T82: JM | U82: 45667
B83: 2 | C83: Mappin House, 4 Winsley Street, W1 | D83: 2nd ,3rd ,4th | E83: LR | F83: 28370 | G83: 45628 | H83: London Mappin House Center | I83: Lease renewal on the same terms as the existing lease(s) for a term of 3 years at a Headline Rent of £1,648,856 per annum. As per the existing lease a personal side deed will be annexed to the lease documenting a rental concession for the Guaranteed Rent to be set a 60% of a Headline Rent equating to £989,313 per annum. | J83: 1648856 | K83: 1648856 | L83: =J83-K83 -> 0 | M83: =J83/F83 -> 58.119704 | N83: =K83/F83 -> 58.119704 | O83: 62.37 | P83: Field Fisher | Q83: Wallace | R83: YES | S83: Completed 14/01/2025 | T83: JM | U83: 45674
B84: 3 | C84: Ground / Basement, 26 Eastcastle street | D84: Ground & Basement | E84: LR | F84: 2940 | G84: 45618 | H84: Hela Brands Ltd | I84: 3yr lease from 23/12/2024 T/O break after 12 month | J84: 132000 | K84: 132000 | L84: =J84-K84 -> 0 | M84: =J84/F84 -> 44.897959 | N84: =K84/F84 -> 44.897959 | O84: 38.98 | P84: TBC | Q84: SH | R84: Yes | S84: Documents signed by both parties. Awaiting completion monies. 07.02.25 | T84: SH | U84: Completed. 07.02.25
B85: 4 | C85: Julco House, 26-28 Great Portland Street | D85: 5th | E85: LR | F85: 1829 | G85: 45581 | H85: Oakvale Capital | I85: 5 years, T/O break 3rd year | J85: 120700 | K85: 112852 | L85: =J85-K85 -> 7848 | M85: =J85/F85 -> 65.992346 | N85: =K85/F85 -> 61.701476 | O85: 65 | P85: TBC | Q85: SH | R85: YES | S85: Engrossments returened to SH in readiness for completion. Complete 014.02.25 | T85: CD | U85: 45702
B86: 5 | C86: 50 Great Portland Street | D86: 4th Floor | E86: LR | F86: 314 | G86: 45740 | H86: James Boatman | I86: 3 Year lease renewal, rental uplift to £17,500. No rent free | J86: 17500 | K86: 17050 | L86: =J86-K86 -> 450 | M86: =J86/F86 -> 55.732484 | N86: =K86/F86 -> 54.299363 | O86: 49.36 | P86: Tenant acting on their behalf. | Q86: SH | R86: YES | S86: COMPLETED 08/04/2025 | T86: CD
B87: 6 | C87: 20 Great Portland Street | D87: 1st Rear | E87: LR | F87: 310 | G87: 45748 | H87: Face2Face Counselling Services Limited | I87: 5 year lease with tenant break in year 3, subject to 6 months notice | J87: 15500 | K87: 15500 | L87: =J87-K87 -> 0 | M87: =J87/F87 -> 50 | N87: =K87/F87 -> 50 | O87: =N87 -> 50 | P87: Tenant acting on their behalf. | Q87: SH | R87: YES | S87: Completed 16/04/2025 | T87: YS
B88: 7 | C88: 20 Great Portland Street | D88: 2nd Rear | E88: LR | F88: 310 | G88: 45748 | H88: Psychotherapy UK Training Ltd | I88: 5 year lease with tenant break in year 3, subject to 6 months notice | J88: 15500 | K88: 15500 | L88: =J88-K88 -> 0 | M88: =J88/F88 -> 50 | N88: =K88/F88 -> 50 | O88: =N88 -> 50 | P88: Tenant acting on their behalf. | Q88: SH | R88: YES | S88: Completed 16/04/2025 | T88: YS
B89: 8 | C89: 20 Great Portland Street | D89: 3rd Rear | E89: LR | F89: 215 | G89: 45748 | H89: One Therapy Limited | I89: 5 year lease with tenant break in year 3, subject to 6 months notice | J89: 11502 | K89: 10200 | L89: =J89-K89 -> 1302 | M89: =J89/F89 -> 53.497674 | N89: =K89/F89 -> 47.44186 | O89: =N89 -> 47.44186 | P89: Tenant acting on their behalf. | Q89: SH | R89: YES | S89: Completed 16/04/2025 | T89: YS
B90: 9 | C90: 76 Great Portland Street | D90: Ground & Basement | E90: LR | F90: 607 | G90: 45713 | H90: O-Chaa Thai Ltd | I90: Agree to surrender existing lease and grant a new 10 Year lease from 17/02/25, to coincide with the Ground & Basement (Rear), 76 GPS. No rent free. | J90: 27000 | K90: 25000 | L90: =J90-K90 -> 2000 | M90: 44.48 | N90: 41.39 | O90: 41.39 | P90: Ellicotts LLP | Q90: SH | R90: Yes | S90: Completed 01/05/2025 | T90: CM
B91: 10 | C91: 76 Great Portland Street | D91: Ground & Basement | E91: LR | F91: 662 | G91: 45713 | H91: O-Chaa Thai Ltd | I91: 10 Year renewal from 17/02/25. No Rent Free. | J91: 22000 | K91: 20500 | L91: 1500 | M91: 33.23 | N91: 30.97 | O91: 30.21 | P91: Ellicotts LLP | Q91: SH | R91: Yes | S91: Completed 01/05/2025 | T91: CM
B92: 11 | C92: 68 Wells Street | D92: Ground & Basement | E92: LR | F92: 2085 | G92: 45691 | H92: Voltage TV Productions Ltd | I92: 3 Year renewal. No rent free. | J92: 90000 | K92: 80000 | L92: 10000 | M92: =J92/F92 -> 43.165468 | N92: =K92/F92 -> 38.369305 | O92: =N92 -> 38.369305 | P92: Tenant acting on their behalf. | Q92: SH | R92: Yes | S92: Completed 30/04/2025 | T92: CM
B93: 12 | C93: 71/77 Mortimer Street | D93: Ground & Basement | E93: LR | F93: 2323 | G93: 45632 | H93: Folia ltd. | I93: Licence to occupy granted in the interim from 8th January 2025 for both units on all inclusive sum. 71 Mortimer Street - £55,000 works yet to start 77 Mortimer Street - £55,000 | J93: 110000 | K93: 108000 | L93: =J93-K93 -> 2000 | M93: =J93/F93 -> 47.352561 | N93: =K93/F93 -> 46.491606 | O93: 44 | P93: TBC | Q93: SH | R93: YES | S93: Leases completed 9/05/2025 Side letter in place for 71 Mortimer while works continue | T93: YS
B94: 13 | C94: Top Floor Flat, 25 Margaret Street | D94: Flat | E94: LR | F94: 600 | G94: n/a | H94: Mr Ole & Miss Ledo | I94: 12 Month term, no break | J94: 41600 | K94: 40950 | L94: =J94-K94 -> 650 | M94: =J94/F94 -> 69.333333 | N94: =K94/F94 -> 68.25 | O94: 60.23 | P94: N/A | Q94: N/A | R94: Yes | S94: COMPLETED | T94: CM
B95: 14 | C95: 17/18 Margaret Street | D95: 4th Floor | E95: LR | F95: 94 | G95: 45748 | H95: The London Child & Family Therapy Centre | I95: 5 years from 19/03/25 | J95: 7200 | K95: 6950 | L95: =J95-K95 -> 250 | M95: =J95/F95 -> 76.595745 | N95: =K95/F95 -> 73.93617 | O95: £57.55 | P95: Not represented | Q95: SH | R95: Yes | S95: COMPLETED | T95: TH
B96: 15 | C96: 53 Great portland street | D96: Ground and Basement | E96: LR | F96: 807 | G96: 45791 | H96: O-Chaa Thai Ltd | I96: 10yr Lease T.o Break 5yr | J96: 48420 | K96: 34320 | L96: =J96-K96 -> 14100 | M96: =J96/F96 -> 60 | N96: =K96/F96 -> 42.527881 | O96: 42.73 | P96: TBC | Q96: SH | R96: YES | S96: Completed | T96: WS | U96: 45877
B97: 16 | C97: 50 Great Portland Street | D97: 5th | E97: LR | F97: 309 | G97: 45740 | H97: OpenStudio Architects Ltd | I97: 3 Year lease renewal, rental uplift to £17,922 and two months rent free | J97: 17922 | K97: 16000 | L97: =J97-K97 -> 1922 | M97: =J97/F97 -> 58 | N97: =K97/F97 -> 51.779935 | O97: 48.54 | P97: Tenant acting on their behalf. | Q97: SH | R97: yes | S97: Engrossments have been circulated in readiness for completion 11/07/25 | T97: CD | U97: 45863
B98: 17 | C98: 30 Market Place | D98: 2nd | E98: LR | F98: 4463 | G98: 45790 | H98: Joint London | I98: 5yr lease T.o break 3yr | J98: 375750 | K98: 367290 | L98: =J98-K98 -> 8460 | M98: =J98/F98 -> 84.192247 | N98: =K98/F98 -> 82.296661 | O98: 82.46 | P98: TBC | Q98: SH | R98: yes | S98: Completed 27th August 2025 | T98: CD | U98: 45898
B99: 18 | C99: Top Floor Flat, Moray House | D99: Top Floor Flat | E99: LR | F99: 580 | G99: n/a | H99: Mark Versteegh & William Antell | I99: 1 year lease from 11.09.25, no break. | J99: 42016 | K99: 42016 | L99: =J99-K99 -> 0 | M99: =J99/F99 -> 72.441379 | N99: =K99/F99 -> 72.441379 | O99: 45.68 | P99: N/A | Q99: N/A | R99: Yes | S99: Completed | T99: CM | U99: 45905
B100: 19 | C100: Mappin House | D100: Mezzanine | E100: LR | F100: 7519 | G100: 45733 | H100: Perry Ellis Europe Ltd. | I100: Short Term Lease Extension for a period of 6 months at a rent of £505,000. | J100: 505000 | K100: 450600 | L100: =J100-K100 -> 54400 | M100: =J100/F100 -> 67.163187 | N100: =K100/F100 -> 59.928182 | O100: 62.94 | P100: In House | Q100: SH | R100: YES | S100: Awaiting Tenants Signature to complete lease. 13/06/2025. Tenant has expressed intrest in the third floor and JM is putting proposal together for next week. | T100: JM | U100: 45906
B101: 20 | C101: 156 Oxford Street | D101: Ground | E101: LR | F101: 2304 | G101: 45719 | H101: Hawes & Curtis Ltd | I101: 10 year term with Tenant only break at end of year 5. 6 months rent free as 3 months pure rent free and 6 months half rent. | J101: 475000 | K101: 255000 | L101: =J101-K101 -> 220000 | M101: =J101/F101 -> 206.16319 | N101: =K101/F101 -> 110.67708 | O101: =N101 -> 110.67708 | P101: TBC | R101: No | S101: Documents in agreed form ready for circulation. AML Passed expected completion end of month 25/04/2025. Lease and Rent Depoist now agreed. The tenant is on a TAW at £475,000 in the interim. Wording of side letter agreed, targeting completion next week 06/06/25. Tenant now disputing if Listed Building Consent is required. Furhter delay JM to advise board on openly marketing the property to pressure the tenant to complete. A tenancy at will is in place and LEM is raising billing at the annual amount of £475,000 13/06/25. JM has is requesting an explanation from H&C on hold up to explain to client. 20/06/25 | T101: JM
B102: 21 | C102: 32-26 Great Portland Street | D102: 2nd | E102: LR | F102: 1640 | G102: 45789 | H102: AdMaxim | I102: 5yr lease T.o break 3yr | J102: 116000 | K102: 101000 | L102: =J102-K102 -> 15000 | M102: =J102/F102 -> 70.731707 | N102: =K102/F102 -> 61.585366 | O102: 70 | P102: TBC | Q102: SH | R102: Yes | S102: Engrossments in circulation in readiness for complettion. 29/08/25 | T102: CD | U102: 45912
B103: 22 | C103: Windsor House, 40/41 Great Castle Street | D103: 3rd Floor | E103: LR | F103: 620 | G103: 16.07.25 | H103: Arava S.R.L | I103: 3 year lease effective from 12th September 2025 with a Tenant's break option at the end of 18th Months. | J103: 37000 | K103: 33480 | L103: =J103-K103 -> 3520 | M103: =J103/F103 -> 59.677419 | N103: =K103/F103 -> 54 | O103: 58.06 | P103: Ufficio.legal@aravfashion.it. Solicitor is based in Italy | Q103: SH | R103: Yes | S103: Completed. 12.09.25. | T103: SH | U103: 45912
B104: 23 | C104: 142 - 144 Oxford Street | D104: Kiosk | E104: LR | F104: 85 | H104: The Prudential Assurance Company | I104: Lease Renewal for a term of one year from 24 October 2025. Tenant Break option with 3 months notices. Tenant Option to Renew on 24 October 2026 Subject to 3 Months Notice | J104: 71662.5 | K104: 68250 | L104: =J104-K104 -> 3412.5 | M104: =J104/F104 -> 843.08824 | N104: =K104/F104 -> 802.94118 | O104: 65000 | P104: Hogan Lovell | Q104: SH | R104: Yes | S104: Lease Renewal for a term of one year from 24 October 2025. Tenant Break option with 3 months notices. Tenant Option to Renew on 24 October 2026 Subject to 3 Months Notice | T104: JM | U104: 45919
B105: 24 | C105: Kenilworth House, 79-80 Margaret Street | D105: Ground and Basement | E105: LR | F105: 1989 | G105: 45817 | H105: Edwards Cheshire Company Ltd | I105: 10 Years Lease. Mutual Break and Rent Review in Year 5. Financial settlement agreed on outstanding arears of £104,645 to be repaid over 12 months. | J105: 93000 | K105: 82575 | L105: =J105-K105 -> 10425 | M105: =J105/F105 -> 46.757164 | N105: =K105/F105 -> 41.515837 | O105: 37.71 | P105: TBC | Q105: Wallace | R105: Yes | S105: In solicitors hands. First draft lease issued and being reviewed by otherside. 13/06/2025. Completion Funds to be transferred with engrossment due by COB next week. 04/09/2025 | T105: JM | U105: 45919
...
