Workbook

Sheet Buildings
C1: Hide | D1: Hide | E1: Hide
C2: Hide | D2: Hide | E2: Hide | I2: Hide | J2: Hide | R2: Hide | S2: Hide | U2: Hide | W2: Hide | AD2: Hide | AE2: Hide | AF2: Hide | AG2: Hide
B3: Surveyor | C3: Client | D3: Property Number | E3: Property | F3: Unit Demise | G3: Unit Type | H3: Net Area | I3: . | J3: Agency Area group | K3: Tenant Name | L3: Start Date | M3: Expiry Date | N3: Vacant Since? | O3: RRs | P3: Break Date | Q3: Rent PA (£) | R3: check 1 | S3: check 2 | T3: 2023 ERV (£) | U3: check 3 | V3: 2024 ERV (£) | W3: check 4 | X3: ERV 2023 £.Sq.ft | Y3: EPC | Z3: * | AA3: 2024 Cap Valn. (£) | AB3: 1954 Act Protected | AC3: Remarks | AD3: Agency Quoting Rent £.sq.ft | AE3: Monthly Viewings | AF3: Total Viewings | AG3: Marketing Agent
G5: 5-6 Bywell Place
B7: TH | C7: MEL | D7: 550020 | E7: 5-6 Bywell Place | F7: Whole Building | G7: Office | H7: 2011 | I7: =H7 -> 2011 | J7: 2000 | K7: 111 Skin Limited | L7: 45365 | M7: 47190 | P7: 46459 | Q7: 115500 | R7: =Q7 -> 115500 | S7: =R7 -> 115500 | T7: 100600 | U7: =T7 -> 100600 | V7: 115000 | W7: =V7 -> 115000 | X7: =T7/H7 -> 50.024863 | Y7: C | AA7: 1825000 | AB7: No | AC7: Tenant break on 6 months notice. Break penalty of £28,875 if exercised.
F8: 5/6 Bywell Place | H8: =SUM(H7:H7) -> 2011
G9: 22 and 23-25 Eastcastle Street
B11: SH | C11: MEL | D11: 550910 | E11: 22 and 23-25 Eastcastle Street | F11: Lower Ground & Ground (22) | G11: Retail | H11: 2333 | I11: =H11 -> 2333 | J11: 2000 | K11: Top Bridal Ltd | L11: 45736 | M11: 47561 | P11: 46831 | Q11: 0 | R11: =Q11 -> 0 | T11: 110000 | U11: =T11 -> 110000 | V11: 108100 | W11: =V11 -> 108100 | X11: =T11/H11 -> 47.149593 | Y11: C | AB11: No | AC11: Stepped rent. £128,000 wef 20/06/25 increasing to £130,000 wef 20/03/27. Tenant break on 6 months notice. | AE11: 1 | AF11: 3
C12: MEL
C13: MEL | F13: 22, 23 & 25 Eastcastle St | H13: =SUM(H11:H11) -> 2333 | Q13: =SUM(Q11:Q11) -> 0 | S13: =SUM(R10:R11) -> 0 | T13: =SUM(T11:T11) -> 110000 | V13: =SUM(V11:V11) -> 108100 | AA13: 14850000
C14: MEL
C15: MEL | G15: 26 Eastcastle Street
C16: MEL
B17: SH | C17: MEL | D17: 550920 | E17: 26 Eastcastle Street | F17: Lower Ground & Ground | G17: Showroom/ Offices | H17: 2940 | I17: =H17 -> 2940 | J17: 3000 | K17: Hela Brands Ltd | L17: 45649 | M17: 46743 | P17: 46013 | Q17: 132000 | R17: =Q17 -> 132000 | T17: 114600 | U17: =T17 -> 114600 | V17: 124500 | W17: =V17 -> 124500 | X17: =T17/H17 -> 38.979592 | Y17: C | AB17: No | AC17: Tenant rolling break from 22/12/25 on 4 months notice.
C18: MEL
C19: MEL | G19: 27 - 28 Eastcastle Street
C20: MEL
B21: SH | C21: MEL | D21: 550930 | E21: 27 - 28 Eastcastle Street | F21: Lower Ground & Ground | G21: Showroom / Offices | H21: 3668 | I21: =H21 -> 3668 | J21: 3500 | K21: The London Hair Clinic Ltd | L21: 44757 | M21: 48409 | O21: 46583 | Q21: 170000 | R21: =Q21 -> 170000 | T21: 170000 | U21: =T21 -> 170000 | V21: 170000 | W21: =V21 -> 170000 | X21: =T21/H21 -> 46.346783 | Y21: B | AB21: No
C22: MEL
C23: MEL | G23: 10 Great Castle Street
C24: MEL
B25: YS | C25: MEL | D25: 550560 | E25: 10 Great Castle Street | F25: Basmt. Ground - 1 to 4 Floors | G25: Office | H25: 12578 | I25: =H25 -> 12578 | J25: 12500 | K25: Guaranty Trust Bank (UK) Ltd | L25: 44771 | M25: 50249 | O25: 46597 | P25: 48423 | Q25: 633334 | R25: =Q25 -> 633334 | S25: =R25 -> 633334 | T25: 950000 | U25: =T25 -> 950000 | V25: 950000 | W25: =V25 -> 950000 | X25: =T25/H25 -> 75.528701 | Y25: C | AA25: 17050000 | AB25: No | AC25: Fixed increase to £950,000 on 29/07/26. 5 yearly rent reviews. Tenant break on 9 months notice. Rent reduces by 20% for 12 months if break not activated.
C26: MEL | F26: 8-11 Great Castle Street | H26: =SUM(H25:H25) -> 12578 | Q26: =SUM(Q25:Q25) -> 633334 | T26: =SUM(T25:T25) -> 950000 | V26: =SUM(V25:V25) -> 950000
C27: MEL | G27: Windsor House, 40-41 Great Castle Street
C28: MEL
B29: SH | C29: MEL | D29: 550070 | E29: Windsor House, 40-41 Great Castle Street | F29: Basement & Ground Floor | G29: Retail/Café | H29: 2235 | I29: =H29 -> 2235 | J29: 2000 | K29: Vacant | N29: 45754 | Q29: 0 | R29: =Q29 -> 0 | T29: 143000 | U29: =T29 -> 143000 | V29: 145000 | W29: =V29 -> 145000 | X29: =T29/H29 -> 63.982103 | Y29: D | AB29: No | AC29: Lease forfeited on 07/04/25 (Al Falamanki Raoucche Ltd)
C30: MEL
C31: MEL | F31: 40/41 Great Castle Street | H31: =SUM(H29:H29) -> 2235 | Q31: =SUM(Q29:Q29) -> 0 | S31: =SUM(R29:R29) -> 0 | T31: =SUM(T29:T29) -> 143000 | V31: =SUM(V29:V29) -> 145000 | AA31: 4750000
C32: MEL
C33: MEL | G33: Portland House, 4 Great Portland Street
C34: MEL
B35: SH | C35: MEL | D35: 550470 | E35: Portland House, 4 Great Portland Street | F35: Basement (West) | G35: Restaurant/Bar | H35: 2945 | I35: =H35 -> 2945 | J35: 3000 | K35: The London Cocktail Club Ltd | L35: 41457 | M35: 46935 | O35: 45109 | Q35: 147500 | R35: =Q35 -> 147500 | T35: 147500 | U35: =T35 -> 147500 | V35: 147500 | W35: =V35 -> 147500 | X35: =T35/H35 -> 50.08489 | Y35: E | AB35: No | AC35: 5 year reversionary lease from 02/07/28 with day one rent review. Rent review to be documented at passing rent.
B36: SH | C36: MEL | D36: 550470 | E36: Portland House, 4 Great Portland Street | F36: Ground Floor | G36: Retail/Cafe | H36: 2103 | I36: =H36 -> 2103 | J36: 2000 | K36: Costa Ltd | L36: 45669 | M36: 51146 | O36: 47495 | P36: 49320 | Q36: 220000 | R36: =Q36 -> 220000 | T36: 176200 | U36: =T36 -> 176200 | V36: 220000 | W36: =V36 -> 220000 | X36: =T36/H36 -> 83.785069 | Y36: B | AB36: No | AC36: Mutual break on 6 months notice.
B37: SH | C37: MEL | D37: 550470 | E37: Portland House, 4 Great Portland Street | F37: Ground Floor & Basement (East) & Basement Vaults | G37: Restaurant | H37: 5667 | I37: =H37 -> 5667 | J37: 5500 | K37: Futuremaxx Ltd | L37: 45567 | M37: 51044 | O37: 47393 | Q37: 150000 | R37: =Q37 -> 150000 | T37: 255000 | U37: =T37 -> 255000 | V37: 300000 | W37: =V37 -> 300000 | X37: =T37/H37 -> 44.997353 | Y37: B | AB37: No | AC37: Stepped rent. £300,000 wef 02/10/25, £305,000 wef 02/10/26, £310,000 wef 02/10/27 and £320,000 wef 02/10/28. Min rent on review £330,000. Landlord redevelopment break option on 01/07/33 on 6 months notice.
C38: MEL
C39: MEL | G39: 6-10a Great Portland Street
C40: MEL
B41: SH | C41: MEL | D41: 550480 | E41: 6-10a Great Portland Street | F41: Basement & Ground | G41: Retail | H41: 4958 | I41: =H41 -> 4958 | J41: 5000 | K41: PrettyLittleThing.com | L41: 45699 | M41: 47524 | P41: 46793 | Q41: 0 | R41: =Q41 -> 0 | T41: 337100 | U41: =T41 -> 337100 | V41: 380000 | W41: =V41 -> 380000 | X41: =T41/H41 -> 67.991125 | Y41: B | AB41: No | AC41: Rent £187,500 wef 11/05/25 increasing to £375,000 wef 11/09/25. Tenant break on 6 months notice. 3 months rent free if not exercised. | AD41: 68 | AE41: 1 | AF41: 13 | AG41: LEM / Colliers
C42: MEL
C43: MEL | G43: 15-17 Great Portland Street & 6-7 Great Castle Street
C44: MEL
B45: SH | C45: MEL | D45: 550530 | E45: 15-17 Great Portland Street & 6-7 Great Castle Street | F45: Whole Building | G45: Office/Bank | H45: 9884 | I45: =H45 -> 9884 | J45: 10000 | K45: Barclays Bank UK Plc | L45: 44856 | M45: 47411 | O45: 46682 | Q45: 580000 | R45: =Q45 -> 580000 | S45: =R45 -> 580000 | T45: 580000 | U45: =T45 -> 580000 | V45: 607100 | W45: =V45 -> 607100 | X45: =T45/H45 -> 58.680696 | Y45: B | AA45: 10650000 | AB45: Yes
C46: MEL | F46: 15/17 Great Portland Street | H46: =SUM(H45:H45) -> 9884 | Q46: =SUM(Q45:Q45) -> 580000 | T46: =SUM(T45:T45) -> 580000 | V46: =SUM(V45:V45) -> 607100
C47: MEL
C48: MEL | G48: 19-21 Great Portland Street
C49: MEL
B50: CD | C50: MEL | D50: 550410 | E50: 19-21 Great Portland Street . | F50: Basement, Ground & First Floors | G50: Restaurant | H50: 11225 | I50: =H50 -> 11225 | J50: 10000 | K50: UK VAP GPS | L50: 44729 | M50: 50207 | O50: 46555 | P50: 48381 | Q50: 625000 | R50: =Q50 -> 625000 | T50: 750000 | U50: =T50 -> 750000 | V50: 650000 | W50: =V50 -> 650000 | X50: =T50/H50 -> 66.815145 | Y50: B | AB50: No | AC50: Rent increasing to £650,000 wef 25/03/26. Mutual break @ 16/06/32 on 6 months notice.
C51: MEL
C52: MEL | G52: 20 Great Portland Street
C53: MEL
B54: YS | C54: MEL | D54: 550795 | E54: 20 Great Portland Street | F54: Basement | G54: Studio | H54: 1330 | I54: =H54 -> 1330 | K54: Vacant / Landlord | N54: 43670 | Q54: 0 | R54: =Q54 -> 0 | T54: 25000 | U54: =T54 -> 25000 | V54: 25000 | W54: =V54 -> 25000 | X54: =T54/H54 -> 18.796992 | Y54: D | AB54: No
B55: YS | C55: MEL | D55: 550795 | E55: 20 Great Portland Street | F55: Ground Floor Rear | G55: Retail | H55: 260 | I55: =H55 -> 260 | J55: 250 | K55: Express Alteration and Tailoring Ltd | L55: 45645 | M55: 46739 | Q55: 18000 | R55: =Q55 -> 18000 | T55: 11700 | U55: =T55 -> 11700 | V55: 11700 | W55: =V55 -> 11700 | X55: =T55/H55 -> 45 | Y55: C | AB55: No | AF55: 1 | AG55: LEM / RIB
B56: YS | C56: MEL | D56: 550795 | E56: 20 Great Portland Street | F56: Ground Floor Front | G56: Retail | H56: 652 | I56: =H56 -> 652 | J56: 750 | K56: Explore Global Limited | L56: 44851 | M56: 48503 | O56: 46677 | Q56: 55000 | R56: =Q56 -> 55000 | T56: 55000 | U56: =T56 -> 55000 | V56: 55000 | W56: =V56 -> 55000 | X56: =T56/H56 -> 84.355828 | Y56: D | AB56: No
C57: MEL
C58: MEL | G58: Highlight House, 22-24 Great Portland Street
C59: MEL
B60: YS | C60: MEL | D60: 550080 | E60: Highlight House, 22-24 Great Portland Street | F60: Basement & Ground Floor | G60: Restaurant | H60: 3626 | I60: =H60 -> 3626 | J60: 3500 | K60: Mamaye UK Limited. | L60: 44635 | M60: 48287 | O60: 46461 | P60: 46460 | Q60: 220000 | R60: =Q60 -> 220000 | T60: 210000 | U60: =T60 -> 210000 | V60: 227900 | W60: =V60 -> 227900 | X60: =T60/H60 -> 57.915058 | Y60: D | AB60: No | AC60: Rent rises to £237,500 wef 15/03/26.
C61: MEL
C62: MEL | G62: 23-25 Great Portland Street & 54-55 Margaret Street
C63: MEL
B64: CD | C64: MEL | D64: 550400 | E64: 23-25 Great Portland Street & 54-55 Margaret Street | F64: Basement & Ground Floor | G64: Shop/Cafe | H64: 2164 | I64: =H64 -> 2164 | J64: 2000 | K64: Florian James Limited | L64: 44995 | M64: 48647 | O64: 46822 | Q64: 165000 | R64: =Q64 -> 165000 | T64: 165000 | U64: =T64 -> 165000 | V64: 165000 | W64: =V64 -> 165000 | X64: =T64/H64 -> 76.247689 | Y64: D | AB64: No
C65: MEL
C66: MEL | G66: 39 Great Portland Street
C67: MEL
B68: CM | C68: MEL | D68: 550740 | E68: 39 Great Portland Street | F68: Basement & Ground Floor | G68: Showroom | H68: 1524 | I68: =H68 -> 1524 | J68: 1500 | K68: Fads Boutique Limited | L68: 44833 | M68: 45928 | Q68: 72000 | R68: =Q68 -> 72000 | T68: 72000 | U68: =T68 -> 72000 | V68: 72038 | W68: =V68 -> 72038 | X68: =T68/H68 -> 47.244094 | Y68: D | AB68: No
C69: MEL
C70: MEL | G70: 41 Great Portland Street
C71: MEL
B72: CD | C72: MEL | D72: 550840 | E72: 41 Great Portland Street | F72: Basement to Fourth | G72: Offices | H72: 2313 | I72: =H72 -> 2313 | J72: 2250 | K72: S.Hardwick & L.Morris (t/a Hardwick & Morris Chartered Accountants) | L72: 42339 | M72: 45991 | O72: 44166 | Q72: 112000 | R72: =Q72 -> 112000 | S72: =R72 -> 112000 | T72: 106600 | U72: =T72 -> 106600 | V72: 102100 | W72: =V72 -> 102100 | X72: =T72/H72 -> 46.087332 | Y72: E | AA72: 1750000 | AB72: No
C73: MEL
C74: MEL | G74: 42-48 Great Portland Street
C75: MEL
B76: CM | C76: MEL | D76: 550830 | E76: 42-48 Great Portland Street | F76: Basement & Ground Floor | G76: Shop | H76: 4259 | I76: =H76 -> 4259 | J76: 4250 | K76: GP Acoustics (UK) Limited | L76: 44967 | M76: 48619 | O76: 46793 | P76: 46792 | Q76: 215000 | R76: =Q76 -> 215000 | T76: 215000 | U76: =T76 -> 215000 | V76: 215000 | W76: =V76 -> 215000 | X76: =T76/H76 -> 50.481334 | Y76: C | AB76: No | AC76: Tenant break on 6 months notice.
C77: MEL
C78: MEL | G78: 45-49 Great Portland Street
C79: MEL
B80: SH | C80: MEL | D80: 550600 | E80: 45-49 Great Portland Street | F80: Ground Floor & Basement (North) | G80: Showroom | H80: 1449 | I80: =H80 -> 1449 | J80: 1500 | K80: Straight Forward Retail Ltd. | L80: 45624 | M80: 49275 | Q80: 70000 | R80: =Q80 -> 70000 | T80: 76500 | U80: =T80 -> 76500 | V80: 76800 | W80: =V80 -> 76800 | X80: =T80/H80 -> 52.795031 | Y80: C | AB80: No | AC80: Rent increasing to £73,000 @ 28/11/27, £77,500 @ 28/11/30. Landlord break 27/11/27 on 6 months notice.
B81: SH | C81: MEL | D81: 550600 | E81: 45-49 Great Portland Street | F81: Ground Floor & Basement (South | G81: A1/D1 | H81: 1550 | I81: =H81 -> 1550 | J81: 1500 | K81: Reviv Global Ltd | L81: 43293 | M81: 46214 | Q81: 120000 | R81: =Q81 -> 120000 | T81: 81000 | U81: =T81 -> 81000 | V81: 97300 | W81: =V81 -> 97300 | X81: =T81/H81 -> 52.258065 | Y81: C | AB81: No
C82: MEL
C83: MEL | G83: 50 Great Portland Street
C84: MEL
B85: CD | C85: MEL | D85: 550990 | E85: 50 Great Portland Street | F85: Ground Floor & Basement | G85: Retail | H85: 1361 | I85: =H85 -> 1361 | K85: Beautify LDN Ltd. | L85: 45352 | M85: 49003 | O85: 47178 | P85: 47177 | Q85: 60000 | R85: =Q85 -> 60000 | T85: 55600 | U85: =T85 -> 55600 | V85: 59000 | W85: =V85 -> 59000 | X85: =T85/H85 -> 40.852314 | Y85: B | AB85: No | AC85: Mutual break 28/02/29 on 6 months notice. 3 months rent free if break not exercised.
C86: MEL
C87: MEL | G87: 51 Great Portland Street
C88: MEL
B89: YS | C89: MEL | D89: 550700 | E89: 51 Great Portland Street | F89: Ground Floor & Basement | G89: Retail | H89: 750 | I89: =H89 -> 750 | K89: Bernardo Vasconcelos Ltd | L89: 45377 | M89: 49028 | O89: 47203 | Q89: 45000 | R89: =Q89 -> 45000 | T89: 39000 | U89: =T89 -> 39000 | V89: 39000 | W89: =V89 -> 39000 | X89: =T89/H89 -> 52 | Y89: D | AB89: No
C90: MEL
C91: MEL | G91: 53 Great Portland Street
C92: MEL
B93: YS | C93: MEL | D93: 550710 | E93: 53 Great Portland Street | F93: Ground Floor & Basement | G93: Café | H93: 807 | I93: =H93 -> 807 | J93: 1000 | K93: O-Chaa Thai Ltd. | L93: 42179 | M93: 45831 | Q93: 34320 | R93: =Q93 -> 34320 | T93: 34320 | U93: =T93 -> 34320 | V93: 34481 | W93: =V93 -> 34481 | X93: =T93/H93 -> 42.527881 | Y93: E | AB93: No | AC93: Lease renewal terms being discussed.
B94: YS | C94: MEL | D94: 550710 | E94: 53 Great Portland Street | F94: Ground Floor | G94: Kiosk | H94: 60 | I94: =H94 -> 60 | K94: J C Patel | L94: 44075 | M94: 45900 | Q94: 12500 | R94: =Q94 -> 12500 | T94: 12000 | U94: =T94 -> 12000 | V94: 12000 | W94: =V94 -> 12000 | X94: =T94/H94 -> 200 | Y94: E | AB94: No | AC94: All Inclusive.
C95: MEL
C96: MEL | G96: 76 Great Portland Street
C97: MEL
B98: CM | C98: MEL | D98: 550090 | E98: 76 Great Portland Street | F98: Basement & Ground Floor (Front) | G98: Showroom | H98: 607 | I98: =H98 -> 607 | J98: 500 | K98: O-Chaa Thai Ltd. | L98: 44340 | M98: 47991 | O98: 46166 | Q98: 25000 | R98: =Q98 -> 25000 | T98: 25000 | U98: =T98 -> 25000 | V98: 25000 | W98: =V98 -> 25000 | X98: =T98/H98 -> 41.186161 | Y98: B | AB98: No
B99: CM | C99: MEL | D99: 550090 | E99: 76 Great Portland Street | F99: Basement & Ground Floor (Rear) | G99: Restaurant | H99: 662 | I99: =H99 -> 662 | J99: 500 | K99: O-Chaa Thai Ltd. | L99: 43879 | M99: 45705 | Q99: 20500 | R99: =Q99 -> 20500 | T99: 20000 | U99: =T99 -> 20000 | V99: 20000 | W99: =V99 -> 20000 | X99: =T99/H99 -> 30.21148 | Y99: B | AB99: No | AC99: Lease renewal terms agreed.
C100: MEL
C101: MEL | G101: 1 Great Titchfield Street
C102: MEL
B103: YS | C103: MEL | D103: 550750 | E103: 1 Great Titchfield Street | F103: Basement to Third Floor | G103: Shop/Snack Bar | H103: 1305 | I103: =H103 -> 1305 | J103: 1250 | K103: Tikkas Group Ltd | L103: 45748 | M103: 49399 | O103: 47574 | P103: 47573 | Q103: 0 | R103: =Q103 -> 0 | S103: =R103 -> 0 | T103: 90000 | U103: =T103 -> 90000 | V103: 90000 | W103: =V103 -> 90000 | X103: =T103/H103 -> 68.965517 | Y103: D | AA103: 1630000 | AB103: No | AC103: New letting completed. Rent £90,000 wef 01/09/25. Tenant break on 6 months notice. 2 months rent free if break not exercised. | AD103: 69 | AF103: 10 | AG103: LEM
...

Sheet Sheet2
B2: 5-6 Bywell Place
A4: Whole Building | B4: Office | C4: 2011 | D4: =C4 -> 2011 | E4: 2000 | F4: 111 Skin Limited
A5: 5/6 Bywell Place | C5: =SUM(C4:C4) -> 2011
B6: 22 and 23-25 Eastcastle Street
A8: Lower Ground & Ground (22) | B8: Retail | C8: 2333 | D8: =C8 -> 2333 | E8: 2000 | F8: Top Bridal Ltd
A10: 22, 23 & 25 Eastcastle St | C10: =SUM(C8:C8) -> 2333
B12: 26 Eastcastle Street
A14: Lower Ground & Ground | B14: Showroom/ Offices | C14: 2940 | D14: =C14 -> 2940 | E14: 3000 | F14: Hela Brands Ltd
B16: 27 - 28 Eastcastle Street
A18: Lower Ground & Ground | B18: Showroom / Offices | C18: 3668 | D18: =C18 -> 3668 | E18: 3500 | F18: The London Hair Clinic Ltd
B20: 10 Great Castle Street
A22: Basmt. Ground - 1 to 4 Floors | B22: Office | C22: 12578 | D22: =C22 -> 12578 | E22: 12500 | F22: Guaranty Trust Bank (UK) Ltd
A23: 8-11 Great Castle Street | C23: =SUM(C22:C22) -> 12578
B24: Windsor House, 40-41 Great Castle Street
A26: Basement & Ground Floor | B26: Retail/Café | C26: 2235 | D26: =C26 -> 2235 | E26: 2000 | F26: Vacant
A28: 40/41 Great Castle Street | C28: =SUM(C26:C26) -> 2235
B30: Portland House, 4 Great Portland Street
A32: Basement (West) | B32: Restaurant/Bar | C32: 2945 | D32: =C32 -> 2945 | E32: 3000 | F32: The London Cocktail Club Ltd
A33: Ground Floor | B33: Retail/Cafe | C33: 2103 | D33: =C33 -> 2103 | E33: 2000 | F33: Costa Ltd
A34: Ground Floor & Basement (East) & Basement Vaults | B34: Restaurant | C34: 5667 | D34: =C34 -> 5667 | E34: 5500 | F34: Futuremaxx Ltd
B36: 6-10a Great Portland Street
A38: Basement & Ground | B38: Retail | C38: 4958 | D38: =C38 -> 4958 | E38: 5000 | F38: PrettyLittleThing.com
B40: 15-17 Great Portland Street & 6-7 Great Castle Street
A42: Whole Building | B42: Office/Bank | C42: 9884 | D42: =C42 -> 9884 | E42: 10000 | F42: Barclays Bank UK Plc
A43: 15/17 Great Portland Street | C43: =SUM(C42:C42) -> 9884
B45: 19-21 Great Portland Street
A47: Basement, Ground & First Floors | B47: Restaurant | C47: 11225 | D47: =C47 -> 11225 | E47: 10000 | F47: UK VAP GPS
B49: 20 Great Portland Street
A51: Basement | B51: Studio | C51: 1330 | D51: =C51 -> 1330 | F51: Vacant / Landlord
A52: Ground Floor Rear | B52: Retail | C52: 260 | D52: =C52 -> 260 | E52: 250 | F52: Express Alteration and Tailoring Ltd
A53: Ground Floor Front | B53: Retail | C53: 652 | D53: =C53 -> 652 | E53: 750 | F53: Explore Global Limited
B55: Highlight House, 22-24 Great Portland Street
A57: Basement & Ground Floor | B57: Restaurant | C57: 3626 | D57: =C57 -> 3626 | E57: 3500 | F57: Mamaye UK Limited.
B59: 23-25 Great Portland Street & 54-55 Margaret Street
A61: Basement & Ground Floor | B61: Shop/Cafe | C61: 2164 | D61: =C61 -> 2164 | E61: 2000 | F61: Florian James Limited
B63: 39 Great Portland Street
A65: Basement & Ground Floor | B65: Showroom | C65: 1524 | D65: =C65 -> 1524 | E65: 1500 | F65: Fads Boutique Limited
B67: 41 Great Portland Street
A69: Basement to Fourth | B69: Offices | C69: 2313 | D69: =C69 -> 2313 | E69: 2250 | F69: S.Hardwick & L.Morris (t/a Hardwick & Morris Chartered Accountants)
B71: 42-48 Great Portland Street
A73: Basement & Ground Floor | B73: Shop | C73: 4259 | D73: =C73 -> 4259 | E73: 4250 | F73: GP Acoustics (UK) Limited
B75: 45-49 Great Portland Street
A77: Ground Floor & Basement (North) | B77: Showroom | C77: 1449 | D77: =C77 -> 1449 | E77: 1500 | F77: Straight Forward Retail Ltd.
A78: Ground Floor & Basement (South | B78: A1/D1 | C78: 1550 | D78: =C78 -> 1550 | E78: 1500 | F78: Reviv Global Ltd
B80: 50 Great Portland Street
A82: Ground Floor & Basement | B82: Retail | C82: 1361 | D82: =C82 -> 1361 | F82: Beautify LDN Ltd.
B84: 51 Great Portland Street
A86: Ground Floor & Basement | B86: Retail | C86: 750 | D86: =C86 -> 750 | F86: Bernardo Vasconcelos Ltd
B88: 53 Great Portland Street
A90: Ground Floor & Basement | B90: Café | C90: 807 | D90: =C90 -> 807 | E90: 1000 | F90: O-Chaa Thai Ltd.
A91: Ground Floor | B91: Kiosk | C91: 60 | D91: =C91 -> 60 | F91: J C Patel
B93: 76 Great Portland Street
A95: Basement & Ground Floor (Front) | B95: Showroom | C95: 607 | D95: =C95 -> 607 | E95: 500 | F95: O-Chaa Thai Ltd.
A96: Basement & Ground Floor (Rear) | B96: Restaurant | C96: 662 | D96: =C96 -> 662 | E96: 500 | F96: O-Chaa Thai Ltd.
B98: 1 Great Titchfield Street
A100: Basement to Third Floor | B100: Shop/Snack Bar | C100: 1305 | D100: =C100 -> 1305 | E100: 1250 | F100: Tikkas Group Ltd
A101: 1 Great Titchfield Street | C101: =SUM(C100:C100) -> 1305
B103: 3 Great Titchfield Street
A105: Basement & Ground | B105: Restaurant | C105: 1440 | D105: =C105 -> 1440 | E105: 1500 | F105: Pho Trading Ltd.
B107: Great Titchfield House, 14-18 Great Titchfield Street
A109: Ground Floor & Basement (South) | B109: Showroom | C109: 2026 | D109: =C109 -> 2026 | E109: 2000 | F109: Sound Disposition Limited
A110: Ground Floor & Basement (North) | B110: Showroom | C110: 2202 | D110: =C110 -> 2202 | E110: 2000 | F110: Godske Group A/S
B112: Golderbrock House, 15-19 Great Titchfield Street
A114: Ground & Basement (South) | B114: Showroom | C114: 1115 | D114: =C114 -> 1115 | E114: 1000 | F114: Dal Florentino Ltd
B116: Circus House, 21 Great Titchfield Street
A118: Basement & Ground (East) | B118: Showroom/ Office | C118: 3443 | D118: =C118 -> 3443 | E118: 3500 | F118: The Graphical Tree Ltd
B120: Moray House, 23-35 Great Titchfield Street & 63-65 Mortimer Street
A122: Part Lower Ground | B122: Gym / D1 | C122: 2604 | D122: =C122 -> 2604 | E122: 2500 | F122: Rehabilitation & Athletics Performance UK Ltd.
A123: Unit A & B. Ground Floor | B123: Shop/Showroom | C123: 1452 | D123: =C123 -> 1452 | E123: 1500 | F123: Medialab Group Ltd.
A124: Unit C. Ground Floor & Basement | B124: Office/ Showroom | C124: 1949 | D124: =C124 -> 1949 | E124: 2000 | F124: H Illume Ltd (t/a LAPO)
A125: Unit D & E. Ground Floor & Part Basement | B125: Gym / D1 | C125: 4976 | D125: =C125 -> 4976 | E125: 5000 | F125: CSS F45 UK Ltd
B127: 56 Great Titchfield Street
A129: Whole Building | B129: Retail | C129: 2692 | D129: =C129 -> 2692 | E129: 2750 | F129: Morplan Ltd.
B131: 58 Great Titchfield Street
A133: Basement & Ground Floor | B133: Retail | C133: 1171 | D133: =C133 -> 1171 | E133: 1000 | F133: Morplan Ltd.
A134: First, Second & Third Floors | B134: Retail/Showroom/Office | C134: 1120 | D134: =C134 -> 1120 | E134: 1000 | F134: Morplan Ltd.
A136: 58 Great Titchfield Street | C136: =SUM(C133:C134) -> 2291
B138: 12 Hallam Street (The Hallam Hotel)
A140: Whole Building | B140: Hotel 25 Beds | C140: 4284 | D140: =C140 -> 4284 | E140: 4250 | F140: Vacant
A142: 12 Hallam Street | C142: =SUM(C140:C141) -> 4284
B143: 16-20 Hallam Street (Astor Court Hotel)
A145: Whole Building | B145: Hotel 52 Beds | C145: 23500 | D145: =C145 -> 23500 | E145: 23500 | F145: Wesdom Investments Ltd.
B147: Flat 1, 2 Little Portland Street
A149: Flat 1 | B149: Residential | C149: 420 | D149: =C149 -> 420 | E149: 500 | F149: Miss Julia Tressler
A151: Flat 1 2 Little Portland St | C151: =SUM(C149:C150) -> 420
B152: 3/4/4a Little Portland Street
A154: Basement (North & Centre) Part Ground | B154: Storage/Cloakroom | C154: 1911 | D154: =C154 -> 1911 | E154: 2000 | F154: Pure Public Relations Ltd.
A155: Ground Floor (Rear) | B155: Cloakroom | C155: 0 | D155: =C155 -> 0 | F155: Vacant / Landlord
A156: Ground Floor (East) | B156: Showroom | C156: 495 | D156: =C156 -> 495 | E156: 500 | F156: Econnective UK Ltd.
B158: 5 Little Portland Street
A160: Ground & Basement | B160: Bar | C160: 2520 | D160: =C160 -> 2520 | E160: 2500 | F160: The Social Little Portland Street Ltd.
B162: Alexandra House, 6 Little Portland Street
A164: Ground Floor & Part Basement | B164: Restaurant | C164: 4430 | D164: =C164 -> 4430 | E164: 4500 | F164: Burger & Lobster Restaurant Group Ltd.
B166: 9 Little Portland Street
A168: Lower Ground and Ground Floors | B168: Showroom / Office | C168: 747 | D168: =C168 -> 747 | E168: 750 | F168: Order Line Ltd
B170: 21 Little Portland Street
A172: Lower Ground and Ground Floors | B172: Office | C172: 2820 | D172: =C172 -> 2820 | E172: 3000 | F172: FRIBA Limited
B174: 22 Little Portland Street (formerly 22-23 LPS)
A176: Whole Building | B176: Office/ Showroom/ Storage | C176: 9776 | D176: =C176 -> 9776 | E176: 10000 | F176: David Chipperfield Architects Ltd
B178: 9 Margaret Street
...

Sheet Bank Schedule
D1: Hide | E1: Hide | F1: Hide
D2: Hide | E2: Hide | F2: Hide | J2: Hide | K2: Hide | S2: Hide | T2: Hide | V2: Hide | X2: Hide | AE2: Hide | AF2: Hide | AG2: Hide | AH2: Hide
A3: Record_Type | C3: Surveyor | D3: Client | E3: Property Number | F3: Property | G3: Unit Demise | H3: Unit Type | I3: Net Area | J3: . | K3: Agency Area group | L3: Tenant Name | M3: Start Date | N3: Expiry Date | O3: Vacant Since? | P3: RRs | Q3: Break Date | R3: Rent PA (£) | S3: check 1 | T3: check 2 | U3: 2023 ERV (£) | V3: check 3 | W3: 2024 ERV (£) | X3: check 4 | Y3: ERV 2023 £.Sq.ft | Z3: EPC | AA3: * | AB3: 2024 Cap Valn. (£) | AC3: 1954 Act Protected | AD3: Remarks | AE3: Agency Quoting Rent £.sq.ft | AF3: Monthly Viewings | AG3: Total Viewings | AH3: Marketing Agent
A5: BUILD | H5: 5-6 Bywell Place
A7: UNIT | C7: TH | D7: MEL | E7: 550020 | F7: 5-6 Bywell Place | G7: Whole Building | H7: Office | I7: 2011 | J7: =H7 -> Office | K7: 2000 | L7: 111 Skin Limited | M7: 45365 | N7: 47190 | Q7: 46459 | R7: 115500 | S7: =Q7 -> 46459 | T7: =R7 -> 115500 | U7: 100600 | V7: =T7 -> 115500 | W7: 115000 | X7: =V7 -> 115500 | Y7: =T7/H7 -> #VALUE! | Z7: C | AB7: 1825000 | AC7: No | AD7: Tenant break on 6 months notice. Break penalty of £28,875 if exercised.
G8: 5/6 Bywell Place | I8: =SUM(H7:H7) -> 0
A9: BUILD | H9: 22 and 23-25 Eastcastle Street
A11: UNIT | C11: SH | D11: MEL | E11: 550910 | F11: 22 and 23-25 Eastcastle Street | G11: Lower Ground & Ground (22) | H11: Retail | I11: 2333 | J11: =H11 -> Retail | K11: 2000 | L11: Top Bridal Ltd | M11: 45736 | N11: 47561 | Q11: 46831 | R11: 0 | S11: =Q11 -> 46831 | U11: 110000 | V11: =T11 -> 0 | W11: 108100 | X11: =V11 -> 0 | Y11: =T11/H11 -> #VALUE! | Z11: C | AC11: No | AD11: Stepped rent. £128,000 wef 20/06/25 increasing to £130,000 wef 20/03/27. Tenant break on 6 months notice. | AF11: 1 | AG11: 3
A12: UNIT | C12: SH | D12: MEL | E12: 550910 | F12: 22 and 23-25 Eastcastle Street | G12: Lower Ground & Ground (23-25) | H12: Gallery | I12: 6092 | J12: =H12 -> Gallery | K12: 6000 | L12: Sisters Grimm Ltd | M12: 45712 | N12: 47537 | Q12: 46806 | R12: 0 | S12: =Q12 -> 46806 | U12: 225000 | V12: =T12 -> 0 | W12: 226100 | X12: =V12 -> 0 | Y12: =T12/H12 -> #VALUE! | Z12: C | AC12: No | AD12: Rent £325,000 wef 24/05/25. Tenant break on 6 months notice. 1 month rent free from 24/02/28 if break not excerised. | AG12: 3 | AH12: LEM
A13: UNIT | C13: SH | D13: MEL | E13: 550910 | F13: 22 and 23-25 Eastcastle Street | G13: First Floor (22) | H13: Office | I13: 1063 | J13: =H13 -> Office | K13: 1000 | L13: Peter Alexander UK Ltd | M13: 45551 | N13: 47376 | Q13: 46645 | R13: 61425 | S13: =Q13 -> 46645 | U13: 55700 | V13: =T13 -> 0 | W13: 61100 | X13: =V13 -> 0 | Y13: =T13/H13 -> #VALUE! | Z13: D | AC13: No | AD13: Tenant break on 3 months notice. Additional 3 months rent free if not exercised. | AH13: LEM
A14: UNIT | C14: SH | D14: MEL | E14: 550910 | F14: 22 and 23-25 Eastcastle Street | G14: First Floor (23-25) | H14: Office | I14: 2220 | J14: =H14 -> Office | K14: 2000 | L14: Cord Technologies Ltd | M14: 45086 | N14: 46181 | Q14: 45816 | R14: 131400 | S14: =Q14 -> 45816 | U14: 131100 | V14: =T14 -> 0 | W14: 133200 | X14: =V14 -> 0 | Y14: =T14/H14 -> #VALUE! | Z14: D | AC14: No | AD14: Tenant break on 6 months notice.
A15: UNIT | C15: SH | D15: MEL | E15: 550910 | F15: 22 and 23-25 Eastcastle Street | G15: Second Floor (22) | H15: Office | I15: 1124 | J15: =H15 -> Office | K15: 1000 | L15: Cord Technologies Ltd | M15: 45614 | N15: 46181 | Q15: 45816 | R15: 71875 | S15: =Q15 -> 45816 | U15: 60400 | V15: =T15 -> 0 | W15: 61800 | X15: =V15 -> 0 | Y15: =T15/H15 -> #VALUE! | Z15: B | AC15: No | AD15: Tenant break on 6 months notice.
A16: UNIT | C16: SH | D16: MEL | E16: 550910 | F16: 22 and 23-25 Eastcastle Street | G16: Second Floor (23-25) | H16: Office | I16: 2238 | J16: =H16 -> Office | K16: 2000 | L16: Vacant | O16: 45636 | R16: 0 | S16: =Q16 -> 0 | U16: 134300 | V16: =T16 -> 0 | W16: 134300 | X16: =V16 -> 0 | Y16: =T16/H16 -> #VALUE! | Z16: D | AC16: No | AD16: LEM marketing.
A17: UNIT | C17: SH | D17: MEL | E17: 550910 | F17: 22 and 23-25 Eastcastle Street | G17: Third Floor (22) | H17: Office | I17: 400 | J17: =H17 -> Office | K17: 500 | L17: Vacant | O17: 45771 | R17: 0 | S17: =Q17 -> 0 | U17: 20600 | V17: =T17 -> 0 | W17: 23000 | X17: =V17 -> 0 | Y17: =T17/H17 -> #VALUE! | Z17: D | AC17: No | AD17: LEM marketing.
A18: UNIT | C18: SH | D18: MEL | E18: 550910 | F18: 22 and 23-25 Eastcastle Street | G18: Third Floor (23-25) | H18: Office | I18: 1938 | J18: =H18 -> Office | K18: 2000 | L18: Vacant | O18: 45217 | R18: 0 | S18: =Q18 -> 0 | U18: 109000 | V18: =T18 -> 0 | W18: 111400 | X18: =V18 -> 0 | Y18: =T18/H18 -> #VALUE! | Z18: D | AC18: No | AD18: LEM marketing. | AE18: 65 | AF18: 1 | AG18: 3
A19: UNIT | C19: SH | D19: MEL | E19: 550910 | F19: 22 and 23-25 Eastcastle Street | G19: Fourth Floor (22) | H19: Office | I19: 419 | J19: =H19 -> Office | K19: 500 | L19: Element Pictures UK Ltd. | M19: 44539 | N19: 46364 | R19: 23940 | S19: =Q19 -> 0 | U19: 21000 | V19: =T19 -> 0 | W19: 24100 | X19: =V19 -> 0 | Y19: =T19/H19 -> #VALUE! | Z19: D | AC19: No
A20: UNIT | C20: SH | D20: MEL | E20: 550910 | F20: 22 and 23-25 Eastcastle Street | G20: Fourth Floor (23-25) | H20: Office | I20: 972 | J20: =H20 -> Office | K20: 1000 | L20: Encore Search (Newburgh Street) Ltd. | M20: 45100 | N20: 46926 | Q20: 46195 | R20: 58560 | S20: =Q20 -> 46195 | U20: 49400 | V20: =T20 -> 0 | W20: 58300 | X20: =V20 -> 0 | Y20: =T20/H20 -> #VALUE! | Z20: D | AC20: No | AD20: Tenant break on 6 months notice. 3 months rent free if not exercised.
A21: UNIT | C21: SH | D21: MEL | E21: 550910 | F21: 22 and 23-25 Eastcastle Street | G21: Fifth Floor (23-25) | H21: Office | I21: 977 | J21: =H21 -> Office | K21: 1000 | L21: Element Pictures UK Ltd. | M21: 45476 | N21: 47301 | Q21: 46364 | R21: 58496 | S21: =Q21 -> 46364 | U21: 47400 | V21: =T21 -> 0 | W21: 58600 | X21: =V21 -> 0 | Y21: =T21/H21 -> #VALUE! | Z21: B | AC21: No | AD21: Tenant break on 6 months notice.
A22: UNIT | C22: SH | D22: MEL | E22: 550910 | F22: 22 and 23-25 Eastcastle Street | G22: Sixth Floor (23-25) | H22: Office | I22: 744 | J22: =H22 -> Office | K22: 750 | L22: Vacant | O22: 45182 | R22: 0 | S22: =Q22 -> 0 | U22: 34400 | V22: =T22 -> 0 | W22: 42800 | X22: =V22 -> 0 | Y22: =T22/H22 -> #VALUE! | Z22: D | AC22: No | AD22: LEM marketing. | AE22: 63.5 | AF22: 1 | AG22: 3 | AH22: LEM
A23: UNIT | C23: SH | D23: MEL | E23: 550910 | F23: 22 and 23-25 Eastcastle Street | G23: Garage | H23: Parking | I23: 185 | J23: =H23 -> Parking | K23: 200 | L23: Vacant / Landlord | O23: N/A | R23: 0 | S23: =Q23 -> 0 | U23: 3000 | V23: =T23 -> 0 | W23: 4500 | X23: =V23 -> 0 | Y23: =T23/H23 -> #VALUE! | AC23: No
D24: MEL
D25: MEL | G25: 22, 23 & 25 Eastcastle St | I25: =SUM(H11:H23) -> 0 | R25: =SUM(Q11:Q23) -> 324473 | T25: =SUM(R10:R23) -> 405696 | U25: =SUM(T11:T23) -> 0 | W25: =SUM(V11:V23) -> 0 | AB25: 14850000
D26: MEL
A27: BUILD | D27: MEL | H27: 26 Eastcastle Street
D28: MEL
A29: UNIT | C29: SH | D29: MEL | E29: 550920 | F29: 26 Eastcastle Street | G29: Lower Ground & Ground | H29: Showroom/ Offices | I29: 2940 | J29: =H29 -> Showroom/ Offices | K29: 3000 | L29: Hela Brands Ltd | M29: 45649 | N29: 46743 | Q29: 46013 | R29: 132000 | S29: =Q29 -> 46013 | U29: 114600 | V29: =T29 -> 0 | W29: 124500 | X29: =V29 -> 0 | Y29: =T29/H29 -> #VALUE! | Z29: C | AC29: No | AD29: Tenant rolling break from 22/12/25 on 4 months notice.
A30: UNIT | C30: SH | D30: MEL | E30: 550920 | F30: 26 Eastcastle Street | G30: First Floor | H30: Offices | I30: 1398 | J30: =H30 -> Offices | K30: 1000 | L30: Alternative Real Estate Advisors Ltd | M30: 45470 | N30: 47295 | Q30: 46564 | R30: 89833 | S30: =Q30 -> 46564 | U30: 76900 | V30: =T30 -> 0 | W30: 97900 | X30: =V30 -> 0 | Y30: =T30/H30 -> #VALUE! | Z30: D | AC30: No | AD30: Rent increases to £98,000 @ 27/06/27. Tenant break on 6 months notice.
A31: UNIT | C31: SH | D31: MEL | E31: 550920 | F31: 26 Eastcastle Street | G31: Second Floor | H31: Offices | I31: 1110 | J31: =H31 -> Offices | K31: 1000 | L31: Vacant | O31: 43273 | R31: 0 | S31: =Q31 -> 0 | U31: 61100 | V31: =T31 -> 0 | W31: 69400 | X31: =V31 -> 0 | Y31: =T31/H31 -> #VALUE! | Z31: C | AC31: No | AD31: LEM marketing. | AE31: 63.5 | AG31: 1
A32: UNIT | C32: SH | D32: MEL | E32: 550920 | F32: 26 Eastcastle Street | G32: Third Floor | H32: Offices | I32: 481 | J32: =H32 -> Offices | K32: 500 | L32: Mr. A. Park | M32: 45541 | N32: 47366 | Q32: 46635 | R32: 26000 | S32: =Q32 -> 46635 | U32: 25300 | V32: =T32 -> 0 | W32: 25300 | X32: =V32 -> 0 | Y32: =T32/H32 -> #VALUE! | Z32: D | AC32: No | AD32: Tenant break on 6 months notice.
D33: MEL
D34: MEL | G34: 26 Eastcastle Street | I34: =SUM(H29:H32) -> 0 | R34: =SUM(Q29:Q32) -> 139212 | T34: =SUM(R29:R32) -> 247833 | U34: =SUM(T29:T32) -> 0 | W34: =SUM(V29:V32) -> 0 | AB34: 4725000
D35: MEL
A36: BUILD | D36: MEL | H36: 27 - 28 Eastcastle Street
D37: MEL
A38: UNIT | C38: SH | D38: MEL | E38: 550930 | F38: 27 - 28 Eastcastle Street | G38: Lower Ground & Ground | H38: Showroom / Offices | I38: 3668 | J38: =H38 -> Showroom / Offices | K38: 3500 | L38: The London Hair Clinic Ltd | M38: 44757 | N38: 48409 | P38: 46583 | R38: 170000 | S38: =Q38 -> 0 | U38: 170000 | V38: =T38 -> 0 | W38: 170000 | X38: =V38 -> 0 | Y38: =T38/H38 -> #VALUE! | Z38: B | AC38: No
A39: UNIT | C39: SH | D39: MEL | E39: 550930 | F39: 27 - 28 Eastcastle Street | G39: First Floor | H39: Offices | I39: 1418 | J39: =H39 -> Offices | K39: 1500 | L39: Feldberg Capital UK Limited | M39: 45231 | N39: 46326 | R39: 174500 | S39: =Q39 -> 0 | U39: 78000 | V39: =T39 -> 0 | W39: 99300 | X39: =V39 -> 0 | Y39: =T39/H39 -> #VALUE! | Z39: B | AC39: No | AD39: All inclusive including rates and furniture.
A40: UNIT | C40: SH | D40: MEL | E40: 550930 | F40: 27 - 28 Eastcastle Street | G40: Second Floor | H40: Offices | I40: 716 | J40: =H40 -> Offices | K40: 750 | L40: MSP Secretaries Ltd. | M40: 44384 | N40: 46209 | R40: 41000 | S40: =Q40 -> 0 | U40: 39400 | V40: =T40 -> 0 | W40: 41200 | X40: =V40 -> 0 | Y40: =T40/H40 -> #VALUE! | Z40: B | AC40: No
A41: UNIT | C41: SH | D41: MEL | E41: 550930 | F41: 27 - 28 Eastcastle Street | G41: Third Floor | H41: Offices | I41: 665 | J41: =H41 -> Offices | K41: 750 | L41: Principle Estate Management LLP | M41: 45617 | N41: 47442 | Q41: 46527 | R41: 41875 | S41: =Q41 -> 46527 | U41: 36600 | V41: =T41 -> 0 | W41: 38200 | X41: =V41 -> 0 | Y41: =T41/H41 -> #VALUE! | Z41: B | AC41: No | AD41: Tenant break on 6 months notice. 2 months rent free if break not exercised.
D42: MEL
D43: MEL | G43: 27/28 Eastcastle Street | I43: =SUM(H38:H41) -> 0 | R43: =SUM(Q36:Q41) -> 46527 | T43: =SUM(R38:R41) -> 427375 | U43: =SUM(T38:T41) -> 0 | W43: =SUM(V38:V41) -> 0 | AB43: 5675000
D44: MEL
A45: BUILD | D45: MEL | H45: 10 Great Castle Street
D46: MEL
A47: UNIT | C47: YS | D47: MEL | E47: 550560 | F47: 10 Great Castle Street | G47: Basmt. Ground - 1 to 4 Floors | H47: Office | I47: 12578 | J47: =H47 -> Office | K47: 12500 | L47: Guaranty Trust Bank (UK) Ltd | M47: 44771 | N47: 50249 | P47: 46597 | Q47: 48423 | R47: 633334 | S47: =Q47 -> 48423 | T47: =R47 -> 633334 | U47: 950000 | V47: =T47 -> 633334 | W47: 950000 | X47: =V47 -> 633334 | Y47: =T47/H47 -> #VALUE! | Z47: C | AB47: 17050000 | AC47: No | AD47: Fixed increase to £950,000 on 29/07/26. 5 yearly rent reviews. Tenant break on 9 months notice. Rent reduces by 20% for 12 months if break not activated.
D48: MEL | G48: 8-11 Great Castle Street | I48: =SUM(H47:H47) -> 0 | R48: =SUM(Q47:Q47) -> 48423 | U48: =SUM(T47:T47) -> 633334 | W48: =SUM(V47:V47) -> 633334
A49: BUILD | D49: MEL | H49: Windsor House, 40-41 Great Castle Street
D50: MEL
A51: UNIT | C51: SH | D51: MEL | E51: 550070 | F51: Windsor House, 40-41 Great Castle Street | G51: Basement & Ground Floor | H51: Retail/Café | I51: 2235 | J51: =H51 -> Retail/Café | K51: 2000 | L51: Vacant | O51: 45754 | R51: 0 | S51: =Q51 -> 0 | U51: 143000 | V51: =T51 -> 0 | W51: 145000 | X51: =V51 -> 0 | Y51: =T51/H51 -> #VALUE! | Z51: D | AC51: No | AD51: Lease forfeited on 07/04/25 (Al Falamanki Raoucche Ltd)
A52: UNIT | C52: SH | D52: MEL | E52: 550070 | F52: Windsor House, 40-41 Great Castle Street | G52: First Floor | H52: Office | I52: 694 | J52: =H52 -> Office | K52: 750 | L52: JRDL UK Ltd. | M52: 44904 | N52: 45999 | R52: 42000 | S52: =Q52 -> 0 | U52: 42000 | V52: =T52 -> 0 | W52: 42000 | X52: =V52 -> 0 | Y52: =T52/H52 -> #VALUE! | Z52: D | AC52: No
A53: UNIT | C53: SH | D53: MEL | E53: 550070 | F53: Windsor House, 40-41 Great Castle Street | G53: Second Floor | H53: Office | I53: 690 | J53: =H53 -> Office | K53: 750 | L53: Jamieson Stone Services Ltd. | M53: 45412 | N53: 47237 | Q53: 46326 | R53: 40020 | S53: =Q53 -> 46326 | U53: 39700 | V53: =T53 -> 0 | W53: 40000 | X53: =V53 -> 0 | Y53: =T53/H53 -> #VALUE! | Z53: D | AC53: No | AD53: Tenant break on 6 months notice.
A54: UNIT | C54: SH | D54: MEL | E54: 550070 | F54: Windsor House, 40-41 Great Castle Street | G54: Third Floor | H54: Office | I54: 620 | J54: =H54 -> Office | K54: 750 | L54: Arav Fashion UK Ltd. | M54: 44816 | N54: 45911 | R54: 33480 | S54: =Q54 -> 0 | U54: 34100 | V54: =T54 -> 0 | W54: 36000 | X54: =V54 -> 0 | Y54: =T54/H54 -> #VALUE! | Z54: D | AC54: No
A55: UNIT | C55: SH | D55: MEL | E55: 550070 | F55: Windsor House, 40-41 Great Castle Street | G55: Fourth Floor | H55: Office | I55: 400 | J55: =H55 -> Office | K55: 500 | L55: Vacant | O55: 44168 | R55: 0 | S55: =Q55 -> 0 | U55: 21600 | V55: =T55 -> 0 | W55: 22000 | X55: =V55 -> 0 | Y55: =T55/H55 -> #VALUE! | Z55: D | AC55: No | AD55: To be refurbished.
A56: UNIT | C56: SH | D56: MEL | E56: 550070 | F56: Windsor House, 40-41 Great Castle Street | G56: Roof | H56: Air Con Units | I56: 0 | J56: =H56 -> Air Con Units | L56: Vacant / Landlord | O56: N/A | R56: 0 | S56: =Q56 -> 0 | U56: 0 | V56: =T56 -> 0 | W56: 0 | X56: =V56 -> 0 | AC56: No
D57: MEL
D58: MEL | G58: 40/41 Great Castle Street | I58: =SUM(H51:H56) -> 0 | R58: =SUM(Q51:Q56) -> 46326 | T58: =SUM(R51:R56) -> 115500 | U58: =SUM(T51:T56) -> 0 | W58: =SUM(V51:V56) -> 0 | AB58: 4750000
D59: MEL
A60: BUILD | D60: MEL | H60: Portland House, 4 Great Portland Street
D61: MEL
A62: UNIT | C62: SH | D62: MEL | E62: 550470 | F62: Portland House, 4 Great Portland Street | G62: Basement (West) | H62: Restaurant/Bar | I62: 2945 | J62: =H62 -> Restaurant/Bar | K62: 3000 | L62: The London Cocktail Club Ltd | M62: 41457 | N62: 46935 | P62: 45109 | R62: 147500 | S62: =Q62 -> 0 | U62: 147500 | V62: =T62 -> 0 | W62: 147500 | X62: =V62 -> 0 | Y62: =T62/H62 -> #VALUE! | Z62: E | AC62: No | AD62: 5 year reversionary lease from 02/07/28 with day one rent review. Rent review to be documented at passing rent.
A63: UNIT | C63: SH | D63: MEL | E63: 550470 | F63: Portland House, 4 Great Portland Street | G63: Ground Floor | H63: Retail/Cafe | I63: 2103 | J63: =H63 -> Retail/Cafe | K63: 2000 | L63: Costa Ltd | M63: 45669 | N63: 51146 | P63: 47495 | Q63: 49320 | R63: 220000 | S63: =Q63 -> 49320 | U63: 176200 | V63: =T63 -> 0 | W63: 220000 | X63: =V63 -> 0 | Y63: =T63/H63 -> #VALUE! | Z63: B | AC63: No | AD63: Mutual break on 6 months notice.
A64: UNIT | C64: SH | D64: MEL | E64: 550470 | F64: Portland House, 4 Great Portland Street | G64: Ground Floor & Basement (East) & Basement Vaults | H64: Restaurant | I64: 5667 | J64: =H64 -> Restaurant | K64: 5500 | L64: Futuremaxx Ltd | M64: 45567 | N64: 51044 | P64: 47393 | R64: 150000 | S64: =Q64 -> 0 | U64: 255000 | V64: =T64 -> 0 | W64: 300000 | X64: =V64 -> 0 | Y64: =T64/H64 -> #VALUE! | Z64: B | AC64: No | AD64: Stepped rent. £300,000 wef 02/10/25, £305,000 wef 02/10/26, £310,000 wef 02/10/27 and £320,000 wef 02/10/28. Min rent on review £330,000. Landlord redevelopment break option on 01/07/33 on 6 months notice.
A65: UNIT | C65: SH | D65: MEL | E65: 550470 | F65: Portland House, 4 Great Portland Street | G65: First Floor (West) | H65: Office | I65: 1784 | J65: =H65 -> Office | K65: 1750 | L65: Time & Tide Holdings (UK) Ltd | M65: 45457 | N65: 47282 | R65: 60700 | S65: =Q65 -> 0 | U65: 99700 | V65: =T65 -> 0 | W65: 120400 | X65: =V65 -> 0 | Y65: =T65/H65 -> #VALUE! | Z65: B | AC65: No | AD65: Rent increases to £121,400 @ 14/08/25
A66: UNIT | C66: SH | D66: MEL | E66: 550470 | F66: Portland House, 4 Great Portland Street | G66: First Floor (East) | H66: Office | I66: 2075 | J66: =H66 -> Office | K66: 2000 | L66: L52 Communications Ltd | M66: 45384 | N66: 47209 | Q66: 46478 | R66: 133280 | S66: =Q66 -> 46478 | U66: 114700 | V66: =T66 -> 0 | W66: 140100 | X66: =V66 -> 0 | Y66: =T66/H66 -> #VALUE! | Z66: B | AC66: No | AD66: Tenant break on 6 months notice. 1 month rent free from 02/04/27 if not exercised.
A67: UNIT | C67: SH | D67: MEL | E67: 550470 | F67: Portland House, 4 Great Portland Street | G67: Second Floor (East) | H67: Office | I67: 2063 | J67: =H67 -> Office | K67: 2000 | L67: Tekcor4 Limited | M67: 45516 | N67: 47341 | Q67: 46610 | R67: 146450 | S67: =Q67 -> 46610 | U67: 120700 | V67: =T67 -> 0 | W67: 139260 | X67: =V67 -> 0 | Y67: =T67/H67 -> #VALUE! | Z67: B | AC67: No | AD67: Tenant break on 6 months notice.
A68: UNIT | C68: SH | D68: MEL | E68: 550470 | F68: Portland House, 4 Great Portland Street | G68: Second Floor (West) | H68: Office | I68: 1796 | J68: =H68 -> Office | K68: 1750 | L68: Vacant | O68: 45051 | R68: 0 | S68: =Q68 -> 0 | U68: 87300 | V68: =T68 -> 0 | W68: 121240 | X68: =V68 -> 0 | Y68: =T68/H68 -> #VALUE! | Z68: B | AC68: No | AD68: LEM marketing. | AE68: 72.5 | AF68: 2 | AG68: 7 | AH68: LEM/LDG
A69: UNIT | C69: SH | D69: MEL | E69: 550470 | F69: Portland House, 4 Great Portland Street | G69: Third Floor (West) | H69: Office | I69: 1691 | J69: =H69 -> Office | K69: 1500 | L69: J&M Davidson Limited. | M69: 44795 | N69: 46620 | Q69: 45890 | R69: 102705 | S69: =Q69 -> 45890 | U69: 102705 | V69: =T69 -> 0 | W69: 114100 | X69: =V69 -> 0 | Y69: =T69/H69 -> #VALUE! | Z69: B | AC69: No | AD69: Tenant break on 6 months notice.
A70: UNIT | C70: SH | D70: MEL | E70: 550470 | F70: Portland House, 4 Great Portland Street | G70: Third Floor (East) | H70: Office | I70: 2055 | J70: =H70 -> Office | K70: 2000 | L70: Media Campaign Limited | M70: 45488 | N70: 47313 | Q70: 46582 | R70: 181050 | S70: =Q70 -> 46582 | U70: 125050 | V70: =T70 -> 0 | W70: 138700 | X70: =V70 -> 0 | Y70: =T70/H70 -> #VALUE! | Z70: B | AC70: No | AD70: Tenant break on 6 months notice. 2 months rent free @ 15/07/27 if not exercised.
A71: UNIT | C71: SH | D71: MEL | E71: 550470 | F71: Portland House, 4 Great Portland Street | G71: Fourth Floor (West) | H71: Office | I71: 1548 | J71: =H71 -> Office | K71: 1500 | L71: Racoon Media Services Limited | M71: 45609 | N71: 47434 | Q71: 46703 | R71: 90090 | S71: =Q71 -> 46703 | U71: 90100 | V71: =T71 -> 0 | W71: 104500 | X71: =V71 -> 0 | Y71: =T71/H71 -> #VALUE! | Z71: B | AC71: No | AD71: Tenant break on 6 months notice. Rent PA corrected.
A72: UNIT | C72: SH | D72: MEL | E72: 550470 | F72: Portland House, 4 Great Portland Street | G72: Fourth Floor (East) | H72: Office | I72: 1957 | J72: =H72 -> Office | K72: 2000 | L72: Racoon Media Services Limited | M72: 45609 | N72: 47434 | Q72: 46703 | R72: 114253 | S72: =Q72 -> 46703 | U72: 115800 | V72: =T72 -> 0 | W72: 132100 | X72: =V72 -> 0 | Y72: =T72/H72 -> #VALUE! | Z72: B | AC72: No | AD72: Tenant break on 6 months notice.
A73: UNIT | C73: SH | D73: MEL | E73: 550470 | F73: Portland House, 4 Great Portland Street | G73: Fifth Floor (East) | H73: Office | I73: 1845 | J73: =H73 -> Office | K73: 2000 | L73: Greek National Tourism Organisation. | M73: 45256 | N73: 47082 | Q73: 46351 | R73: 115500 | S73: =Q73 -> 46351 | U73: 107400 | V73: =T73 -> 0 | W73: 124500 | X73: =V73 -> 0 | Y73: =T73/H73 -> #VALUE! | Z73: B | AC73: No | AD73: Tenant break on 6 months notice.
A74: UNIT | C74: SH | D74: MEL | E74: 550470 | F74: Portland House, 4 Great Portland Street | G74: Fifth Floor (West) | H74: Office | I74: 1528 | J74: =H74 -> Office | K74: 1500 | L74: Rios Designs Ltd | M74: 45622 | N74: 47447 | Q74: 46716 | R74: 54340 | S74: =Q74 -> 46716 | U74: 76600 | V74: =T74 -> 0 | W74: 103100 | X74: =V74 -> 0 | Y74: =T74/H74 -> #VALUE! | Z74: B | AC74: No | AD74: Rent increases to £108,680 wef 26/11/25. Tenant break on 6 months notice. | AG74: 1 | AH74: LEM/LDG
A75: UNIT | C75: SH | D75: MEL | E75: 550470 | F75: Portland House, 4 Great Portland Street | G75: Sixth Floor (West) | H75: Office | I75: 1253 | J75: =H75 -> Office | K75: 1250 | L75: Directors Cut Films West Limited | M75: 45617 | N75: 47442 | R75: 66700 | S75: =Q75 -> 0 | U75: 66700 | V75: =T75 -> 0 | W75: 78300 | X75: =V75 -> 0 | Y75: =T75/H75 -> #VALUE! | Z75: D | AC75: No
A76: UNIT | C76: SH | D76: MEL | E76: 550470 | F76: Portland House, 4 Great Portland Street | G76: Sixth Floor (East) | H76: Office | I76: 859 | J76: =H76 -> Office | K76: 1000 | L76: Vacant | O76: 44609 | R76: 0 | S76: =Q76 -> 0 | U76: 65750 | V76: =T76 -> 0 | W76: 53700 | X76: =V76 -> 0 | Y76: =T76/H76 -> #VALUE! | Z76: D | AC76: No | AD76: LEM marketing. | AE76: 63 | AG76: 1
A77: UNIT | C77: SH | D77: MEL | E77: 550470 | F77: Portland House, 4 Great Portland Street | G77: Cupboards 2nd, 4th, 5th & 6th Floors | H77: Storage | I77: 0 | J77: =H77 -> Storage | L77: Vacant / Landlord | O77: N/A | R77: 0 | S77: =Q77 -> 0 | U77: 1460 | V77: =T77 -> 0 | W77: 0 | X77: =V77 -> 0 | AD77: To be converted into extra toilet facilities.
A78: UNIT | C78: SH | D78: MEL | E78: 550470 | F78: Portland House, 4 Great Portland Street | G78: Transformer Chamber | H78: Sub-Station | I78: 0 | J78: =H78 -> Sub-Station | L78: London Power Networks Plc | M78: 35240 | N78: 68735 | R78: 0 | S78: =Q78 -> 0 | U78: 0 | V78: =T78 -> 0 | W78: 0 | X78: =V78 -> 0 | AC78: Yes | AD78: Rolling redevelopment break on 6 months notice.
D79: MEL
D80: MEL | G80: 4 Great Portland Street | I80: =SUM(H62:H78) -> 0 | R80: =SUM(Q62:Q78) -> 421353 | T80: =SUM(R62:R78) -> 1582568 | U80: =SUM(T62:T78) -> 0 | W80: =SUM(V62:V78) -> 0 | AB80: 34025000
D81: MEL
A82: BUILD | D82: MEL | H82: 6-10a Great Portland Street
D83: MEL
A84: UNIT | C84: SH | D84: MEL | E84: 550480 | F84: 6-10a Great Portland Street | G84: Basement & Ground | H84: Retail | I84: 4958 | J84: =H84 -> Retail | K84: 5000 | L84: PrettyLittleThing.com | M84: 45699 | N84: 47524 | Q84: 46793 | R84: 0 | S84: =Q84 -> 46793 | U84: 337100 | V84: =T84 -> 0 | W84: 380000 | X84: =V84 -> 0 | Y84: =T84/H84 -> #VALUE! | Z84: B | AC84: No | AD84: Rent £187,500 wef 11/05/25 increasing to £375,000 wef 11/09/25. Tenant break on 6 months notice. 3 months rent free if not exercised. | AE84: 68 | AF84: 1 | AG84: 13 | AH84: LEM / Colliers
A85: UNIT | C85: SH | D85: MEL | E85: 550480 | F85: 6-10a Great Portland Street | G85: First Floor | H85: Office | I85: 1862 | J85: =H85 -> Office | K85: 2000 | L85: The Yuki Clinic Ltd. | M85: 44452 | N85: 46277 | R85: 108170 | S85: =Q85 -> 0 | U85: 107200 | V85: =T85 -> 0 | W85: 114500 | X85: =V85 -> 0 | Y85: =T85/H85 -> #VALUE! | Z85: D | AC85: No
A86: UNIT | C86: SH | D86: MEL | E86: 550480 | F86: 6-10a Great Portland Street | G86: Second Floor | H86: Office | I86: 1818 | J86: =H86 -> Office | K86: 2000 | L86: Vacant | O86: 45609 | R86: 0 | S86: =Q86 -> 0 | U86: 105500 | V86: =T86 -> 0 | W86: 109100 | X86: =V86 -> 0 | Y86: =T86/H86 -> #VALUE! | Z86: E | AC86: No | AD86: LEM marketing. | AE86: 65
A87: UNIT | C87: SH | D87: MEL | E87: 550480 | F87: 6-10a Great Portland Street | G87: Third Floor | H87: Office | I87: 1808 | J87: =H87 -> Office | K87: 2000 | L87: Vacant | O87: 45609 | R87: 0 | S87: =Q87 -> 0 | U87: 108800 | V87: =T87 -> 0 | W87: 108500 | X87: =V87 -> 0 | Y87: =T87/H87 -> #VALUE! | Z87: E | AC87: No | AD87: LEM marketing. | AE87: 65
A88: UNIT | C88: SH | D88: MEL | E88: 550480 | F88: 6-10a Great Portland Street | G88: Fourth Floor | H88: Office | I88: 1672 | J88: =H88 -> Office | K88: 1500 | L88: Vacant | O88: 45457 | R88: 0 | S88: =Q88 -> 0 | U88: 94400 | V88: =T88 -> 0 | W88: 97800 | X88: =V88 -> 0 | Y88: =T88/H88 -> #VALUE! | Z88: B | AC88: No | AD88: To be refurbished. | AE88: 65 | AF88: 1 | AG88: 2 | AH88: LEM
A89: UNIT | C89: SH | D89: MEL | E89: 550480 | F89: 6-10a Great Portland Street | G89: Fifth Floor | H89: Office | I89: 995 | J89: =H89 -> Office | K89: 1000 | L89: Racoon Media Services Limited | M89: 45609 | N89: 47434 | Q89: 46703 | R89: 61928 | S89: =Q89 -> 46703 | U89: 61200 | V89: =T89 -> 0 | W89: 57200 | X89: =V89 -> 0 | Y89: =T89/H89 -> #VALUE! | Z89: E | AC89: No | AD89: Tenant break on 6 months notice.
A90: UNIT | C90: SH | D90: MEL | E90: 550480 | F90: 6-10a Great Portland Street | G90: Basement | H90: Sub-Station | I90: 0 | J90: =H90 -> Sub-Station | L90: London Power Networks Plc | M90: 39295 | N90: 46599 | P90: 44409 | R90: 677 | S90: =Q90 -> 0 | U90: 625 | V90: =T90 -> 0 | W90: 625 | X90: =V90 -> 0 | AC90: No | AD90: Landlords redevelopment break on 6 months notice. Rent review is RPI indexation.
D91: MEL
D92: MEL | G92: 6/10a Great Portland Street | I92: =SUM(H84:H90) -> 0 | R92: =SUM(Q84:Q90) -> 93496 | T92: =SUM(R83:R90) -> 170775 | U92: =SUM(T84:T90) -> 0 | W92: =SUM(V84:V90) -> 0 | AB92: 13775000
D93: MEL
A94: BUILD | D94: MEL | H94: 15-17 Great Portland Street & 6-7 Great Castle Street
D95: MEL
A96: UNIT | C96: SH | D96: MEL | E96: 550530 | F96: 15-17 Great Portland Street & 6-7 Great Castle Street | G96: Whole Building | H96: Office/Bank | I96: 9884 | J96: =H96 -> Office/Bank | K96: 10000 | L96: Barclays Bank UK Plc | M96: 44856 | N96: 47411 | P96: 46682 | R96: 580000 | S96: =Q96 -> 0 | T96: =R96 -> 580000 | U96: 580000 | V96: =T96 -> 580000 | W96: 607100 | X96: =V96 -> 580000 | Y96: =T96/H96 -> #VALUE! | Z96: B | AB96: 10650000 | AC96: Yes
D97: MEL | G97: 15/17 Great Portland Street | I97: =SUM(H96:H96) -> 0 | R97: =SUM(Q96:Q96) -> 0 | U97: =SUM(T96:T96) -> 580000 | W97: =SUM(V96:V96) -> 580000
D98: MEL
A99: BUILD | D99: MEL | H99: 19-21 Great Portland Street
D100: MEL
A101: UNIT | C101: CD | D101: MEL | E101: 550410 | F101: 19-21 Great Portland Street . | G101: Basement, Ground & First Floors | H101: Restaurant | I101: 11225 | J101: =H101 -> Restaurant | K101: 10000 | L101: UK VAP GPS | M101: 44729 | N101: 50207 | P101: 46555 | Q101: 48381 | R101: 625000 | S101: =Q101 -> 48381 | U101: 750000 | V101: =T101 -> 0 | W101: 650000 | X101: =V101 -> 0 | Y101: =T101/H101 -> #VALUE! | Z101: B | AC101: No | AD101: Rent increasing to £650,000 wef 25/03/26. Mutual break @ 16/06/32 on 6 months notice.
A102: UNIT | C102: CD | D102: MEL | E102: 550410 | F102: 19-21 Great Portland Street . | G102: Second Floor. | H102: Offices | I102: 2847 | J102: =H102 -> Offices | K102: 3000 | L102: Vacant | O102: 45219 | R102: 0 | S102: =Q102 -> 0 | U102: 170000 | V102: =T102 -> 0 | W102: 185100 | X102: =V102 -> 0 | Y102: =T102/H102 -> #VALUE! | Z102: B | AC102: No | AD102: LEM marketing. | AE102: 70 | AG102: 7 | AH102: LEM / Savills
A103: UNIT | C103: CD | D103: MEL | E103: 550410 | F103: 19-21 Great Portland Street . | G103: Third Floor | H103: Offices | I103: 2651 | J103: =H103 -> Offices | K103: 2500 | L103: Vacant | O103: 44124 | R103: 0 | S103: =Q103 -> 0 | U103: 172000 | V103: =T103 -> 0 | W103: 181600 | X103: =V103 -> 0 | Y103: =T103/H103 -> #VALUE! | Z103: B | AC103: No | AD103: LEM marketing. | AE103: 72.5 | AG103: 7 | AH103: LEM / Savills
...

Sheet Voids Tab
B3: Surveyor | C3: Client | D3: Property Number | E3: Property | F3: Unit Demise | G3: Unit Type | H3: Net Area | I3: . | J3: Tenant Name | K3: Start Date | L3: Expiry Date | M3: Vacant Since? | N3: RRs | O3: Break Date | P3: Rent PA (£) | Q3: check 1 | R3: check 2 | S3: 2023 ERV (£) | T3: check 3 | U3: 2024 ERV (£) | V3: check 4 | W3: ERV 2023 £.Sq.ft | X3: EPC | Y3: * | Z3: 2024 Cap Valn. (£) | AA3: 1954 Act Protected | AB3: Remarks | AC3: Agency Quoting Rent £.sq.ft | AD3: Monthly Viewings | AE3: Total Viewings | AF3: Marketing Agent
A4: {=IFERROR(INDEX('Bank Schedule'!A:A, SMALL(IF('Bank Schedule'!$K$2:$K$825="Vacant", ROW('Bank Schedule'!$K$2:$K$825)), ROW(1:1))), "")} | B4: {=IFERROR(INDEX('Bank Schedule'!B:B, SMALL(IF('Bank Schedule'!$K$2:$K$825="Vacant", ROW('Bank Schedule'!$K$2:$K$825)), ROW(1:1))), "")} | C4: {=IFERROR(INDEX('Bank Schedule'!C:C, SMALL(IF('Bank Schedule'!$K$2:$K$825="Vacant", ROW('Bank Schedule'!$K$2:$K$825)), ROW(1:1))), "")} | D4: {=IFERROR(INDEX('Bank Schedule'!D:D, SMALL(IF('Bank Schedule'!$K$2:$K$825="Vacant", ROW('Bank Schedule'!$K$2:$K$825)), ROW(1:1))), "")} | E4: {=IFERROR(INDEX('Bank Schedule'!E:E, SMALL(IF('Bank Schedule'!$K$2:$K$825="Vacant", ROW('Bank Schedule'!$K$2:$K$825)), ROW(1:1))), "")} | F4: {=IFERROR(INDEX('Bank Schedule'!F:F, SMALL(IF('Bank Schedule'!$K$2:$K$825="Vacant", ROW('Bank Schedule'!$K$2:$K$825)), ROW(1:1))), "")} | G4: {=IFERROR(INDEX('Bank Schedule'!G:G, SMALL(IF('Bank Schedule'!$K$2:$K$825="Vacant", ROW('Bank Schedule'!$K$2:$K$825)), ROW(1:1))), "")} | H4: {=IFERROR(INDEX('Bank Schedule'!H:H, SMALL(IF('Bank Schedule'!$K$2:$K$825="Vacant", ROW('Bank Schedule'!$K$2:$K$825)), ROW(1:1))), "")} | I4: {=IFERROR(INDEX('Bank Schedule'!I:I, SMALL(IF('Bank Schedule'!$K$2:$K$825="Vacant", ROW('Bank Schedule'!$K$2:$K$825)), ROW(1:1))), "")} | J4: {=IFERROR(INDEX('Bank Schedule'!K:K, SMALL(IF('Bank Schedule'!$K$2:$K$825="Vacant", ROW('Bank Schedule'!$K$2:$K$825)), ROW(1:1))), "")} | K4: {=IFERROR(INDEX('Bank Schedule'!L:L, SMALL(IF('Bank Schedule'!$K$2:$K$825="Vacant", ROW('Bank Schedule'!$K$2:$K$825)), ROW(1:1))), "")} | L4: {=IFERROR(INDEX('Bank Schedule'!M:M, SMALL(IF('Bank Schedule'!$K$2:$K$825="Vacant", ROW('Bank Schedule'!$K$2:$K$825)), ROW(1:1))), "")} | M4: {=IFERROR(INDEX('Bank Schedule'!N:N, SMALL(IF('Bank Schedule'!$K$2:$K$825="Vacant", ROW('Bank Schedule'!$K$2:$K$825)), ROW(1:1))), "")} | N4: {=IFERROR(INDEX('Bank Schedule'!O:O, SMALL(IF('Bank Schedule'!$K$2:$K$825="Vacant", ROW('Bank Schedule'!$K$2:$K$825)), ROW(1:1))), "")} | O4: {=IFERROR(INDEX('Bank Schedule'!P:P, SMALL(IF('Bank Schedule'!$K$2:$K$825="Vacant", ROW('Bank Schedule'!$K$2:$K$825)), ROW(1:1))), "")} | P4: {=IFERROR(INDEX('Bank Schedule'!Q:Q, SMALL(IF('Bank Schedule'!$K$2:$K$825="Vacant", ROW('Bank Schedule'!$K$2:$K$825)), ROW(1:1))), "")} | Q4: {=IFERROR(INDEX('Bank Schedule'!R:R, SMALL(IF('Bank Schedule'!$K$2:$K$825="Vacant", ROW('Bank Schedule'!$K$2:$K$825)), ROW(1:1))), "")} | R4: {=IFERROR(INDEX('Bank Schedule'!S:S, SMALL(IF('Bank Schedule'!$K$2:$K$825="Vacant", ROW('Bank Schedule'!$K$2:$K$825)), ROW(1:1))), "")} | S4: {=IFERROR(INDEX('Bank Schedule'!T:T, SMALL(IF('Bank Schedule'!$K$2:$K$825="Vacant", ROW('Bank Schedule'!$K$2:$K$825)), ROW(1:1))), "")} | T4: {=IFERROR(INDEX('Bank Schedule'!U:U, SMALL(IF('Bank Schedule'!$K$2:$K$825="Vacant", ROW('Bank Schedule'!$K$2:$K$825)), ROW(1:1))), "")} | U4: {=IFERROR(INDEX('Bank Schedule'!V:V, SMALL(IF('Bank Schedule'!$K$2:$K$825="Vacant", ROW('Bank Schedule'!$K$2:$K$825)), ROW(1:1))), "")} | V4: {=IFERROR(INDEX('Bank Schedule'!W:W, SMALL(IF('Bank Schedule'!$K$2:$K$825="Vacant", ROW('Bank Schedule'!$K$2:$K$825)), ROW(1:1))), "")} | W4: {=IFERROR(INDEX('Bank Schedule'!X:X, SMALL(IF('Bank Schedule'!$K$2:$K$825="Vacant", ROW('Bank Schedule'!$K$2:$K$825)), ROW(1:1))), "")} | X4: {=IFERROR(INDEX('Bank Schedule'!Y:Y, SMALL(IF('Bank Schedule'!$K$2:$K$825="Vacant", ROW('Bank Schedule'!$K$2:$K$825)), ROW(1:1))), "")} | Y4: {=IFERROR(INDEX('Bank Schedule'!Z:Z, SMALL(IF('Bank Schedule'!$K$2:$K$825="Vacant", ROW('Bank Schedule'!$K$2:$K$825)), ROW(1:1))), "")} | Z4: {=IFERROR(INDEX('Bank Schedule'!AA:AA, SMALL(IF('Bank Schedule'!$K$2:$K$825="Vacant", ROW('Bank Schedule'!$K$2:$K$825)), ROW(1:1))), "")} | AA4: {=IFERROR(INDEX('Bank Schedule'!AB:AB, SMALL(IF('Bank Schedule'!$K$2:$K$825="Vacant", ROW('Bank Schedule'!$K$2:$K$825)), ROW(1:1))), "")} | AB4: {=IFERROR(INDEX('Bank Schedule'!AC:AC, SMALL(IF('Bank Schedule'!$K$2:$K$825="Vacant", ROW('Bank Schedule'!$K$2:$K$825)), ROW(1:1))), "")} | AC4: {=IFERROR(INDEX('Bank Schedule'!AD:AD, SMALL(IF('Bank Schedule'!$K$2:$K$825="Vacant", ROW('Bank Schedule'!$K$2:$K$825)), ROW(1:1))), "")} | AD4: {=IFERROR(INDEX('Bank Schedule'!AE:AE, SMALL(IF('Bank Schedule'!$K$2:$K$825="Vacant", ROW('Bank Schedule'!$K$2:$K$825)), ROW(1:1))), "")} | AE4: {=IFERROR(INDEX('Bank Schedule'!AF:AF, SMALL(IF('Bank Schedule'!$K$2:$K$825="Vacant", ROW('Bank Schedule'!$K$2:$K$825)), ROW(1:1))), "")}
A5: {=IFERROR(INDEX('Bank Schedule'!A:A, SMALL(IF('Bank Schedule'!$K$2:$K$825="Vacant", ROW('Bank Schedule'!$K$2:$K$825)), ROW(2:2))), "")} | B5: {=IFERROR(INDEX('Bank Schedule'!B:B, SMALL(IF('Bank Schedule'!$K$2:$K$825="Vacant", ROW('Bank Schedule'!$K$2:$K$825)), ROW(2:2))), "")} | C5: {=IFERROR(INDEX('Bank Schedule'!C:C, SMALL(IF('Bank Schedule'!$K$2:$K$825="Vacant", ROW('Bank Schedule'!$K$2:$K$825)), ROW(2:2))), "")} | D5: {=IFERROR(INDEX('Bank Schedule'!D:D, SMALL(IF('Bank Schedule'!$K$2:$K$825="Vacant", ROW('Bank Schedule'!$K$2:$K$825)), ROW(2:2))), "")} | E5: {=IFERROR(INDEX('Bank Schedule'!E:E, SMALL(IF('Bank Schedule'!$K$2:$K$825="Vacant", ROW('Bank Schedule'!$K$2:$K$825)), ROW(2:2))), "")} | F5: {=IFERROR(INDEX('Bank Schedule'!F:F, SMALL(IF('Bank Schedule'!$K$2:$K$825="Vacant", ROW('Bank Schedule'!$K$2:$K$825)), ROW(2:2))), "")} | G5: {=IFERROR(INDEX('Bank Schedule'!G:G, SMALL(IF('Bank Schedule'!$K$2:$K$825="Vacant", ROW('Bank Schedule'!$K$2:$K$825)), ROW(2:2))), "")} | H5: {=IFERROR(INDEX('Bank Schedule'!H:H, SMALL(IF('Bank Schedule'!$K$2:$K$825="Vacant", ROW('Bank Schedule'!$K$2:$K$825)), ROW(2:2))), "")} | I5: {=IFERROR(INDEX('Bank Schedule'!I:I, SMALL(IF('Bank Schedule'!$K$2:$K$825="Vacant", ROW('Bank Schedule'!$K$2:$K$825)), ROW(2:2))), "")} | J5: {=IFERROR(INDEX('Bank Schedule'!K:K, SMALL(IF('Bank Schedule'!$K$2:$K$825="Vacant", ROW('Bank Schedule'!$K$2:$K$825)), ROW(2:2))), "")} | K5: {=IFERROR(INDEX('Bank Schedule'!L:L, SMALL(IF('Bank Schedule'!$K$2:$K$825="Vacant", ROW('Bank Schedule'!$K$2:$K$825)), ROW(2:2))), "")} | L5: {=IFERROR(INDEX('Bank Schedule'!M:M, SMALL(IF('Bank Schedule'!$K$2:$K$825="Vacant", ROW('Bank Schedule'!$K$2:$K$825)), ROW(2:2))), "")} | M5: {=IFERROR(INDEX('Bank Schedule'!N:N, SMALL(IF('Bank Schedule'!$K$2:$K$825="Vacant", ROW('Bank Schedule'!$K$2:$K$825)), ROW(2:2))), "")} | N5: {=IFERROR(INDEX('Bank Schedule'!O:O, SMALL(IF('Bank Schedule'!$K$2:$K$825="Vacant", ROW('Bank Schedule'!$K$2:$K$825)), ROW(2:2))), "")} | O5: {=IFERROR(INDEX('Bank Schedule'!P:P, SMALL(IF('Bank Schedule'!$K$2:$K$825="Vacant", ROW('Bank Schedule'!$K$2:$K$825)), ROW(2:2))), "")} | P5: {=IFERROR(INDEX('Bank Schedule'!Q:Q, SMALL(IF('Bank Schedule'!$K$2:$K$825="Vacant", ROW('Bank Schedule'!$K$2:$K$825)), ROW(2:2))), "")} | Q5: {=IFERROR(INDEX('Bank Schedule'!R:R, SMALL(IF('Bank Schedule'!$K$2:$K$825="Vacant", ROW('Bank Schedule'!$K$2:$K$825)), ROW(2:2))), "")} | R5: {=IFERROR(INDEX('Bank Schedule'!S:S, SMALL(IF('Bank Schedule'!$K$2:$K$825="Vacant", ROW('Bank Schedule'!$K$2:$K$825)), ROW(2:2))), "")} | S5: {=IFERROR(INDEX('Bank Schedule'!T:T, SMALL(IF('Bank Schedule'!$K$2:$K$825="Vacant", ROW('Bank Schedule'!$K$2:$K$825)), ROW(2:2))), "")} | T5: {=IFERROR(INDEX('Bank Schedule'!U:U, SMALL(IF('Bank Schedule'!$K$2:$K$825="Vacant", ROW('Bank Schedule'!$K$2:$K$825)), ROW(2:2))), "")} | U5: {=IFERROR(INDEX('Bank Schedule'!V:V, SMALL(IF('Bank Schedule'!$K$2:$K$825="Vacant", ROW('Bank Schedule'!$K$2:$K$825)), ROW(2:2))), "")} | V5: {=IFERROR(INDEX('Bank Schedule'!W:W, SMALL(IF('Bank Schedule'!$K$2:$K$825="Vacant", ROW('Bank Schedule'!$K$2:$K$825)), ROW(2:2))), "")} | W5: {=IFERROR(INDEX('Bank Schedule'!X:X, SMALL(IF('Bank Schedule'!$K$2:$K$825="Vacant", ROW('Bank Schedule'!$K$2:$K$825)), ROW(2:2))), "")} | X5: {=IFERROR(INDEX('Bank Schedule'!Y:Y, SMALL(IF('Bank Schedule'!$K$2:$K$825="Vacant", ROW('Bank Schedule'!$K$2:$K$825)), ROW(2:2))), "")} | Y5: {=IFERROR(INDEX('Bank Schedule'!Z:Z, SMALL(IF('Bank Schedule'!$K$2:$K$825="Vacant", ROW('Bank Schedule'!$K$2:$K$825)), ROW(2:2))), "")} | Z5: {=IFERROR(INDEX('Bank Schedule'!AA:AA, SMALL(IF('Bank Schedule'!$K$2:$K$825="Vacant", ROW('Bank Schedule'!$K$2:$K$825)), ROW(2:2))), "")} | AA5: {=IFERROR(INDEX('Bank Schedule'!AB:AB, SMALL(IF('Bank Schedule'!$K$2:$K$825="Vacant", ROW('Bank Schedule'!$K$2:$K$825)), ROW(2:2))), "")} | AB5: {=IFERROR(INDEX('Bank Schedule'!AC:AC, SMALL(IF('Bank Schedule'!$K$2:$K$825="Vacant", ROW('Bank Schedule'!$K$2:$K$825)), ROW(2:2))), "")} | AC5: {=IFERROR(INDEX('Bank Schedule'!AD:AD, SMALL(IF('Bank Schedule'!$K$2:$K$825="Vacant", ROW('Bank Schedule'!$K$2:$K$825)), ROW(2:2))), "")} | AD5: {=IFERROR(INDEX('Bank Schedule'!AE:AE, SMALL(IF('Bank Schedule'!$K$2:$K$825="Vacant", ROW('Bank Schedule'!$K$2:$K$825)), ROW(2:2))), "")} | AE5: {=IFERROR(INDEX('Bank Schedule'!AF:AF, SMALL(IF('Bank Schedule'!$K$2:$K$825="Vacant", ROW('Bank Schedule'!$K$2:$K$825)), ROW(2:2))), "")} | AF5: {=IFERROR(INDEX('Bank Schedule'!AG:AG, SMALL(IF('Bank Schedule'!$K$2:$K$825="Vacant", ROW('Bank Schedule'!$K$2:$K$825)), ROW(2:2))), "")}
A6: {=IFERROR(INDEX('Bank Schedule'!A:A, SMALL(IF('Bank Schedule'!$K$2:$K$825="Vacant", ROW('Bank Schedule'!$K$2:$K$825)), ROW(3:3))), "")} | B6: {=IFERROR(INDEX('Bank Schedule'!B:B, SMALL(IF('Bank Schedule'!$K$2:$K$825="Vacant", ROW('Bank Schedule'!$K$2:$K$825)), ROW(3:3))), "")} | C6: {=IFERROR(INDEX('Bank Schedule'!C:C, SMALL(IF('Bank Schedule'!$K$2:$K$825="Vacant", ROW('Bank Schedule'!$K$2:$K$825)), ROW(3:3))), "")} | D6: {=IFERROR(INDEX('Bank Schedule'!D:D, SMALL(IF('Bank Schedule'!$K$2:$K$825="Vacant", ROW('Bank Schedule'!$K$2:$K$825)), ROW(3:3))), "")} | E6: {=IFERROR(INDEX('Bank Schedule'!E:E, SMALL(IF('Bank Schedule'!$K$2:$K$825="Vacant", ROW('Bank Schedule'!$K$2:$K$825)), ROW(3:3))), "")} | F6: {=IFERROR(INDEX('Bank Schedule'!F:F, SMALL(IF('Bank Schedule'!$K$2:$K$825="Vacant", ROW('Bank Schedule'!$K$2:$K$825)), ROW(3:3))), "")} | G6: {=IFERROR(INDEX('Bank Schedule'!G:G, SMALL(IF('Bank Schedule'!$K$2:$K$825="Vacant", ROW('Bank Schedule'!$K$2:$K$825)), ROW(3:3))), "")} | H6: {=IFERROR(INDEX('Bank Schedule'!H:H, SMALL(IF('Bank Schedule'!$K$2:$K$825="Vacant", ROW('Bank Schedule'!$K$2:$K$825)), ROW(3:3))), "")} | I6: {=IFERROR(INDEX('Bank Schedule'!I:I, SMALL(IF('Bank Schedule'!$K$2:$K$825="Vacant", ROW('Bank Schedule'!$K$2:$K$825)), ROW(3:3))), "")} | J6: {=IFERROR(INDEX('Bank Schedule'!K:K, SMALL(IF('Bank Schedule'!$K$2:$K$825="Vacant", ROW('Bank Schedule'!$K$2:$K$825)), ROW(3:3))), "")} | K6: {=IFERROR(INDEX('Bank Schedule'!L:L, SMALL(IF('Bank Schedule'!$K$2:$K$825="Vacant", ROW('Bank Schedule'!$K$2:$K$825)), ROW(3:3))), "")} | L6: {=IFERROR(INDEX('Bank Schedule'!M:M, SMALL(IF('Bank Schedule'!$K$2:$K$825="Vacant", ROW('Bank Schedule'!$K$2:$K$825)), ROW(3:3))), "")} | M6: {=IFERROR(INDEX('Bank Schedule'!N:N, SMALL(IF('Bank Schedule'!$K$2:$K$825="Vacant", ROW('Bank Schedule'!$K$2:$K$825)), ROW(3:3))), "")} | N6: {=IFERROR(INDEX('Bank Schedule'!O:O, SMALL(IF('Bank Schedule'!$K$2:$K$825="Vacant", ROW('Bank Schedule'!$K$2:$K$825)), ROW(3:3))), "")} | O6: {=IFERROR(INDEX('Bank Schedule'!P:P, SMALL(IF('Bank Schedule'!$K$2:$K$825="Vacant", ROW('Bank Schedule'!$K$2:$K$825)), ROW(3:3))), "")} | P6: {=IFERROR(INDEX('Bank Schedule'!Q:Q, SMALL(IF('Bank Schedule'!$K$2:$K$825="Vacant", ROW('Bank Schedule'!$K$2:$K$825)), ROW(3:3))), "")} | Q6: {=IFERROR(INDEX('Bank Schedule'!R:R, SMALL(IF('Bank Schedule'!$K$2:$K$825="Vacant", ROW('Bank Schedule'!$K$2:$K$825)), ROW(3:3))), "")} | R6: {=IFERROR(INDEX('Bank Schedule'!S:S, SMALL(IF('Bank Schedule'!$K$2:$K$825="Vacant", ROW('Bank Schedule'!$K$2:$K$825)), ROW(3:3))), "")} | S6: {=IFERROR(INDEX('Bank Schedule'!T:T, SMALL(IF('Bank Schedule'!$K$2:$K$825="Vacant", ROW('Bank Schedule'!$K$2:$K$825)), ROW(3:3))), "")} | T6: {=IFERROR(INDEX('Bank Schedule'!U:U, SMALL(IF('Bank Schedule'!$K$2:$K$825="Vacant", ROW('Bank Schedule'!$K$2:$K$825)), ROW(3:3))), "")} | U6: {=IFERROR(INDEX('Bank Schedule'!V:V, SMALL(IF('Bank Schedule'!$K$2:$K$825="Vacant", ROW('Bank Schedule'!$K$2:$K$825)), ROW(3:3))), "")} | V6: {=IFERROR(INDEX('Bank Schedule'!W:W, SMALL(IF('Bank Schedule'!$K$2:$K$825="Vacant", ROW('Bank Schedule'!$K$2:$K$825)), ROW(3:3))), "")} | W6: {=IFERROR(INDEX('Bank Schedule'!X:X, SMALL(IF('Bank Schedule'!$K$2:$K$825="Vacant", ROW('Bank Schedule'!$K$2:$K$825)), ROW(3:3))), "")} | X6: {=IFERROR(INDEX('Bank Schedule'!Y:Y, SMALL(IF('Bank Schedule'!$K$2:$K$825="Vacant", ROW('Bank Schedule'!$K$2:$K$825)), ROW(3:3))), "")} | Y6: {=IFERROR(INDEX('Bank Schedule'!Z:Z, SMALL(IF('Bank Schedule'!$K$2:$K$825="Vacant", ROW('Bank Schedule'!$K$2:$K$825)), ROW(3:3))), "")} | Z6: {=IFERROR(INDEX('Bank Schedule'!AA:AA, SMALL(IF('Bank Schedule'!$K$2:$K$825="Vacant", ROW('Bank Schedule'!$K$2:$K$825)), ROW(3:3))), "")} | AA6: {=IFERROR(INDEX('Bank Schedule'!AB:AB, SMALL(IF('Bank Schedule'!$K$2:$K$825="Vacant", ROW('Bank Schedule'!$K$2:$K$825)), ROW(3:3))), "")} | AB6: {=IFERROR(INDEX('Bank Schedule'!AC:AC, SMALL(IF('Bank Schedule'!$K$2:$K$825="Vacant", ROW('Bank Schedule'!$K$2:$K$825)), ROW(3:3))), "")} | AC6: {=IFERROR(INDEX('Bank Schedule'!AD:AD, SMALL(IF('Bank Schedule'!$K$2:$K$825="Vacant", ROW('Bank Schedule'!$K$2:$K$825)), ROW(3:3))), "")} | AD6: {=IFERROR(INDEX('Bank Schedule'!AE:AE, SMALL(IF('Bank Schedule'!$K$2:$K$825="Vacant", ROW('Bank Schedule'!$K$2:$K$825)), ROW(3:3))), "")} | AE6: {=IFERROR(INDEX('Bank Schedule'!AF:AF, SMALL(IF('Bank Schedule'!$K$2:$K$825="Vacant", ROW('Bank Schedule'!$K$2:$K$825)), ROW(3:3))), "")}
A7: {=IFERROR(INDEX('Bank Schedule'!A:A, SMALL(IF('Bank Schedule'!$K$2:$K$825="Vacant", ROW('Bank Schedule'!$K$2:$K$825)), ROW(4:4))), "")} | B7: {=IFERROR(INDEX('Bank Schedule'!B:B, SMALL(IF('Bank Schedule'!$K$2:$K$825="Vacant", ROW('Bank Schedule'!$K$2:$K$825)), ROW(4:4))), "")} | C7: {=IFERROR(INDEX('Bank Schedule'!C:C, SMALL(IF('Bank Schedule'!$K$2:$K$825="Vacant", ROW('Bank Schedule'!$K$2:$K$825)), ROW(4:4))), "")} | D7: {=IFERROR(INDEX('Bank Schedule'!D:D, SMALL(IF('Bank Schedule'!$K$2:$K$825="Vacant", ROW('Bank Schedule'!$K$2:$K$825)), ROW(4:4))), "")} | E7: {=IFERROR(INDEX('Bank Schedule'!E:E, SMALL(IF('Bank Schedule'!$K$2:$K$825="Vacant", ROW('Bank Schedule'!$K$2:$K$825)), ROW(4:4))), "")} | F7: {=IFERROR(INDEX('Bank Schedule'!F:F, SMALL(IF('Bank Schedule'!$K$2:$K$825="Vacant", ROW('Bank Schedule'!$K$2:$K$825)), ROW(4:4))), "")} | G7: {=IFERROR(INDEX('Bank Schedule'!G:G, SMALL(IF('Bank Schedule'!$K$2:$K$825="Vacant", ROW('Bank Schedule'!$K$2:$K$825)), ROW(4:4))), "")} | H7: {=IFERROR(INDEX('Bank Schedule'!H:H, SMALL(IF('Bank Schedule'!$K$2:$K$825="Vacant", ROW('Bank Schedule'!$K$2:$K$825)), ROW(4:4))), "")} | I7: {=IFERROR(INDEX('Bank Schedule'!I:I, SMALL(IF('Bank Schedule'!$K$2:$K$825="Vacant", ROW('Bank Schedule'!$K$2:$K$825)), ROW(4:4))), "")} | J7: {=IFERROR(INDEX('Bank Schedule'!K:K, SMALL(IF('Bank Schedule'!$K$2:$K$825="Vacant", ROW('Bank Schedule'!$K$2:$K$825)), ROW(4:4))), "")} | K7: {=IFERROR(INDEX('Bank Schedule'!L:L, SMALL(IF('Bank Schedule'!$K$2:$K$825="Vacant", ROW('Bank Schedule'!$K$2:$K$825)), ROW(4:4))), "")} | L7: {=IFERROR(INDEX('Bank Schedule'!M:M, SMALL(IF('Bank Schedule'!$K$2:$K$825="Vacant", ROW('Bank Schedule'!$K$2:$K$825)), ROW(4:4))), "")} | M7: {=IFERROR(INDEX('Bank Schedule'!N:N, SMALL(IF('Bank Schedule'!$K$2:$K$825="Vacant", ROW('Bank Schedule'!$K$2:$K$825)), ROW(4:4))), "")} | N7: {=IFERROR(INDEX('Bank Schedule'!O:O, SMALL(IF('Bank Schedule'!$K$2:$K$825="Vacant", ROW('Bank Schedule'!$K$2:$K$825)), ROW(4:4))), "")} | O7: {=IFERROR(INDEX('Bank Schedule'!P:P, SMALL(IF('Bank Schedule'!$K$2:$K$825="Vacant", ROW('Bank Schedule'!$K$2:$K$825)), ROW(4:4))), "")} | P7: {=IFERROR(INDEX('Bank Schedule'!Q:Q, SMALL(IF('Bank Schedule'!$K$2:$K$825="Vacant", ROW('Bank Schedule'!$K$2:$K$825)), ROW(4:4))), "")} | Q7: {=IFERROR(INDEX('Bank Schedule'!R:R, SMALL(IF('Bank Schedule'!$K$2:$K$825="Vacant", ROW('Bank Schedule'!$K$2:$K$825)), ROW(4:4))), "")} | R7: {=IFERROR(INDEX('Bank Schedule'!S:S, SMALL(IF('Bank Schedule'!$K$2:$K$825="Vacant", ROW('Bank Schedule'!$K$2:$K$825)), ROW(4:4))), "")} | S7: {=IFERROR(INDEX('Bank Schedule'!T:T, SMALL(IF('Bank Schedule'!$K$2:$K$825="Vacant", ROW('Bank Schedule'!$K$2:$K$825)), ROW(4:4))), "")} | T7: {=IFERROR(INDEX('Bank Schedule'!U:U, SMALL(IF('Bank Schedule'!$K$2:$K$825="Vacant", ROW('Bank Schedule'!$K$2:$K$825)), ROW(4:4))), "")} | U7: {=IFERROR(INDEX('Bank Schedule'!V:V, SMALL(IF('Bank Schedule'!$K$2:$K$825="Vacant", ROW('Bank Schedule'!$K$2:$K$825)), ROW(4:4))), "")} | V7: {=IFERROR(INDEX('Bank Schedule'!W:W, SMALL(IF('Bank Schedule'!$K$2:$K$825="Vacant", ROW('Bank Schedule'!$K$2:$K$825)), ROW(4:4))), "")} | W7: {=IFERROR(INDEX('Bank Schedule'!X:X, SMALL(IF('Bank Schedule'!$K$2:$K$825="Vacant", ROW('Bank Schedule'!$K$2:$K$825)), ROW(4:4))), "")} | X7: {=IFERROR(INDEX('Bank Schedule'!Y:Y, SMALL(IF('Bank Schedule'!$K$2:$K$825="Vacant", ROW('Bank Schedule'!$K$2:$K$825)), ROW(4:4))), "")} | Y7: {=IFERROR(INDEX('Bank Schedule'!Z:Z, SMALL(IF('Bank Schedule'!$K$2:$K$825="Vacant", ROW('Bank Schedule'!$K$2:$K$825)), ROW(4:4))), "")} | Z7: {=IFERROR(INDEX('Bank Schedule'!AA:AA, SMALL(IF('Bank Schedule'!$K$2:$K$825="Vacant", ROW('Bank Schedule'!$K$2:$K$825)), ROW(4:4))), "")} | AA7: {=IFERROR(INDEX('Bank Schedule'!AB:AB, SMALL(IF('Bank Schedule'!$K$2:$K$825="Vacant", ROW('Bank Schedule'!$K$2:$K$825)), ROW(4:4))), "")} | AB7: {=IFERROR(INDEX('Bank Schedule'!AC:AC, SMALL(IF('Bank Schedule'!$K$2:$K$825="Vacant", ROW('Bank Schedule'!$K$2:$K$825)), ROW(4:4))), "")} | AC7: {=IFERROR(INDEX('Bank Schedule'!AD:AD, SMALL(IF('Bank Schedule'!$K$2:$K$825="Vacant", ROW('Bank Schedule'!$K$2:$K$825)), ROW(4:4))), "")} | AD7: {=IFERROR(INDEX('Bank Schedule'!AE:AE, SMALL(IF('Bank Schedule'!$K$2:$K$825="Vacant", ROW('Bank Schedule'!$K$2:$K$825)), ROW(4:4))), "")} | AE7: {=IFERROR(INDEX('Bank Schedule'!AF:AF, SMALL(IF('Bank Schedule'!$K$2:$K$825="Vacant", ROW('Bank Schedule'!$K$2:$K$825)), ROW(4:4))), "")} | AF7: {=IFERROR(INDEX('Bank Schedule'!AG:AG, SMALL(IF('Bank Schedule'!$K$2:$K$825="Vacant", ROW('Bank Schedule'!$K$2:$K$825)), ROW(4:4))), "")}
A8: {=IFERROR(INDEX('Bank Schedule'!A:A, SMALL(IF('Bank Schedule'!$K$2:$K$825="Vacant", ROW('Bank Schedule'!$K$2:$K$825)), ROW(5:5))), "")} | B8: {=IFERROR(INDEX('Bank Schedule'!B:B, SMALL(IF('Bank Schedule'!$K$2:$K$825="Vacant", ROW('Bank Schedule'!$K$2:$K$825)), ROW(5:5))), "")} | C8: {=IFERROR(INDEX('Bank Schedule'!C:C, SMALL(IF('Bank Schedule'!$K$2:$K$825="Vacant", ROW('Bank Schedule'!$K$2:$K$825)), ROW(5:5))), "")} | D8: {=IFERROR(INDEX('Bank Schedule'!D:D, SMALL(IF('Bank Schedule'!$K$2:$K$825="Vacant", ROW('Bank Schedule'!$K$2:$K$825)), ROW(5:5))), "")} | E8: {=IFERROR(INDEX('Bank Schedule'!E:E, SMALL(IF('Bank Schedule'!$K$2:$K$825="Vacant", ROW('Bank Schedule'!$K$2:$K$825)), ROW(5:5))), "")} | F8: {=IFERROR(INDEX('Bank Schedule'!F:F, SMALL(IF('Bank Schedule'!$K$2:$K$825="Vacant", ROW('Bank Schedule'!$K$2:$K$825)), ROW(5:5))), "")} | G8: {=IFERROR(INDEX('Bank Schedule'!G:G, SMALL(IF('Bank Schedule'!$K$2:$K$825="Vacant", ROW('Bank Schedule'!$K$2:$K$825)), ROW(5:5))), "")} | H8: {=IFERROR(INDEX('Bank Schedule'!H:H, SMALL(IF('Bank Schedule'!$K$2:$K$825="Vacant", ROW('Bank Schedule'!$K$2:$K$825)), ROW(5:5))), "")} | I8: {=IFERROR(INDEX('Bank Schedule'!I:I, SMALL(IF('Bank Schedule'!$K$2:$K$825="Vacant", ROW('Bank Schedule'!$K$2:$K$825)), ROW(5:5))), "")} | J8: {=IFERROR(INDEX('Bank Schedule'!K:K, SMALL(IF('Bank Schedule'!$K$2:$K$825="Vacant", ROW('Bank Schedule'!$K$2:$K$825)), ROW(5:5))), "")} | K8: {=IFERROR(INDEX('Bank Schedule'!L:L, SMALL(IF('Bank Schedule'!$K$2:$K$825="Vacant", ROW('Bank Schedule'!$K$2:$K$825)), ROW(5:5))), "")} | L8: {=IFERROR(INDEX('Bank Schedule'!M:M, SMALL(IF('Bank Schedule'!$K$2:$K$825="Vacant", ROW('Bank Schedule'!$K$2:$K$825)), ROW(5:5))), "")} | M8: {=IFERROR(INDEX('Bank Schedule'!N:N, SMALL(IF('Bank Schedule'!$K$2:$K$825="Vacant", ROW('Bank Schedule'!$K$2:$K$825)), ROW(5:5))), "")} | N8: {=IFERROR(INDEX('Bank Schedule'!O:O, SMALL(IF('Bank Schedule'!$K$2:$K$825="Vacant", ROW('Bank Schedule'!$K$2:$K$825)), ROW(5:5))), "")} | O8: {=IFERROR(INDEX('Bank Schedule'!P:P, SMALL(IF('Bank Schedule'!$K$2:$K$825="Vacant", ROW('Bank Schedule'!$K$2:$K$825)), ROW(5:5))), "")} | P8: {=IFERROR(INDEX('Bank Schedule'!Q:Q, SMALL(IF('Bank Schedule'!$K$2:$K$825="Vacant", ROW('Bank Schedule'!$K$2:$K$825)), ROW(5:5))), "")} | Q8: {=IFERROR(INDEX('Bank Schedule'!R:R, SMALL(IF('Bank Schedule'!$K$2:$K$825="Vacant", ROW('Bank Schedule'!$K$2:$K$825)), ROW(5:5))), "")} | R8: {=IFERROR(INDEX('Bank Schedule'!S:S, SMALL(IF('Bank Schedule'!$K$2:$K$825="Vacant", ROW('Bank Schedule'!$K$2:$K$825)), ROW(5:5))), "")} | S8: {=IFERROR(INDEX('Bank Schedule'!T:T, SMALL(IF('Bank Schedule'!$K$2:$K$825="Vacant", ROW('Bank Schedule'!$K$2:$K$825)), ROW(5:5))), "")} | T8: {=IFERROR(INDEX('Bank Schedule'!U:U, SMALL(IF('Bank Schedule'!$K$2:$K$825="Vacant", ROW('Bank Schedule'!$K$2:$K$825)), ROW(5:5))), "")} | U8: {=IFERROR(INDEX('Bank Schedule'!V:V, SMALL(IF('Bank Schedule'!$K$2:$K$825="Vacant", ROW('Bank Schedule'!$K$2:$K$825)), ROW(5:5))), "")} | V8: {=IFERROR(INDEX('Bank Schedule'!W:W, SMALL(IF('Bank Schedule'!$K$2:$K$825="Vacant", ROW('Bank Schedule'!$K$2:$K$825)), ROW(5:5))), "")} | W8: {=IFERROR(INDEX('Bank Schedule'!X:X, SMALL(IF('Bank Schedule'!$K$2:$K$825="Vacant", ROW('Bank Schedule'!$K$2:$K$825)), ROW(5:5))), "")} | X8: {=IFERROR(INDEX('Bank Schedule'!Y:Y, SMALL(IF('Bank Schedule'!$K$2:$K$825="Vacant", ROW('Bank Schedule'!$K$2:$K$825)), ROW(5:5))), "")} | Y8: {=IFERROR(INDEX('Bank Schedule'!Z:Z, SMALL(IF('Bank Schedule'!$K$2:$K$825="Vacant", ROW('Bank Schedule'!$K$2:$K$825)), ROW(5:5))), "")} | Z8: {=IFERROR(INDEX('Bank Schedule'!AA:AA, SMALL(IF('Bank Schedule'!$K$2:$K$825="Vacant", ROW('Bank Schedule'!$K$2:$K$825)), ROW(5:5))), "")} | AA8: {=IFERROR(INDEX('Bank Schedule'!AB:AB, SMALL(IF('Bank Schedule'!$K$2:$K$825="Vacant", ROW('Bank Schedule'!$K$2:$K$825)), ROW(5:5))), "")} | AB8: {=IFERROR(INDEX('Bank Schedule'!AC:AC, SMALL(IF('Bank Schedule'!$K$2:$K$825="Vacant", ROW('Bank Schedule'!$K$2:$K$825)), ROW(5:5))), "")} | AC8: {=IFERROR(INDEX('Bank Schedule'!AD:AD, SMALL(IF('Bank Schedule'!$K$2:$K$825="Vacant", ROW('Bank Schedule'!$K$2:$K$825)), ROW(5:5))), "")} | AD8: {=IFERROR(INDEX('Bank Schedule'!AE:AE, SMALL(IF('Bank Schedule'!$K$2:$K$825="Vacant", ROW('Bank Schedule'!$K$2:$K$825)), ROW(5:5))), "")} | AE8: {=IFERROR(INDEX('Bank Schedule'!AF:AF, SMALL(IF('Bank Schedule'!$K$2:$K$825="Vacant", ROW('Bank Schedule'!$K$2:$K$825)), ROW(5:5))), "")}
A9: {=IFERROR(INDEX('Bank Schedule'!A:A, SMALL(IF('Bank Schedule'!$K$2:$K$825="Vacant", ROW('Bank Schedule'!$K$2:$K$825)), ROW(6:6))), "")} | B9: {=IFERROR(INDEX('Bank Schedule'!B:B, SMALL(IF('Bank Schedule'!$K$2:$K$825="Vacant", ROW('Bank Schedule'!$K$2:$K$825)), ROW(6:6))), "")} | C9: {=IFERROR(INDEX('Bank Schedule'!C:C, SMALL(IF('Bank Schedule'!$K$2:$K$825="Vacant", ROW('Bank Schedule'!$K$2:$K$825)), ROW(6:6))), "")} | D9: {=IFERROR(INDEX('Bank Schedule'!D:D, SMALL(IF('Bank Schedule'!$K$2:$K$825="Vacant", ROW('Bank Schedule'!$K$2:$K$825)), ROW(6:6))), "")} | E9: {=IFERROR(INDEX('Bank Schedule'!E:E, SMALL(IF('Bank Schedule'!$K$2:$K$825="Vacant", ROW('Bank Schedule'!$K$2:$K$825)), ROW(6:6))), "")} | F9: {=IFERROR(INDEX('Bank Schedule'!F:F, SMALL(IF('Bank Schedule'!$K$2:$K$825="Vacant", ROW('Bank Schedule'!$K$2:$K$825)), ROW(6:6))), "")} | G9: {=IFERROR(INDEX('Bank Schedule'!G:G, SMALL(IF('Bank Schedule'!$K$2:$K$825="Vacant", ROW('Bank Schedule'!$K$2:$K$825)), ROW(6:6))), "")} | H9: {=IFERROR(INDEX('Bank Schedule'!H:H, SMALL(IF('Bank Schedule'!$K$2:$K$825="Vacant", ROW('Bank Schedule'!$K$2:$K$825)), ROW(6:6))), "")} | I9: {=IFERROR(INDEX('Bank Schedule'!I:I, SMALL(IF('Bank Schedule'!$K$2:$K$825="Vacant", ROW('Bank Schedule'!$K$2:$K$825)), ROW(6:6))), "")} | J9: {=IFERROR(INDEX('Bank Schedule'!K:K, SMALL(IF('Bank Schedule'!$K$2:$K$825="Vacant", ROW('Bank Schedule'!$K$2:$K$825)), ROW(6:6))), "")} | K9: {=IFERROR(INDEX('Bank Schedule'!L:L, SMALL(IF('Bank Schedule'!$K$2:$K$825="Vacant", ROW('Bank Schedule'!$K$2:$K$825)), ROW(6:6))), "")} | L9: {=IFERROR(INDEX('Bank Schedule'!M:M, SMALL(IF('Bank Schedule'!$K$2:$K$825="Vacant", ROW('Bank Schedule'!$K$2:$K$825)), ROW(6:6))), "")} | M9: {=IFERROR(INDEX('Bank Schedule'!N:N, SMALL(IF('Bank Schedule'!$K$2:$K$825="Vacant", ROW('Bank Schedule'!$K$2:$K$825)), ROW(6:6))), "")} | N9: {=IFERROR(INDEX('Bank Schedule'!O:O, SMALL(IF('Bank Schedule'!$K$2:$K$825="Vacant", ROW('Bank Schedule'!$K$2:$K$825)), ROW(6:6))), "")} | O9: {=IFERROR(INDEX('Bank Schedule'!P:P, SMALL(IF('Bank Schedule'!$K$2:$K$825="Vacant", ROW('Bank Schedule'!$K$2:$K$825)), ROW(6:6))), "")} | P9: {=IFERROR(INDEX('Bank Schedule'!Q:Q, SMALL(IF('Bank Schedule'!$K$2:$K$825="Vacant", ROW('Bank Schedule'!$K$2:$K$825)), ROW(6:6))), "")} | Q9: {=IFERROR(INDEX('Bank Schedule'!R:R, SMALL(IF('Bank Schedule'!$K$2:$K$825="Vacant", ROW('Bank Schedule'!$K$2:$K$825)), ROW(6:6))), "")} | R9: {=IFERROR(INDEX('Bank Schedule'!S:S, SMALL(IF('Bank Schedule'!$K$2:$K$825="Vacant", ROW('Bank Schedule'!$K$2:$K$825)), ROW(6:6))), "")} | S9: {=IFERROR(INDEX('Bank Schedule'!T:T, SMALL(IF('Bank Schedule'!$K$2:$K$825="Vacant", ROW('Bank Schedule'!$K$2:$K$825)), ROW(6:6))), "")} | T9: {=IFERROR(INDEX('Bank Schedule'!U:U, SMALL(IF('Bank Schedule'!$K$2:$K$825="Vacant", ROW('Bank Schedule'!$K$2:$K$825)), ROW(6:6))), "")} | U9: {=IFERROR(INDEX('Bank Schedule'!V:V, SMALL(IF('Bank Schedule'!$K$2:$K$825="Vacant", ROW('Bank Schedule'!$K$2:$K$825)), ROW(6:6))), "")} | V9: {=IFERROR(INDEX('Bank Schedule'!W:W, SMALL(IF('Bank Schedule'!$K$2:$K$825="Vacant", ROW('Bank Schedule'!$K$2:$K$825)), ROW(6:6))), "")} | W9: {=IFERROR(INDEX('Bank Schedule'!X:X, SMALL(IF('Bank Schedule'!$K$2:$K$825="Vacant", ROW('Bank Schedule'!$K$2:$K$825)), ROW(6:6))), "")} | X9: {=IFERROR(INDEX('Bank Schedule'!Y:Y, SMALL(IF('Bank Schedule'!$K$2:$K$825="Vacant", ROW('Bank Schedule'!$K$2:$K$825)), ROW(6:6))), "")} | Y9: {=IFERROR(INDEX('Bank Schedule'!Z:Z, SMALL(IF('Bank Schedule'!$K$2:$K$825="Vacant", ROW('Bank Schedule'!$K$2:$K$825)), ROW(6:6))), "")} | Z9: {=IFERROR(INDEX('Bank Schedule'!AA:AA, SMALL(IF('Bank Schedule'!$K$2:$K$825="Vacant", ROW('Bank Schedule'!$K$2:$K$825)), ROW(6:6))), "")} | AA9: {=IFERROR(INDEX('Bank Schedule'!AB:AB, SMALL(IF('Bank Schedule'!$K$2:$K$825="Vacant", ROW('Bank Schedule'!$K$2:$K$825)), ROW(6:6))), "")} | AB9: {=IFERROR(INDEX('Bank Schedule'!AC:AC, SMALL(IF('Bank Schedule'!$K$2:$K$825="Vacant", ROW('Bank Schedule'!$K$2:$K$825)), ROW(6:6))), "")} | AC9: {=IFERROR(INDEX('Bank Schedule'!AD:AD, SMALL(IF('Bank Schedule'!$K$2:$K$825="Vacant", ROW('Bank Schedule'!$K$2:$K$825)), ROW(6:6))), "")} | AD9: {=IFERROR(INDEX('Bank Schedule'!AE:AE, SMALL(IF('Bank Schedule'!$K$2:$K$825="Vacant", ROW('Bank Schedule'!$K$2:$K$825)), ROW(6:6))), "")} | AE9: {=IFERROR(INDEX('Bank Schedule'!AF:AF, SMALL(IF('Bank Schedule'!$K$2:$K$825="Vacant", ROW('Bank Schedule'!$K$2:$K$825)), ROW(6:6))), "")}
A10: {=IFERROR(INDEX('Bank Schedule'!A:A, SMALL(IF('Bank Schedule'!$K$2:$K$825="Vacant", ROW('Bank Schedule'!$K$2:$K$825)), ROW(7:7))), "")} | B10: {=IFERROR(INDEX('Bank Schedule'!B:B, SMALL(IF('Bank Schedule'!$K$2:$K$825="Vacant", ROW('Bank Schedule'!$K$2:$K$825)), ROW(7:7))), "")} | C10: {=IFERROR(INDEX('Bank Schedule'!C:C, SMALL(IF('Bank Schedule'!$K$2:$K$825="Vacant", ROW('Bank Schedule'!$K$2:$K$825)), ROW(7:7))), "")} | D10: {=IFERROR(INDEX('Bank Schedule'!D:D, SMALL(IF('Bank Schedule'!$K$2:$K$825="Vacant", ROW('Bank Schedule'!$K$2:$K$825)), ROW(7:7))), "")} | E10: {=IFERROR(INDEX('Bank Schedule'!E:E, SMALL(IF('Bank Schedule'!$K$2:$K$825="Vacant", ROW('Bank Schedule'!$K$2:$K$825)), ROW(7:7))), "")} | F10: {=IFERROR(INDEX('Bank Schedule'!F:F, SMALL(IF('Bank Schedule'!$K$2:$K$825="Vacant", ROW('Bank Schedule'!$K$2:$K$825)), ROW(7:7))), "")} | G10: {=IFERROR(INDEX('Bank Schedule'!G:G, SMALL(IF('Bank Schedule'!$K$2:$K$825="Vacant", ROW('Bank Schedule'!$K$2:$K$825)), ROW(7:7))), "")} | H10: {=IFERROR(INDEX('Bank Schedule'!H:H, SMALL(IF('Bank Schedule'!$K$2:$K$825="Vacant", ROW('Bank Schedule'!$K$2:$K$825)), ROW(7:7))), "")} | I10: {=IFERROR(INDEX('Bank Schedule'!I:I, SMALL(IF('Bank Schedule'!$K$2:$K$825="Vacant", ROW('Bank Schedule'!$K$2:$K$825)), ROW(7:7))), "")} | J10: {=IFERROR(INDEX('Bank Schedule'!K:K, SMALL(IF('Bank Schedule'!$K$2:$K$825="Vacant", ROW('Bank Schedule'!$K$2:$K$825)), ROW(7:7))), "")} | K10: {=IFERROR(INDEX('Bank Schedule'!L:L, SMALL(IF('Bank Schedule'!$K$2:$K$825="Vacant", ROW('Bank Schedule'!$K$2:$K$825)), ROW(7:7))), "")} | L10: {=IFERROR(INDEX('Bank Schedule'!M:M, SMALL(IF('Bank Schedule'!$K$2:$K$825="Vacant", ROW('Bank Schedule'!$K$2:$K$825)), ROW(7:7))), "")} | M10: {=IFERROR(INDEX('Bank Schedule'!N:N, SMALL(IF('Bank Schedule'!$K$2:$K$825="Vacant", ROW('Bank Schedule'!$K$2:$K$825)), ROW(7:7))), "")} | N10: {=IFERROR(INDEX('Bank Schedule'!O:O, SMALL(IF('Bank Schedule'!$K$2:$K$825="Vacant", ROW('Bank Schedule'!$K$2:$K$825)), ROW(7:7))), "")} | O10: {=IFERROR(INDEX('Bank Schedule'!P:P, SMALL(IF('Bank Schedule'!$K$2:$K$825="Vacant", ROW('Bank Schedule'!$K$2:$K$825)), ROW(7:7))), "")} | P10: {=IFERROR(INDEX('Bank Schedule'!Q:Q, SMALL(IF('Bank Schedule'!$K$2:$K$825="Vacant", ROW('Bank Schedule'!$K$2:$K$825)), ROW(7:7))), "")} | Q10: {=IFERROR(INDEX('Bank Schedule'!R:R, SMALL(IF('Bank Schedule'!$K$2:$K$825="Vacant", ROW('Bank Schedule'!$K$2:$K$825)), ROW(7:7))), "")} | R10: {=IFERROR(INDEX('Bank Schedule'!S:S, SMALL(IF('Bank Schedule'!$K$2:$K$825="Vacant", ROW('Bank Schedule'!$K$2:$K$825)), ROW(7:7))), "")} | S10: {=IFERROR(INDEX('Bank Schedule'!T:T, SMALL(IF('Bank Schedule'!$K$2:$K$825="Vacant", ROW('Bank Schedule'!$K$2:$K$825)), ROW(7:7))), "")} | T10: {=IFERROR(INDEX('Bank Schedule'!U:U, SMALL(IF('Bank Schedule'!$K$2:$K$825="Vacant", ROW('Bank Schedule'!$K$2:$K$825)), ROW(7:7))), "")} | U10: {=IFERROR(INDEX('Bank Schedule'!V:V, SMALL(IF('Bank Schedule'!$K$2:$K$825="Vacant", ROW('Bank Schedule'!$K$2:$K$825)), ROW(7:7))), "")} | V10: {=IFERROR(INDEX('Bank Schedule'!W:W, SMALL(IF('Bank Schedule'!$K$2:$K$825="Vacant", ROW('Bank Schedule'!$K$2:$K$825)), ROW(7:7))), "")} | W10: {=IFERROR(INDEX('Bank Schedule'!X:X, SMALL(IF('Bank Schedule'!$K$2:$K$825="Vacant", ROW('Bank Schedule'!$K$2:$K$825)), ROW(7:7))), "")} | X10: {=IFERROR(INDEX('Bank Schedule'!Y:Y, SMALL(IF('Bank Schedule'!$K$2:$K$825="Vacant", ROW('Bank Schedule'!$K$2:$K$825)), ROW(7:7))), "")} | Y10: {=IFERROR(INDEX('Bank Schedule'!Z:Z, SMALL(IF('Bank Schedule'!$K$2:$K$825="Vacant", ROW('Bank Schedule'!$K$2:$K$825)), ROW(7:7))), "")} | Z10: {=IFERROR(INDEX('Bank Schedule'!AA:AA, SMALL(IF('Bank Schedule'!$K$2:$K$825="Vacant", ROW('Bank Schedule'!$K$2:$K$825)), ROW(7:7))), "")} | AA10: {=IFERROR(INDEX('Bank Schedule'!AB:AB, SMALL(IF('Bank Schedule'!$K$2:$K$825="Vacant", ROW('Bank Schedule'!$K$2:$K$825)), ROW(7:7))), "")} | AB10: {=IFERROR(INDEX('Bank Schedule'!AC:AC, SMALL(IF('Bank Schedule'!$K$2:$K$825="Vacant", ROW('Bank Schedule'!$K$2:$K$825)), ROW(7:7))), "")} | AC10: {=IFERROR(INDEX('Bank Schedule'!AD:AD, SMALL(IF('Bank Schedule'!$K$2:$K$825="Vacant", ROW('Bank Schedule'!$K$2:$K$825)), ROW(7:7))), "")} | AD10: {=IFERROR(INDEX('Bank Schedule'!AE:AE, SMALL(IF('Bank Schedule'!$K$2:$K$825="Vacant", ROW('Bank Schedule'!$K$2:$K$825)), ROW(7:7))), "")} | AE10: {=IFERROR(INDEX('Bank Schedule'!AF:AF, SMALL(IF('Bank Schedule'!$K$2:$K$825="Vacant", ROW('Bank Schedule'!$K$2:$K$825)), ROW(7:7))), "")} | AF10: {=IFERROR(INDEX('Bank Schedule'!AG:AG, SMALL(IF('Bank Schedule'!$K$2:$K$825="Vacant", ROW('Bank Schedule'!$K$2:$K$825)), ROW(7:7))), "")}
A11: {=IFERROR(INDEX('Bank Schedule'!A:A, SMALL(IF('Bank Schedule'!$K$2:$K$825="Vacant", ROW('Bank Schedule'!$K$2:$K$825)), ROW(8:8))), "")} | B11: {=IFERROR(INDEX('Bank Schedule'!B:B, SMALL(IF('Bank Schedule'!$K$2:$K$825="Vacant", ROW('Bank Schedule'!$K$2:$K$825)), ROW(8:8))), "")} | C11: {=IFERROR(INDEX('Bank Schedule'!C:C, SMALL(IF('Bank Schedule'!$K$2:$K$825="Vacant", ROW('Bank Schedule'!$K$2:$K$825)), ROW(8:8))), "")} | D11: {=IFERROR(INDEX('Bank Schedule'!D:D, SMALL(IF('Bank Schedule'!$K$2:$K$825="Vacant", ROW('Bank Schedule'!$K$2:$K$825)), ROW(8:8))), "")} | E11: {=IFERROR(INDEX('Bank Schedule'!E:E, SMALL(IF('Bank Schedule'!$K$2:$K$825="Vacant", ROW('Bank Schedule'!$K$2:$K$825)), ROW(8:8))), "")} | F11: {=IFERROR(INDEX('Bank Schedule'!F:F, SMALL(IF('Bank Schedule'!$K$2:$K$825="Vacant", ROW('Bank Schedule'!$K$2:$K$825)), ROW(8:8))), "")} | G11: {=IFERROR(INDEX('Bank Schedule'!G:G, SMALL(IF('Bank Schedule'!$K$2:$K$825="Vacant", ROW('Bank Schedule'!$K$2:$K$825)), ROW(8:8))), "")} | H11: {=IFERROR(INDEX('Bank Schedule'!H:H, SMALL(IF('Bank Schedule'!$K$2:$K$825="Vacant", ROW('Bank Schedule'!$K$2:$K$825)), ROW(8:8))), "")} | I11: {=IFERROR(INDEX('Bank Schedule'!I:I, SMALL(IF('Bank Schedule'!$K$2:$K$825="Vacant", ROW('Bank Schedule'!$K$2:$K$825)), ROW(8:8))), "")} | J11: {=IFERROR(INDEX('Bank Schedule'!K:K, SMALL(IF('Bank Schedule'!$K$2:$K$825="Vacant", ROW('Bank Schedule'!$K$2:$K$825)), ROW(8:8))), "")} | K11: {=IFERROR(INDEX('Bank Schedule'!L:L, SMALL(IF('Bank Schedule'!$K$2:$K$825="Vacant", ROW('Bank Schedule'!$K$2:$K$825)), ROW(8:8))), "")} | L11: {=IFERROR(INDEX('Bank Schedule'!M:M, SMALL(IF('Bank Schedule'!$K$2:$K$825="Vacant", ROW('Bank Schedule'!$K$2:$K$825)), ROW(8:8))), "")} | M11: {=IFERROR(INDEX('Bank Schedule'!N:N, SMALL(IF('Bank Schedule'!$K$2:$K$825="Vacant", ROW('Bank Schedule'!$K$2:$K$825)), ROW(8:8))), "")} | N11: {=IFERROR(INDEX('Bank Schedule'!O:O, SMALL(IF('Bank Schedule'!$K$2:$K$825="Vacant", ROW('Bank Schedule'!$K$2:$K$825)), ROW(8:8))), "")} | O11: {=IFERROR(INDEX('Bank Schedule'!P:P, SMALL(IF('Bank Schedule'!$K$2:$K$825="Vacant", ROW('Bank Schedule'!$K$2:$K$825)), ROW(8:8))), "")} | P11: {=IFERROR(INDEX('Bank Schedule'!Q:Q, SMALL(IF('Bank Schedule'!$K$2:$K$825="Vacant", ROW('Bank Schedule'!$K$2:$K$825)), ROW(8:8))), "")} | Q11: {=IFERROR(INDEX('Bank Schedule'!R:R, SMALL(IF('Bank Schedule'!$K$2:$K$825="Vacant", ROW('Bank Schedule'!$K$2:$K$825)), ROW(8:8))), "")} | R11: {=IFERROR(INDEX('Bank Schedule'!S:S, SMALL(IF('Bank Schedule'!$K$2:$K$825="Vacant", ROW('Bank Schedule'!$K$2:$K$825)), ROW(8:8))), "")} | S11: {=IFERROR(INDEX('Bank Schedule'!T:T, SMALL(IF('Bank Schedule'!$K$2:$K$825="Vacant", ROW('Bank Schedule'!$K$2:$K$825)), ROW(8:8))), "")} | T11: {=IFERROR(INDEX('Bank Schedule'!U:U, SMALL(IF('Bank Schedule'!$K$2:$K$825="Vacant", ROW('Bank Schedule'!$K$2:$K$825)), ROW(8:8))), "")} | U11: {=IFERROR(INDEX('Bank Schedule'!V:V, SMALL(IF('Bank Schedule'!$K$2:$K$825="Vacant", ROW('Bank Schedule'!$K$2:$K$825)), ROW(8:8))), "")} | V11: {=IFERROR(INDEX('Bank Schedule'!W:W, SMALL(IF('Bank Schedule'!$K$2:$K$825="Vacant", ROW('Bank Schedule'!$K$2:$K$825)), ROW(8:8))), "")} | W11: {=IFERROR(INDEX('Bank Schedule'!X:X, SMALL(IF('Bank Schedule'!$K$2:$K$825="Vacant", ROW('Bank Schedule'!$K$2:$K$825)), ROW(8:8))), "")} | X11: {=IFERROR(INDEX('Bank Schedule'!Y:Y, SMALL(IF('Bank Schedule'!$K$2:$K$825="Vacant", ROW('Bank Schedule'!$K$2:$K$825)), ROW(8:8))), "")} | Y11: {=IFERROR(INDEX('Bank Schedule'!Z:Z, SMALL(IF('Bank Schedule'!$K$2:$K$825="Vacant", ROW('Bank Schedule'!$K$2:$K$825)), ROW(8:8))), "")} | Z11: {=IFERROR(INDEX('Bank Schedule'!AA:AA, SMALL(IF('Bank Schedule'!$K$2:$K$825="Vacant", ROW('Bank Schedule'!$K$2:$K$825)), ROW(8:8))), "")} | AA11: {=IFERROR(INDEX('Bank Schedule'!AB:AB, SMALL(IF('Bank Schedule'!$K$2:$K$825="Vacant", ROW('Bank Schedule'!$K$2:$K$825)), ROW(8:8))), "")} | AB11: {=IFERROR(INDEX('Bank Schedule'!AC:AC, SMALL(IF('Bank Schedule'!$K$2:$K$825="Vacant", ROW('Bank Schedule'!$K$2:$K$825)), ROW(8:8))), "")} | AC11: {=IFERROR(INDEX('Bank Schedule'!AD:AD, SMALL(IF('Bank Schedule'!$K$2:$K$825="Vacant", ROW('Bank Schedule'!$K$2:$K$825)), ROW(8:8))), "")} | AD11: {=IFERROR(INDEX('Bank Schedule'!AE:AE, SMALL(IF('Bank Schedule'!$K$2:$K$825="Vacant", ROW('Bank Schedule'!$K$2:$K$825)), ROW(8:8))), "")} | AE11: {=IFERROR(INDEX('Bank Schedule'!AF:AF, SMALL(IF('Bank Schedule'!$K$2:$K$825="Vacant", ROW('Bank Schedule'!$K$2:$K$825)), ROW(8:8))), "")}
A12: {=IFERROR(INDEX('Bank Schedule'!A:A, SMALL(IF('Bank Schedule'!$K$2:$K$825="Vacant", ROW('Bank Schedule'!$K$2:$K$825)), ROW(9:9))), "")} | B12: {=IFERROR(INDEX('Bank Schedule'!B:B, SMALL(IF('Bank Schedule'!$K$2:$K$825="Vacant", ROW('Bank Schedule'!$K$2:$K$825)), ROW(9:9))), "")} | C12: {=IFERROR(INDEX('Bank Schedule'!C:C, SMALL(IF('Bank Schedule'!$K$2:$K$825="Vacant", ROW('Bank Schedule'!$K$2:$K$825)), ROW(9:9))), "")} | D12: {=IFERROR(INDEX('Bank Schedule'!D:D, SMALL(IF('Bank Schedule'!$K$2:$K$825="Vacant", ROW('Bank Schedule'!$K$2:$K$825)), ROW(9:9))), "")} | E12: {=IFERROR(INDEX('Bank Schedule'!E:E, SMALL(IF('Bank Schedule'!$K$2:$K$825="Vacant", ROW('Bank Schedule'!$K$2:$K$825)), ROW(9:9))), "")} | F12: {=IFERROR(INDEX('Bank Schedule'!F:F, SMALL(IF('Bank Schedule'!$K$2:$K$825="Vacant", ROW('Bank Schedule'!$K$2:$K$825)), ROW(9:9))), "")} | G12: {=IFERROR(INDEX('Bank Schedule'!G:G, SMALL(IF('Bank Schedule'!$K$2:$K$825="Vacant", ROW('Bank Schedule'!$K$2:$K$825)), ROW(9:9))), "")} | H12: {=IFERROR(INDEX('Bank Schedule'!H:H, SMALL(IF('Bank Schedule'!$K$2:$K$825="Vacant", ROW('Bank Schedule'!$K$2:$K$825)), ROW(9:9))), "")} | I12: {=IFERROR(INDEX('Bank Schedule'!I:I, SMALL(IF('Bank Schedule'!$K$2:$K$825="Vacant", ROW('Bank Schedule'!$K$2:$K$825)), ROW(9:9))), "")} | J12: {=IFERROR(INDEX('Bank Schedule'!K:K, SMALL(IF('Bank Schedule'!$K$2:$K$825="Vacant", ROW('Bank Schedule'!$K$2:$K$825)), ROW(9:9))), "")} | K12: {=IFERROR(INDEX('Bank Schedule'!L:L, SMALL(IF('Bank Schedule'!$K$2:$K$825="Vacant", ROW('Bank Schedule'!$K$2:$K$825)), ROW(9:9))), "")} | L12: {=IFERROR(INDEX('Bank Schedule'!M:M, SMALL(IF('Bank Schedule'!$K$2:$K$825="Vacant", ROW('Bank Schedule'!$K$2:$K$825)), ROW(9:9))), "")} | M12: {=IFERROR(INDEX('Bank Schedule'!N:N, SMALL(IF('Bank Schedule'!$K$2:$K$825="Vacant", ROW('Bank Schedule'!$K$2:$K$825)), ROW(9:9))), "")} | N12: {=IFERROR(INDEX('Bank Schedule'!O:O, SMALL(IF('Bank Schedule'!$K$2:$K$825="Vacant", ROW('Bank Schedule'!$K$2:$K$825)), ROW(9:9))), "")} | O12: {=IFERROR(INDEX('Bank Schedule'!P:P, SMALL(IF('Bank Schedule'!$K$2:$K$825="Vacant", ROW('Bank Schedule'!$K$2:$K$825)), ROW(9:9))), "")} | P12: {=IFERROR(INDEX('Bank Schedule'!Q:Q, SMALL(IF('Bank Schedule'!$K$2:$K$825="Vacant", ROW('Bank Schedule'!$K$2:$K$825)), ROW(9:9))), "")} | Q12: {=IFERROR(INDEX('Bank Schedule'!R:R, SMALL(IF('Bank Schedule'!$K$2:$K$825="Vacant", ROW('Bank Schedule'!$K$2:$K$825)), ROW(9:9))), "")} | R12: {=IFERROR(INDEX('Bank Schedule'!S:S, SMALL(IF('Bank Schedule'!$K$2:$K$825="Vacant", ROW('Bank Schedule'!$K$2:$K$825)), ROW(9:9))), "")} | S12: {=IFERROR(INDEX('Bank Schedule'!T:T, SMALL(IF('Bank Schedule'!$K$2:$K$825="Vacant", ROW('Bank Schedule'!$K$2:$K$825)), ROW(9:9))), "")} | T12: {=IFERROR(INDEX('Bank Schedule'!U:U, SMALL(IF('Bank Schedule'!$K$2:$K$825="Vacant", ROW('Bank Schedule'!$K$2:$K$825)), ROW(9:9))), "")} | U12: {=IFERROR(INDEX('Bank Schedule'!V:V, SMALL(IF('Bank Schedule'!$K$2:$K$825="Vacant", ROW('Bank Schedule'!$K$2:$K$825)), ROW(9:9))), "")} | V12: {=IFERROR(INDEX('Bank Schedule'!W:W, SMALL(IF('Bank Schedule'!$K$2:$K$825="Vacant", ROW('Bank Schedule'!$K$2:$K$825)), ROW(9:9))), "")} | W12: {=IFERROR(INDEX('Bank Schedule'!X:X, SMALL(IF('Bank Schedule'!$K$2:$K$825="Vacant", ROW('Bank Schedule'!$K$2:$K$825)), ROW(9:9))), "")} | X12: {=IFERROR(INDEX('Bank Schedule'!Y:Y, SMALL(IF('Bank Schedule'!$K$2:$K$825="Vacant", ROW('Bank Schedule'!$K$2:$K$825)), ROW(9:9))), "")} | Y12: {=IFERROR(INDEX('Bank Schedule'!Z:Z, SMALL(IF('Bank Schedule'!$K$2:$K$825="Vacant", ROW('Bank Schedule'!$K$2:$K$825)), ROW(9:9))), "")} | Z12: {=IFERROR(INDEX('Bank Schedule'!AA:AA, SMALL(IF('Bank Schedule'!$K$2:$K$825="Vacant", ROW('Bank Schedule'!$K$2:$K$825)), ROW(9:9))), "")} | AA12: {=IFERROR(INDEX('Bank Schedule'!AB:AB, SMALL(IF('Bank Schedule'!$K$2:$K$825="Vacant", ROW('Bank Schedule'!$K$2:$K$825)), ROW(9:9))), "")} | AB12: {=IFERROR(INDEX('Bank Schedule'!AC:AC, SMALL(IF('Bank Schedule'!$K$2:$K$825="Vacant", ROW('Bank Schedule'!$K$2:$K$825)), ROW(9:9))), "")} | AC12: {=IFERROR(INDEX('Bank Schedule'!AD:AD, SMALL(IF('Bank Schedule'!$K$2:$K$825="Vacant", ROW('Bank Schedule'!$K$2:$K$825)), ROW(9:9))), "")} | AD12: {=IFERROR(INDEX('Bank Schedule'!AE:AE, SMALL(IF('Bank Schedule'!$K$2:$K$825="Vacant", ROW('Bank Schedule'!$K$2:$K$825)), ROW(9:9))), "")} | AE12: {=IFERROR(INDEX('Bank Schedule'!AF:AF, SMALL(IF('Bank Schedule'!$K$2:$K$825="Vacant", ROW('Bank Schedule'!$K$2:$K$825)), ROW(9:9))), "")} | AF12: {=IFERROR(INDEX('Bank Schedule'!AG:AG, SMALL(IF('Bank Schedule'!$K$2:$K$825="Vacant", ROW('Bank Schedule'!$K$2:$K$825)), ROW(9:9))), "")}
A13: {=IFERROR(INDEX('Bank Schedule'!A:A, SMALL(IF('Bank Schedule'!$K$2:$K$825="Vacant", ROW('Bank Schedule'!$K$2:$K$825)), ROW(10:10))), "")} | B13: {=IFERROR(INDEX('Bank Schedule'!B:B, SMALL(IF('Bank Schedule'!$K$2:$K$825="Vacant", ROW('Bank Schedule'!$K$2:$K$825)), ROW(10:10))), "")} | C13: {=IFERROR(INDEX('Bank Schedule'!C:C, SMALL(IF('Bank Schedule'!$K$2:$K$825="Vacant", ROW('Bank Schedule'!$K$2:$K$825)), ROW(10:10))), "")} | D13: {=IFERROR(INDEX('Bank Schedule'!D:D, SMALL(IF('Bank Schedule'!$K$2:$K$825="Vacant", ROW('Bank Schedule'!$K$2:$K$825)), ROW(10:10))), "")} | E13: {=IFERROR(INDEX('Bank Schedule'!E:E, SMALL(IF('Bank Schedule'!$K$2:$K$825="Vacant", ROW('Bank Schedule'!$K$2:$K$825)), ROW(10:10))), "")} | F13: {=IFERROR(INDEX('Bank Schedule'!F:F, SMALL(IF('Bank Schedule'!$K$2:$K$825="Vacant", ROW('Bank Schedule'!$K$2:$K$825)), ROW(10:10))), "")} | G13: {=IFERROR(INDEX('Bank Schedule'!G:G, SMALL(IF('Bank Schedule'!$K$2:$K$825="Vacant", ROW('Bank Schedule'!$K$2:$K$825)), ROW(10:10))), "")} | H13: {=IFERROR(INDEX('Bank Schedule'!H:H, SMALL(IF('Bank Schedule'!$K$2:$K$825="Vacant", ROW('Bank Schedule'!$K$2:$K$825)), ROW(10:10))), "")} | I13: {=IFERROR(INDEX('Bank Schedule'!I:I, SMALL(IF('Bank Schedule'!$K$2:$K$825="Vacant", ROW('Bank Schedule'!$K$2:$K$825)), ROW(10:10))), "")} | J13: {=IFERROR(INDEX('Bank Schedule'!K:K, SMALL(IF('Bank Schedule'!$K$2:$K$825="Vacant", ROW('Bank Schedule'!$K$2:$K$825)), ROW(10:10))), "")} | K13: {=IFERROR(INDEX('Bank Schedule'!L:L, SMALL(IF('Bank Schedule'!$K$2:$K$825="Vacant", ROW('Bank Schedule'!$K$2:$K$825)), ROW(10:10))), "")} | L13: {=IFERROR(INDEX('Bank Schedule'!M:M, SMALL(IF('Bank Schedule'!$K$2:$K$825="Vacant", ROW('Bank Schedule'!$K$2:$K$825)), ROW(10:10))), "")} | M13: {=IFERROR(INDEX('Bank Schedule'!N:N, SMALL(IF('Bank Schedule'!$K$2:$K$825="Vacant", ROW('Bank Schedule'!$K$2:$K$825)), ROW(10:10))), "")} | N13: {=IFERROR(INDEX('Bank Schedule'!O:O, SMALL(IF('Bank Schedule'!$K$2:$K$825="Vacant", ROW('Bank Schedule'!$K$2:$K$825)), ROW(10:10))), "")} | O13: {=IFERROR(INDEX('Bank Schedule'!P:P, SMALL(IF('Bank Schedule'!$K$2:$K$825="Vacant", ROW('Bank Schedule'!$K$2:$K$825)), ROW(10:10))), "")} | P13: {=IFERROR(INDEX('Bank Schedule'!Q:Q, SMALL(IF('Bank Schedule'!$K$2:$K$825="Vacant", ROW('Bank Schedule'!$K$2:$K$825)), ROW(10:10))), "")} | Q13: {=IFERROR(INDEX('Bank Schedule'!R:R, SMALL(IF('Bank Schedule'!$K$2:$K$825="Vacant", ROW('Bank Schedule'!$K$2:$K$825)), ROW(10:10))), "")} | R13: {=IFERROR(INDEX('Bank Schedule'!S:S, SMALL(IF('Bank Schedule'!$K$2:$K$825="Vacant", ROW('Bank Schedule'!$K$2:$K$825)), ROW(10:10))), "")} | S13: {=IFERROR(INDEX('Bank Schedule'!T:T, SMALL(IF('Bank Schedule'!$K$2:$K$825="Vacant", ROW('Bank Schedule'!$K$2:$K$825)), ROW(10:10))), "")} | T13: {=IFERROR(INDEX('Bank Schedule'!U:U, SMALL(IF('Bank Schedule'!$K$2:$K$825="Vacant", ROW('Bank Schedule'!$K$2:$K$825)), ROW(10:10))), "")} | U13: {=IFERROR(INDEX('Bank Schedule'!V:V, SMALL(IF('Bank Schedule'!$K$2:$K$825="Vacant", ROW('Bank Schedule'!$K$2:$K$825)), ROW(10:10))), "")} | V13: {=IFERROR(INDEX('Bank Schedule'!W:W, SMALL(IF('Bank Schedule'!$K$2:$K$825="Vacant", ROW('Bank Schedule'!$K$2:$K$825)), ROW(10:10))), "")} | W13: {=IFERROR(INDEX('Bank Schedule'!X:X, SMALL(IF('Bank Schedule'!$K$2:$K$825="Vacant", ROW('Bank Schedule'!$K$2:$K$825)), ROW(10:10))), "")} | X13: {=IFERROR(INDEX('Bank Schedule'!Y:Y, SMALL(IF('Bank Schedule'!$K$2:$K$825="Vacant", ROW('Bank Schedule'!$K$2:$K$825)), ROW(10:10))), "")} | Y13: {=IFERROR(INDEX('Bank Schedule'!Z:Z, SMALL(IF('Bank Schedule'!$K$2:$K$825="Vacant", ROW('Bank Schedule'!$K$2:$K$825)), ROW(10:10))), "")} | Z13: {=IFERROR(INDEX('Bank Schedule'!AA:AA, SMALL(IF('Bank Schedule'!$K$2:$K$825="Vacant", ROW('Bank Schedule'!$K$2:$K$825)), ROW(10:10))), "")} | AA13: {=IFERROR(INDEX('Bank Schedule'!AB:AB, SMALL(IF('Bank Schedule'!$K$2:$K$825="Vacant", ROW('Bank Schedule'!$K$2:$K$825)), ROW(10:10))), "")} | AB13: {=IFERROR(INDEX('Bank Schedule'!AC:AC, SMALL(IF('Bank Schedule'!$K$2:$K$825="Vacant", ROW('Bank Schedule'!$K$2:$K$825)), ROW(10:10))), "")} | AC13: {=IFERROR(INDEX('Bank Schedule'!AD:AD, SMALL(IF('Bank Schedule'!$K$2:$K$825="Vacant", ROW('Bank Schedule'!$K$2:$K$825)), ROW(10:10))), "")} | AD13: {=IFERROR(INDEX('Bank Schedule'!AE:AE, SMALL(IF('Bank Schedule'!$K$2:$K$825="Vacant", ROW('Bank Schedule'!$K$2:$K$825)), ROW(10:10))), "")} | AE13: {=IFERROR(INDEX('Bank Schedule'!AF:AF, SMALL(IF('Bank Schedule'!$K$2:$K$825="Vacant", ROW('Bank Schedule'!$K$2:$K$825)), ROW(10:10))), "")} | AF13: {=IFERROR(INDEX('Bank Schedule'!AG:AG, SMALL(IF('Bank Schedule'!$K$2:$K$825="Vacant", ROW('Bank Schedule'!$K$2:$K$825)), ROW(10:10))), "")}
A14: {=IFERROR(INDEX('Bank Schedule'!A:A, SMALL(IF('Bank Schedule'!$K$2:$K$825="Vacant", ROW('Bank Schedule'!$K$2:$K$825)), ROW(11:11))), "")} | B14: {=IFERROR(INDEX('Bank Schedule'!B:B, SMALL(IF('Bank Schedule'!$K$2:$K$825="Vacant", ROW('Bank Schedule'!$K$2:$K$825)), ROW(11:11))), "")} | C14: {=IFERROR(INDEX('Bank Schedule'!C:C, SMALL(IF('Bank Schedule'!$K$2:$K$825="Vacant", ROW('Bank Schedule'!$K$2:$K$825)), ROW(11:11))), "")} | D14: {=IFERROR(INDEX('Bank Schedule'!D:D, SMALL(IF('Bank Schedule'!$K$2:$K$825="Vacant", ROW('Bank Schedule'!$K$2:$K$825)), ROW(11:11))), "")} | E14: {=IFERROR(INDEX('Bank Schedule'!E:E, SMALL(IF('Bank Schedule'!$K$2:$K$825="Vacant", ROW('Bank Schedule'!$K$2:$K$825)), ROW(11:11))), "")} | F14: {=IFERROR(INDEX('Bank Schedule'!F:F, SMALL(IF('Bank Schedule'!$K$2:$K$825="Vacant", ROW('Bank Schedule'!$K$2:$K$825)), ROW(11:11))), "")} | G14: {=IFERROR(INDEX('Bank Schedule'!G:G, SMALL(IF('Bank Schedule'!$K$2:$K$825="Vacant", ROW('Bank Schedule'!$K$2:$K$825)), ROW(11:11))), "")} | H14: {=IFERROR(INDEX('Bank Schedule'!H:H, SMALL(IF('Bank Schedule'!$K$2:$K$825="Vacant", ROW('Bank Schedule'!$K$2:$K$825)), ROW(11:11))), "")} | I14: {=IFERROR(INDEX('Bank Schedule'!I:I, SMALL(IF('Bank Schedule'!$K$2:$K$825="Vacant", ROW('Bank Schedule'!$K$2:$K$825)), ROW(11:11))), "")} | J14: {=IFERROR(INDEX('Bank Schedule'!K:K, SMALL(IF('Bank Schedule'!$K$2:$K$825="Vacant", ROW('Bank Schedule'!$K$2:$K$825)), ROW(11:11))), "")} | K14: {=IFERROR(INDEX('Bank Schedule'!L:L, SMALL(IF('Bank Schedule'!$K$2:$K$825="Vacant", ROW('Bank Schedule'!$K$2:$K$825)), ROW(11:11))), "")} | L14: {=IFERROR(INDEX('Bank Schedule'!M:M, SMALL(IF('Bank Schedule'!$K$2:$K$825="Vacant", ROW('Bank Schedule'!$K$2:$K$825)), ROW(11:11))), "")} | M14: {=IFERROR(INDEX('Bank Schedule'!N:N, SMALL(IF('Bank Schedule'!$K$2:$K$825="Vacant", ROW('Bank Schedule'!$K$2:$K$825)), ROW(11:11))), "")} | N14: {=IFERROR(INDEX('Bank Schedule'!O:O, SMALL(IF('Bank Schedule'!$K$2:$K$825="Vacant", ROW('Bank Schedule'!$K$2:$K$825)), ROW(11:11))), "")} | O14: {=IFERROR(INDEX('Bank Schedule'!P:P, SMALL(IF('Bank Schedule'!$K$2:$K$825="Vacant", ROW('Bank Schedule'!$K$2:$K$825)), ROW(11:11))), "")} | P14: {=IFERROR(INDEX('Bank Schedule'!Q:Q, SMALL(IF('Bank Schedule'!$K$2:$K$825="Vacant", ROW('Bank Schedule'!$K$2:$K$825)), ROW(11:11))), "")} | Q14: {=IFERROR(INDEX('Bank Schedule'!R:R, SMALL(IF('Bank Schedule'!$K$2:$K$825="Vacant", ROW('Bank Schedule'!$K$2:$K$825)), ROW(11:11))), "")} | R14: {=IFERROR(INDEX('Bank Schedule'!S:S, SMALL(IF('Bank Schedule'!$K$2:$K$825="Vacant", ROW('Bank Schedule'!$K$2:$K$825)), ROW(11:11))), "")} | S14: {=IFERROR(INDEX('Bank Schedule'!T:T, SMALL(IF('Bank Schedule'!$K$2:$K$825="Vacant", ROW('Bank Schedule'!$K$2:$K$825)), ROW(11:11))), "")} | T14: {=IFERROR(INDEX('Bank Schedule'!U:U, SMALL(IF('Bank Schedule'!$K$2:$K$825="Vacant", ROW('Bank Schedule'!$K$2:$K$825)), ROW(11:11))), "")} | U14: {=IFERROR(INDEX('Bank Schedule'!V:V, SMALL(IF('Bank Schedule'!$K$2:$K$825="Vacant", ROW('Bank Schedule'!$K$2:$K$825)), ROW(11:11))), "")} | V14: {=IFERROR(INDEX('Bank Schedule'!W:W, SMALL(IF('Bank Schedule'!$K$2:$K$825="Vacant", ROW('Bank Schedule'!$K$2:$K$825)), ROW(11:11))), "")} | W14: {=IFERROR(INDEX('Bank Schedule'!X:X, SMALL(IF('Bank Schedule'!$K$2:$K$825="Vacant", ROW('Bank Schedule'!$K$2:$K$825)), ROW(11:11))), "")} | X14: {=IFERROR(INDEX('Bank Schedule'!Y:Y, SMALL(IF('Bank Schedule'!$K$2:$K$825="Vacant", ROW('Bank Schedule'!$K$2:$K$825)), ROW(11:11))), "")} | Y14: {=IFERROR(INDEX('Bank Schedule'!Z:Z, SMALL(IF('Bank Schedule'!$K$2:$K$825="Vacant", ROW('Bank Schedule'!$K$2:$K$825)), ROW(11:11))), "")} | Z14: {=IFERROR(INDEX('Bank Schedule'!AA:AA, SMALL(IF('Bank Schedule'!$K$2:$K$825="Vacant", ROW('Bank Schedule'!$K$2:$K$825)), ROW(11:11))), "")} | AA14: {=IFERROR(INDEX('Bank Schedule'!AB:AB, SMALL(IF('Bank Schedule'!$K$2:$K$825="Vacant", ROW('Bank Schedule'!$K$2:$K$825)), ROW(11:11))), "")} | AB14: {=IFERROR(INDEX('Bank Schedule'!AC:AC, SMALL(IF('Bank Schedule'!$K$2:$K$825="Vacant", ROW('Bank Schedule'!$K$2:$K$825)), ROW(11:11))), "")} | AC14: {=IFERROR(INDEX('Bank Schedule'!AD:AD, SMALL(IF('Bank Schedule'!$K$2:$K$825="Vacant", ROW('Bank Schedule'!$K$2:$K$825)), ROW(11:11))), "")} | AD14: {=IFERROR(INDEX('Bank Schedule'!AE:AE, SMALL(IF('Bank Schedule'!$K$2:$K$825="Vacant", ROW('Bank Schedule'!$K$2:$K$825)), ROW(11:11))), "")} | AE14: {=IFERROR(INDEX('Bank Schedule'!AF:AF, SMALL(IF('Bank Schedule'!$K$2:$K$825="Vacant", ROW('Bank Schedule'!$K$2:$K$825)), ROW(11:11))), "")} | AF14: {=IFERROR(INDEX('Bank Schedule'!AG:AG, SMALL(IF('Bank Schedule'!$K$2:$K$825="Vacant", ROW('Bank Schedule'!$K$2:$K$825)), ROW(11:11))), "")}
A15: {=IFERROR(INDEX('Bank Schedule'!A:A, SMALL(IF('Bank Schedule'!$K$2:$K$825="Vacant", ROW('Bank Schedule'!$K$2:$K$825)), ROW(12:12))), "")} | B15: {=IFERROR(INDEX('Bank Schedule'!B:B, SMALL(IF('Bank Schedule'!$K$2:$K$825="Vacant", ROW('Bank Schedule'!$K$2:$K$825)), ROW(12:12))), "")} | C15: {=IFERROR(INDEX('Bank Schedule'!C:C, SMALL(IF('Bank Schedule'!$K$2:$K$825="Vacant", ROW('Bank Schedule'!$K$2:$K$825)), ROW(12:12))), "")} | D15: {=IFERROR(INDEX('Bank Schedule'!D:D, SMALL(IF('Bank Schedule'!$K$2:$K$825="Vacant", ROW('Bank Schedule'!$K$2:$K$825)), ROW(12:12))), "")} | E15: {=IFERROR(INDEX('Bank Schedule'!E:E, SMALL(IF('Bank Schedule'!$K$2:$K$825="Vacant", ROW('Bank Schedule'!$K$2:$K$825)), ROW(12:12))), "")} | F15: {=IFERROR(INDEX('Bank Schedule'!F:F, SMALL(IF('Bank Schedule'!$K$2:$K$825="Vacant", ROW('Bank Schedule'!$K$2:$K$825)), ROW(12:12))), "")} | G15: {=IFERROR(INDEX('Bank Schedule'!G:G, SMALL(IF('Bank Schedule'!$K$2:$K$825="Vacant", ROW('Bank Schedule'!$K$2:$K$825)), ROW(12:12))), "")} | H15: {=IFERROR(INDEX('Bank Schedule'!H:H, SMALL(IF('Bank Schedule'!$K$2:$K$825="Vacant", ROW('Bank Schedule'!$K$2:$K$825)), ROW(12:12))), "")} | I15: {=IFERROR(INDEX('Bank Schedule'!I:I, SMALL(IF('Bank Schedule'!$K$2:$K$825="Vacant", ROW('Bank Schedule'!$K$2:$K$825)), ROW(12:12))), "")} | J15: {=IFERROR(INDEX('Bank Schedule'!K:K, SMALL(IF('Bank Schedule'!$K$2:$K$825="Vacant", ROW('Bank Schedule'!$K$2:$K$825)), ROW(12:12))), "")} | K15: {=IFERROR(INDEX('Bank Schedule'!L:L, SMALL(IF('Bank Schedule'!$K$2:$K$825="Vacant", ROW('Bank Schedule'!$K$2:$K$825)), ROW(12:12))), "")} | L15: {=IFERROR(INDEX('Bank Schedule'!M:M, SMALL(IF('Bank Schedule'!$K$2:$K$825="Vacant", ROW('Bank Schedule'!$K$2:$K$825)), ROW(12:12))), "")} | M15: {=IFERROR(INDEX('Bank Schedule'!N:N, SMALL(IF('Bank Schedule'!$K$2:$K$825="Vacant", ROW('Bank Schedule'!$K$2:$K$825)), ROW(12:12))), "")} | N15: {=IFERROR(INDEX('Bank Schedule'!O:O, SMALL(IF('Bank Schedule'!$K$2:$K$825="Vacant", ROW('Bank Schedule'!$K$2:$K$825)), ROW(12:12))), "")} | O15: {=IFERROR(INDEX('Bank Schedule'!P:P, SMALL(IF('Bank Schedule'!$K$2:$K$825="Vacant", ROW('Bank Schedule'!$K$2:$K$825)), ROW(12:12))), "")} | P15: {=IFERROR(INDEX('Bank Schedule'!Q:Q, SMALL(IF('Bank Schedule'!$K$2:$K$825="Vacant", ROW('Bank Schedule'!$K$2:$K$825)), ROW(12:12))), "")} | Q15: {=IFERROR(INDEX('Bank Schedule'!R:R, SMALL(IF('Bank Schedule'!$K$2:$K$825="Vacant", ROW('Bank Schedule'!$K$2:$K$825)), ROW(12:12))), "")} | R15: {=IFERROR(INDEX('Bank Schedule'!S:S, SMALL(IF('Bank Schedule'!$K$2:$K$825="Vacant", ROW('Bank Schedule'!$K$2:$K$825)), ROW(12:12))), "")} | S15: {=IFERROR(INDEX('Bank Schedule'!T:T, SMALL(IF('Bank Schedule'!$K$2:$K$825="Vacant", ROW('Bank Schedule'!$K$2:$K$825)), ROW(12:12))), "")} | T15: {=IFERROR(INDEX('Bank Schedule'!U:U, SMALL(IF('Bank Schedule'!$K$2:$K$825="Vacant", ROW('Bank Schedule'!$K$2:$K$825)), ROW(12:12))), "")} | U15: {=IFERROR(INDEX('Bank Schedule'!V:V, SMALL(IF('Bank Schedule'!$K$2:$K$825="Vacant", ROW('Bank Schedule'!$K$2:$K$825)), ROW(12:12))), "")} | V15: {=IFERROR(INDEX('Bank Schedule'!W:W, SMALL(IF('Bank Schedule'!$K$2:$K$825="Vacant", ROW('Bank Schedule'!$K$2:$K$825)), ROW(12:12))), "")} | W15: {=IFERROR(INDEX('Bank Schedule'!X:X, SMALL(IF('Bank Schedule'!$K$2:$K$825="Vacant", ROW('Bank Schedule'!$K$2:$K$825)), ROW(12:12))), "")} | X15: {=IFERROR(INDEX('Bank Schedule'!Y:Y, SMALL(IF('Bank Schedule'!$K$2:$K$825="Vacant", ROW('Bank Schedule'!$K$2:$K$825)), ROW(12:12))), "")} | Y15: {=IFERROR(INDEX('Bank Schedule'!Z:Z, SMALL(IF('Bank Schedule'!$K$2:$K$825="Vacant", ROW('Bank Schedule'!$K$2:$K$825)), ROW(12:12))), "")} | Z15: {=IFERROR(INDEX('Bank Schedule'!AA:AA, SMALL(IF('Bank Schedule'!$K$2:$K$825="Vacant", ROW('Bank Schedule'!$K$2:$K$825)), ROW(12:12))), "")} | AA15: {=IFERROR(INDEX('Bank Schedule'!AB:AB, SMALL(IF('Bank Schedule'!$K$2:$K$825="Vacant", ROW('Bank Schedule'!$K$2:$K$825)), ROW(12:12))), "")} | AB15: {=IFERROR(INDEX('Bank Schedule'!AC:AC, SMALL(IF('Bank Schedule'!$K$2:$K$825="Vacant", ROW('Bank Schedule'!$K$2:$K$825)), ROW(12:12))), "")} | AC15: {=IFERROR(INDEX('Bank Schedule'!AD:AD, SMALL(IF('Bank Schedule'!$K$2:$K$825="Vacant", ROW('Bank Schedule'!$K$2:$K$825)), ROW(12:12))), "")} | AD15: {=IFERROR(INDEX('Bank Schedule'!AE:AE, SMALL(IF('Bank Schedule'!$K$2:$K$825="Vacant", ROW('Bank Schedule'!$K$2:$K$825)), ROW(12:12))), "")} | AE15: {=IFERROR(INDEX('Bank Schedule'!AF:AF, SMALL(IF('Bank Schedule'!$K$2:$K$825="Vacant", ROW('Bank Schedule'!$K$2:$K$825)), ROW(12:12))), "")} | AF15: {=IFERROR(INDEX('Bank Schedule'!AG:AG, SMALL(IF('Bank Schedule'!$K$2:$K$825="Vacant", ROW('Bank Schedule'!$K$2:$K$825)), ROW(12:12))), "")}
A16: {=IFERROR(INDEX('Bank Schedule'!A:A, SMALL(IF('Bank Schedule'!$K$2:$K$825="Vacant", ROW('Bank Schedule'!$K$2:$K$825)), ROW(13:13))), "")} | B16: {=IFERROR(INDEX('Bank Schedule'!B:B, SMALL(IF('Bank Schedule'!$K$2:$K$825="Vacant", ROW('Bank Schedule'!$K$2:$K$825)), ROW(13:13))), "")} | C16: {=IFERROR(INDEX('Bank Schedule'!C:C, SMALL(IF('Bank Schedule'!$K$2:$K$825="Vacant", ROW('Bank Schedule'!$K$2:$K$825)), ROW(13:13))), "")} | D16: {=IFERROR(INDEX('Bank Schedule'!D:D, SMALL(IF('Bank Schedule'!$K$2:$K$825="Vacant", ROW('Bank Schedule'!$K$2:$K$825)), ROW(13:13))), "")} | E16: {=IFERROR(INDEX('Bank Schedule'!E:E, SMALL(IF('Bank Schedule'!$K$2:$K$825="Vacant", ROW('Bank Schedule'!$K$2:$K$825)), ROW(13:13))), "")} | F16: {=IFERROR(INDEX('Bank Schedule'!F:F, SMALL(IF('Bank Schedule'!$K$2:$K$825="Vacant", ROW('Bank Schedule'!$K$2:$K$825)), ROW(13:13))), "")} | G16: {=IFERROR(INDEX('Bank Schedule'!G:G, SMALL(IF('Bank Schedule'!$K$2:$K$825="Vacant", ROW('Bank Schedule'!$K$2:$K$825)), ROW(13:13))), "")} | H16: {=IFERROR(INDEX('Bank Schedule'!H:H, SMALL(IF('Bank Schedule'!$K$2:$K$825="Vacant", ROW('Bank Schedule'!$K$2:$K$825)), ROW(13:13))), "")} | I16: {=IFERROR(INDEX('Bank Schedule'!I:I, SMALL(IF('Bank Schedule'!$K$2:$K$825="Vacant", ROW('Bank Schedule'!$K$2:$K$825)), ROW(13:13))), "")} | J16: {=IFERROR(INDEX('Bank Schedule'!K:K, SMALL(IF('Bank Schedule'!$K$2:$K$825="Vacant", ROW('Bank Schedule'!$K$2:$K$825)), ROW(13:13))), "")} | K16: {=IFERROR(INDEX('Bank Schedule'!L:L, SMALL(IF('Bank Schedule'!$K$2:$K$825="Vacant", ROW('Bank Schedule'!$K$2:$K$825)), ROW(13:13))), "")} | L16: {=IFERROR(INDEX('Bank Schedule'!M:M, SMALL(IF('Bank Schedule'!$K$2:$K$825="Vacant", ROW('Bank Schedule'!$K$2:$K$825)), ROW(13:13))), "")} | M16: {=IFERROR(INDEX('Bank Schedule'!N:N, SMALL(IF('Bank Schedule'!$K$2:$K$825="Vacant", ROW('Bank Schedule'!$K$2:$K$825)), ROW(13:13))), "")} | N16: {=IFERROR(INDEX('Bank Schedule'!O:O, SMALL(IF('Bank Schedule'!$K$2:$K$825="Vacant", ROW('Bank Schedule'!$K$2:$K$825)), ROW(13:13))), "")} | O16: {=IFERROR(INDEX('Bank Schedule'!P:P, SMALL(IF('Bank Schedule'!$K$2:$K$825="Vacant", ROW('Bank Schedule'!$K$2:$K$825)), ROW(13:13))), "")} | P16: {=IFERROR(INDEX('Bank Schedule'!Q:Q, SMALL(IF('Bank Schedule'!$K$2:$K$825="Vacant", ROW('Bank Schedule'!$K$2:$K$825)), ROW(13:13))), "")} | Q16: {=IFERROR(INDEX('Bank Schedule'!R:R, SMALL(IF('Bank Schedule'!$K$2:$K$825="Vacant", ROW('Bank Schedule'!$K$2:$K$825)), ROW(13:13))), "")} | R16: {=IFERROR(INDEX('Bank Schedule'!S:S, SMALL(IF('Bank Schedule'!$K$2:$K$825="Vacant", ROW('Bank Schedule'!$K$2:$K$825)), ROW(13:13))), "")} | S16: {=IFERROR(INDEX('Bank Schedule'!T:T, SMALL(IF('Bank Schedule'!$K$2:$K$825="Vacant", ROW('Bank Schedule'!$K$2:$K$825)), ROW(13:13))), "")} | T16: {=IFERROR(INDEX('Bank Schedule'!U:U, SMALL(IF('Bank Schedule'!$K$2:$K$825="Vacant", ROW('Bank Schedule'!$K$2:$K$825)), ROW(13:13))), "")} | U16: {=IFERROR(INDEX('Bank Schedule'!V:V, SMALL(IF('Bank Schedule'!$K$2:$K$825="Vacant", ROW('Bank Schedule'!$K$2:$K$825)), ROW(13:13))), "")} | V16: {=IFERROR(INDEX('Bank Schedule'!W:W, SMALL(IF('Bank Schedule'!$K$2:$K$825="Vacant", ROW('Bank Schedule'!$K$2:$K$825)), ROW(13:13))), "")} | W16: {=IFERROR(INDEX('Bank Schedule'!X:X, SMALL(IF('Bank Schedule'!$K$2:$K$825="Vacant", ROW('Bank Schedule'!$K$2:$K$825)), ROW(13:13))), "")} | X16: {=IFERROR(INDEX('Bank Schedule'!Y:Y, SMALL(IF('Bank Schedule'!$K$2:$K$825="Vacant", ROW('Bank Schedule'!$K$2:$K$825)), ROW(13:13))), "")} | Y16: {=IFERROR(INDEX('Bank Schedule'!Z:Z, SMALL(IF('Bank Schedule'!$K$2:$K$825="Vacant", ROW('Bank Schedule'!$K$2:$K$825)), ROW(13:13))), "")} | Z16: {=IFERROR(INDEX('Bank Schedule'!AA:AA, SMALL(IF('Bank Schedule'!$K$2:$K$825="Vacant", ROW('Bank Schedule'!$K$2:$K$825)), ROW(13:13))), "")} | AA16: {=IFERROR(INDEX('Bank Schedule'!AB:AB, SMALL(IF('Bank Schedule'!$K$2:$K$825="Vacant", ROW('Bank Schedule'!$K$2:$K$825)), ROW(13:13))), "")} | AB16: {=IFERROR(INDEX('Bank Schedule'!AC:AC, SMALL(IF('Bank Schedule'!$K$2:$K$825="Vacant", ROW('Bank Schedule'!$K$2:$K$825)), ROW(13:13))), "")} | AC16: {=IFERROR(INDEX('Bank Schedule'!AD:AD, SMALL(IF('Bank Schedule'!$K$2:$K$825="Vacant", ROW('Bank Schedule'!$K$2:$K$825)), ROW(13:13))), "")} | AD16: {=IFERROR(INDEX('Bank Schedule'!AE:AE, SMALL(IF('Bank Schedule'!$K$2:$K$825="Vacant", ROW('Bank Schedule'!$K$2:$K$825)), ROW(13:13))), "")} | AE16: {=IFERROR(INDEX('Bank Schedule'!AF:AF, SMALL(IF('Bank Schedule'!$K$2:$K$825="Vacant", ROW('Bank Schedule'!$K$2:$K$825)), ROW(13:13))), "")} | AF16: {=IFERROR(INDEX('Bank Schedule'!AG:AG, SMALL(IF('Bank Schedule'!$K$2:$K$825="Vacant", ROW('Bank Schedule'!$K$2:$K$825)), ROW(13:13))), "")}
A17: {=IFERROR(INDEX('Bank Schedule'!A:A, SMALL(IF('Bank Schedule'!$K$2:$K$825="Vacant", ROW('Bank Schedule'!$K$2:$K$825)), ROW(14:14))), "")} | B17: {=IFERROR(INDEX('Bank Schedule'!B:B, SMALL(IF('Bank Schedule'!$K$2:$K$825="Vacant", ROW('Bank Schedule'!$K$2:$K$825)), ROW(14:14))), "")} | C17: {=IFERROR(INDEX('Bank Schedule'!C:C, SMALL(IF('Bank Schedule'!$K$2:$K$825="Vacant", ROW('Bank Schedule'!$K$2:$K$825)), ROW(14:14))), "")} | D17: {=IFERROR(INDEX('Bank Schedule'!D:D, SMALL(IF('Bank Schedule'!$K$2:$K$825="Vacant", ROW('Bank Schedule'!$K$2:$K$825)), ROW(14:14))), "")} | E17: {=IFERROR(INDEX('Bank Schedule'!E:E, SMALL(IF('Bank Schedule'!$K$2:$K$825="Vacant", ROW('Bank Schedule'!$K$2:$K$825)), ROW(14:14))), "")} | F17: {=IFERROR(INDEX('Bank Schedule'!F:F, SMALL(IF('Bank Schedule'!$K$2:$K$825="Vacant", ROW('Bank Schedule'!$K$2:$K$825)), ROW(14:14))), "")} | G17: {=IFERROR(INDEX('Bank Schedule'!G:G, SMALL(IF('Bank Schedule'!$K$2:$K$825="Vacant", ROW('Bank Schedule'!$K$2:$K$825)), ROW(14:14))), "")} | H17: {=IFERROR(INDEX('Bank Schedule'!H:H, SMALL(IF('Bank Schedule'!$K$2:$K$825="Vacant", ROW('Bank Schedule'!$K$2:$K$825)), ROW(14:14))), "")} | I17: {=IFERROR(INDEX('Bank Schedule'!I:I, SMALL(IF('Bank Schedule'!$K$2:$K$825="Vacant", ROW('Bank Schedule'!$K$2:$K$825)), ROW(14:14))), "")} | J17: {=IFERROR(INDEX('Bank Schedule'!K:K, SMALL(IF('Bank Schedule'!$K$2:$K$825="Vacant", ROW('Bank Schedule'!$K$2:$K$825)), ROW(14:14))), "")} | K17: {=IFERROR(INDEX('Bank Schedule'!L:L, SMALL(IF('Bank Schedule'!$K$2:$K$825="Vacant", ROW('Bank Schedule'!$K$2:$K$825)), ROW(14:14))), "")} | L17: {=IFERROR(INDEX('Bank Schedule'!M:M, SMALL(IF('Bank Schedule'!$K$2:$K$825="Vacant", ROW('Bank Schedule'!$K$2:$K$825)), ROW(14:14))), "")} | M17: {=IFERROR(INDEX('Bank Schedule'!N:N, SMALL(IF('Bank Schedule'!$K$2:$K$825="Vacant", ROW('Bank Schedule'!$K$2:$K$825)), ROW(14:14))), "")} | N17: {=IFERROR(INDEX('Bank Schedule'!O:O, SMALL(IF('Bank Schedule'!$K$2:$K$825="Vacant", ROW('Bank Schedule'!$K$2:$K$825)), ROW(14:14))), "")} | O17: {=IFERROR(INDEX('Bank Schedule'!P:P, SMALL(IF('Bank Schedule'!$K$2:$K$825="Vacant", ROW('Bank Schedule'!$K$2:$K$825)), ROW(14:14))), "")} | P17: {=IFERROR(INDEX('Bank Schedule'!Q:Q, SMALL(IF('Bank Schedule'!$K$2:$K$825="Vacant", ROW('Bank Schedule'!$K$2:$K$825)), ROW(14:14))), "")} | Q17: {=IFERROR(INDEX('Bank Schedule'!R:R, SMALL(IF('Bank Schedule'!$K$2:$K$825="Vacant", ROW('Bank Schedule'!$K$2:$K$825)), ROW(14:14))), "")} | R17: {=IFERROR(INDEX('Bank Schedule'!S:S, SMALL(IF('Bank Schedule'!$K$2:$K$825="Vacant", ROW('Bank Schedule'!$K$2:$K$825)), ROW(14:14))), "")} | S17: {=IFERROR(INDEX('Bank Schedule'!T:T, SMALL(IF('Bank Schedule'!$K$2:$K$825="Vacant", ROW('Bank Schedule'!$K$2:$K$825)), ROW(14:14))), "")} | T17: {=IFERROR(INDEX('Bank Schedule'!U:U, SMALL(IF('Bank Schedule'!$K$2:$K$825="Vacant", ROW('Bank Schedule'!$K$2:$K$825)), ROW(14:14))), "")} | U17: {=IFERROR(INDEX('Bank Schedule'!V:V, SMALL(IF('Bank Schedule'!$K$2:$K$825="Vacant", ROW('Bank Schedule'!$K$2:$K$825)), ROW(14:14))), "")} | V17: {=IFERROR(INDEX('Bank Schedule'!W:W, SMALL(IF('Bank Schedule'!$K$2:$K$825="Vacant", ROW('Bank Schedule'!$K$2:$K$825)), ROW(14:14))), "")} | W17: {=IFERROR(INDEX('Bank Schedule'!X:X, SMALL(IF('Bank Schedule'!$K$2:$K$825="Vacant", ROW('Bank Schedule'!$K$2:$K$825)), ROW(14:14))), "")} | X17: {=IFERROR(INDEX('Bank Schedule'!Y:Y, SMALL(IF('Bank Schedule'!$K$2:$K$825="Vacant", ROW('Bank Schedule'!$K$2:$K$825)), ROW(14:14))), "")} | Y17: {=IFERROR(INDEX('Bank Schedule'!Z:Z, SMALL(IF('Bank Schedule'!$K$2:$K$825="Vacant", ROW('Bank Schedule'!$K$2:$K$825)), ROW(14:14))), "")} | Z17: {=IFERROR(INDEX('Bank Schedule'!AA:AA, SMALL(IF('Bank Schedule'!$K$2:$K$825="Vacant", ROW('Bank Schedule'!$K$2:$K$825)), ROW(14:14))), "")} | AA17: {=IFERROR(INDEX('Bank Schedule'!AB:AB, SMALL(IF('Bank Schedule'!$K$2:$K$825="Vacant", ROW('Bank Schedule'!$K$2:$K$825)), ROW(14:14))), "")} | AB17: {=IFERROR(INDEX('Bank Schedule'!AC:AC, SMALL(IF('Bank Schedule'!$K$2:$K$825="Vacant", ROW('Bank Schedule'!$K$2:$K$825)), ROW(14:14))), "")} | AC17: {=IFERROR(INDEX('Bank Schedule'!AD:AD, SMALL(IF('Bank Schedule'!$K$2:$K$825="Vacant", ROW('Bank Schedule'!$K$2:$K$825)), ROW(14:14))), "")} | AD17: {=IFERROR(INDEX('Bank Schedule'!AE:AE, SMALL(IF('Bank Schedule'!$K$2:$K$825="Vacant", ROW('Bank Schedule'!$K$2:$K$825)), ROW(14:14))), "")} | AE17: {=IFERROR(INDEX('Bank Schedule'!AF:AF, SMALL(IF('Bank Schedule'!$K$2:$K$825="Vacant", ROW('Bank Schedule'!$K$2:$K$825)), ROW(14:14))), "")} | AF17: {=IFERROR(INDEX('Bank Schedule'!AG:AG, SMALL(IF('Bank Schedule'!$K$2:$K$825="Vacant", ROW('Bank Schedule'!$K$2:$K$825)), ROW(14:14))), "")}
A18: {=IFERROR(INDEX('Bank Schedule'!A:A, SMALL(IF('Bank Schedule'!$K$2:$K$825="Vacant", ROW('Bank Schedule'!$K$2:$K$825)), ROW(15:15))), "")} | B18: {=IFERROR(INDEX('Bank Schedule'!B:B, SMALL(IF('Bank Schedule'!$K$2:$K$825="Vacant", ROW('Bank Schedule'!$K$2:$K$825)), ROW(15:15))), "")} | C18: {=IFERROR(INDEX('Bank Schedule'!C:C, SMALL(IF('Bank Schedule'!$K$2:$K$825="Vacant", ROW('Bank Schedule'!$K$2:$K$825)), ROW(15:15))), "")} | D18: {=IFERROR(INDEX('Bank Schedule'!D:D, SMALL(IF('Bank Schedule'!$K$2:$K$825="Vacant", ROW('Bank Schedule'!$K$2:$K$825)), ROW(15:15))), "")} | E18: {=IFERROR(INDEX('Bank Schedule'!E:E, SMALL(IF('Bank Schedule'!$K$2:$K$825="Vacant", ROW('Bank Schedule'!$K$2:$K$825)), ROW(15:15))), "")} | F18: {=IFERROR(INDEX('Bank Schedule'!F:F, SMALL(IF('Bank Schedule'!$K$2:$K$825="Vacant", ROW('Bank Schedule'!$K$2:$K$825)), ROW(15:15))), "")} | G18: {=IFERROR(INDEX('Bank Schedule'!G:G, SMALL(IF('Bank Schedule'!$K$2:$K$825="Vacant", ROW('Bank Schedule'!$K$2:$K$825)), ROW(15:15))), "")} | H18: {=IFERROR(INDEX('Bank Schedule'!H:H, SMALL(IF('Bank Schedule'!$K$2:$K$825="Vacant", ROW('Bank Schedule'!$K$2:$K$825)), ROW(15:15))), "")} | I18: {=IFERROR(INDEX('Bank Schedule'!I:I, SMALL(IF('Bank Schedule'!$K$2:$K$825="Vacant", ROW('Bank Schedule'!$K$2:$K$825)), ROW(15:15))), "")} | J18: {=IFERROR(INDEX('Bank Schedule'!K:K, SMALL(IF('Bank Schedule'!$K$2:$K$825="Vacant", ROW('Bank Schedule'!$K$2:$K$825)), ROW(15:15))), "")} | K18: {=IFERROR(INDEX('Bank Schedule'!L:L, SMALL(IF('Bank Schedule'!$K$2:$K$825="Vacant", ROW('Bank Schedule'!$K$2:$K$825)), ROW(15:15))), "")} | L18: {=IFERROR(INDEX('Bank Schedule'!M:M, SMALL(IF('Bank Schedule'!$K$2:$K$825="Vacant", ROW('Bank Schedule'!$K$2:$K$825)), ROW(15:15))), "")} | M18: {=IFERROR(INDEX('Bank Schedule'!N:N, SMALL(IF('Bank Schedule'!$K$2:$K$825="Vacant", ROW('Bank Schedule'!$K$2:$K$825)), ROW(15:15))), "")} | N18: {=IFERROR(INDEX('Bank Schedule'!O:O, SMALL(IF('Bank Schedule'!$K$2:$K$825="Vacant", ROW('Bank Schedule'!$K$2:$K$825)), ROW(15:15))), "")} | O18: {=IFERROR(INDEX('Bank Schedule'!P:P, SMALL(IF('Bank Schedule'!$K$2:$K$825="Vacant", ROW('Bank Schedule'!$K$2:$K$825)), ROW(15:15))), "")} | P18: {=IFERROR(INDEX('Bank Schedule'!Q:Q, SMALL(IF('Bank Schedule'!$K$2:$K$825="Vacant", ROW('Bank Schedule'!$K$2:$K$825)), ROW(15:15))), "")} | Q18: {=IFERROR(INDEX('Bank Schedule'!R:R, SMALL(IF('Bank Schedule'!$K$2:$K$825="Vacant", ROW('Bank Schedule'!$K$2:$K$825)), ROW(15:15))), "")} | R18: {=IFERROR(INDEX('Bank Schedule'!S:S, SMALL(IF('Bank Schedule'!$K$2:$K$825="Vacant", ROW('Bank Schedule'!$K$2:$K$825)), ROW(15:15))), "")} | S18: {=IFERROR(INDEX('Bank Schedule'!T:T, SMALL(IF('Bank Schedule'!$K$2:$K$825="Vacant", ROW('Bank Schedule'!$K$2:$K$825)), ROW(15:15))), "")} | T18: {=IFERROR(INDEX('Bank Schedule'!U:U, SMALL(IF('Bank Schedule'!$K$2:$K$825="Vacant", ROW('Bank Schedule'!$K$2:$K$825)), ROW(15:15))), "")} | U18: {=IFERROR(INDEX('Bank Schedule'!V:V, SMALL(IF('Bank Schedule'!$K$2:$K$825="Vacant", ROW('Bank Schedule'!$K$2:$K$825)), ROW(15:15))), "")} | V18: {=IFERROR(INDEX('Bank Schedule'!W:W, SMALL(IF('Bank Schedule'!$K$2:$K$825="Vacant", ROW('Bank Schedule'!$K$2:$K$825)), ROW(15:15))), "")} | W18: {=IFERROR(INDEX('Bank Schedule'!X:X, SMALL(IF('Bank Schedule'!$K$2:$K$825="Vacant", ROW('Bank Schedule'!$K$2:$K$825)), ROW(15:15))), "")} | X18: {=IFERROR(INDEX('Bank Schedule'!Y:Y, SMALL(IF('Bank Schedule'!$K$2:$K$825="Vacant", ROW('Bank Schedule'!$K$2:$K$825)), ROW(15:15))), "")} | Y18: {=IFERROR(INDEX('Bank Schedule'!Z:Z, SMALL(IF('Bank Schedule'!$K$2:$K$825="Vacant", ROW('Bank Schedule'!$K$2:$K$825)), ROW(15:15))), "")} | Z18: {=IFERROR(INDEX('Bank Schedule'!AA:AA, SMALL(IF('Bank Schedule'!$K$2:$K$825="Vacant", ROW('Bank Schedule'!$K$2:$K$825)), ROW(15:15))), "")} | AA18: {=IFERROR(INDEX('Bank Schedule'!AB:AB, SMALL(IF('Bank Schedule'!$K$2:$K$825="Vacant", ROW('Bank Schedule'!$K$2:$K$825)), ROW(15:15))), "")} | AB18: {=IFERROR(INDEX('Bank Schedule'!AC:AC, SMALL(IF('Bank Schedule'!$K$2:$K$825="Vacant", ROW('Bank Schedule'!$K$2:$K$825)), ROW(15:15))), "")} | AC18: {=IFERROR(INDEX('Bank Schedule'!AD:AD, SMALL(IF('Bank Schedule'!$K$2:$K$825="Vacant", ROW('Bank Schedule'!$K$2:$K$825)), ROW(15:15))), "")} | AD18: {=IFERROR(INDEX('Bank Schedule'!AE:AE, SMALL(IF('Bank Schedule'!$K$2:$K$825="Vacant", ROW('Bank Schedule'!$K$2:$K$825)), ROW(15:15))), "")} | AE18: {=IFERROR(INDEX('Bank Schedule'!AF:AF, SMALL(IF('Bank Schedule'!$K$2:$K$825="Vacant", ROW('Bank Schedule'!$K$2:$K$825)), ROW(15:15))), "")} | AF18: {=IFERROR(INDEX('Bank Schedule'!AG:AG, SMALL(IF('Bank Schedule'!$K$2:$K$825="Vacant", ROW('Bank Schedule'!$K$2:$K$825)), ROW(15:15))), "")}
A19: {=IFERROR(INDEX('Bank Schedule'!A:A, SMALL(IF('Bank Schedule'!$K$2:$K$825="Vacant", ROW('Bank Schedule'!$K$2:$K$825)), ROW(16:16))), "")} | B19: {=IFERROR(INDEX('Bank Schedule'!B:B, SMALL(IF('Bank Schedule'!$K$2:$K$825="Vacant", ROW('Bank Schedule'!$K$2:$K$825)), ROW(16:16))), "")} | C19: {=IFERROR(INDEX('Bank Schedule'!C:C, SMALL(IF('Bank Schedule'!$K$2:$K$825="Vacant", ROW('Bank Schedule'!$K$2:$K$825)), ROW(16:16))), "")} | D19: {=IFERROR(INDEX('Bank Schedule'!D:D, SMALL(IF('Bank Schedule'!$K$2:$K$825="Vacant", ROW('Bank Schedule'!$K$2:$K$825)), ROW(16:16))), "")} | E19: {=IFERROR(INDEX('Bank Schedule'!E:E, SMALL(IF('Bank Schedule'!$K$2:$K$825="Vacant", ROW('Bank Schedule'!$K$2:$K$825)), ROW(16:16))), "")} | F19: {=IFERROR(INDEX('Bank Schedule'!F:F, SMALL(IF('Bank Schedule'!$K$2:$K$825="Vacant", ROW('Bank Schedule'!$K$2:$K$825)), ROW(16:16))), "")} | G19: {=IFERROR(INDEX('Bank Schedule'!G:G, SMALL(IF('Bank Schedule'!$K$2:$K$825="Vacant", ROW('Bank Schedule'!$K$2:$K$825)), ROW(16:16))), "")} | H19: {=IFERROR(INDEX('Bank Schedule'!H:H, SMALL(IF('Bank Schedule'!$K$2:$K$825="Vacant", ROW('Bank Schedule'!$K$2:$K$825)), ROW(16:16))), "")} | I19: {=IFERROR(INDEX('Bank Schedule'!I:I, SMALL(IF('Bank Schedule'!$K$2:$K$825="Vacant", ROW('Bank Schedule'!$K$2:$K$825)), ROW(16:16))), "")} | J19: {=IFERROR(INDEX('Bank Schedule'!K:K, SMALL(IF('Bank Schedule'!$K$2:$K$825="Vacant", ROW('Bank Schedule'!$K$2:$K$825)), ROW(16:16))), "")} | K19: {=IFERROR(INDEX('Bank Schedule'!L:L, SMALL(IF('Bank Schedule'!$K$2:$K$825="Vacant", ROW('Bank Schedule'!$K$2:$K$825)), ROW(16:16))), "")} | L19: {=IFERROR(INDEX('Bank Schedule'!M:M, SMALL(IF('Bank Schedule'!$K$2:$K$825="Vacant", ROW('Bank Schedule'!$K$2:$K$825)), ROW(16:16))), "")} | M19: {=IFERROR(INDEX('Bank Schedule'!N:N, SMALL(IF('Bank Schedule'!$K$2:$K$825="Vacant", ROW('Bank Schedule'!$K$2:$K$825)), ROW(16:16))), "")} | N19: {=IFERROR(INDEX('Bank Schedule'!O:O, SMALL(IF('Bank Schedule'!$K$2:$K$825="Vacant", ROW('Bank Schedule'!$K$2:$K$825)), ROW(16:16))), "")} | O19: {=IFERROR(INDEX('Bank Schedule'!P:P, SMALL(IF('Bank Schedule'!$K$2:$K$825="Vacant", ROW('Bank Schedule'!$K$2:$K$825)), ROW(16:16))), "")} | P19: {=IFERROR(INDEX('Bank Schedule'!Q:Q, SMALL(IF('Bank Schedule'!$K$2:$K$825="Vacant", ROW('Bank Schedule'!$K$2:$K$825)), ROW(16:16))), "")} | Q19: {=IFERROR(INDEX('Bank Schedule'!R:R, SMALL(IF('Bank Schedule'!$K$2:$K$825="Vacant", ROW('Bank Schedule'!$K$2:$K$825)), ROW(16:16))), "")} | R19: {=IFERROR(INDEX('Bank Schedule'!S:S, SMALL(IF('Bank Schedule'!$K$2:$K$825="Vacant", ROW('Bank Schedule'!$K$2:$K$825)), ROW(16:16))), "")} | S19: {=IFERROR(INDEX('Bank Schedule'!T:T, SMALL(IF('Bank Schedule'!$K$2:$K$825="Vacant", ROW('Bank Schedule'!$K$2:$K$825)), ROW(16:16))), "")} | T19: {=IFERROR(INDEX('Bank Schedule'!U:U, SMALL(IF('Bank Schedule'!$K$2:$K$825="Vacant", ROW('Bank Schedule'!$K$2:$K$825)), ROW(16:16))), "")} | U19: {=IFERROR(INDEX('Bank Schedule'!V:V, SMALL(IF('Bank Schedule'!$K$2:$K$825="Vacant", ROW('Bank Schedule'!$K$2:$K$825)), ROW(16:16))), "")} | V19: {=IFERROR(INDEX('Bank Schedule'!W:W, SMALL(IF('Bank Schedule'!$K$2:$K$825="Vacant", ROW('Bank Schedule'!$K$2:$K$825)), ROW(16:16))), "")} | W19: {=IFERROR(INDEX('Bank Schedule'!X:X, SMALL(IF('Bank Schedule'!$K$2:$K$825="Vacant", ROW('Bank Schedule'!$K$2:$K$825)), ROW(16:16))), "")} | X19: {=IFERROR(INDEX('Bank Schedule'!Y:Y, SMALL(IF('Bank Schedule'!$K$2:$K$825="Vacant", ROW('Bank Schedule'!$K$2:$K$825)), ROW(16:16))), "")} | Y19: {=IFERROR(INDEX('Bank Schedule'!Z:Z, SMALL(IF('Bank Schedule'!$K$2:$K$825="Vacant", ROW('Bank Schedule'!$K$2:$K$825)), ROW(16:16))), "")} | Z19: {=IFERROR(INDEX('Bank Schedule'!AA:AA, SMALL(IF('Bank Schedule'!$K$2:$K$825="Vacant", ROW('Bank Schedule'!$K$2:$K$825)), ROW(16:16))), "")} | AA19: {=IFERROR(INDEX('Bank Schedule'!AB:AB, SMALL(IF('Bank Schedule'!$K$2:$K$825="Vacant", ROW('Bank Schedule'!$K$2:$K$825)), ROW(16:16))), "")} | AB19: {=IFERROR(INDEX('Bank Schedule'!AC:AC, SMALL(IF('Bank Schedule'!$K$2:$K$825="Vacant", ROW('Bank Schedule'!$K$2:$K$825)), ROW(16:16))), "")} | AC19: {=IFERROR(INDEX('Bank Schedule'!AD:AD, SMALL(IF('Bank Schedule'!$K$2:$K$825="Vacant", ROW('Bank Schedule'!$K$2:$K$825)), ROW(16:16))), "")} | AD19: {=IFERROR(INDEX('Bank Schedule'!AE:AE, SMALL(IF('Bank Schedule'!$K$2:$K$825="Vacant", ROW('Bank Schedule'!$K$2:$K$825)), ROW(16:16))), "")} | AE19: {=IFERROR(INDEX('Bank Schedule'!AF:AF, SMALL(IF('Bank Schedule'!$K$2:$K$825="Vacant", ROW('Bank Schedule'!$K$2:$K$825)), ROW(16:16))), "")} | AF19: {=IFERROR(INDEX('Bank Schedule'!AG:AG, SMALL(IF('Bank Schedule'!$K$2:$K$825="Vacant", ROW('Bank Schedule'!$K$2:$K$825)), ROW(16:16))), "")}
A20: {=IFERROR(INDEX('Bank Schedule'!A:A, SMALL(IF('Bank Schedule'!$K$2:$K$825="Vacant", ROW('Bank Schedule'!$K$2:$K$825)), ROW(17:17))), "")} | B20: {=IFERROR(INDEX('Bank Schedule'!B:B, SMALL(IF('Bank Schedule'!$K$2:$K$825="Vacant", ROW('Bank Schedule'!$K$2:$K$825)), ROW(17:17))), "")} | C20: {=IFERROR(INDEX('Bank Schedule'!C:C, SMALL(IF('Bank Schedule'!$K$2:$K$825="Vacant", ROW('Bank Schedule'!$K$2:$K$825)), ROW(17:17))), "")} | D20: {=IFERROR(INDEX('Bank Schedule'!D:D, SMALL(IF('Bank Schedule'!$K$2:$K$825="Vacant", ROW('Bank Schedule'!$K$2:$K$825)), ROW(17:17))), "")} | E20: {=IFERROR(INDEX('Bank Schedule'!E:E, SMALL(IF('Bank Schedule'!$K$2:$K$825="Vacant", ROW('Bank Schedule'!$K$2:$K$825)), ROW(17:17))), "")} | F20: {=IFERROR(INDEX('Bank Schedule'!F:F, SMALL(IF('Bank Schedule'!$K$2:$K$825="Vacant", ROW('Bank Schedule'!$K$2:$K$825)), ROW(17:17))), "")} | G20: {=IFERROR(INDEX('Bank Schedule'!G:G, SMALL(IF('Bank Schedule'!$K$2:$K$825="Vacant", ROW('Bank Schedule'!$K$2:$K$825)), ROW(17:17))), "")} | H20: {=IFERROR(INDEX('Bank Schedule'!H:H, SMALL(IF('Bank Schedule'!$K$2:$K$825="Vacant", ROW('Bank Schedule'!$K$2:$K$825)), ROW(17:17))), "")} | I20: {=IFERROR(INDEX('Bank Schedule'!I:I, SMALL(IF('Bank Schedule'!$K$2:$K$825="Vacant", ROW('Bank Schedule'!$K$2:$K$825)), ROW(17:17))), "")} | J20: {=IFERROR(INDEX('Bank Schedule'!K:K, SMALL(IF('Bank Schedule'!$K$2:$K$825="Vacant", ROW('Bank Schedule'!$K$2:$K$825)), ROW(17:17))), "")} | K20: {=IFERROR(INDEX('Bank Schedule'!L:L, SMALL(IF('Bank Schedule'!$K$2:$K$825="Vacant", ROW('Bank Schedule'!$K$2:$K$825)), ROW(17:17))), "")} | L20: {=IFERROR(INDEX('Bank Schedule'!M:M, SMALL(IF('Bank Schedule'!$K$2:$K$825="Vacant", ROW('Bank Schedule'!$K$2:$K$825)), ROW(17:17))), "")} | M20: {=IFERROR(INDEX('Bank Schedule'!N:N, SMALL(IF('Bank Schedule'!$K$2:$K$825="Vacant", ROW('Bank Schedule'!$K$2:$K$825)), ROW(17:17))), "")} | N20: {=IFERROR(INDEX('Bank Schedule'!O:O, SMALL(IF('Bank Schedule'!$K$2:$K$825="Vacant", ROW('Bank Schedule'!$K$2:$K$825)), ROW(17:17))), "")} | O20: {=IFERROR(INDEX('Bank Schedule'!P:P, SMALL(IF('Bank Schedule'!$K$2:$K$825="Vacant", ROW('Bank Schedule'!$K$2:$K$825)), ROW(17:17))), "")} | P20: {=IFERROR(INDEX('Bank Schedule'!Q:Q, SMALL(IF('Bank Schedule'!$K$2:$K$825="Vacant", ROW('Bank Schedule'!$K$2:$K$825)), ROW(17:17))), "")} | Q20: {=IFERROR(INDEX('Bank Schedule'!R:R, SMALL(IF('Bank Schedule'!$K$2:$K$825="Vacant", ROW('Bank Schedule'!$K$2:$K$825)), ROW(17:17))), "")} | R20: {=IFERROR(INDEX('Bank Schedule'!S:S, SMALL(IF('Bank Schedule'!$K$2:$K$825="Vacant", ROW('Bank Schedule'!$K$2:$K$825)), ROW(17:17))), "")} | S20: {=IFERROR(INDEX('Bank Schedule'!T:T, SMALL(IF('Bank Schedule'!$K$2:$K$825="Vacant", ROW('Bank Schedule'!$K$2:$K$825)), ROW(17:17))), "")} | T20: {=IFERROR(INDEX('Bank Schedule'!U:U, SMALL(IF('Bank Schedule'!$K$2:$K$825="Vacant", ROW('Bank Schedule'!$K$2:$K$825)), ROW(17:17))), "")} | U20: {=IFERROR(INDEX('Bank Schedule'!V:V, SMALL(IF('Bank Schedule'!$K$2:$K$825="Vacant", ROW('Bank Schedule'!$K$2:$K$825)), ROW(17:17))), "")} | V20: {=IFERROR(INDEX('Bank Schedule'!W:W, SMALL(IF('Bank Schedule'!$K$2:$K$825="Vacant", ROW('Bank Schedule'!$K$2:$K$825)), ROW(17:17))), "")} | W20: {=IFERROR(INDEX('Bank Schedule'!X:X, SMALL(IF('Bank Schedule'!$K$2:$K$825="Vacant", ROW('Bank Schedule'!$K$2:$K$825)), ROW(17:17))), "")} | X20: {=IFERROR(INDEX('Bank Schedule'!Y:Y, SMALL(IF('Bank Schedule'!$K$2:$K$825="Vacant", ROW('Bank Schedule'!$K$2:$K$825)), ROW(17:17))), "")} | Y20: {=IFERROR(INDEX('Bank Schedule'!Z:Z, SMALL(IF('Bank Schedule'!$K$2:$K$825="Vacant", ROW('Bank Schedule'!$K$2:$K$825)), ROW(17:17))), "")} | Z20: {=IFERROR(INDEX('Bank Schedule'!AA:AA, SMALL(IF('Bank Schedule'!$K$2:$K$825="Vacant", ROW('Bank Schedule'!$K$2:$K$825)), ROW(17:17))), "")} | AA20: {=IFERROR(INDEX('Bank Schedule'!AB:AB, SMALL(IF('Bank Schedule'!$K$2:$K$825="Vacant", ROW('Bank Schedule'!$K$2:$K$825)), ROW(17:17))), "")} | AB20: {=IFERROR(INDEX('Bank Schedule'!AC:AC, SMALL(IF('Bank Schedule'!$K$2:$K$825="Vacant", ROW('Bank Schedule'!$K$2:$K$825)), ROW(17:17))), "")} | AC20: {=IFERROR(INDEX('Bank Schedule'!AD:AD, SMALL(IF('Bank Schedule'!$K$2:$K$825="Vacant", ROW('Bank Schedule'!$K$2:$K$825)), ROW(17:17))), "")} | AD20: {=IFERROR(INDEX('Bank Schedule'!AE:AE, SMALL(IF('Bank Schedule'!$K$2:$K$825="Vacant", ROW('Bank Schedule'!$K$2:$K$825)), ROW(17:17))), "")} | AE20: {=IFERROR(INDEX('Bank Schedule'!AF:AF, SMALL(IF('Bank Schedule'!$K$2:$K$825="Vacant", ROW('Bank Schedule'!$K$2:$K$825)), ROW(17:17))), "")} | AF20: {=IFERROR(INDEX('Bank Schedule'!AG:AG, SMALL(IF('Bank Schedule'!$K$2:$K$825="Vacant", ROW('Bank Schedule'!$K$2:$K$825)), ROW(17:17))), "")}
A21: {=IFERROR(INDEX('Bank Schedule'!A:A, SMALL(IF('Bank Schedule'!$K$2:$K$825="Vacant", ROW('Bank Schedule'!$K$2:$K$825)), ROW(18:18))), "")} | B21: {=IFERROR(INDEX('Bank Schedule'!B:B, SMALL(IF('Bank Schedule'!$K$2:$K$825="Vacant", ROW('Bank Schedule'!$K$2:$K$825)), ROW(18:18))), "")} | C21: {=IFERROR(INDEX('Bank Schedule'!C:C, SMALL(IF('Bank Schedule'!$K$2:$K$825="Vacant", ROW('Bank Schedule'!$K$2:$K$825)), ROW(18:18))), "")} | D21: {=IFERROR(INDEX('Bank Schedule'!D:D, SMALL(IF('Bank Schedule'!$K$2:$K$825="Vacant", ROW('Bank Schedule'!$K$2:$K$825)), ROW(18:18))), "")} | E21: {=IFERROR(INDEX('Bank Schedule'!E:E, SMALL(IF('Bank Schedule'!$K$2:$K$825="Vacant", ROW('Bank Schedule'!$K$2:$K$825)), ROW(18:18))), "")} | F21: {=IFERROR(INDEX('Bank Schedule'!F:F, SMALL(IF('Bank Schedule'!$K$2:$K$825="Vacant", ROW('Bank Schedule'!$K$2:$K$825)), ROW(18:18))), "")} | G21: {=IFERROR(INDEX('Bank Schedule'!G:G, SMALL(IF('Bank Schedule'!$K$2:$K$825="Vacant", ROW('Bank Schedule'!$K$2:$K$825)), ROW(18:18))), "")} | H21: {=IFERROR(INDEX('Bank Schedule'!H:H, SMALL(IF('Bank Schedule'!$K$2:$K$825="Vacant", ROW('Bank Schedule'!$K$2:$K$825)), ROW(18:18))), "")} | I21: {=IFERROR(INDEX('Bank Schedule'!I:I, SMALL(IF('Bank Schedule'!$K$2:$K$825="Vacant", ROW('Bank Schedule'!$K$2:$K$825)), ROW(18:18))), "")} | J21: {=IFERROR(INDEX('Bank Schedule'!K:K, SMALL(IF('Bank Schedule'!$K$2:$K$825="Vacant", ROW('Bank Schedule'!$K$2:$K$825)), ROW(18:18))), "")} | K21: {=IFERROR(INDEX('Bank Schedule'!L:L, SMALL(IF('Bank Schedule'!$K$2:$K$825="Vacant", ROW('Bank Schedule'!$K$2:$K$825)), ROW(18:18))), "")} | L21: {=IFERROR(INDEX('Bank Schedule'!M:M, SMALL(IF('Bank Schedule'!$K$2:$K$825="Vacant", ROW('Bank Schedule'!$K$2:$K$825)), ROW(18:18))), "")} | M21: {=IFERROR(INDEX('Bank Schedule'!N:N, SMALL(IF('Bank Schedule'!$K$2:$K$825="Vacant", ROW('Bank Schedule'!$K$2:$K$825)), ROW(18:18))), "")} | N21: {=IFERROR(INDEX('Bank Schedule'!O:O, SMALL(IF('Bank Schedule'!$K$2:$K$825="Vacant", ROW('Bank Schedule'!$K$2:$K$825)), ROW(18:18))), "")} | O21: {=IFERROR(INDEX('Bank Schedule'!P:P, SMALL(IF('Bank Schedule'!$K$2:$K$825="Vacant", ROW('Bank Schedule'!$K$2:$K$825)), ROW(18:18))), "")} | P21: {=IFERROR(INDEX('Bank Schedule'!Q:Q, SMALL(IF('Bank Schedule'!$K$2:$K$825="Vacant", ROW('Bank Schedule'!$K$2:$K$825)), ROW(18:18))), "")} | Q21: {=IFERROR(INDEX('Bank Schedule'!R:R, SMALL(IF('Bank Schedule'!$K$2:$K$825="Vacant", ROW('Bank Schedule'!$K$2:$K$825)), ROW(18:18))), "")} | R21: {=IFERROR(INDEX('Bank Schedule'!S:S, SMALL(IF('Bank Schedule'!$K$2:$K$825="Vacant", ROW('Bank Schedule'!$K$2:$K$825)), ROW(18:18))), "")} | S21: {=IFERROR(INDEX('Bank Schedule'!T:T, SMALL(IF('Bank Schedule'!$K$2:$K$825="Vacant", ROW('Bank Schedule'!$K$2:$K$825)), ROW(18:18))), "")} | T21: {=IFERROR(INDEX('Bank Schedule'!U:U, SMALL(IF('Bank Schedule'!$K$2:$K$825="Vacant", ROW('Bank Schedule'!$K$2:$K$825)), ROW(18:18))), "")} | U21: {=IFERROR(INDEX('Bank Schedule'!V:V, SMALL(IF('Bank Schedule'!$K$2:$K$825="Vacant", ROW('Bank Schedule'!$K$2:$K$825)), ROW(18:18))), "")} | V21: {=IFERROR(INDEX('Bank Schedule'!W:W, SMALL(IF('Bank Schedule'!$K$2:$K$825="Vacant", ROW('Bank Schedule'!$K$2:$K$825)), ROW(18:18))), "")} | W21: {=IFERROR(INDEX('Bank Schedule'!X:X, SMALL(IF('Bank Schedule'!$K$2:$K$825="Vacant", ROW('Bank Schedule'!$K$2:$K$825)), ROW(18:18))), "")} | X21: {=IFERROR(INDEX('Bank Schedule'!Y:Y, SMALL(IF('Bank Schedule'!$K$2:$K$825="Vacant", ROW('Bank Schedule'!$K$2:$K$825)), ROW(18:18))), "")} | Y21: {=IFERROR(INDEX('Bank Schedule'!Z:Z, SMALL(IF('Bank Schedule'!$K$2:$K$825="Vacant", ROW('Bank Schedule'!$K$2:$K$825)), ROW(18:18))), "")} | Z21: {=IFERROR(INDEX('Bank Schedule'!AA:AA, SMALL(IF('Bank Schedule'!$K$2:$K$825="Vacant", ROW('Bank Schedule'!$K$2:$K$825)), ROW(18:18))), "")} | AA21: {=IFERROR(INDEX('Bank Schedule'!AB:AB, SMALL(IF('Bank Schedule'!$K$2:$K$825="Vacant", ROW('Bank Schedule'!$K$2:$K$825)), ROW(18:18))), "")} | AB21: {=IFERROR(INDEX('Bank Schedule'!AC:AC, SMALL(IF('Bank Schedule'!$K$2:$K$825="Vacant", ROW('Bank Schedule'!$K$2:$K$825)), ROW(18:18))), "")} | AC21: {=IFERROR(INDEX('Bank Schedule'!AD:AD, SMALL(IF('Bank Schedule'!$K$2:$K$825="Vacant", ROW('Bank Schedule'!$K$2:$K$825)), ROW(18:18))), "")} | AD21: {=IFERROR(INDEX('Bank Schedule'!AE:AE, SMALL(IF('Bank Schedule'!$K$2:$K$825="Vacant", ROW('Bank Schedule'!$K$2:$K$825)), ROW(18:18))), "")} | AE21: {=IFERROR(INDEX('Bank Schedule'!AF:AF, SMALL(IF('Bank Schedule'!$K$2:$K$825="Vacant", ROW('Bank Schedule'!$K$2:$K$825)), ROW(18:18))), "")} | AF21: {=IFERROR(INDEX('Bank Schedule'!AG:AG, SMALL(IF('Bank Schedule'!$K$2:$K$825="Vacant", ROW('Bank Schedule'!$K$2:$K$825)), ROW(18:18))), "")}
A22: {=IFERROR(INDEX('Bank Schedule'!A:A, SMALL(IF('Bank Schedule'!$K$2:$K$825="Vacant", ROW('Bank Schedule'!$K$2:$K$825)), ROW(19:19))), "")} | B22: {=IFERROR(INDEX('Bank Schedule'!B:B, SMALL(IF('Bank Schedule'!$K$2:$K$825="Vacant", ROW('Bank Schedule'!$K$2:$K$825)), ROW(19:19))), "")} | C22: {=IFERROR(INDEX('Bank Schedule'!C:C, SMALL(IF('Bank Schedule'!$K$2:$K$825="Vacant", ROW('Bank Schedule'!$K$2:$K$825)), ROW(19:19))), "")} | D22: {=IFERROR(INDEX('Bank Schedule'!D:D, SMALL(IF('Bank Schedule'!$K$2:$K$825="Vacant", ROW('Bank Schedule'!$K$2:$K$825)), ROW(19:19))), "")} | E22: {=IFERROR(INDEX('Bank Schedule'!E:E, SMALL(IF('Bank Schedule'!$K$2:$K$825="Vacant", ROW('Bank Schedule'!$K$2:$K$825)), ROW(19:19))), "")} | F22: {=IFERROR(INDEX('Bank Schedule'!F:F, SMALL(IF('Bank Schedule'!$K$2:$K$825="Vacant", ROW('Bank Schedule'!$K$2:$K$825)), ROW(19:19))), "")} | G22: {=IFERROR(INDEX('Bank Schedule'!G:G, SMALL(IF('Bank Schedule'!$K$2:$K$825="Vacant", ROW('Bank Schedule'!$K$2:$K$825)), ROW(19:19))), "")} | H22: {=IFERROR(INDEX('Bank Schedule'!H:H, SMALL(IF('Bank Schedule'!$K$2:$K$825="Vacant", ROW('Bank Schedule'!$K$2:$K$825)), ROW(19:19))), "")} | I22: {=IFERROR(INDEX('Bank Schedule'!I:I, SMALL(IF('Bank Schedule'!$K$2:$K$825="Vacant", ROW('Bank Schedule'!$K$2:$K$825)), ROW(19:19))), "")} | J22: {=IFERROR(INDEX('Bank Schedule'!K:K, SMALL(IF('Bank Schedule'!$K$2:$K$825="Vacant", ROW('Bank Schedule'!$K$2:$K$825)), ROW(19:19))), "")} | K22: {=IFERROR(INDEX('Bank Schedule'!L:L, SMALL(IF('Bank Schedule'!$K$2:$K$825="Vacant", ROW('Bank Schedule'!$K$2:$K$825)), ROW(19:19))), "")} | L22: {=IFERROR(INDEX('Bank Schedule'!M:M, SMALL(IF('Bank Schedule'!$K$2:$K$825="Vacant", ROW('Bank Schedule'!$K$2:$K$825)), ROW(19:19))), "")} | M22: {=IFERROR(INDEX('Bank Schedule'!N:N, SMALL(IF('Bank Schedule'!$K$2:$K$825="Vacant", ROW('Bank Schedule'!$K$2:$K$825)), ROW(19:19))), "")} | N22: {=IFERROR(INDEX('Bank Schedule'!O:O, SMALL(IF('Bank Schedule'!$K$2:$K$825="Vacant", ROW('Bank Schedule'!$K$2:$K$825)), ROW(19:19))), "")} | O22: {=IFERROR(INDEX('Bank Schedule'!P:P, SMALL(IF('Bank Schedule'!$K$2:$K$825="Vacant", ROW('Bank Schedule'!$K$2:$K$825)), ROW(19:19))), "")} | P22: {=IFERROR(INDEX('Bank Schedule'!Q:Q, SMALL(IF('Bank Schedule'!$K$2:$K$825="Vacant", ROW('Bank Schedule'!$K$2:$K$825)), ROW(19:19))), "")} | Q22: {=IFERROR(INDEX('Bank Schedule'!R:R, SMALL(IF('Bank Schedule'!$K$2:$K$825="Vacant", ROW('Bank Schedule'!$K$2:$K$825)), ROW(19:19))), "")} | R22: {=IFERROR(INDEX('Bank Schedule'!S:S, SMALL(IF('Bank Schedule'!$K$2:$K$825="Vacant", ROW('Bank Schedule'!$K$2:$K$825)), ROW(19:19))), "")} | S22: {=IFERROR(INDEX('Bank Schedule'!T:T, SMALL(IF('Bank Schedule'!$K$2:$K$825="Vacant", ROW('Bank Schedule'!$K$2:$K$825)), ROW(19:19))), "")} | T22: {=IFERROR(INDEX('Bank Schedule'!U:U, SMALL(IF('Bank Schedule'!$K$2:$K$825="Vacant", ROW('Bank Schedule'!$K$2:$K$825)), ROW(19:19))), "")} | U22: {=IFERROR(INDEX('Bank Schedule'!V:V, SMALL(IF('Bank Schedule'!$K$2:$K$825="Vacant", ROW('Bank Schedule'!$K$2:$K$825)), ROW(19:19))), "")} | V22: {=IFERROR(INDEX('Bank Schedule'!W:W, SMALL(IF('Bank Schedule'!$K$2:$K$825="Vacant", ROW('Bank Schedule'!$K$2:$K$825)), ROW(19:19))), "")} | W22: {=IFERROR(INDEX('Bank Schedule'!X:X, SMALL(IF('Bank Schedule'!$K$2:$K$825="Vacant", ROW('Bank Schedule'!$K$2:$K$825)), ROW(19:19))), "")} | X22: {=IFERROR(INDEX('Bank Schedule'!Y:Y, SMALL(IF('Bank Schedule'!$K$2:$K$825="Vacant", ROW('Bank Schedule'!$K$2:$K$825)), ROW(19:19))), "")} | Y22: {=IFERROR(INDEX('Bank Schedule'!Z:Z, SMALL(IF('Bank Schedule'!$K$2:$K$825="Vacant", ROW('Bank Schedule'!$K$2:$K$825)), ROW(19:19))), "")} | Z22: {=IFERROR(INDEX('Bank Schedule'!AA:AA, SMALL(IF('Bank Schedule'!$K$2:$K$825="Vacant", ROW('Bank Schedule'!$K$2:$K$825)), ROW(19:19))), "")} | AA22: {=IFERROR(INDEX('Bank Schedule'!AB:AB, SMALL(IF('Bank Schedule'!$K$2:$K$825="Vacant", ROW('Bank Schedule'!$K$2:$K$825)), ROW(19:19))), "")} | AB22: {=IFERROR(INDEX('Bank Schedule'!AC:AC, SMALL(IF('Bank Schedule'!$K$2:$K$825="Vacant", ROW('Bank Schedule'!$K$2:$K$825)), ROW(19:19))), "")} | AC22: {=IFERROR(INDEX('Bank Schedule'!AD:AD, SMALL(IF('Bank Schedule'!$K$2:$K$825="Vacant", ROW('Bank Schedule'!$K$2:$K$825)), ROW(19:19))), "")} | AD22: {=IFERROR(INDEX('Bank Schedule'!AE:AE, SMALL(IF('Bank Schedule'!$K$2:$K$825="Vacant", ROW('Bank Schedule'!$K$2:$K$825)), ROW(19:19))), "")} | AE22: {=IFERROR(INDEX('Bank Schedule'!AF:AF, SMALL(IF('Bank Schedule'!$K$2:$K$825="Vacant", ROW('Bank Schedule'!$K$2:$K$825)), ROW(19:19))), "")} | AF22: {=IFERROR(INDEX('Bank Schedule'!AG:AG, SMALL(IF('Bank Schedule'!$K$2:$K$825="Vacant", ROW('Bank Schedule'!$K$2:$K$825)), ROW(19:19))), "")}
A23: {=IFERROR(INDEX('Bank Schedule'!A:A, SMALL(IF('Bank Schedule'!$K$2:$K$825="Vacant", ROW('Bank Schedule'!$K$2:$K$825)), ROW(20:20))), "")} | B23: {=IFERROR(INDEX('Bank Schedule'!B:B, SMALL(IF('Bank Schedule'!$K$2:$K$825="Vacant", ROW('Bank Schedule'!$K$2:$K$825)), ROW(20:20))), "")} | C23: {=IFERROR(INDEX('Bank Schedule'!C:C, SMALL(IF('Bank Schedule'!$K$2:$K$825="Vacant", ROW('Bank Schedule'!$K$2:$K$825)), ROW(20:20))), "")} | D23: {=IFERROR(INDEX('Bank Schedule'!D:D, SMALL(IF('Bank Schedule'!$K$2:$K$825="Vacant", ROW('Bank Schedule'!$K$2:$K$825)), ROW(20:20))), "")} | E23: {=IFERROR(INDEX('Bank Schedule'!E:E, SMALL(IF('Bank Schedule'!$K$2:$K$825="Vacant", ROW('Bank Schedule'!$K$2:$K$825)), ROW(20:20))), "")} | F23: {=IFERROR(INDEX('Bank Schedule'!F:F, SMALL(IF('Bank Schedule'!$K$2:$K$825="Vacant", ROW('Bank Schedule'!$K$2:$K$825)), ROW(20:20))), "")} | G23: {=IFERROR(INDEX('Bank Schedule'!G:G, SMALL(IF('Bank Schedule'!$K$2:$K$825="Vacant", ROW('Bank Schedule'!$K$2:$K$825)), ROW(20:20))), "")} | H23: {=IFERROR(INDEX('Bank Schedule'!H:H, SMALL(IF('Bank Schedule'!$K$2:$K$825="Vacant", ROW('Bank Schedule'!$K$2:$K$825)), ROW(20:20))), "")} | I23: {=IFERROR(INDEX('Bank Schedule'!I:I, SMALL(IF('Bank Schedule'!$K$2:$K$825="Vacant", ROW('Bank Schedule'!$K$2:$K$825)), ROW(20:20))), "")} | J23: {=IFERROR(INDEX('Bank Schedule'!K:K, SMALL(IF('Bank Schedule'!$K$2:$K$825="Vacant", ROW('Bank Schedule'!$K$2:$K$825)), ROW(20:20))), "")} | K23: {=IFERROR(INDEX('Bank Schedule'!L:L, SMALL(IF('Bank Schedule'!$K$2:$K$825="Vacant", ROW('Bank Schedule'!$K$2:$K$825)), ROW(20:20))), "")} | L23: {=IFERROR(INDEX('Bank Schedule'!M:M, SMALL(IF('Bank Schedule'!$K$2:$K$825="Vacant", ROW('Bank Schedule'!$K$2:$K$825)), ROW(20:20))), "")} | M23: {=IFERROR(INDEX('Bank Schedule'!N:N, SMALL(IF('Bank Schedule'!$K$2:$K$825="Vacant", ROW('Bank Schedule'!$K$2:$K$825)), ROW(20:20))), "")} | N23: {=IFERROR(INDEX('Bank Schedule'!O:O, SMALL(IF('Bank Schedule'!$K$2:$K$825="Vacant", ROW('Bank Schedule'!$K$2:$K$825)), ROW(20:20))), "")} | O23: {=IFERROR(INDEX('Bank Schedule'!P:P, SMALL(IF('Bank Schedule'!$K$2:$K$825="Vacant", ROW('Bank Schedule'!$K$2:$K$825)), ROW(20:20))), "")} | P23: {=IFERROR(INDEX('Bank Schedule'!Q:Q, SMALL(IF('Bank Schedule'!$K$2:$K$825="Vacant", ROW('Bank Schedule'!$K$2:$K$825)), ROW(20:20))), "")} | Q23: {=IFERROR(INDEX('Bank Schedule'!R:R, SMALL(IF('Bank Schedule'!$K$2:$K$825="Vacant", ROW('Bank Schedule'!$K$2:$K$825)), ROW(20:20))), "")} | R23: {=IFERROR(INDEX('Bank Schedule'!S:S, SMALL(IF('Bank Schedule'!$K$2:$K$825="Vacant", ROW('Bank Schedule'!$K$2:$K$825)), ROW(20:20))), "")} | S23: {=IFERROR(INDEX('Bank Schedule'!T:T, SMALL(IF('Bank Schedule'!$K$2:$K$825="Vacant", ROW('Bank Schedule'!$K$2:$K$825)), ROW(20:20))), "")} | T23: {=IFERROR(INDEX('Bank Schedule'!U:U, SMALL(IF('Bank Schedule'!$K$2:$K$825="Vacant", ROW('Bank Schedule'!$K$2:$K$825)), ROW(20:20))), "")} | U23: {=IFERROR(INDEX('Bank Schedule'!V:V, SMALL(IF('Bank Schedule'!$K$2:$K$825="Vacant", ROW('Bank Schedule'!$K$2:$K$825)), ROW(20:20))), "")} | V23: {=IFERROR(INDEX('Bank Schedule'!W:W, SMALL(IF('Bank Schedule'!$K$2:$K$825="Vacant", ROW('Bank Schedule'!$K$2:$K$825)), ROW(20:20))), "")} | W23: {=IFERROR(INDEX('Bank Schedule'!X:X, SMALL(IF('Bank Schedule'!$K$2:$K$825="Vacant", ROW('Bank Schedule'!$K$2:$K$825)), ROW(20:20))), "")} | X23: {=IFERROR(INDEX('Bank Schedule'!Y:Y, SMALL(IF('Bank Schedule'!$K$2:$K$825="Vacant", ROW('Bank Schedule'!$K$2:$K$825)), ROW(20:20))), "")} | Y23: {=IFERROR(INDEX('Bank Schedule'!Z:Z, SMALL(IF('Bank Schedule'!$K$2:$K$825="Vacant", ROW('Bank Schedule'!$K$2:$K$825)), ROW(20:20))), "")} | Z23: {=IFERROR(INDEX('Bank Schedule'!AA:AA, SMALL(IF('Bank Schedule'!$K$2:$K$825="Vacant", ROW('Bank Schedule'!$K$2:$K$825)), ROW(20:20))), "")} | AA23: {=IFERROR(INDEX('Bank Schedule'!AB:AB, SMALL(IF('Bank Schedule'!$K$2:$K$825="Vacant", ROW('Bank Schedule'!$K$2:$K$825)), ROW(20:20))), "")} | AB23: {=IFERROR(INDEX('Bank Schedule'!AC:AC, SMALL(IF('Bank Schedule'!$K$2:$K$825="Vacant", ROW('Bank Schedule'!$K$2:$K$825)), ROW(20:20))), "")} | AC23: {=IFERROR(INDEX('Bank Schedule'!AD:AD, SMALL(IF('Bank Schedule'!$K$2:$K$825="Vacant", ROW('Bank Schedule'!$K$2:$K$825)), ROW(20:20))), "")} | AD23: {=IFERROR(INDEX('Bank Schedule'!AE:AE, SMALL(IF('Bank Schedule'!$K$2:$K$825="Vacant", ROW('Bank Schedule'!$K$2:$K$825)), ROW(20:20))), "")} | AE23: {=IFERROR(INDEX('Bank Schedule'!AF:AF, SMALL(IF('Bank Schedule'!$K$2:$K$825="Vacant", ROW('Bank Schedule'!$K$2:$K$825)), ROW(20:20))), "")} | AF23: {=IFERROR(INDEX('Bank Schedule'!AG:AG, SMALL(IF('Bank Schedule'!$K$2:$K$825="Vacant", ROW('Bank Schedule'!$K$2:$K$825)), ROW(20:20))), "")}
A24: {=IFERROR(INDEX('Bank Schedule'!A:A, SMALL(IF('Bank Schedule'!$K$2:$K$825="Vacant", ROW('Bank Schedule'!$K$2:$K$825)), ROW(21:21))), "")} | B24: {=IFERROR(INDEX('Bank Schedule'!B:B, SMALL(IF('Bank Schedule'!$K$2:$K$825="Vacant", ROW('Bank Schedule'!$K$2:$K$825)), ROW(21:21))), "")} | C24: {=IFERROR(INDEX('Bank Schedule'!C:C, SMALL(IF('Bank Schedule'!$K$2:$K$825="Vacant", ROW('Bank Schedule'!$K$2:$K$825)), ROW(21:21))), "")} | D24: {=IFERROR(INDEX('Bank Schedule'!D:D, SMALL(IF('Bank Schedule'!$K$2:$K$825="Vacant", ROW('Bank Schedule'!$K$2:$K$825)), ROW(21:21))), "")} | E24: {=IFERROR(INDEX('Bank Schedule'!E:E, SMALL(IF('Bank Schedule'!$K$2:$K$825="Vacant", ROW('Bank Schedule'!$K$2:$K$825)), ROW(21:21))), "")} | F24: {=IFERROR(INDEX('Bank Schedule'!F:F, SMALL(IF('Bank Schedule'!$K$2:$K$825="Vacant", ROW('Bank Schedule'!$K$2:$K$825)), ROW(21:21))), "")} | G24: {=IFERROR(INDEX('Bank Schedule'!G:G, SMALL(IF('Bank Schedule'!$K$2:$K$825="Vacant", ROW('Bank Schedule'!$K$2:$K$825)), ROW(21:21))), "")} | H24: {=IFERROR(INDEX('Bank Schedule'!H:H, SMALL(IF('Bank Schedule'!$K$2:$K$825="Vacant", ROW('Bank Schedule'!$K$2:$K$825)), ROW(21:21))), "")} | I24: {=IFERROR(INDEX('Bank Schedule'!I:I, SMALL(IF('Bank Schedule'!$K$2:$K$825="Vacant", ROW('Bank Schedule'!$K$2:$K$825)), ROW(21:21))), "")} | J24: {=IFERROR(INDEX('Bank Schedule'!K:K, SMALL(IF('Bank Schedule'!$K$2:$K$825="Vacant", ROW('Bank Schedule'!$K$2:$K$825)), ROW(21:21))), "")} | K24: {=IFERROR(INDEX('Bank Schedule'!L:L, SMALL(IF('Bank Schedule'!$K$2:$K$825="Vacant", ROW('Bank Schedule'!$K$2:$K$825)), ROW(21:21))), "")} | L24: {=IFERROR(INDEX('Bank Schedule'!M:M, SMALL(IF('Bank Schedule'!$K$2:$K$825="Vacant", ROW('Bank Schedule'!$K$2:$K$825)), ROW(21:21))), "")} | M24: {=IFERROR(INDEX('Bank Schedule'!N:N, SMALL(IF('Bank Schedule'!$K$2:$K$825="Vacant", ROW('Bank Schedule'!$K$2:$K$825)), ROW(21:21))), "")} | N24: {=IFERROR(INDEX('Bank Schedule'!O:O, SMALL(IF('Bank Schedule'!$K$2:$K$825="Vacant", ROW('Bank Schedule'!$K$2:$K$825)), ROW(21:21))), "")} | O24: {=IFERROR(INDEX('Bank Schedule'!P:P, SMALL(IF('Bank Schedule'!$K$2:$K$825="Vacant", ROW('Bank Schedule'!$K$2:$K$825)), ROW(21:21))), "")} | P24: {=IFERROR(INDEX('Bank Schedule'!Q:Q, SMALL(IF('Bank Schedule'!$K$2:$K$825="Vacant", ROW('Bank Schedule'!$K$2:$K$825)), ROW(21:21))), "")} | Q24: {=IFERROR(INDEX('Bank Schedule'!R:R, SMALL(IF('Bank Schedule'!$K$2:$K$825="Vacant", ROW('Bank Schedule'!$K$2:$K$825)), ROW(21:21))), "")} | R24: {=IFERROR(INDEX('Bank Schedule'!S:S, SMALL(IF('Bank Schedule'!$K$2:$K$825="Vacant", ROW('Bank Schedule'!$K$2:$K$825)), ROW(21:21))), "")} | S24: {=IFERROR(INDEX('Bank Schedule'!T:T, SMALL(IF('Bank Schedule'!$K$2:$K$825="Vacant", ROW('Bank Schedule'!$K$2:$K$825)), ROW(21:21))), "")} | T24: {=IFERROR(INDEX('Bank Schedule'!U:U, SMALL(IF('Bank Schedule'!$K$2:$K$825="Vacant", ROW('Bank Schedule'!$K$2:$K$825)), ROW(21:21))), "")} | U24: {=IFERROR(INDEX('Bank Schedule'!V:V, SMALL(IF('Bank Schedule'!$K$2:$K$825="Vacant", ROW('Bank Schedule'!$K$2:$K$825)), ROW(21:21))), "")} | V24: {=IFERROR(INDEX('Bank Schedule'!W:W, SMALL(IF('Bank Schedule'!$K$2:$K$825="Vacant", ROW('Bank Schedule'!$K$2:$K$825)), ROW(21:21))), "")} | W24: {=IFERROR(INDEX('Bank Schedule'!X:X, SMALL(IF('Bank Schedule'!$K$2:$K$825="Vacant", ROW('Bank Schedule'!$K$2:$K$825)), ROW(21:21))), "")} | X24: {=IFERROR(INDEX('Bank Schedule'!Y:Y, SMALL(IF('Bank Schedule'!$K$2:$K$825="Vacant", ROW('Bank Schedule'!$K$2:$K$825)), ROW(21:21))), "")} | Y24: {=IFERROR(INDEX('Bank Schedule'!Z:Z, SMALL(IF('Bank Schedule'!$K$2:$K$825="Vacant", ROW('Bank Schedule'!$K$2:$K$825)), ROW(21:21))), "")} | Z24: {=IFERROR(INDEX('Bank Schedule'!AA:AA, SMALL(IF('Bank Schedule'!$K$2:$K$825="Vacant", ROW('Bank Schedule'!$K$2:$K$825)), ROW(21:21))), "")} | AA24: {=IFERROR(INDEX('Bank Schedule'!AB:AB, SMALL(IF('Bank Schedule'!$K$2:$K$825="Vacant", ROW('Bank Schedule'!$K$2:$K$825)), ROW(21:21))), "")} | AB24: {=IFERROR(INDEX('Bank Schedule'!AC:AC, SMALL(IF('Bank Schedule'!$K$2:$K$825="Vacant", ROW('Bank Schedule'!$K$2:$K$825)), ROW(21:21))), "")} | AC24: {=IFERROR(INDEX('Bank Schedule'!AD:AD, SMALL(IF('Bank Schedule'!$K$2:$K$825="Vacant", ROW('Bank Schedule'!$K$2:$K$825)), ROW(21:21))), "")} | AD24: {=IFERROR(INDEX('Bank Schedule'!AE:AE, SMALL(IF('Bank Schedule'!$K$2:$K$825="Vacant", ROW('Bank Schedule'!$K$2:$K$825)), ROW(21:21))), "")} | AE24: {=IFERROR(INDEX('Bank Schedule'!AF:AF, SMALL(IF('Bank Schedule'!$K$2:$K$825="Vacant", ROW('Bank Schedule'!$K$2:$K$825)), ROW(21:21))), "")} | AF24: {=IFERROR(INDEX('Bank Schedule'!AG:AG, SMALL(IF('Bank Schedule'!$K$2:$K$825="Vacant", ROW('Bank Schedule'!$K$2:$K$825)), ROW(21:21))), "")}
A25: {=IFERROR(INDEX('Bank Schedule'!A:A, SMALL(IF('Bank Schedule'!$K$2:$K$825="Vacant", ROW('Bank Schedule'!$K$2:$K$825)), ROW(22:22))), "")} | B25: {=IFERROR(INDEX('Bank Schedule'!B:B, SMALL(IF('Bank Schedule'!$K$2:$K$825="Vacant", ROW('Bank Schedule'!$K$2:$K$825)), ROW(22:22))), "")} | C25: {=IFERROR(INDEX('Bank Schedule'!C:C, SMALL(IF('Bank Schedule'!$K$2:$K$825="Vacant", ROW('Bank Schedule'!$K$2:$K$825)), ROW(22:22))), "")} | D25: {=IFERROR(INDEX('Bank Schedule'!D:D, SMALL(IF('Bank Schedule'!$K$2:$K$825="Vacant", ROW('Bank Schedule'!$K$2:$K$825)), ROW(22:22))), "")} | E25: {=IFERROR(INDEX('Bank Schedule'!E:E, SMALL(IF('Bank Schedule'!$K$2:$K$825="Vacant", ROW('Bank Schedule'!$K$2:$K$825)), ROW(22:22))), "")} | F25: {=IFERROR(INDEX('Bank Schedule'!F:F, SMALL(IF('Bank Schedule'!$K$2:$K$825="Vacant", ROW('Bank Schedule'!$K$2:$K$825)), ROW(22:22))), "")} | G25: {=IFERROR(INDEX('Bank Schedule'!G:G, SMALL(IF('Bank Schedule'!$K$2:$K$825="Vacant", ROW('Bank Schedule'!$K$2:$K$825)), ROW(22:22))), "")} | H25: {=IFERROR(INDEX('Bank Schedule'!H:H, SMALL(IF('Bank Schedule'!$K$2:$K$825="Vacant", ROW('Bank Schedule'!$K$2:$K$825)), ROW(22:22))), "")} | I25: {=IFERROR(INDEX('Bank Schedule'!I:I, SMALL(IF('Bank Schedule'!$K$2:$K$825="Vacant", ROW('Bank Schedule'!$K$2:$K$825)), ROW(22:22))), "")} | J25: {=IFERROR(INDEX('Bank Schedule'!K:K, SMALL(IF('Bank Schedule'!$K$2:$K$825="Vacant", ROW('Bank Schedule'!$K$2:$K$825)), ROW(22:22))), "")} | K25: {=IFERROR(INDEX('Bank Schedule'!L:L, SMALL(IF('Bank Schedule'!$K$2:$K$825="Vacant", ROW('Bank Schedule'!$K$2:$K$825)), ROW(22:22))), "")} | L25: {=IFERROR(INDEX('Bank Schedule'!M:M, SMALL(IF('Bank Schedule'!$K$2:$K$825="Vacant", ROW('Bank Schedule'!$K$2:$K$825)), ROW(22:22))), "")} | M25: {=IFERROR(INDEX('Bank Schedule'!N:N, SMALL(IF('Bank Schedule'!$K$2:$K$825="Vacant", ROW('Bank Schedule'!$K$2:$K$825)), ROW(22:22))), "")} | N25: {=IFERROR(INDEX('Bank Schedule'!O:O, SMALL(IF('Bank Schedule'!$K$2:$K$825="Vacant", ROW('Bank Schedule'!$K$2:$K$825)), ROW(22:22))), "")} | O25: {=IFERROR(INDEX('Bank Schedule'!P:P, SMALL(IF('Bank Schedule'!$K$2:$K$825="Vacant", ROW('Bank Schedule'!$K$2:$K$825)), ROW(22:22))), "")} | P25: {=IFERROR(INDEX('Bank Schedule'!Q:Q, SMALL(IF('Bank Schedule'!$K$2:$K$825="Vacant", ROW('Bank Schedule'!$K$2:$K$825)), ROW(22:22))), "")} | Q25: {=IFERROR(INDEX('Bank Schedule'!R:R, SMALL(IF('Bank Schedule'!$K$2:$K$825="Vacant", ROW('Bank Schedule'!$K$2:$K$825)), ROW(22:22))), "")} | R25: {=IFERROR(INDEX('Bank Schedule'!S:S, SMALL(IF('Bank Schedule'!$K$2:$K$825="Vacant", ROW('Bank Schedule'!$K$2:$K$825)), ROW(22:22))), "")} | S25: {=IFERROR(INDEX('Bank Schedule'!T:T, SMALL(IF('Bank Schedule'!$K$2:$K$825="Vacant", ROW('Bank Schedule'!$K$2:$K$825)), ROW(22:22))), "")} | T25: {=IFERROR(INDEX('Bank Schedule'!U:U, SMALL(IF('Bank Schedule'!$K$2:$K$825="Vacant", ROW('Bank Schedule'!$K$2:$K$825)), ROW(22:22))), "")} | U25: {=IFERROR(INDEX('Bank Schedule'!V:V, SMALL(IF('Bank Schedule'!$K$2:$K$825="Vacant", ROW('Bank Schedule'!$K$2:$K$825)), ROW(22:22))), "")} | V25: {=IFERROR(INDEX('Bank Schedule'!W:W, SMALL(IF('Bank Schedule'!$K$2:$K$825="Vacant", ROW('Bank Schedule'!$K$2:$K$825)), ROW(22:22))), "")} | W25: {=IFERROR(INDEX('Bank Schedule'!X:X, SMALL(IF('Bank Schedule'!$K$2:$K$825="Vacant", ROW('Bank Schedule'!$K$2:$K$825)), ROW(22:22))), "")} | X25: {=IFERROR(INDEX('Bank Schedule'!Y:Y, SMALL(IF('Bank Schedule'!$K$2:$K$825="Vacant", ROW('Bank Schedule'!$K$2:$K$825)), ROW(22:22))), "")} | Y25: {=IFERROR(INDEX('Bank Schedule'!Z:Z, SMALL(IF('Bank Schedule'!$K$2:$K$825="Vacant", ROW('Bank Schedule'!$K$2:$K$825)), ROW(22:22))), "")} | Z25: {=IFERROR(INDEX('Bank Schedule'!AA:AA, SMALL(IF('Bank Schedule'!$K$2:$K$825="Vacant", ROW('Bank Schedule'!$K$2:$K$825)), ROW(22:22))), "")} | AA25: {=IFERROR(INDEX('Bank Schedule'!AB:AB, SMALL(IF('Bank Schedule'!$K$2:$K$825="Vacant", ROW('Bank Schedule'!$K$2:$K$825)), ROW(22:22))), "")} | AB25: {=IFERROR(INDEX('Bank Schedule'!AC:AC, SMALL(IF('Bank Schedule'!$K$2:$K$825="Vacant", ROW('Bank Schedule'!$K$2:$K$825)), ROW(22:22))), "")} | AC25: {=IFERROR(INDEX('Bank Schedule'!AD:AD, SMALL(IF('Bank Schedule'!$K$2:$K$825="Vacant", ROW('Bank Schedule'!$K$2:$K$825)), ROW(22:22))), "")} | AD25: {=IFERROR(INDEX('Bank Schedule'!AE:AE, SMALL(IF('Bank Schedule'!$K$2:$K$825="Vacant", ROW('Bank Schedule'!$K$2:$K$825)), ROW(22:22))), "")} | AE25: {=IFERROR(INDEX('Bank Schedule'!AF:AF, SMALL(IF('Bank Schedule'!$K$2:$K$825="Vacant", ROW('Bank Schedule'!$K$2:$K$825)), ROW(22:22))), "")} | AF25: {=IFERROR(INDEX('Bank Schedule'!AG:AG, SMALL(IF('Bank Schedule'!$K$2:$K$825="Vacant", ROW('Bank Schedule'!$K$2:$K$825)), ROW(22:22))), "")}
A26: {=IFERROR(INDEX('Bank Schedule'!A:A, SMALL(IF('Bank Schedule'!$K$2:$K$825="Vacant", ROW('Bank Schedule'!$K$2:$K$825)), ROW(23:23))), "")} | B26: {=IFERROR(INDEX('Bank Schedule'!B:B, SMALL(IF('Bank Schedule'!$K$2:$K$825="Vacant", ROW('Bank Schedule'!$K$2:$K$825)), ROW(23:23))), "")} | C26: {=IFERROR(INDEX('Bank Schedule'!C:C, SMALL(IF('Bank Schedule'!$K$2:$K$825="Vacant", ROW('Bank Schedule'!$K$2:$K$825)), ROW(23:23))), "")} | D26: {=IFERROR(INDEX('Bank Schedule'!D:D, SMALL(IF('Bank Schedule'!$K$2:$K$825="Vacant", ROW('Bank Schedule'!$K$2:$K$825)), ROW(23:23))), "")} | E26: {=IFERROR(INDEX('Bank Schedule'!E:E, SMALL(IF('Bank Schedule'!$K$2:$K$825="Vacant", ROW('Bank Schedule'!$K$2:$K$825)), ROW(23:23))), "")} | F26: {=IFERROR(INDEX('Bank Schedule'!F:F, SMALL(IF('Bank Schedule'!$K$2:$K$825="Vacant", ROW('Bank Schedule'!$K$2:$K$825)), ROW(23:23))), "")} | G26: {=IFERROR(INDEX('Bank Schedule'!G:G, SMALL(IF('Bank Schedule'!$K$2:$K$825="Vacant", ROW('Bank Schedule'!$K$2:$K$825)), ROW(23:23))), "")} | H26: {=IFERROR(INDEX('Bank Schedule'!H:H, SMALL(IF('Bank Schedule'!$K$2:$K$825="Vacant", ROW('Bank Schedule'!$K$2:$K$825)), ROW(23:23))), "")} | I26: {=IFERROR(INDEX('Bank Schedule'!I:I, SMALL(IF('Bank Schedule'!$K$2:$K$825="Vacant", ROW('Bank Schedule'!$K$2:$K$825)), ROW(23:23))), "")} | J26: {=IFERROR(INDEX('Bank Schedule'!K:K, SMALL(IF('Bank Schedule'!$K$2:$K$825="Vacant", ROW('Bank Schedule'!$K$2:$K$825)), ROW(23:23))), "")} | K26: {=IFERROR(INDEX('Bank Schedule'!L:L, SMALL(IF('Bank Schedule'!$K$2:$K$825="Vacant", ROW('Bank Schedule'!$K$2:$K$825)), ROW(23:23))), "")} | L26: {=IFERROR(INDEX('Bank Schedule'!M:M, SMALL(IF('Bank Schedule'!$K$2:$K$825="Vacant", ROW('Bank Schedule'!$K$2:$K$825)), ROW(23:23))), "")} | M26: {=IFERROR(INDEX('Bank Schedule'!N:N, SMALL(IF('Bank Schedule'!$K$2:$K$825="Vacant", ROW('Bank Schedule'!$K$2:$K$825)), ROW(23:23))), "")} | N26: {=IFERROR(INDEX('Bank Schedule'!O:O, SMALL(IF('Bank Schedule'!$K$2:$K$825="Vacant", ROW('Bank Schedule'!$K$2:$K$825)), ROW(23:23))), "")} | O26: {=IFERROR(INDEX('Bank Schedule'!P:P, SMALL(IF('Bank Schedule'!$K$2:$K$825="Vacant", ROW('Bank Schedule'!$K$2:$K$825)), ROW(23:23))), "")} | P26: {=IFERROR(INDEX('Bank Schedule'!Q:Q, SMALL(IF('Bank Schedule'!$K$2:$K$825="Vacant", ROW('Bank Schedule'!$K$2:$K$825)), ROW(23:23))), "")} | Q26: {=IFERROR(INDEX('Bank Schedule'!R:R, SMALL(IF('Bank Schedule'!$K$2:$K$825="Vacant", ROW('Bank Schedule'!$K$2:$K$825)), ROW(23:23))), "")} | R26: {=IFERROR(INDEX('Bank Schedule'!S:S, SMALL(IF('Bank Schedule'!$K$2:$K$825="Vacant", ROW('Bank Schedule'!$K$2:$K$825)), ROW(23:23))), "")} | S26: {=IFERROR(INDEX('Bank Schedule'!T:T, SMALL(IF('Bank Schedule'!$K$2:$K$825="Vacant", ROW('Bank Schedule'!$K$2:$K$825)), ROW(23:23))), "")} | T26: {=IFERROR(INDEX('Bank Schedule'!U:U, SMALL(IF('Bank Schedule'!$K$2:$K$825="Vacant", ROW('Bank Schedule'!$K$2:$K$825)), ROW(23:23))), "")} | U26: {=IFERROR(INDEX('Bank Schedule'!V:V, SMALL(IF('Bank Schedule'!$K$2:$K$825="Vacant", ROW('Bank Schedule'!$K$2:$K$825)), ROW(23:23))), "")} | V26: {=IFERROR(INDEX('Bank Schedule'!W:W, SMALL(IF('Bank Schedule'!$K$2:$K$825="Vacant", ROW('Bank Schedule'!$K$2:$K$825)), ROW(23:23))), "")} | W26: {=IFERROR(INDEX('Bank Schedule'!X:X, SMALL(IF('Bank Schedule'!$K$2:$K$825="Vacant", ROW('Bank Schedule'!$K$2:$K$825)), ROW(23:23))), "")} | X26: {=IFERROR(INDEX('Bank Schedule'!Y:Y, SMALL(IF('Bank Schedule'!$K$2:$K$825="Vacant", ROW('Bank Schedule'!$K$2:$K$825)), ROW(23:23))), "")} | Y26: {=IFERROR(INDEX('Bank Schedule'!Z:Z, SMALL(IF('Bank Schedule'!$K$2:$K$825="Vacant", ROW('Bank Schedule'!$K$2:$K$825)), ROW(23:23))), "")} | Z26: {=IFERROR(INDEX('Bank Schedule'!AA:AA, SMALL(IF('Bank Schedule'!$K$2:$K$825="Vacant", ROW('Bank Schedule'!$K$2:$K$825)), ROW(23:23))), "")} | AA26: {=IFERROR(INDEX('Bank Schedule'!AB:AB, SMALL(IF('Bank Schedule'!$K$2:$K$825="Vacant", ROW('Bank Schedule'!$K$2:$K$825)), ROW(23:23))), "")} | AB26: {=IFERROR(INDEX('Bank Schedule'!AC:AC, SMALL(IF('Bank Schedule'!$K$2:$K$825="Vacant", ROW('Bank Schedule'!$K$2:$K$825)), ROW(23:23))), "")} | AC26: {=IFERROR(INDEX('Bank Schedule'!AD:AD, SMALL(IF('Bank Schedule'!$K$2:$K$825="Vacant", ROW('Bank Schedule'!$K$2:$K$825)), ROW(23:23))), "")} | AD26: {=IFERROR(INDEX('Bank Schedule'!AE:AE, SMALL(IF('Bank Schedule'!$K$2:$K$825="Vacant", ROW('Bank Schedule'!$K$2:$K$825)), ROW(23:23))), "")} | AE26: {=IFERROR(INDEX('Bank Schedule'!AF:AF, SMALL(IF('Bank Schedule'!$K$2:$K$825="Vacant", ROW('Bank Schedule'!$K$2:$K$825)), ROW(23:23))), "")} | AF26: {=IFERROR(INDEX('Bank Schedule'!AG:AG, SMALL(IF('Bank Schedule'!$K$2:$K$825="Vacant", ROW('Bank Schedule'!$K$2:$K$825)), ROW(23:23))), "")}
A27: {=IFERROR(INDEX('Bank Schedule'!A:A, SMALL(IF('Bank Schedule'!$K$2:$K$825="Vacant", ROW('Bank Schedule'!$K$2:$K$825)), ROW(24:24))), "")} | B27: {=IFERROR(INDEX('Bank Schedule'!B:B, SMALL(IF('Bank Schedule'!$K$2:$K$825="Vacant", ROW('Bank Schedule'!$K$2:$K$825)), ROW(24:24))), "")} | C27: {=IFERROR(INDEX('Bank Schedule'!C:C, SMALL(IF('Bank Schedule'!$K$2:$K$825="Vacant", ROW('Bank Schedule'!$K$2:$K$825)), ROW(24:24))), "")} | D27: {=IFERROR(INDEX('Bank Schedule'!D:D, SMALL(IF('Bank Schedule'!$K$2:$K$825="Vacant", ROW('Bank Schedule'!$K$2:$K$825)), ROW(24:24))), "")} | E27: {=IFERROR(INDEX('Bank Schedule'!E:E, SMALL(IF('Bank Schedule'!$K$2:$K$825="Vacant", ROW('Bank Schedule'!$K$2:$K$825)), ROW(24:24))), "")} | F27: {=IFERROR(INDEX('Bank Schedule'!F:F, SMALL(IF('Bank Schedule'!$K$2:$K$825="Vacant", ROW('Bank Schedule'!$K$2:$K$825)), ROW(24:24))), "")} | G27: {=IFERROR(INDEX('Bank Schedule'!G:G, SMALL(IF('Bank Schedule'!$K$2:$K$825="Vacant", ROW('Bank Schedule'!$K$2:$K$825)), ROW(24:24))), "")} | H27: {=IFERROR(INDEX('Bank Schedule'!H:H, SMALL(IF('Bank Schedule'!$K$2:$K$825="Vacant", ROW('Bank Schedule'!$K$2:$K$825)), ROW(24:24))), "")} | I27: {=IFERROR(INDEX('Bank Schedule'!I:I, SMALL(IF('Bank Schedule'!$K$2:$K$825="Vacant", ROW('Bank Schedule'!$K$2:$K$825)), ROW(24:24))), "")} | J27: {=IFERROR(INDEX('Bank Schedule'!K:K, SMALL(IF('Bank Schedule'!$K$2:$K$825="Vacant", ROW('Bank Schedule'!$K$2:$K$825)), ROW(24:24))), "")} | K27: {=IFERROR(INDEX('Bank Schedule'!L:L, SMALL(IF('Bank Schedule'!$K$2:$K$825="Vacant", ROW('Bank Schedule'!$K$2:$K$825)), ROW(24:24))), "")} | L27: {=IFERROR(INDEX('Bank Schedule'!M:M, SMALL(IF('Bank Schedule'!$K$2:$K$825="Vacant", ROW('Bank Schedule'!$K$2:$K$825)), ROW(24:24))), "")} | M27: {=IFERROR(INDEX('Bank Schedule'!N:N, SMALL(IF('Bank Schedule'!$K$2:$K$825="Vacant", ROW('Bank Schedule'!$K$2:$K$825)), ROW(24:24))), "")} | N27: {=IFERROR(INDEX('Bank Schedule'!O:O, SMALL(IF('Bank Schedule'!$K$2:$K$825="Vacant", ROW('Bank Schedule'!$K$2:$K$825)), ROW(24:24))), "")} | O27: {=IFERROR(INDEX('Bank Schedule'!P:P, SMALL(IF('Bank Schedule'!$K$2:$K$825="Vacant", ROW('Bank Schedule'!$K$2:$K$825)), ROW(24:24))), "")} | P27: {=IFERROR(INDEX('Bank Schedule'!Q:Q, SMALL(IF('Bank Schedule'!$K$2:$K$825="Vacant", ROW('Bank Schedule'!$K$2:$K$825)), ROW(24:24))), "")} | Q27: {=IFERROR(INDEX('Bank Schedule'!R:R, SMALL(IF('Bank Schedule'!$K$2:$K$825="Vacant", ROW('Bank Schedule'!$K$2:$K$825)), ROW(24:24))), "")} | R27: {=IFERROR(INDEX('Bank Schedule'!S:S, SMALL(IF('Bank Schedule'!$K$2:$K$825="Vacant", ROW('Bank Schedule'!$K$2:$K$825)), ROW(24:24))), "")} | S27: {=IFERROR(INDEX('Bank Schedule'!T:T, SMALL(IF('Bank Schedule'!$K$2:$K$825="Vacant", ROW('Bank Schedule'!$K$2:$K$825)), ROW(24:24))), "")} | T27: {=IFERROR(INDEX('Bank Schedule'!U:U, SMALL(IF('Bank Schedule'!$K$2:$K$825="Vacant", ROW('Bank Schedule'!$K$2:$K$825)), ROW(24:24))), "")} | U27: {=IFERROR(INDEX('Bank Schedule'!V:V, SMALL(IF('Bank Schedule'!$K$2:$K$825="Vacant", ROW('Bank Schedule'!$K$2:$K$825)), ROW(24:24))), "")} | V27: {=IFERROR(INDEX('Bank Schedule'!W:W, SMALL(IF('Bank Schedule'!$K$2:$K$825="Vacant", ROW('Bank Schedule'!$K$2:$K$825)), ROW(24:24))), "")} | W27: {=IFERROR(INDEX('Bank Schedule'!X:X, SMALL(IF('Bank Schedule'!$K$2:$K$825="Vacant", ROW('Bank Schedule'!$K$2:$K$825)), ROW(24:24))), "")} | X27: {=IFERROR(INDEX('Bank Schedule'!Y:Y, SMALL(IF('Bank Schedule'!$K$2:$K$825="Vacant", ROW('Bank Schedule'!$K$2:$K$825)), ROW(24:24))), "")} | Y27: {=IFERROR(INDEX('Bank Schedule'!Z:Z, SMALL(IF('Bank Schedule'!$K$2:$K$825="Vacant", ROW('Bank Schedule'!$K$2:$K$825)), ROW(24:24))), "")} | Z27: {=IFERROR(INDEX('Bank Schedule'!AA:AA, SMALL(IF('Bank Schedule'!$K$2:$K$825="Vacant", ROW('Bank Schedule'!$K$2:$K$825)), ROW(24:24))), "")} | AA27: {=IFERROR(INDEX('Bank Schedule'!AB:AB, SMALL(IF('Bank Schedule'!$K$2:$K$825="Vacant", ROW('Bank Schedule'!$K$2:$K$825)), ROW(24:24))), "")} | AB27: {=IFERROR(INDEX('Bank Schedule'!AC:AC, SMALL(IF('Bank Schedule'!$K$2:$K$825="Vacant", ROW('Bank Schedule'!$K$2:$K$825)), ROW(24:24))), "")} | AC27: {=IFERROR(INDEX('Bank Schedule'!AD:AD, SMALL(IF('Bank Schedule'!$K$2:$K$825="Vacant", ROW('Bank Schedule'!$K$2:$K$825)), ROW(24:24))), "")} | AD27: {=IFERROR(INDEX('Bank Schedule'!AE:AE, SMALL(IF('Bank Schedule'!$K$2:$K$825="Vacant", ROW('Bank Schedule'!$K$2:$K$825)), ROW(24:24))), "")} | AE27: {=IFERROR(INDEX('Bank Schedule'!AF:AF, SMALL(IF('Bank Schedule'!$K$2:$K$825="Vacant", ROW('Bank Schedule'!$K$2:$K$825)), ROW(24:24))), "")} | AF27: {=IFERROR(INDEX('Bank Schedule'!AG:AG, SMALL(IF('Bank Schedule'!$K$2:$K$825="Vacant", ROW('Bank Schedule'!$K$2:$K$825)), ROW(24:24))), "")}
A28: {=IFERROR(INDEX('Bank Schedule'!A:A, SMALL(IF('Bank Schedule'!$K$2:$K$825="Vacant", ROW('Bank Schedule'!$K$2:$K$825)), ROW(25:25))), "")} | B28: {=IFERROR(INDEX('Bank Schedule'!B:B, SMALL(IF('Bank Schedule'!$K$2:$K$825="Vacant", ROW('Bank Schedule'!$K$2:$K$825)), ROW(25:25))), "")} | C28: {=IFERROR(INDEX('Bank Schedule'!C:C, SMALL(IF('Bank Schedule'!$K$2:$K$825="Vacant", ROW('Bank Schedule'!$K$2:$K$825)), ROW(25:25))), "")} | D28: {=IFERROR(INDEX('Bank Schedule'!D:D, SMALL(IF('Bank Schedule'!$K$2:$K$825="Vacant", ROW('Bank Schedule'!$K$2:$K$825)), ROW(25:25))), "")} | E28: {=IFERROR(INDEX('Bank Schedule'!E:E, SMALL(IF('Bank Schedule'!$K$2:$K$825="Vacant", ROW('Bank Schedule'!$K$2:$K$825)), ROW(25:25))), "")} | F28: {=IFERROR(INDEX('Bank Schedule'!F:F, SMALL(IF('Bank Schedule'!$K$2:$K$825="Vacant", ROW('Bank Schedule'!$K$2:$K$825)), ROW(25:25))), "")} | G28: {=IFERROR(INDEX('Bank Schedule'!G:G, SMALL(IF('Bank Schedule'!$K$2:$K$825="Vacant", ROW('Bank Schedule'!$K$2:$K$825)), ROW(25:25))), "")} | H28: {=IFERROR(INDEX('Bank Schedule'!H:H, SMALL(IF('Bank Schedule'!$K$2:$K$825="Vacant", ROW('Bank Schedule'!$K$2:$K$825)), ROW(25:25))), "")} | I28: {=IFERROR(INDEX('Bank Schedule'!I:I, SMALL(IF('Bank Schedule'!$K$2:$K$825="Vacant", ROW('Bank Schedule'!$K$2:$K$825)), ROW(25:25))), "")} | J28: {=IFERROR(INDEX('Bank Schedule'!K:K, SMALL(IF('Bank Schedule'!$K$2:$K$825="Vacant", ROW('Bank Schedule'!$K$2:$K$825)), ROW(25:25))), "")} | K28: {=IFERROR(INDEX('Bank Schedule'!L:L, SMALL(IF('Bank Schedule'!$K$2:$K$825="Vacant", ROW('Bank Schedule'!$K$2:$K$825)), ROW(25:25))), "")} | L28: {=IFERROR(INDEX('Bank Schedule'!M:M, SMALL(IF('Bank Schedule'!$K$2:$K$825="Vacant", ROW('Bank Schedule'!$K$2:$K$825)), ROW(25:25))), "")} | M28: {=IFERROR(INDEX('Bank Schedule'!N:N, SMALL(IF('Bank Schedule'!$K$2:$K$825="Vacant", ROW('Bank Schedule'!$K$2:$K$825)), ROW(25:25))), "")} | N28: {=IFERROR(INDEX('Bank Schedule'!O:O, SMALL(IF('Bank Schedule'!$K$2:$K$825="Vacant", ROW('Bank Schedule'!$K$2:$K$825)), ROW(25:25))), "")} | O28: {=IFERROR(INDEX('Bank Schedule'!P:P, SMALL(IF('Bank Schedule'!$K$2:$K$825="Vacant", ROW('Bank Schedule'!$K$2:$K$825)), ROW(25:25))), "")} | P28: {=IFERROR(INDEX('Bank Schedule'!Q:Q, SMALL(IF('Bank Schedule'!$K$2:$K$825="Vacant", ROW('Bank Schedule'!$K$2:$K$825)), ROW(25:25))), "")} | Q28: {=IFERROR(INDEX('Bank Schedule'!R:R, SMALL(IF('Bank Schedule'!$K$2:$K$825="Vacant", ROW('Bank Schedule'!$K$2:$K$825)), ROW(25:25))), "")} | R28: {=IFERROR(INDEX('Bank Schedule'!S:S, SMALL(IF('Bank Schedule'!$K$2:$K$825="Vacant", ROW('Bank Schedule'!$K$2:$K$825)), ROW(25:25))), "")} | S28: {=IFERROR(INDEX('Bank Schedule'!T:T, SMALL(IF('Bank Schedule'!$K$2:$K$825="Vacant", ROW('Bank Schedule'!$K$2:$K$825)), ROW(25:25))), "")} | T28: {=IFERROR(INDEX('Bank Schedule'!U:U, SMALL(IF('Bank Schedule'!$K$2:$K$825="Vacant", ROW('Bank Schedule'!$K$2:$K$825)), ROW(25:25))), "")} | U28: {=IFERROR(INDEX('Bank Schedule'!V:V, SMALL(IF('Bank Schedule'!$K$2:$K$825="Vacant", ROW('Bank Schedule'!$K$2:$K$825)), ROW(25:25))), "")} | V28: {=IFERROR(INDEX('Bank Schedule'!W:W, SMALL(IF('Bank Schedule'!$K$2:$K$825="Vacant", ROW('Bank Schedule'!$K$2:$K$825)), ROW(25:25))), "")} | W28: {=IFERROR(INDEX('Bank Schedule'!X:X, SMALL(IF('Bank Schedule'!$K$2:$K$825="Vacant", ROW('Bank Schedule'!$K$2:$K$825)), ROW(25:25))), "")} | X28: {=IFERROR(INDEX('Bank Schedule'!Y:Y, SMALL(IF('Bank Schedule'!$K$2:$K$825="Vacant", ROW('Bank Schedule'!$K$2:$K$825)), ROW(25:25))), "")} | Y28: {=IFERROR(INDEX('Bank Schedule'!Z:Z, SMALL(IF('Bank Schedule'!$K$2:$K$825="Vacant", ROW('Bank Schedule'!$K$2:$K$825)), ROW(25:25))), "")} | Z28: {=IFERROR(INDEX('Bank Schedule'!AA:AA, SMALL(IF('Bank Schedule'!$K$2:$K$825="Vacant", ROW('Bank Schedule'!$K$2:$K$825)), ROW(25:25))), "")} | AA28: {=IFERROR(INDEX('Bank Schedule'!AB:AB, SMALL(IF('Bank Schedule'!$K$2:$K$825="Vacant", ROW('Bank Schedule'!$K$2:$K$825)), ROW(25:25))), "")} | AB28: {=IFERROR(INDEX('Bank Schedule'!AC:AC, SMALL(IF('Bank Schedule'!$K$2:$K$825="Vacant", ROW('Bank Schedule'!$K$2:$K$825)), ROW(25:25))), "")} | AC28: {=IFERROR(INDEX('Bank Schedule'!AD:AD, SMALL(IF('Bank Schedule'!$K$2:$K$825="Vacant", ROW('Bank Schedule'!$K$2:$K$825)), ROW(25:25))), "")} | AD28: {=IFERROR(INDEX('Bank Schedule'!AE:AE, SMALL(IF('Bank Schedule'!$K$2:$K$825="Vacant", ROW('Bank Schedule'!$K$2:$K$825)), ROW(25:25))), "")} | AE28: {=IFERROR(INDEX('Bank Schedule'!AF:AF, SMALL(IF('Bank Schedule'!$K$2:$K$825="Vacant", ROW('Bank Schedule'!$K$2:$K$825)), ROW(25:25))), "")} | AF28: {=IFERROR(INDEX('Bank Schedule'!AG:AG, SMALL(IF('Bank Schedule'!$K$2:$K$825="Vacant", ROW('Bank Schedule'!$K$2:$K$825)), ROW(25:25))), "")}
A29: {=IFERROR(INDEX('Bank Schedule'!A:A, SMALL(IF('Bank Schedule'!$K$2:$K$825="Vacant", ROW('Bank Schedule'!$K$2:$K$825)), ROW(26:26))), "")} | B29: {=IFERROR(INDEX('Bank Schedule'!B:B, SMALL(IF('Bank Schedule'!$K$2:$K$825="Vacant", ROW('Bank Schedule'!$K$2:$K$825)), ROW(26:26))), "")} | C29: {=IFERROR(INDEX('Bank Schedule'!C:C, SMALL(IF('Bank Schedule'!$K$2:$K$825="Vacant", ROW('Bank Schedule'!$K$2:$K$825)), ROW(26:26))), "")} | D29: {=IFERROR(INDEX('Bank Schedule'!D:D, SMALL(IF('Bank Schedule'!$K$2:$K$825="Vacant", ROW('Bank Schedule'!$K$2:$K$825)), ROW(26:26))), "")} | E29: {=IFERROR(INDEX('Bank Schedule'!E:E, SMALL(IF('Bank Schedule'!$K$2:$K$825="Vacant", ROW('Bank Schedule'!$K$2:$K$825)), ROW(26:26))), "")} | F29: {=IFERROR(INDEX('Bank Schedule'!F:F, SMALL(IF('Bank Schedule'!$K$2:$K$825="Vacant", ROW('Bank Schedule'!$K$2:$K$825)), ROW(26:26))), "")} | G29: {=IFERROR(INDEX('Bank Schedule'!G:G, SMALL(IF('Bank Schedule'!$K$2:$K$825="Vacant", ROW('Bank Schedule'!$K$2:$K$825)), ROW(26:26))), "")} | H29: {=IFERROR(INDEX('Bank Schedule'!H:H, SMALL(IF('Bank Schedule'!$K$2:$K$825="Vacant", ROW('Bank Schedule'!$K$2:$K$825)), ROW(26:26))), "")} | I29: {=IFERROR(INDEX('Bank Schedule'!I:I, SMALL(IF('Bank Schedule'!$K$2:$K$825="Vacant", ROW('Bank Schedule'!$K$2:$K$825)), ROW(26:26))), "")} | J29: {=IFERROR(INDEX('Bank Schedule'!K:K, SMALL(IF('Bank Schedule'!$K$2:$K$825="Vacant", ROW('Bank Schedule'!$K$2:$K$825)), ROW(26:26))), "")} | K29: {=IFERROR(INDEX('Bank Schedule'!L:L, SMALL(IF('Bank Schedule'!$K$2:$K$825="Vacant", ROW('Bank Schedule'!$K$2:$K$825)), ROW(26:26))), "")} | L29: {=IFERROR(INDEX('Bank Schedule'!M:M, SMALL(IF('Bank Schedule'!$K$2:$K$825="Vacant", ROW('Bank Schedule'!$K$2:$K$825)), ROW(26:26))), "")} | M29: {=IFERROR(INDEX('Bank Schedule'!N:N, SMALL(IF('Bank Schedule'!$K$2:$K$825="Vacant", ROW('Bank Schedule'!$K$2:$K$825)), ROW(26:26))), "")} | N29: {=IFERROR(INDEX('Bank Schedule'!O:O, SMALL(IF('Bank Schedule'!$K$2:$K$825="Vacant", ROW('Bank Schedule'!$K$2:$K$825)), ROW(26:26))), "")} | O29: {=IFERROR(INDEX('Bank Schedule'!P:P, SMALL(IF('Bank Schedule'!$K$2:$K$825="Vacant", ROW('Bank Schedule'!$K$2:$K$825)), ROW(26:26))), "")} | P29: {=IFERROR(INDEX('Bank Schedule'!Q:Q, SMALL(IF('Bank Schedule'!$K$2:$K$825="Vacant", ROW('Bank Schedule'!$K$2:$K$825)), ROW(26:26))), "")} | Q29: {=IFERROR(INDEX('Bank Schedule'!R:R, SMALL(IF('Bank Schedule'!$K$2:$K$825="Vacant", ROW('Bank Schedule'!$K$2:$K$825)), ROW(26:26))), "")} | R29: {=IFERROR(INDEX('Bank Schedule'!S:S, SMALL(IF('Bank Schedule'!$K$2:$K$825="Vacant", ROW('Bank Schedule'!$K$2:$K$825)), ROW(26:26))), "")} | S29: {=IFERROR(INDEX('Bank Schedule'!T:T, SMALL(IF('Bank Schedule'!$K$2:$K$825="Vacant", ROW('Bank Schedule'!$K$2:$K$825)), ROW(26:26))), "")} | T29: {=IFERROR(INDEX('Bank Schedule'!U:U, SMALL(IF('Bank Schedule'!$K$2:$K$825="Vacant", ROW('Bank Schedule'!$K$2:$K$825)), ROW(26:26))), "")} | U29: {=IFERROR(INDEX('Bank Schedule'!V:V, SMALL(IF('Bank Schedule'!$K$2:$K$825="Vacant", ROW('Bank Schedule'!$K$2:$K$825)), ROW(26:26))), "")} | V29: {=IFERROR(INDEX('Bank Schedule'!W:W, SMALL(IF('Bank Schedule'!$K$2:$K$825="Vacant", ROW('Bank Schedule'!$K$2:$K$825)), ROW(26:26))), "")} | W29: {=IFERROR(INDEX('Bank Schedule'!X:X, SMALL(IF('Bank Schedule'!$K$2:$K$825="Vacant", ROW('Bank Schedule'!$K$2:$K$825)), ROW(26:26))), "")} | X29: {=IFERROR(INDEX('Bank Schedule'!Y:Y, SMALL(IF('Bank Schedule'!$K$2:$K$825="Vacant", ROW('Bank Schedule'!$K$2:$K$825)), ROW(26:26))), "")} | Y29: {=IFERROR(INDEX('Bank Schedule'!Z:Z, SMALL(IF('Bank Schedule'!$K$2:$K$825="Vacant", ROW('Bank Schedule'!$K$2:$K$825)), ROW(26:26))), "")} | Z29: {=IFERROR(INDEX('Bank Schedule'!AA:AA, SMALL(IF('Bank Schedule'!$K$2:$K$825="Vacant", ROW('Bank Schedule'!$K$2:$K$825)), ROW(26:26))), "")} | AA29: {=IFERROR(INDEX('Bank Schedule'!AB:AB, SMALL(IF('Bank Schedule'!$K$2:$K$825="Vacant", ROW('Bank Schedule'!$K$2:$K$825)), ROW(26:26))), "")} | AB29: {=IFERROR(INDEX('Bank Schedule'!AC:AC, SMALL(IF('Bank Schedule'!$K$2:$K$825="Vacant", ROW('Bank Schedule'!$K$2:$K$825)), ROW(26:26))), "")} | AC29: {=IFERROR(INDEX('Bank Schedule'!AD:AD, SMALL(IF('Bank Schedule'!$K$2:$K$825="Vacant", ROW('Bank Schedule'!$K$2:$K$825)), ROW(26:26))), "")} | AD29: {=IFERROR(INDEX('Bank Schedule'!AE:AE, SMALL(IF('Bank Schedule'!$K$2:$K$825="Vacant", ROW('Bank Schedule'!$K$2:$K$825)), ROW(26:26))), "")} | AE29: {=IFERROR(INDEX('Bank Schedule'!AF:AF, SMALL(IF('Bank Schedule'!$K$2:$K$825="Vacant", ROW('Bank Schedule'!$K$2:$K$825)), ROW(26:26))), "")} | AF29: {=IFERROR(INDEX('Bank Schedule'!AG:AG, SMALL(IF('Bank Schedule'!$K$2:$K$825="Vacant", ROW('Bank Schedule'!$K$2:$K$825)), ROW(26:26))), "")}
A30: {=IFERROR(INDEX('Bank Schedule'!A:A, SMALL(IF('Bank Schedule'!$K$2:$K$825="Vacant", ROW('Bank Schedule'!$K$2:$K$825)), ROW(27:27))), "")} | B30: {=IFERROR(INDEX('Bank Schedule'!B:B, SMALL(IF('Bank Schedule'!$K$2:$K$825="Vacant", ROW('Bank Schedule'!$K$2:$K$825)), ROW(27:27))), "")} | C30: {=IFERROR(INDEX('Bank Schedule'!C:C, SMALL(IF('Bank Schedule'!$K$2:$K$825="Vacant", ROW('Bank Schedule'!$K$2:$K$825)), ROW(27:27))), "")} | D30: {=IFERROR(INDEX('Bank Schedule'!D:D, SMALL(IF('Bank Schedule'!$K$2:$K$825="Vacant", ROW('Bank Schedule'!$K$2:$K$825)), ROW(27:27))), "")} | E30: {=IFERROR(INDEX('Bank Schedule'!E:E, SMALL(IF('Bank Schedule'!$K$2:$K$825="Vacant", ROW('Bank Schedule'!$K$2:$K$825)), ROW(27:27))), "")} | F30: {=IFERROR(INDEX('Bank Schedule'!F:F, SMALL(IF('Bank Schedule'!$K$2:$K$825="Vacant", ROW('Bank Schedule'!$K$2:$K$825)), ROW(27:27))), "")} | G30: {=IFERROR(INDEX('Bank Schedule'!G:G, SMALL(IF('Bank Schedule'!$K$2:$K$825="Vacant", ROW('Bank Schedule'!$K$2:$K$825)), ROW(27:27))), "")} | H30: {=IFERROR(INDEX('Bank Schedule'!H:H, SMALL(IF('Bank Schedule'!$K$2:$K$825="Vacant", ROW('Bank Schedule'!$K$2:$K$825)), ROW(27:27))), "")} | I30: {=IFERROR(INDEX('Bank Schedule'!I:I, SMALL(IF('Bank Schedule'!$K$2:$K$825="Vacant", ROW('Bank Schedule'!$K$2:$K$825)), ROW(27:27))), "")} | J30: {=IFERROR(INDEX('Bank Schedule'!K:K, SMALL(IF('Bank Schedule'!$K$2:$K$825="Vacant", ROW('Bank Schedule'!$K$2:$K$825)), ROW(27:27))), "")} | K30: {=IFERROR(INDEX('Bank Schedule'!L:L, SMALL(IF('Bank Schedule'!$K$2:$K$825="Vacant", ROW('Bank Schedule'!$K$2:$K$825)), ROW(27:27))), "")} | L30: {=IFERROR(INDEX('Bank Schedule'!M:M, SMALL(IF('Bank Schedule'!$K$2:$K$825="Vacant", ROW('Bank Schedule'!$K$2:$K$825)), ROW(27:27))), "")} | M30: {=IFERROR(INDEX('Bank Schedule'!N:N, SMALL(IF('Bank Schedule'!$K$2:$K$825="Vacant", ROW('Bank Schedule'!$K$2:$K$825)), ROW(27:27))), "")} | N30: {=IFERROR(INDEX('Bank Schedule'!O:O, SMALL(IF('Bank Schedule'!$K$2:$K$825="Vacant", ROW('Bank Schedule'!$K$2:$K$825)), ROW(27:27))), "")} | O30: {=IFERROR(INDEX('Bank Schedule'!P:P, SMALL(IF('Bank Schedule'!$K$2:$K$825="Vacant", ROW('Bank Schedule'!$K$2:$K$825)), ROW(27:27))), "")} | P30: {=IFERROR(INDEX('Bank Schedule'!Q:Q, SMALL(IF('Bank Schedule'!$K$2:$K$825="Vacant", ROW('Bank Schedule'!$K$2:$K$825)), ROW(27:27))), "")} | Q30: {=IFERROR(INDEX('Bank Schedule'!R:R, SMALL(IF('Bank Schedule'!$K$2:$K$825="Vacant", ROW('Bank Schedule'!$K$2:$K$825)), ROW(27:27))), "")} | R30: {=IFERROR(INDEX('Bank Schedule'!S:S, SMALL(IF('Bank Schedule'!$K$2:$K$825="Vacant", ROW('Bank Schedule'!$K$2:$K$825)), ROW(27:27))), "")} | S30: {=IFERROR(INDEX('Bank Schedule'!T:T, SMALL(IF('Bank Schedule'!$K$2:$K$825="Vacant", ROW('Bank Schedule'!$K$2:$K$825)), ROW(27:27))), "")} | T30: {=IFERROR(INDEX('Bank Schedule'!U:U, SMALL(IF('Bank Schedule'!$K$2:$K$825="Vacant", ROW('Bank Schedule'!$K$2:$K$825)), ROW(27:27))), "")} | U30: {=IFERROR(INDEX('Bank Schedule'!V:V, SMALL(IF('Bank Schedule'!$K$2:$K$825="Vacant", ROW('Bank Schedule'!$K$2:$K$825)), ROW(27:27))), "")} | V30: {=IFERROR(INDEX('Bank Schedule'!W:W, SMALL(IF('Bank Schedule'!$K$2:$K$825="Vacant", ROW('Bank Schedule'!$K$2:$K$825)), ROW(27:27))), "")} | W30: {=IFERROR(INDEX('Bank Schedule'!X:X, SMALL(IF('Bank Schedule'!$K$2:$K$825="Vacant", ROW('Bank Schedule'!$K$2:$K$825)), ROW(27:27))), "")} | X30: {=IFERROR(INDEX('Bank Schedule'!Y:Y, SMALL(IF('Bank Schedule'!$K$2:$K$825="Vacant", ROW('Bank Schedule'!$K$2:$K$825)), ROW(27:27))), "")} | Y30: {=IFERROR(INDEX('Bank Schedule'!Z:Z, SMALL(IF('Bank Schedule'!$K$2:$K$825="Vacant", ROW('Bank Schedule'!$K$2:$K$825)), ROW(27:27))), "")} | Z30: {=IFERROR(INDEX('Bank Schedule'!AA:AA, SMALL(IF('Bank Schedule'!$K$2:$K$825="Vacant", ROW('Bank Schedule'!$K$2:$K$825)), ROW(27:27))), "")} | AA30: {=IFERROR(INDEX('Bank Schedule'!AB:AB, SMALL(IF('Bank Schedule'!$K$2:$K$825="Vacant", ROW('Bank Schedule'!$K$2:$K$825)), ROW(27:27))), "")} | AB30: {=IFERROR(INDEX('Bank Schedule'!AC:AC, SMALL(IF('Bank Schedule'!$K$2:$K$825="Vacant", ROW('Bank Schedule'!$K$2:$K$825)), ROW(27:27))), "")} | AC30: {=IFERROR(INDEX('Bank Schedule'!AD:AD, SMALL(IF('Bank Schedule'!$K$2:$K$825="Vacant", ROW('Bank Schedule'!$K$2:$K$825)), ROW(27:27))), "")} | AD30: {=IFERROR(INDEX('Bank Schedule'!AE:AE, SMALL(IF('Bank Schedule'!$K$2:$K$825="Vacant", ROW('Bank Schedule'!$K$2:$K$825)), ROW(27:27))), "")} | AE30: {=IFERROR(INDEX('Bank Schedule'!AF:AF, SMALL(IF('Bank Schedule'!$K$2:$K$825="Vacant", ROW('Bank Schedule'!$K$2:$K$825)), ROW(27:27))), "")} | AF30: {=IFERROR(INDEX('Bank Schedule'!AG:AG, SMALL(IF('Bank Schedule'!$K$2:$K$825="Vacant", ROW('Bank Schedule'!$K$2:$K$825)), ROW(27:27))), "")}
A31: {=IFERROR(INDEX('Bank Schedule'!A:A, SMALL(IF('Bank Schedule'!$K$2:$K$825="Vacant", ROW('Bank Schedule'!$K$2:$K$825)), ROW(28:28))), "")} | B31: {=IFERROR(INDEX('Bank Schedule'!B:B, SMALL(IF('Bank Schedule'!$K$2:$K$825="Vacant", ROW('Bank Schedule'!$K$2:$K$825)), ROW(28:28))), "")} | C31: {=IFERROR(INDEX('Bank Schedule'!C:C, SMALL(IF('Bank Schedule'!$K$2:$K$825="Vacant", ROW('Bank Schedule'!$K$2:$K$825)), ROW(28:28))), "")} | D31: {=IFERROR(INDEX('Bank Schedule'!D:D, SMALL(IF('Bank Schedule'!$K$2:$K$825="Vacant", ROW('Bank Schedule'!$K$2:$K$825)), ROW(28:28))), "")} | E31: {=IFERROR(INDEX('Bank Schedule'!E:E, SMALL(IF('Bank Schedule'!$K$2:$K$825="Vacant", ROW('Bank Schedule'!$K$2:$K$825)), ROW(28:28))), "")} | F31: {=IFERROR(INDEX('Bank Schedule'!F:F, SMALL(IF('Bank Schedule'!$K$2:$K$825="Vacant", ROW('Bank Schedule'!$K$2:$K$825)), ROW(28:28))), "")} | G31: {=IFERROR(INDEX('Bank Schedule'!G:G, SMALL(IF('Bank Schedule'!$K$2:$K$825="Vacant", ROW('Bank Schedule'!$K$2:$K$825)), ROW(28:28))), "")} | H31: {=IFERROR(INDEX('Bank Schedule'!H:H, SMALL(IF('Bank Schedule'!$K$2:$K$825="Vacant", ROW('Bank Schedule'!$K$2:$K$825)), ROW(28:28))), "")} | I31: {=IFERROR(INDEX('Bank Schedule'!I:I, SMALL(IF('Bank Schedule'!$K$2:$K$825="Vacant", ROW('Bank Schedule'!$K$2:$K$825)), ROW(28:28))), "")} | J31: {=IFERROR(INDEX('Bank Schedule'!K:K, SMALL(IF('Bank Schedule'!$K$2:$K$825="Vacant", ROW('Bank Schedule'!$K$2:$K$825)), ROW(28:28))), "")} | K31: {=IFERROR(INDEX('Bank Schedule'!L:L, SMALL(IF('Bank Schedule'!$K$2:$K$825="Vacant", ROW('Bank Schedule'!$K$2:$K$825)), ROW(28:28))), "")} | L31: {=IFERROR(INDEX('Bank Schedule'!M:M, SMALL(IF('Bank Schedule'!$K$2:$K$825="Vacant", ROW('Bank Schedule'!$K$2:$K$825)), ROW(28:28))), "")} | M31: {=IFERROR(INDEX('Bank Schedule'!N:N, SMALL(IF('Bank Schedule'!$K$2:$K$825="Vacant", ROW('Bank Schedule'!$K$2:$K$825)), ROW(28:28))), "")} | N31: {=IFERROR(INDEX('Bank Schedule'!O:O, SMALL(IF('Bank Schedule'!$K$2:$K$825="Vacant", ROW('Bank Schedule'!$K$2:$K$825)), ROW(28:28))), "")} | O31: {=IFERROR(INDEX('Bank Schedule'!P:P, SMALL(IF('Bank Schedule'!$K$2:$K$825="Vacant", ROW('Bank Schedule'!$K$2:$K$825)), ROW(28:28))), "")} | P31: {=IFERROR(INDEX('Bank Schedule'!Q:Q, SMALL(IF('Bank Schedule'!$K$2:$K$825="Vacant", ROW('Bank Schedule'!$K$2:$K$825)), ROW(28:28))), "")} | Q31: {=IFERROR(INDEX('Bank Schedule'!R:R, SMALL(IF('Bank Schedule'!$K$2:$K$825="Vacant", ROW('Bank Schedule'!$K$2:$K$825)), ROW(28:28))), "")} | R31: {=IFERROR(INDEX('Bank Schedule'!S:S, SMALL(IF('Bank Schedule'!$K$2:$K$825="Vacant", ROW('Bank Schedule'!$K$2:$K$825)), ROW(28:28))), "")} | S31: {=IFERROR(INDEX('Bank Schedule'!T:T, SMALL(IF('Bank Schedule'!$K$2:$K$825="Vacant", ROW('Bank Schedule'!$K$2:$K$825)), ROW(28:28))), "")} | T31: {=IFERROR(INDEX('Bank Schedule'!U:U, SMALL(IF('Bank Schedule'!$K$2:$K$825="Vacant", ROW('Bank Schedule'!$K$2:$K$825)), ROW(28:28))), "")} | U31: {=IFERROR(INDEX('Bank Schedule'!V:V, SMALL(IF('Bank Schedule'!$K$2:$K$825="Vacant", ROW('Bank Schedule'!$K$2:$K$825)), ROW(28:28))), "")} | V31: {=IFERROR(INDEX('Bank Schedule'!W:W, SMALL(IF('Bank Schedule'!$K$2:$K$825="Vacant", ROW('Bank Schedule'!$K$2:$K$825)), ROW(28:28))), "")} | W31: {=IFERROR(INDEX('Bank Schedule'!X:X, SMALL(IF('Bank Schedule'!$K$2:$K$825="Vacant", ROW('Bank Schedule'!$K$2:$K$825)), ROW(28:28))), "")} | X31: {=IFERROR(INDEX('Bank Schedule'!Y:Y, SMALL(IF('Bank Schedule'!$K$2:$K$825="Vacant", ROW('Bank Schedule'!$K$2:$K$825)), ROW(28:28))), "")} | Y31: {=IFERROR(INDEX('Bank Schedule'!Z:Z, SMALL(IF('Bank Schedule'!$K$2:$K$825="Vacant", ROW('Bank Schedule'!$K$2:$K$825)), ROW(28:28))), "")} | Z31: {=IFERROR(INDEX('Bank Schedule'!AA:AA, SMALL(IF('Bank Schedule'!$K$2:$K$825="Vacant", ROW('Bank Schedule'!$K$2:$K$825)), ROW(28:28))), "")} | AA31: {=IFERROR(INDEX('Bank Schedule'!AB:AB, SMALL(IF('Bank Schedule'!$K$2:$K$825="Vacant", ROW('Bank Schedule'!$K$2:$K$825)), ROW(28:28))), "")} | AB31: {=IFERROR(INDEX('Bank Schedule'!AC:AC, SMALL(IF('Bank Schedule'!$K$2:$K$825="Vacant", ROW('Bank Schedule'!$K$2:$K$825)), ROW(28:28))), "")} | AC31: {=IFERROR(INDEX('Bank Schedule'!AD:AD, SMALL(IF('Bank Schedule'!$K$2:$K$825="Vacant", ROW('Bank Schedule'!$K$2:$K$825)), ROW(28:28))), "")} | AD31: {=IFERROR(INDEX('Bank Schedule'!AE:AE, SMALL(IF('Bank Schedule'!$K$2:$K$825="Vacant", ROW('Bank Schedule'!$K$2:$K$825)), ROW(28:28))), "")} | AE31: {=IFERROR(INDEX('Bank Schedule'!AF:AF, SMALL(IF('Bank Schedule'!$K$2:$K$825="Vacant", ROW('Bank Schedule'!$K$2:$K$825)), ROW(28:28))), "")} | AF31: {=IFERROR(INDEX('Bank Schedule'!AG:AG, SMALL(IF('Bank Schedule'!$K$2:$K$825="Vacant", ROW('Bank Schedule'!$K$2:$K$825)), ROW(28:28))), "")}
A32: {=IFERROR(INDEX('Bank Schedule'!A:A, SMALL(IF('Bank Schedule'!$K$2:$K$825="Vacant", ROW('Bank Schedule'!$K$2:$K$825)), ROW(29:29))), "")} | B32: {=IFERROR(INDEX('Bank Schedule'!B:B, SMALL(IF('Bank Schedule'!$K$2:$K$825="Vacant", ROW('Bank Schedule'!$K$2:$K$825)), ROW(29:29))), "")} | C32: {=IFERROR(INDEX('Bank Schedule'!C:C, SMALL(IF('Bank Schedule'!$K$2:$K$825="Vacant", ROW('Bank Schedule'!$K$2:$K$825)), ROW(29:29))), "")} | D32: {=IFERROR(INDEX('Bank Schedule'!D:D, SMALL(IF('Bank Schedule'!$K$2:$K$825="Vacant", ROW('Bank Schedule'!$K$2:$K$825)), ROW(29:29))), "")} | E32: {=IFERROR(INDEX('Bank Schedule'!E:E, SMALL(IF('Bank Schedule'!$K$2:$K$825="Vacant", ROW('Bank Schedule'!$K$2:$K$825)), ROW(29:29))), "")} | F32: {=IFERROR(INDEX('Bank Schedule'!F:F, SMALL(IF('Bank Schedule'!$K$2:$K$825="Vacant", ROW('Bank Schedule'!$K$2:$K$825)), ROW(29:29))), "")} | G32: {=IFERROR(INDEX('Bank Schedule'!G:G, SMALL(IF('Bank Schedule'!$K$2:$K$825="Vacant", ROW('Bank Schedule'!$K$2:$K$825)), ROW(29:29))), "")} | H32: {=IFERROR(INDEX('Bank Schedule'!H:H, SMALL(IF('Bank Schedule'!$K$2:$K$825="Vacant", ROW('Bank Schedule'!$K$2:$K$825)), ROW(29:29))), "")} | I32: {=IFERROR(INDEX('Bank Schedule'!I:I, SMALL(IF('Bank Schedule'!$K$2:$K$825="Vacant", ROW('Bank Schedule'!$K$2:$K$825)), ROW(29:29))), "")} | J32: {=IFERROR(INDEX('Bank Schedule'!K:K, SMALL(IF('Bank Schedule'!$K$2:$K$825="Vacant", ROW('Bank Schedule'!$K$2:$K$825)), ROW(29:29))), "")} | K32: {=IFERROR(INDEX('Bank Schedule'!L:L, SMALL(IF('Bank Schedule'!$K$2:$K$825="Vacant", ROW('Bank Schedule'!$K$2:$K$825)), ROW(29:29))), "")} | L32: {=IFERROR(INDEX('Bank Schedule'!M:M, SMALL(IF('Bank Schedule'!$K$2:$K$825="Vacant", ROW('Bank Schedule'!$K$2:$K$825)), ROW(29:29))), "")} | M32: {=IFERROR(INDEX('Bank Schedule'!N:N, SMALL(IF('Bank Schedule'!$K$2:$K$825="Vacant", ROW('Bank Schedule'!$K$2:$K$825)), ROW(29:29))), "")} | N32: {=IFERROR(INDEX('Bank Schedule'!O:O, SMALL(IF('Bank Schedule'!$K$2:$K$825="Vacant", ROW('Bank Schedule'!$K$2:$K$825)), ROW(29:29))), "")} | O32: {=IFERROR(INDEX('Bank Schedule'!P:P, SMALL(IF('Bank Schedule'!$K$2:$K$825="Vacant", ROW('Bank Schedule'!$K$2:$K$825)), ROW(29:29))), "")} | P32: {=IFERROR(INDEX('Bank Schedule'!Q:Q, SMALL(IF('Bank Schedule'!$K$2:$K$825="Vacant", ROW('Bank Schedule'!$K$2:$K$825)), ROW(29:29))), "")} | Q32: {=IFERROR(INDEX('Bank Schedule'!R:R, SMALL(IF('Bank Schedule'!$K$2:$K$825="Vacant", ROW('Bank Schedule'!$K$2:$K$825)), ROW(29:29))), "")} | R32: {=IFERROR(INDEX('Bank Schedule'!S:S, SMALL(IF('Bank Schedule'!$K$2:$K$825="Vacant", ROW('Bank Schedule'!$K$2:$K$825)), ROW(29:29))), "")} | S32: {=IFERROR(INDEX('Bank Schedule'!T:T, SMALL(IF('Bank Schedule'!$K$2:$K$825="Vacant", ROW('Bank Schedule'!$K$2:$K$825)), ROW(29:29))), "")} | T32: {=IFERROR(INDEX('Bank Schedule'!U:U, SMALL(IF('Bank Schedule'!$K$2:$K$825="Vacant", ROW('Bank Schedule'!$K$2:$K$825)), ROW(29:29))), "")} | U32: {=IFERROR(INDEX('Bank Schedule'!V:V, SMALL(IF('Bank Schedule'!$K$2:$K$825="Vacant", ROW('Bank Schedule'!$K$2:$K$825)), ROW(29:29))), "")} | V32: {=IFERROR(INDEX('Bank Schedule'!W:W, SMALL(IF('Bank Schedule'!$K$2:$K$825="Vacant", ROW('Bank Schedule'!$K$2:$K$825)), ROW(29:29))), "")} | W32: {=IFERROR(INDEX('Bank Schedule'!X:X, SMALL(IF('Bank Schedule'!$K$2:$K$825="Vacant", ROW('Bank Schedule'!$K$2:$K$825)), ROW(29:29))), "")} | X32: {=IFERROR(INDEX('Bank Schedule'!Y:Y, SMALL(IF('Bank Schedule'!$K$2:$K$825="Vacant", ROW('Bank Schedule'!$K$2:$K$825)), ROW(29:29))), "")} | Y32: {=IFERROR(INDEX('Bank Schedule'!Z:Z, SMALL(IF('Bank Schedule'!$K$2:$K$825="Vacant", ROW('Bank Schedule'!$K$2:$K$825)), ROW(29:29))), "")} | Z32: {=IFERROR(INDEX('Bank Schedule'!AA:AA, SMALL(IF('Bank Schedule'!$K$2:$K$825="Vacant", ROW('Bank Schedule'!$K$2:$K$825)), ROW(29:29))), "")} | AA32: {=IFERROR(INDEX('Bank Schedule'!AB:AB, SMALL(IF('Bank Schedule'!$K$2:$K$825="Vacant", ROW('Bank Schedule'!$K$2:$K$825)), ROW(29:29))), "")} | AB32: {=IFERROR(INDEX('Bank Schedule'!AC:AC, SMALL(IF('Bank Schedule'!$K$2:$K$825="Vacant", ROW('Bank Schedule'!$K$2:$K$825)), ROW(29:29))), "")} | AC32: {=IFERROR(INDEX('Bank Schedule'!AD:AD, SMALL(IF('Bank Schedule'!$K$2:$K$825="Vacant", ROW('Bank Schedule'!$K$2:$K$825)), ROW(29:29))), "")} | AD32: {=IFERROR(INDEX('Bank Schedule'!AE:AE, SMALL(IF('Bank Schedule'!$K$2:$K$825="Vacant", ROW('Bank Schedule'!$K$2:$K$825)), ROW(29:29))), "")} | AE32: {=IFERROR(INDEX('Bank Schedule'!AF:AF, SMALL(IF('Bank Schedule'!$K$2:$K$825="Vacant", ROW('Bank Schedule'!$K$2:$K$825)), ROW(29:29))), "")} | AF32: {=IFERROR(INDEX('Bank Schedule'!AG:AG, SMALL(IF('Bank Schedule'!$K$2:$K$825="Vacant", ROW('Bank Schedule'!$K$2:$K$825)), ROW(29:29))), "")}
A33: {=IFERROR(INDEX('Bank Schedule'!A:A, SMALL(IF('Bank Schedule'!$K$2:$K$825="Vacant", ROW('Bank Schedule'!$K$2:$K$825)), ROW(30:30))), "")} | B33: {=IFERROR(INDEX('Bank Schedule'!B:B, SMALL(IF('Bank Schedule'!$K$2:$K$825="Vacant", ROW('Bank Schedule'!$K$2:$K$825)), ROW(30:30))), "")} | C33: {=IFERROR(INDEX('Bank Schedule'!C:C, SMALL(IF('Bank Schedule'!$K$2:$K$825="Vacant", ROW('Bank Schedule'!$K$2:$K$825)), ROW(30:30))), "")} | D33: {=IFERROR(INDEX('Bank Schedule'!D:D, SMALL(IF('Bank Schedule'!$K$2:$K$825="Vacant", ROW('Bank Schedule'!$K$2:$K$825)), ROW(30:30))), "")} | E33: {=IFERROR(INDEX('Bank Schedule'!E:E, SMALL(IF('Bank Schedule'!$K$2:$K$825="Vacant", ROW('Bank Schedule'!$K$2:$K$825)), ROW(30:30))), "")} | F33: {=IFERROR(INDEX('Bank Schedule'!F:F, SMALL(IF('Bank Schedule'!$K$2:$K$825="Vacant", ROW('Bank Schedule'!$K$2:$K$825)), ROW(30:30))), "")} | G33: {=IFERROR(INDEX('Bank Schedule'!G:G, SMALL(IF('Bank Schedule'!$K$2:$K$825="Vacant", ROW('Bank Schedule'!$K$2:$K$825)), ROW(30:30))), "")} | H33: {=IFERROR(INDEX('Bank Schedule'!H:H, SMALL(IF('Bank Schedule'!$K$2:$K$825="Vacant", ROW('Bank Schedule'!$K$2:$K$825)), ROW(30:30))), "")} | I33: {=IFERROR(INDEX('Bank Schedule'!I:I, SMALL(IF('Bank Schedule'!$K$2:$K$825="Vacant", ROW('Bank Schedule'!$K$2:$K$825)), ROW(30:30))), "")} | J33: {=IFERROR(INDEX('Bank Schedule'!K:K, SMALL(IF('Bank Schedule'!$K$2:$K$825="Vacant", ROW('Bank Schedule'!$K$2:$K$825)), ROW(30:30))), "")} | K33: {=IFERROR(INDEX('Bank Schedule'!L:L, SMALL(IF('Bank Schedule'!$K$2:$K$825="Vacant", ROW('Bank Schedule'!$K$2:$K$825)), ROW(30:30))), "")} | L33: {=IFERROR(INDEX('Bank Schedule'!M:M, SMALL(IF('Bank Schedule'!$K$2:$K$825="Vacant", ROW('Bank Schedule'!$K$2:$K$825)), ROW(30:30))), "")} | M33: {=IFERROR(INDEX('Bank Schedule'!N:N, SMALL(IF('Bank Schedule'!$K$2:$K$825="Vacant", ROW('Bank Schedule'!$K$2:$K$825)), ROW(30:30))), "")} | N33: {=IFERROR(INDEX('Bank Schedule'!O:O, SMALL(IF('Bank Schedule'!$K$2:$K$825="Vacant", ROW('Bank Schedule'!$K$2:$K$825)), ROW(30:30))), "")} | O33: {=IFERROR(INDEX('Bank Schedule'!P:P, SMALL(IF('Bank Schedule'!$K$2:$K$825="Vacant", ROW('Bank Schedule'!$K$2:$K$825)), ROW(30:30))), "")} | P33: {=IFERROR(INDEX('Bank Schedule'!Q:Q, SMALL(IF('Bank Schedule'!$K$2:$K$825="Vacant", ROW('Bank Schedule'!$K$2:$K$825)), ROW(30:30))), "")} | Q33: {=IFERROR(INDEX('Bank Schedule'!R:R, SMALL(IF('Bank Schedule'!$K$2:$K$825="Vacant", ROW('Bank Schedule'!$K$2:$K$825)), ROW(30:30))), "")} | R33: {=IFERROR(INDEX('Bank Schedule'!S:S, SMALL(IF('Bank Schedule'!$K$2:$K$825="Vacant", ROW('Bank Schedule'!$K$2:$K$825)), ROW(30:30))), "")} | S33: {=IFERROR(INDEX('Bank Schedule'!T:T, SMALL(IF('Bank Schedule'!$K$2:$K$825="Vacant", ROW('Bank Schedule'!$K$2:$K$825)), ROW(30:30))), "")} | T33: {=IFERROR(INDEX('Bank Schedule'!U:U, SMALL(IF('Bank Schedule'!$K$2:$K$825="Vacant", ROW('Bank Schedule'!$K$2:$K$825)), ROW(30:30))), "")} | U33: {=IFERROR(INDEX('Bank Schedule'!V:V, SMALL(IF('Bank Schedule'!$K$2:$K$825="Vacant", ROW('Bank Schedule'!$K$2:$K$825)), ROW(30:30))), "")} | V33: {=IFERROR(INDEX('Bank Schedule'!W:W, SMALL(IF('Bank Schedule'!$K$2:$K$825="Vacant", ROW('Bank Schedule'!$K$2:$K$825)), ROW(30:30))), "")} | W33: {=IFERROR(INDEX('Bank Schedule'!X:X, SMALL(IF('Bank Schedule'!$K$2:$K$825="Vacant", ROW('Bank Schedule'!$K$2:$K$825)), ROW(30:30))), "")} | X33: {=IFERROR(INDEX('Bank Schedule'!Y:Y, SMALL(IF('Bank Schedule'!$K$2:$K$825="Vacant", ROW('Bank Schedule'!$K$2:$K$825)), ROW(30:30))), "")} | Y33: {=IFERROR(INDEX('Bank Schedule'!Z:Z, SMALL(IF('Bank Schedule'!$K$2:$K$825="Vacant", ROW('Bank Schedule'!$K$2:$K$825)), ROW(30:30))), "")} | Z33: {=IFERROR(INDEX('Bank Schedule'!AA:AA, SMALL(IF('Bank Schedule'!$K$2:$K$825="Vacant", ROW('Bank Schedule'!$K$2:$K$825)), ROW(30:30))), "")} | AA33: {=IFERROR(INDEX('Bank Schedule'!AB:AB, SMALL(IF('Bank Schedule'!$K$2:$K$825="Vacant", ROW('Bank Schedule'!$K$2:$K$825)), ROW(30:30))), "")} | AB33: {=IFERROR(INDEX('Bank Schedule'!AC:AC, SMALL(IF('Bank Schedule'!$K$2:$K$825="Vacant", ROW('Bank Schedule'!$K$2:$K$825)), ROW(30:30))), "")} | AC33: {=IFERROR(INDEX('Bank Schedule'!AD:AD, SMALL(IF('Bank Schedule'!$K$2:$K$825="Vacant", ROW('Bank Schedule'!$K$2:$K$825)), ROW(30:30))), "")} | AD33: {=IFERROR(INDEX('Bank Schedule'!AE:AE, SMALL(IF('Bank Schedule'!$K$2:$K$825="Vacant", ROW('Bank Schedule'!$K$2:$K$825)), ROW(30:30))), "")} | AE33: {=IFERROR(INDEX('Bank Schedule'!AF:AF, SMALL(IF('Bank Schedule'!$K$2:$K$825="Vacant", ROW('Bank Schedule'!$K$2:$K$825)), ROW(30:30))), "")} | AF33: {=IFERROR(INDEX('Bank Schedule'!AG:AG, SMALL(IF('Bank Schedule'!$K$2:$K$825="Vacant", ROW('Bank Schedule'!$K$2:$K$825)), ROW(30:30))), "")}
A34: {=IFERROR(INDEX('Bank Schedule'!A:A, SMALL(IF('Bank Schedule'!$K$2:$K$825="Vacant", ROW('Bank Schedule'!$K$2:$K$825)), ROW(31:31))), "")} | B34: {=IFERROR(INDEX('Bank Schedule'!B:B, SMALL(IF('Bank Schedule'!$K$2:$K$825="Vacant", ROW('Bank Schedule'!$K$2:$K$825)), ROW(31:31))), "")} | C34: {=IFERROR(INDEX('Bank Schedule'!C:C, SMALL(IF('Bank Schedule'!$K$2:$K$825="Vacant", ROW('Bank Schedule'!$K$2:$K$825)), ROW(31:31))), "")} | D34: {=IFERROR(INDEX('Bank Schedule'!D:D, SMALL(IF('Bank Schedule'!$K$2:$K$825="Vacant", ROW('Bank Schedule'!$K$2:$K$825)), ROW(31:31))), "")} | E34: {=IFERROR(INDEX('Bank Schedule'!E:E, SMALL(IF('Bank Schedule'!$K$2:$K$825="Vacant", ROW('Bank Schedule'!$K$2:$K$825)), ROW(31:31))), "")} | F34: {=IFERROR(INDEX('Bank Schedule'!F:F, SMALL(IF('Bank Schedule'!$K$2:$K$825="Vacant", ROW('Bank Schedule'!$K$2:$K$825)), ROW(31:31))), "")} | G34: {=IFERROR(INDEX('Bank Schedule'!G:G, SMALL(IF('Bank Schedule'!$K$2:$K$825="Vacant", ROW('Bank Schedule'!$K$2:$K$825)), ROW(31:31))), "")} | H34: {=IFERROR(INDEX('Bank Schedule'!H:H, SMALL(IF('Bank Schedule'!$K$2:$K$825="Vacant", ROW('Bank Schedule'!$K$2:$K$825)), ROW(31:31))), "")} | I34: {=IFERROR(INDEX('Bank Schedule'!I:I, SMALL(IF('Bank Schedule'!$K$2:$K$825="Vacant", ROW('Bank Schedule'!$K$2:$K$825)), ROW(31:31))), "")} | J34: {=IFERROR(INDEX('Bank Schedule'!K:K, SMALL(IF('Bank Schedule'!$K$2:$K$825="Vacant", ROW('Bank Schedule'!$K$2:$K$825)), ROW(31:31))), "")} | K34: {=IFERROR(INDEX('Bank Schedule'!L:L, SMALL(IF('Bank Schedule'!$K$2:$K$825="Vacant", ROW('Bank Schedule'!$K$2:$K$825)), ROW(31:31))), "")} | L34: {=IFERROR(INDEX('Bank Schedule'!M:M, SMALL(IF('Bank Schedule'!$K$2:$K$825="Vacant", ROW('Bank Schedule'!$K$2:$K$825)), ROW(31:31))), "")} | M34: {=IFERROR(INDEX('Bank Schedule'!N:N, SMALL(IF('Bank Schedule'!$K$2:$K$825="Vacant", ROW('Bank Schedule'!$K$2:$K$825)), ROW(31:31))), "")} | N34: {=IFERROR(INDEX('Bank Schedule'!O:O, SMALL(IF('Bank Schedule'!$K$2:$K$825="Vacant", ROW('Bank Schedule'!$K$2:$K$825)), ROW(31:31))), "")} | O34: {=IFERROR(INDEX('Bank Schedule'!P:P, SMALL(IF('Bank Schedule'!$K$2:$K$825="Vacant", ROW('Bank Schedule'!$K$2:$K$825)), ROW(31:31))), "")} | P34: {=IFERROR(INDEX('Bank Schedule'!Q:Q, SMALL(IF('Bank Schedule'!$K$2:$K$825="Vacant", ROW('Bank Schedule'!$K$2:$K$825)), ROW(31:31))), "")} | Q34: {=IFERROR(INDEX('Bank Schedule'!R:R, SMALL(IF('Bank Schedule'!$K$2:$K$825="Vacant", ROW('Bank Schedule'!$K$2:$K$825)), ROW(31:31))), "")} | R34: {=IFERROR(INDEX('Bank Schedule'!S:S, SMALL(IF('Bank Schedule'!$K$2:$K$825="Vacant", ROW('Bank Schedule'!$K$2:$K$825)), ROW(31:31))), "")} | S34: {=IFERROR(INDEX('Bank Schedule'!T:T, SMALL(IF('Bank Schedule'!$K$2:$K$825="Vacant", ROW('Bank Schedule'!$K$2:$K$825)), ROW(31:31))), "")} | T34: {=IFERROR(INDEX('Bank Schedule'!U:U, SMALL(IF('Bank Schedule'!$K$2:$K$825="Vacant", ROW('Bank Schedule'!$K$2:$K$825)), ROW(31:31))), "")} | U34: {=IFERROR(INDEX('Bank Schedule'!V:V, SMALL(IF('Bank Schedule'!$K$2:$K$825="Vacant", ROW('Bank Schedule'!$K$2:$K$825)), ROW(31:31))), "")} | V34: {=IFERROR(INDEX('Bank Schedule'!W:W, SMALL(IF('Bank Schedule'!$K$2:$K$825="Vacant", ROW('Bank Schedule'!$K$2:$K$825)), ROW(31:31))), "")} | W34: {=IFERROR(INDEX('Bank Schedule'!X:X, SMALL(IF('Bank Schedule'!$K$2:$K$825="Vacant", ROW('Bank Schedule'!$K$2:$K$825)), ROW(31:31))), "")} | X34: {=IFERROR(INDEX('Bank Schedule'!Y:Y, SMALL(IF('Bank Schedule'!$K$2:$K$825="Vacant", ROW('Bank Schedule'!$K$2:$K$825)), ROW(31:31))), "")} | Y34: {=IFERROR(INDEX('Bank Schedule'!Z:Z, SMALL(IF('Bank Schedule'!$K$2:$K$825="Vacant", ROW('Bank Schedule'!$K$2:$K$825)), ROW(31:31))), "")} | Z34: {=IFERROR(INDEX('Bank Schedule'!AA:AA, SMALL(IF('Bank Schedule'!$K$2:$K$825="Vacant", ROW('Bank Schedule'!$K$2:$K$825)), ROW(31:31))), "")} | AA34: {=IFERROR(INDEX('Bank Schedule'!AB:AB, SMALL(IF('Bank Schedule'!$K$2:$K$825="Vacant", ROW('Bank Schedule'!$K$2:$K$825)), ROW(31:31))), "")} | AB34: {=IFERROR(INDEX('Bank Schedule'!AC:AC, SMALL(IF('Bank Schedule'!$K$2:$K$825="Vacant", ROW('Bank Schedule'!$K$2:$K$825)), ROW(31:31))), "")} | AC34: {=IFERROR(INDEX('Bank Schedule'!AD:AD, SMALL(IF('Bank Schedule'!$K$2:$K$825="Vacant", ROW('Bank Schedule'!$K$2:$K$825)), ROW(31:31))), "")} | AD34: {=IFERROR(INDEX('Bank Schedule'!AE:AE, SMALL(IF('Bank Schedule'!$K$2:$K$825="Vacant", ROW('Bank Schedule'!$K$2:$K$825)), ROW(31:31))), "")} | AE34: {=IFERROR(INDEX('Bank Schedule'!AF:AF, SMALL(IF('Bank Schedule'!$K$2:$K$825="Vacant", ROW('Bank Schedule'!$K$2:$K$825)), ROW(31:31))), "")} | AF34: {=IFERROR(INDEX('Bank Schedule'!AG:AG, SMALL(IF('Bank Schedule'!$K$2:$K$825="Vacant", ROW('Bank Schedule'!$K$2:$K$825)), ROW(31:31))), "")}
A35: {=IFERROR(INDEX('Bank Schedule'!A:A, SMALL(IF('Bank Schedule'!$K$2:$K$825="Vacant", ROW('Bank Schedule'!$K$2:$K$825)), ROW(32:32))), "")} | B35: {=IFERROR(INDEX('Bank Schedule'!B:B, SMALL(IF('Bank Schedule'!$K$2:$K$825="Vacant", ROW('Bank Schedule'!$K$2:$K$825)), ROW(32:32))), "")} | C35: {=IFERROR(INDEX('Bank Schedule'!C:C, SMALL(IF('Bank Schedule'!$K$2:$K$825="Vacant", ROW('Bank Schedule'!$K$2:$K$825)), ROW(32:32))), "")} | D35: {=IFERROR(INDEX('Bank Schedule'!D:D, SMALL(IF('Bank Schedule'!$K$2:$K$825="Vacant", ROW('Bank Schedule'!$K$2:$K$825)), ROW(32:32))), "")} | E35: {=IFERROR(INDEX('Bank Schedule'!E:E, SMALL(IF('Bank Schedule'!$K$2:$K$825="Vacant", ROW('Bank Schedule'!$K$2:$K$825)), ROW(32:32))), "")} | F35: {=IFERROR(INDEX('Bank Schedule'!F:F, SMALL(IF('Bank Schedule'!$K$2:$K$825="Vacant", ROW('Bank Schedule'!$K$2:$K$825)), ROW(32:32))), "")} | G35: {=IFERROR(INDEX('Bank Schedule'!G:G, SMALL(IF('Bank Schedule'!$K$2:$K$825="Vacant", ROW('Bank Schedule'!$K$2:$K$825)), ROW(32:32))), "")} | H35: {=IFERROR(INDEX('Bank Schedule'!H:H, SMALL(IF('Bank Schedule'!$K$2:$K$825="Vacant", ROW('Bank Schedule'!$K$2:$K$825)), ROW(32:32))), "")} | I35: {=IFERROR(INDEX('Bank Schedule'!I:I, SMALL(IF('Bank Schedule'!$K$2:$K$825="Vacant", ROW('Bank Schedule'!$K$2:$K$825)), ROW(32:32))), "")} | J35: {=IFERROR(INDEX('Bank Schedule'!K:K, SMALL(IF('Bank Schedule'!$K$2:$K$825="Vacant", ROW('Bank Schedule'!$K$2:$K$825)), ROW(32:32))), "")} | K35: {=IFERROR(INDEX('Bank Schedule'!L:L, SMALL(IF('Bank Schedule'!$K$2:$K$825="Vacant", ROW('Bank Schedule'!$K$2:$K$825)), ROW(32:32))), "")} | L35: {=IFERROR(INDEX('Bank Schedule'!M:M, SMALL(IF('Bank Schedule'!$K$2:$K$825="Vacant", ROW('Bank Schedule'!$K$2:$K$825)), ROW(32:32))), "")} | M35: {=IFERROR(INDEX('Bank Schedule'!N:N, SMALL(IF('Bank Schedule'!$K$2:$K$825="Vacant", ROW('Bank Schedule'!$K$2:$K$825)), ROW(32:32))), "")} | N35: {=IFERROR(INDEX('Bank Schedule'!O:O, SMALL(IF('Bank Schedule'!$K$2:$K$825="Vacant", ROW('Bank Schedule'!$K$2:$K$825)), ROW(32:32))), "")} | O35: {=IFERROR(INDEX('Bank Schedule'!P:P, SMALL(IF('Bank Schedule'!$K$2:$K$825="Vacant", ROW('Bank Schedule'!$K$2:$K$825)), ROW(32:32))), "")} | P35: {=IFERROR(INDEX('Bank Schedule'!Q:Q, SMALL(IF('Bank Schedule'!$K$2:$K$825="Vacant", ROW('Bank Schedule'!$K$2:$K$825)), ROW(32:32))), "")} | Q35: {=IFERROR(INDEX('Bank Schedule'!R:R, SMALL(IF('Bank Schedule'!$K$2:$K$825="Vacant", ROW('Bank Schedule'!$K$2:$K$825)), ROW(32:32))), "")} | R35: {=IFERROR(INDEX('Bank Schedule'!S:S, SMALL(IF('Bank Schedule'!$K$2:$K$825="Vacant", ROW('Bank Schedule'!$K$2:$K$825)), ROW(32:32))), "")} | S35: {=IFERROR(INDEX('Bank Schedule'!T:T, SMALL(IF('Bank Schedule'!$K$2:$K$825="Vacant", ROW('Bank Schedule'!$K$2:$K$825)), ROW(32:32))), "")} | T35: {=IFERROR(INDEX('Bank Schedule'!U:U, SMALL(IF('Bank Schedule'!$K$2:$K$825="Vacant", ROW('Bank Schedule'!$K$2:$K$825)), ROW(32:32))), "")} | U35: {=IFERROR(INDEX('Bank Schedule'!V:V, SMALL(IF('Bank Schedule'!$K$2:$K$825="Vacant", ROW('Bank Schedule'!$K$2:$K$825)), ROW(32:32))), "")} | V35: {=IFERROR(INDEX('Bank Schedule'!W:W, SMALL(IF('Bank Schedule'!$K$2:$K$825="Vacant", ROW('Bank Schedule'!$K$2:$K$825)), ROW(32:32))), "")} | W35: {=IFERROR(INDEX('Bank Schedule'!X:X, SMALL(IF('Bank Schedule'!$K$2:$K$825="Vacant", ROW('Bank Schedule'!$K$2:$K$825)), ROW(32:32))), "")} | X35: {=IFERROR(INDEX('Bank Schedule'!Y:Y, SMALL(IF('Bank Schedule'!$K$2:$K$825="Vacant", ROW('Bank Schedule'!$K$2:$K$825)), ROW(32:32))), "")} | Y35: {=IFERROR(INDEX('Bank Schedule'!Z:Z, SMALL(IF('Bank Schedule'!$K$2:$K$825="Vacant", ROW('Bank Schedule'!$K$2:$K$825)), ROW(32:32))), "")} | Z35: {=IFERROR(INDEX('Bank Schedule'!AA:AA, SMALL(IF('Bank Schedule'!$K$2:$K$825="Vacant", ROW('Bank Schedule'!$K$2:$K$825)), ROW(32:32))), "")} | AA35: {=IFERROR(INDEX('Bank Schedule'!AB:AB, SMALL(IF('Bank Schedule'!$K$2:$K$825="Vacant", ROW('Bank Schedule'!$K$2:$K$825)), ROW(32:32))), "")} | AB35: {=IFERROR(INDEX('Bank Schedule'!AC:AC, SMALL(IF('Bank Schedule'!$K$2:$K$825="Vacant", ROW('Bank Schedule'!$K$2:$K$825)), ROW(32:32))), "")} | AC35: {=IFERROR(INDEX('Bank Schedule'!AD:AD, SMALL(IF('Bank Schedule'!$K$2:$K$825="Vacant", ROW('Bank Schedule'!$K$2:$K$825)), ROW(32:32))), "")} | AD35: {=IFERROR(INDEX('Bank Schedule'!AE:AE, SMALL(IF('Bank Schedule'!$K$2:$K$825="Vacant", ROW('Bank Schedule'!$K$2:$K$825)), ROW(32:32))), "")} | AE35: {=IFERROR(INDEX('Bank Schedule'!AF:AF, SMALL(IF('Bank Schedule'!$K$2:$K$825="Vacant", ROW('Bank Schedule'!$K$2:$K$825)), ROW(32:32))), "")} | AF35: {=IFERROR(INDEX('Bank Schedule'!AG:AG, SMALL(IF('Bank Schedule'!$K$2:$K$825="Vacant", ROW('Bank Schedule'!$K$2:$K$825)), ROW(32:32))), "")}
