Workbook

Sheet Bank Schedule
C1: Hide | D1: Hide | E1: Hide
C2: Hide | D2: Hide | E2: Hide | I2: Hide | J2: Hide | R2: Hide | S2: Hide | U2: Hide | W2: Hide | AE2: Hide | AF2: Hide | AG2: Hide | AH2: Hide
B3: Surveyor | C3: Client | D3: Property Number | E3: Property | F3: Unit Demise | G3: Unit Type | H3: Net Area | I3: . | J3: Agency Area group | K3: Tenant Name | L3: Start Date | M3: Expiry Date | N3: Vacant Since? | O3: RRs | P3: Break Date | Q3: Rent PA (£) | R3: check 1 | S3: check 2 | T3: 2023 ERV (£) | U3: check 3 | V3: 2024 ERV (£) | W3: check 4 | X3: ERV 2024 £.Sq.ft | Y3: ERV Variation | Z3: EPC | AA3: * | AB3: 2024 Cap Valn. (£) | AC3: 1954 Act Protected | AD3: Remarks | AE3: Agency Quoting Rent £.sq.ft | AF3: Monthly Viewings | AG3: Total Viewings | AH3: Marketing Agent | AI3: NEW COLUMN | AJ3: other column
AI4: 1 | AJ4: 44026
G5: 5-6 Bywell Place
AI6: 1
B7: JM | C7: MEL | D7: 550020 | E7: 5-6 Bywell Place | F7: Whole Building | G7: Office | H7: 2011 | I7: =H7 -> 2011 | J7: 2000 | K7: 111 Skin Limited | L7: 45365 | M7: 47190 | P7: 46459 | Q7: 115500 | R7: =Q7 -> 115500 | S7: =R7 -> 115500 | T7: 100600 | U7: =T7 -> 100600 | V7: 115000 | W7: =V7 -> 115000 | X7: =V7/H7 -> 57.18548 | Y7: =SUM(V7-T7)/T7 -> 0.14314115 | Z7: C | AB7: 1825000 | AC7: No | AD7: Tenant break on 6 months notice. Break penalty of £28,875 if exercised.
F8: 5/6 Bywell Place | H8: =SUM(H7) -> 2011 | AI8: 2
G9: 22 and 23-25 Eastcastle Street
B11: SH | C11: MEL | D11: 550910 | E11: 22 and 23-25 Eastcastle Street | F11: Lower Ground & Ground (22) | G11: Retail | H11: 2333 | I11: =H11 -> 2333 | J11: 2000 | K11: Top Bridal Ltd | L11: 45736 | M11: 47561 | P11: 46831 | Q11: 128000 | R11: =Q11 -> 128000 | T11: 110000 | U11: =T11 -> 110000 | V11: 108100 | W11: =V11 -> 108100 | X11: =V11/H11 -> 46.335191 | Y11: =SUM(V11-T11)/T11 -> -0.017272727 | Z11: C | AC11: No | AD11: Stepped rent increasing to £130,000 wef 20/03/27. Tenant break on 6 months notice. | AF11: 1 | AG11: 3 | AI11: 4
B12: SH | C12: MEL | D12: 550910 | E12: 22 and 23-25 Eastcastle Street | F12: Lower Ground & Ground (23-25) | G12: Gallery | H12: 6092 | I12: =H12 -> 6092 | J12: 6000 | K12: Sisters Grimm Ltd | L12: 45712 | M12: 47537 | P12: 46806 | Q12: 325000 | R12: =Q12 -> 325000 | T12: 225000 | U12: =T12 -> 225000 | V12: 226100 | W12: =V12 -> 226100 | X12: =V12/H12 -> 37.114248 | Y12: =SUM(V12-T12)/T12 -> 0.0048888889 | Z12: B | AC12: No | AD12: Tenant break on 6 months notice. 1 month rent free from 24/02/28 if break not excerised. | AG12: 3 | AH12: LEM
B13: SH | C13: MEL | D13: 550910 | E13: 22 and 23-25 Eastcastle Street | F13: First Floor (22) | G13: Office | H13: 1063 | I13: =H13 -> 1063 | J13: 1000 | K13: Peter Alexander UK Ltd | L13: 45551 | M13: 47376 | P13: 46645 | Q13: 61425 | R13: =Q13 -> 61425 | T13: 55700 | U13: =T13 -> 55700 | V13: 61100 | W13: =V13 -> 61100 | X13: =V13/H13 -> 57.478833 | Y13: =SUM(V13-T13)/T13 -> 0.096947935 | Z13: D | AC13: No | AD13: Tenant break on 3 months notice. Additional 3 months rent free if not exercised. | AH13: LEM
B14: SH | C14: MEL | D14: 550910 | E14: 22 and 23-25 Eastcastle Street | F14: First Floor (23-25) | G14: Office | H14: 2220 | I14: =H14 -> 2220 | J14: 2000 | K14: Cord Technologies Ltd | L14: 45086 | M14: 46181 | Q14: 131400 | R14: =Q14 -> 131400 | T14: 131100 | U14: =T14 -> 131100 | V14: 133200 | W14: =V14 -> 133200 | X14: =V14/H14 -> 60 | Y14: =SUM(V14-T14)/T14 -> 0.016018307 | Z14: D | AC14: No | AD14: Tenant break passed.
B15: SH | C15: MEL | D15: 550910 | E15: 22 and 23-25 Eastcastle Street | F15: Second Floor (22) | G15: Office | H15: 1124 | I15: =H15 -> 1124 | J15: 1000 | K15: Cord Technologies Ltd | L15: 45614 | M15: 46181 | Q15: 71875 | R15: =Q15 -> 71875 | T15: 60400 | U15: =T15 -> 60400 | V15: 61800 | W15: =V15 -> 61800 | X15: =V15/H15 -> 54.982206 | Y15: =SUM(V15-T15)/T15 -> 0.023178808 | Z15: B | AC15: No | AD15: Tenant break passed.
B16: SH | C16: MEL | D16: 550910 | E16: 22 and 23-25 Eastcastle Street | F16: Second Floor (23-25) | G16: Office | H16: 2238 | I16: =H16 -> 2238 | J16: 2000 | K16: Vacant | N16: 45636 | Q16: 0 | R16: =Q16 -> 0 | T16: 134300 | U16: =T16 -> 134300 | V16: 134300 | W16: =V16 -> 134300 | X16: =V16/H16 -> 60.008937 | Y16: =SUM(V16-T16)/T16 -> 0 | Z16: D | AC16: No | AD16: LEM marketing. | AF16: 2 | AG16: 2
B17: SH | C17: MEL | D17: 550910 | E17: 22 and 23-25 Eastcastle Street | F17: Third Floor (22) | G17: Office | H17: 400 | I17: =H17 -> 400 | J17: 500 | K17: Vacant | N17: 45771 | Q17: 0 | R17: =Q17 -> 0 | T17: 20600 | U17: =T17 -> 20600 | V17: 23000 | W17: =V17 -> 23000 | X17: =V17/H17 -> 57.5 | Y17: =SUM(V17-T17)/T17 -> 0.11650485 | Z17: D | AC17: No | AD17: LEM marketing. | AF17: 1 | AG17: 1
B18: SH | C18: MEL | D18: 550910 | E18: 22 and 23-25 Eastcastle Street | F18: Third Floor (23-25) | G18: Office | H18: 1938 | I18: =H18 -> 1938 | J18: 2000 | K18: Vacant | N18: 45217 | Q18: 0 | R18: =Q18 -> 0 | T18: 109000 | U18: =T18 -> 109000 | V18: 111400 | W18: =V18 -> 111400 | X18: =V18/H18 -> 57.48194 | Y18: =SUM(V18-T18)/T18 -> 0.022018349 | Z18: D | AC18: No | AD18: LEM marketing. | AE18: 65 | AF18: 2 | AG18: 4
B19: SH | C19: MEL | D19: 550910 | E19: 22 and 23-25 Eastcastle Street | F19: Fourth Floor (22) | G19: Office | H19: 419 | I19: =H19 -> 419 | J19: 500 | K19: Element Pictures UK Ltd. | L19: 44539 | M19: 46364 | Q19: 23940 | R19: =Q19 -> 23940 | T19: 21000 | U19: =T19 -> 21000 | V19: 24100 | W19: =V19 -> 24100 | X19: =V19/H19 -> 57.5179 | Y19: =SUM(V19-T19)/T19 -> 0.14761905 | Z19: D | AC19: No | AF19: 1 | AG19: 1
B20: SH | C20: MEL | D20: 550910 | E20: 22 and 23-25 Eastcastle Street | F20: Fourth Floor (23-25) | G20: Office | H20: 972 | I20: =H20 -> 972 | J20: 1000 | K20: Encore Search (Newburgh Street) Ltd. | L20: 45100 | M20: 46926 | P20: 46195 | Q20: 58560 | R20: =Q20 -> 58560 | T20: 49400 | U20: =T20 -> 49400 | V20: 58300 | W20: =V20 -> 58300 | X20: =V20/H20 -> 59.979424 | Y20: =SUM(V20-T20)/T20 -> 0.18016194 | Z20: D | AC20: No | AD20: Tenant break on 6 months notice. 3 months rent free if not exercised.
B21: SH | C21: MEL | D21: 550910 | E21: 22 and 23-25 Eastcastle Street | F21: Fifth Floor (23-25) | G21: Office | H21: 977 | I21: =H21 -> 977 | J21: 1000 | K21: Element Pictures UK Ltd. | L21: 45476 | M21: 47301 | P21: 46364 | Q21: 58496 | R21: =Q21 -> 58496 | T21: 47400 | U21: =T21 -> 47400 | V21: 58600 | W21: =V21 -> 58600 | X21: =V21/H21 -> 59.979529 | Y21: =SUM(V21-T21)/T21 -> 0.23628692 | Z21: B | AC21: No | AD21: Tenant break on 6 months notice.
B22: SH | C22: MEL | D22: 550910 | E22: 22 and 23-25 Eastcastle Street | F22: Sixth Floor (23-25) | G22: Office | H22: 744 | I22: =H22 -> 744 | J22: 750 | K22: Vacant | N22: 45182 | Q22: 0 | R22: =Q22 -> 0 | T22: 34400 | U22: =T22 -> 34400 | V22: 47000 | W22: =V22 -> 47000 | X22: =V22/H22 -> 63.172043 | Y22: =SUM(V22-T22)/T22 -> 0.36627907 | Z22: D | AC22: No | AD22: LEM marketing. | AE22: 63.5 | AF22: 2 | AG22: 4 | AH22: LEM
B23: SH | C23: MEL | D23: 550910 | E23: 22 and 23-25 Eastcastle Street | F23: Garage | G23: Parking | H23: 185 | I23: =H23 -> 185 | J23: 200 | K23: Vacant / Landlord | N23: N/A | Q23: 0 | R23: =Q23 -> 0 | T23: 3000 | U23: =T23 -> 3000 | V23: 4500 | W23: =V23 -> 4500 | X23: =V23/H23 -> 24.324324 | Y23: =SUM(V23-T23)/T23 -> 0.5 | AC23: No
C24: MEL
C25: MEL | F25: 22, 23 & 25 Eastcastle St | H25: =SUM(H11:H23) -> 20705 | Q25: =SUM(Q11:Q23) -> 858696 | S25: =SUM(R10:R23) -> 858696 | T25: =SUM(T11:T23) -> 1001300 | V25: =SUM(V11:V23) -> 1051500 | AB25: 14850000
C26: MEL
C27: MEL | G27: 26 Eastcastle Street
C28: MEL
B29: SH | C29: MEL | D29: 550920 | E29: 26 Eastcastle Street | F29: Lower Ground & Ground | G29: Showroom/ Offices | H29: 2940 | I29: =H29 -> 2940 | J29: 3000 | K29: Hela Brands Ltd | L29: 45649 | M29: 46743 | P29: 46013 | Q29: 132000 | R29: =Q29 -> 132000 | T29: 114600 | U29: =T29 -> 114600 | V29: 124500 | W29: =V29 -> 124500 | X29: =V29/H29 -> 42.346939 | Y29: =SUM(V29-T29)/T29 -> 0.086387435 | Z29: C | AC29: No | AD29: Tenant rolling break from 22/12/25 on 4 months notice.
B30: SH | C30: MEL | D30: 550920 | E30: 26 Eastcastle Street | F30: First Floor | G30: Offices | H30: 1398 | I30: =H30 -> 1398 | J30: 1000 | K30: Alternative Real Estate Advisors Ltd | L30: 45470 | M30: 47295 | P30: 46564 | Q30: 89833 | R30: =Q30 -> 89833 | T30: 76900 | U30: =T30 -> 76900 | V30: 97900 | W30: =V30 -> 97900 | X30: =V30/H30 -> 70.028612 | Y30: =SUM(V30-T30)/T30 -> 0.27308192 | Z30: D | AC30: No | AD30: Rent increases to £98,000 wef 27/06/27. Tenant break on 6 months notice.
B31: SH | C31: MEL | D31: 550920 | E31: 26 Eastcastle Street | F31: Second Floor | G31: Offices | H31: 1110 | I31: =H31 -> 1110 | J31: 1000 | K31: Vacant | N31: 43273 | Q31: 0 | R31: =Q31 -> 0 | T31: 61100 | U31: =T31 -> 61100 | V31: 69400 | W31: =V31 -> 69400 | X31: =V31/H31 -> 62.522523 | Y31: =SUM(V31-T31)/T31 -> 0.13584288 | Z31: C | AC31: No | AD31: LEM marketing. | AE31: 63.5 | AG31: 1
B32: SH | C32: MEL | D32: 550920 | E32: 26 Eastcastle Street | F32: Third Floor | G32: Offices | H32: 481 | I32: =H32 -> 481 | J32: 500 | K32: Mr. A. Park | L32: 45541 | M32: 47366 | P32: 46635 | Q32: 26000 | R32: =Q32 -> 26000 | T32: 25300 | U32: =T32 -> 25300 | V32: 25300 | W32: =V32 -> 25300 | X32: =V32/H32 -> 52.598753 | Y32: =SUM(V32-T32)/T32 -> 0 | Z32: D | AC32: No | AD32: Tenant break on 6 months notice.
C33: MEL
C34: MEL | F34: 26 Eastcastle Street | H34: =SUM(H29:H32) -> 5929 | Q34: =SUM(Q29:Q32) -> 247833 | S34: =SUM(R29:R32) -> 247833 | T34: =SUM(T29:T32) -> 277900 | V34: =SUM(V29:V32) -> 317100 | AB34: 4725000
C35: MEL
C36: MEL | G36: 27 - 28 Eastcastle Street
C37: MEL
B38: SH | C38: MEL | D38: 550930 | E38: 27 - 28 Eastcastle Street | F38: Lower Ground & Ground | G38: Showroom / Offices | H38: 3668 | I38: =H38 -> 3668 | J38: 3500 | K38: The London Hair Clinic Ltd | L38: 44757 | M38: 48409 | O38: 46583 | Q38: 170000 | R38: =Q38 -> 170000 | T38: 170000 | U38: =T38 -> 170000 | V38: 170000 | W38: =V38 -> 170000 | X38: =V38/H38 -> 46.346783 | Y38: =SUM(V38-T38)/T38 -> 0 | Z38: B | AC38: No
B39: SH | C39: MEL | D39: 550930 | E39: 27 - 28 Eastcastle Street | F39: First Floor | G39: Offices | H39: 1418 | I39: =H39 -> 1418 | J39: 1500 | K39: Feldberg Capital UK Limited | L39: 45231 | M39: 46326 | Q39: 174500 | R39: =Q39 -> 174500 | T39: 78000 | U39: =T39 -> 78000 | V39: 99300 | W39: =V39 -> 99300 | X39: =V39/H39 -> 70.028209 | Y39: =SUM(V39-T39)/T39 -> 0.27307692 | Z39: B | AC39: No | AD39: All inclusive including rates and furniture.
B40: SH | C40: MEL | D40: 550930 | E40: 27 - 28 Eastcastle Street | F40: Second Floor | G40: Offices | H40: 716 | I40: =H40 -> 716 | J40: 750 | K40: MSP Secretaries Ltd. | L40: 44384 | M40: 46209 | Q40: 41000 | R40: =Q40 -> 41000 | T40: 39400 | U40: =T40 -> 39400 | V40: 41200 | W40: =V40 -> 41200 | X40: =V40/H40 -> 57.541899 | Y40: =SUM(V40-T40)/T40 -> 0.045685279 | Z40: B | AC40: No
B41: SH | C41: MEL | D41: 550930 | E41: 27 - 28 Eastcastle Street | F41: Third Floor | G41: Offices | H41: 665 | I41: =H41 -> 665 | J41: 750 | K41: Principle Estate Management LLP | L41: 45617 | M41: 47442 | P41: 46527 | Q41: 41875 | R41: =Q41 -> 41875 | T41: 36600 | U41: =T41 -> 36600 | V41: 38200 | W41: =V41 -> 38200 | X41: =V41/H41 -> 57.443609 | Y41: =SUM(V41-T41)/T41 -> 0.043715847 | Z41: B | AC41: No | AD41: Tenant break on 6 months notice. 2 months rent free if break not exercised.
C42: MEL
C43: MEL | F43: 27/28 Eastcastle Street | H43: =SUM(H38:H41) -> 6467 | Q43: =SUM(Q36:Q41) -> 427375 | S43: =SUM(R38:R41) -> 427375 | T43: =SUM(T38:T41) -> 324000 | V43: =SUM(V38:V41) -> 348700 | AB43: 5675000
C44: MEL
C45: MEL | G45: 10 Great Castle Street
C46: MEL
B47: WS | C47: MEL | D47: 550560 | E47: 10 Great Castle Street | F47: Basmt. Ground - 1 to 4 Floors | G47: Office | H47: 12578 | I47: =H47 -> 12578 | J47: 12500 | K47: Guaranty Trust Bank (UK) Ltd | L47: 44771 | M47: 50249 | O47: 46597 | P47: 48423 | Q47: 633334 | R47: =Q47 -> 633334 | S47: =R47 -> 633334 | T47: 950000 | U47: =T47 -> 950000 | V47: 950000 | W47: =V47 -> 950000 | X47: =V47/H47 -> 75.528701 | Y47: =SUM(V47-T47)/T47 -> 0 | Z47: C | AB47: 17050000 | AC47: No | AD47: Fixed increase to £950,000 wef 29/07/26. 5 yearly rent reviews. Tenant break on 9 months notice. Rent reduces by 20% for 12 months if break not activated.
C48: MEL | F48: 8-11 Great Castle Street | H48: =SUM(H47) -> 12578 | Q48: =SUM(Q47) -> 633334 | T48: =SUM(T47) -> 950000 | V48: =SUM(V47) -> 950000
C49: MEL | G49: Windsor House, 40-41 Great Castle Street
C50: MEL
B51: SH | C51: MEL | D51: 550070 | E51: Windsor House, 40-41 Great Castle Street | F51: Basement & Ground Floor | G51: Retail/Café | H51: 2235 | I51: =H51 -> 2235 | J51: 2000 | K51: Vacant | N51: 45754 | Q51: 0 | R51: =Q51 -> 0 | T51: 143000 | U51: =T51 -> 143000 | V51: 145000 | W51: =V51 -> 145000 | X51: =V51/H51 -> 64.876957 | Y51: =SUM(V51-T51)/T51 -> 0.013986014 | Z51: D | AC51: No | AD51: LEM Marketing. | AF51: 15 | AG51: 15
B52: SH | C52: MEL | D52: 550070 | E52: Windsor House, 40-41 Great Castle Street | F52: First Floor | G52: Office | H52: 694 | I52: =H52 -> 694 | J52: 750 | K52: JRDL UK Ltd. | L52: 44904 | M52: 45999 | Q52: 42000 | R52: =Q52 -> 42000 | T52: 42000 | U52: =T52 -> 42000 | V52: 42000 | W52: =V52 -> 42000 | X52: =V52/H52 -> 60.518732 | Y52: =SUM(V52-T52)/T52 -> 0 | Z52: D | AC52: No
B53: SH | C53: MEL | D53: 550070 | E53: Windsor House, 40-41 Great Castle Street | F53: Second Floor | G53: Office | H53: 690 | I53: =H53 -> 690 | J53: 750 | K53: Jamieson Stone Services Ltd. | L53: 45412 | M53: 47237 | P53: 46326 | Q53: 40020 | R53: =Q53 -> 40020 | T53: 39700 | U53: =T53 -> 39700 | V53: 40000 | W53: =V53 -> 40000 | X53: =V53/H53 -> 57.971014 | Y53: =SUM(V53-T53)/T53 -> 0.0075566751 | Z53: D | AC53: No | AD53: Tenant break on 6 months notice.
B54: SH | C54: MEL | D54: 550070 | E54: Windsor House, 40-41 Great Castle Street | F54: Third Floor | G54: Office | H54: 620 | I54: =H54 -> 620 | J54: 750 | K54: Arav Fashion UK Ltd. | L54: 44816 | M54: 45911 | Q54: 33480 | R54: =Q54 -> 33480 | T54: 34100 | U54: =T54 -> 34100 | V54: 36000 | W54: =V54 -> 36000 | X54: =V54/H54 -> 58.064516 | Y54: =SUM(V54-T54)/T54 -> 0.055718475 | Z54: D | AC54: No
B55: SH | C55: MEL | D55: 550070 | E55: Windsor House, 40-41 Great Castle Street | F55: Fourth Floor | G55: Office | H55: 400 | I55: =H55 -> 400 | J55: 500 | K55: Vacant | N55: 44168 | Q55: 0 | R55: =Q55 -> 0 | T55: 21600 | U55: =T55 -> 21600 | V55: 22000 | W55: =V55 -> 22000 | X55: =V55/H55 -> 55 | Y55: =SUM(V55-T55)/T55 -> 0.018518519 | Z55: D | AC55: No | AD55: To be refurbished.
B56: SH | C56: MEL | D56: 550070 | E56: Windsor House, 40-41 Great Castle Street | F56: Roof | G56: Air Con Units | H56: 0 | I56: =H56 -> 0 | K56: Vacant / Landlord | N56: N/A | Q56: 0 | R56: =Q56 -> 0 | T56: 0 | U56: =T56 -> 0 | V56: 0 | W56: =V56 -> 0 | AC56: No
C57: MEL
C58: MEL | F58: 40/41 Great Castle Street | H58: =SUM(H51:H56) -> 4639 | Q58: =SUM(Q51:Q56) -> 115500 | S58: =SUM(R51:R56) -> 115500 | T58: =SUM(T51:T56) -> 280400 | V58: =SUM(V51:V56) -> 285000 | AB58: 4750000
C59: MEL
C60: MEL | G60: Portland House, 4 Great Portland Street
C61: MEL
B62: SH | C62: MEL | D62: 550470 | E62: Portland House, 4 Great Portland Street | F62: Basement (West) | G62: Restaurant/Bar | H62: 2945 | I62: =H62 -> 2945 | J62: 3000 | K62: The London Cocktail Club Ltd | L62: 41457 | M62: 46935 | Q62: 147500 | R62: =Q62 -> 147500 | T62: 147500 | U62: =T62 -> 147500 | V62: 147500 | W62: =V62 -> 147500 | X62: =V62/H62 -> 50.08489 | Y62: =SUM(V62-T62)/T62 -> 0 | Z62: E | AC62: No | AD62: 5 year reversionary lease completed from 02/07/28 with day one rent review. Rent review to be documented at passing rent.
B63: SH | C63: MEL | D63: 550470 | E63: Portland House, 4 Great Portland Street | F63: Ground Floor | G63: Retail/Cafe | H63: 2103 | I63: =H63 -> 2103 | J63: 2000 | K63: Costa Ltd | L63: 45669 | M63: 51146 | O63: 47495 | P63: 49320 | Q63: 220000 | R63: =Q63 -> 220000 | T63: 176200 | U63: =T63 -> 176200 | V63: 220000 | W63: =V63 -> 220000 | X63: =V63/H63 -> 104.61246 | Y63: =SUM(V63-T63)/T63 -> 0.24858116 | Z63: B | AC63: No | AD63: Mutual break on 6 months notice.
B64: SH | C64: MEL | D64: 550470 | E64: Portland House, 4 Great Portland Street | F64: Ground Floor & Basement (East) & Basement Vaults | G64: Restaurant | H64: 5667 | I64: =H64 -> 5667 | J64: 5500 | K64: Futuremaxx Ltd | L64: 45567 | M64: 51044 | O64: 47393 | Q64: 150000 | R64: =Q64 -> 150000 | T64: 255000 | U64: =T64 -> 255000 | V64: 300000 | W64: =V64 -> 300000 | X64: =V64/H64 -> 52.938062 | Y64: =SUM(V64-T64)/T64 -> 0.17647059 | Z64: B | AC64: No | AD64: Stepped rent. £300,000 wef 02/10/25, £305,000 wef 02/10/26, £310,000 wef 02/10/27 and £320,000 wef 02/10/28. Min rent on review £330,000. Landlord redevelopment break option on 01/07/33 on 6 months notice.
B65: SH | C65: MEL | D65: 550470 | E65: Portland House, 4 Great Portland Street | F65: First Floor (West) | G65: Office | H65: 1784 | I65: =H65 -> 1784 | J65: 1750 | K65: Time & Tide Holdings (UK) Ltd | L65: 45457 | M65: 47282 | Q65: 60700 | R65: =Q65 -> 60700 | T65: 99700 | U65: =T65 -> 99700 | V65: 120400 | W65: =V65 -> 120400 | X65: =V65/H65 -> 67.488789 | Y65: =SUM(V65-T65)/T65 -> 0.20762287 | Z65: B | AC65: No | AD65: Rent increases to £121,400 wef 14/08/25
B66: SH | C66: MEL | D66: 550470 | E66: Portland House, 4 Great Portland Street | F66: First Floor (East) | G66: Office | H66: 2075 | I66: =H66 -> 2075 | J66: 2000 | K66: L52 Communications Ltd | L66: 45384 | M66: 47209 | P66: 46478 | Q66: 133280 | R66: =Q66 -> 133280 | T66: 114700 | U66: =T66 -> 114700 | V66: 140100 | W66: =V66 -> 140100 | X66: =V66/H66 -> 67.518072 | Y66: =SUM(V66-T66)/T66 -> 0.22144725 | Z66: B | AC66: No | AD66: Tenant break on 6 months notice. 1 month rent free from 02/04/27 if not exercised.
B67: SH | C67: MEL | D67: 550470 | E67: Portland House, 4 Great Portland Street | F67: Second Floor (East) | G67: Office | H67: 2063 | I67: =H67 -> 2063 | J67: 2000 | K67: Tekcor4 Limited | L67: 45516 | M67: 47341 | P67: 46610 | Q67: 146450 | R67: =Q67 -> 146450 | T67: 120700 | U67: =T67 -> 120700 | V67: 139260 | W67: =V67 -> 139260 | X67: =V67/H67 -> 67.503635 | Y67: =SUM(V67-T67)/T67 -> 0.15376968 | Z67: B | AC67: No | AD67: Tenant break on 6 months notice.
B68: SH | C68: MEL | D68: 550470 | E68: Portland House, 4 Great Portland Street | F68: Second Floor (West) | G68: Office | H68: 1796 | I68: =H68 -> 1796 | J68: 1750 | K68: Vacant | N68: 45051 | Q68: 0 | R68: =Q68 -> 0 | T68: 87300 | U68: =T68 -> 87300 | V68: 121240 | W68: =V68 -> 121240 | X68: =V68/H68 -> 67.505568 | Y68: =SUM(V68-T68)/T68 -> 0.38877434 | Z68: B | AC68: No | AD68: LEM marketing. | AE68: 72.5 | AF68: 3 | AG68: 13 | AH68: LEM/LDG
B69: SH | C69: MEL | D69: 550470 | E69: Portland House, 4 Great Portland Street | F69: Third Floor (West) | G69: Office | H69: 1691 | I69: =H69 -> 1691 | J69: 1500 | K69: J&M Davidson Limited. | L69: 44795 | M69: 46620 | P69: 45890 | Q69: 102705 | R69: =Q69 -> 102705 | T69: 102705 | U69: =T69 -> 102705 | V69: 114100 | W69: =V69 -> 114100 | X69: =V69/H69 -> 67.474867 | Y69: =SUM(V69-T69)/T69 -> 0.11094883 | Z69: B | AC69: No | AD69: Tenant break on 6 months notice.
B70: SH | C70: MEL | D70: 550470 | E70: Portland House, 4 Great Portland Street | F70: Third Floor (East) | G70: Office | H70: 2055 | I70: =H70 -> 2055 | J70: 2000 | K70: Media Campaign Limited | L70: 45488 | M70: 47313 | P70: 46582 | Q70: 181050 | R70: =Q70 -> 181050 | T70: 125050 | U70: =T70 -> 125050 | V70: 138700 | W70: =V70 -> 138700 | X70: =V70/H70 -> 67.493917 | Y70: =SUM(V70-T70)/T70 -> 0.10915634 | Z70: B | AC70: No | AD70: Tenant break on 6 months notice. 2 months rent free @ 15/07/27 if not exercised.
B71: SH | C71: MEL | D71: 550470 | E71: Portland House, 4 Great Portland Street | F71: Fourth Floor (West) | G71: Office | H71: 1548 | I71: =H71 -> 1548 | J71: 1500 | K71: Racoon Media Services Limited | L71: 45609 | M71: 47434 | P71: 46703 | Q71: 90090 | R71: =Q71 -> 90090 | T71: 90100 | U71: =T71 -> 90100 | V71: 104500 | W71: =V71 -> 104500 | X71: =V71/H71 -> 67.50646 | Y71: =SUM(V71-T71)/T71 -> 0.15982242 | Z71: B | AC71: No | AD71: Tenant break on 6 months notice. Rent PA corrected.
B72: SH | C72: MEL | D72: 550470 | E72: Portland House, 4 Great Portland Street | F72: Fourth Floor (East) | G72: Office | H72: 1957 | I72: =H72 -> 1957 | J72: 2000 | K72: Racoon Media Services Limited | L72: 45609 | M72: 47434 | P72: 46703 | Q72: 114253 | R72: =Q72 -> 114253 | T72: 115800 | U72: =T72 -> 115800 | V72: 132100 | W72: =V72 -> 132100 | X72: =V72/H72 -> 67.501277 | Y72: =SUM(V72-T72)/T72 -> 0.14075993 | Z72: B | AC72: No | AD72: Tenant break on 6 months notice.
B73: SH | C73: MEL | D73: 550470 | E73: Portland House, 4 Great Portland Street | F73: Fifth Floor (East) | G73: Office | H73: 1845 | I73: =H73 -> 1845 | J73: 2000 | K73: Greek National Tourism Organisation. | L73: 45256 | M73: 47082 | P73: 46351 | Q73: 115500 | R73: =Q73 -> 115500 | T73: 107400 | U73: =T73 -> 107400 | V73: 124500 | W73: =V73 -> 124500 | X73: =V73/H73 -> 67.479675 | Y73: =SUM(V73-T73)/T73 -> 0.15921788 | Z73: B | AC73: No | AD73: Tenant break on 6 months notice.
B74: SH | C74: MEL | D74: 550470 | E74: Portland House, 4 Great Portland Street | F74: Fifth Floor (West) | G74: Office | H74: 1528 | I74: =H74 -> 1528 | J74: 1500 | K74: Rios Designs Ltd | L74: 45622 | M74: 47447 | P74: 46716 | Q74: 54340 | R74: =Q74 -> 54340 | T74: 76600 | U74: =T74 -> 76600 | V74: 103100 | W74: =V74 -> 103100 | X74: =V74/H74 -> 67.473822 | Y74: =SUM(V74-T74)/T74 -> 0.345953 | Z74: B | AC74: No | AD74: Rent increases to £108,680 wef 26/11/25. Tenant break on 6 months notice. | AG74: 2 | AH74: LEM/LDG
B75: SH | C75: MEL | D75: 550470 | E75: Portland House, 4 Great Portland Street | F75: Sixth Floor (West) | G75: Office | H75: 1253 | I75: =H75 -> 1253 | J75: 1250 | K75: Directors Cut Films West Limited | L75: 45617 | M75: 47442 | Q75: 66700 | R75: =Q75 -> 66700 | T75: 66700 | U75: =T75 -> 66700 | V75: 78300 | W75: =V75 -> 78300 | X75: =V75/H75 -> 62.490024 | Y75: =SUM(V75-T75)/T75 -> 0.17391304 | Z75: D | AC75: No
B76: SH | C76: MEL | D76: 550470 | E76: Portland House, 4 Great Portland Street | F76: Sixth Floor (East) | G76: Office | H76: 859 | I76: =H76 -> 859 | J76: 1000 | K76: Vacant | N76: 44609 | Q76: 0 | R76: =Q76 -> 0 | T76: 65750 | U76: =T76 -> 65750 | V76: 53700 | W76: =V76 -> 53700 | X76: =V76/H76 -> 62.514552 | Y76: =SUM(V76-T76)/T76 -> -0.18326996 | Z76: D | AC76: No | AD76: LEM marketing. | AE76: 63 | AG76: 2
B77: SH | C77: MEL | D77: 550470 | E77: Portland House, 4 Great Portland Street | F77: Cupboards 2nd, 4th, 5th & 6th Floors | G77: Storage | H77: 0 | I77: =H77 -> 0 | K77: Vacant / Landlord | N77: N/A | Q77: 0 | R77: =Q77 -> 0 | T77: 1460 | U77: =T77 -> 1460 | V77: 0 | W77: =V77 -> 0 | AD77: To be converted into extra toilet facilities.
B78: SH | C78: MEL | D78: 550470 | E78: Portland House, 4 Great Portland Street | F78: Transformer Chamber | G78: Sub-Station | H78: 0 | I78: =H78 -> 0 | K78: London Power Networks Plc | L78: 35240 | M78: 68735 | Q78: 0 | R78: =Q78 -> 0 | T78: 0 | U78: =T78 -> 0 | V78: 0 | W78: =V78 -> 0 | AC78: Yes | AD78: Rolling redevelopment break on 6 months notice.
C79: MEL
C80: MEL | F80: 4 Great Portland Street | H80: =SUM(H62:H78) -> 31169 | Q80: =SUM(Q62:Q78) -> 1582568 | S80: =SUM(R62:R78) -> 1582568 | T80: =SUM(T62:T78) -> 1752665 | V80: =SUM(V62:V78) -> 2037500 | AB80: 34025000
C81: MEL
C82: MEL | G82: 6-10a Great Portland Street
C83: MEL
B84: SH | C84: MEL | D84: 550480 | E84: 6-10a Great Portland Street | F84: Basement & Ground | G84: Retail | H84: 4958 | I84: =H84 -> 4958 | J84: 5000 | K84: PrettyLittleThing.com | L84: 45699 | M84: 47524 | P84: 46793 | Q84: 187500 | R84: =Q84 -> 187500 | T84: 337100 | U84: =T84 -> 337100 | V84: 380000 | W84: =V84 -> 380000 | X84: =V84/H84 -> 76.643808 | Y84: =SUM(V84-T84)/T84 -> 0.12726194 | Z84: B | AC84: No | AD84: Rent increasing to £375,000 wef 11/09/25. Tenant break on 6 months notice. 3 months rent free if not exercised. | AE84: 68 | AF84: 1 | AG84: 13 | AH84: LEM / Colliers
B85: SH | C85: MEL | D85: 550480 | E85: 6-10a Great Portland Street | F85: First Floor | G85: Office | H85: 1862 | I85: =H85 -> 1862 | J85: 2000 | K85: The Yuki Clinic Ltd. | L85: 44452 | M85: 46277 | Q85: 108170 | R85: =Q85 -> 108170 | T85: 107200 | U85: =T85 -> 107200 | V85: 114500 | W85: =V85 -> 114500 | X85: =V85/H85 -> 61.493018 | Y85: =SUM(V85-T85)/T85 -> 0.068097015 | Z85: D | AC85: No
B86: SH | C86: MEL | D86: 550480 | E86: 6-10a Great Portland Street | F86: Second Floor | G86: Office | H86: 1818 | I86: =H86 -> 1818 | J86: 2000 | K86: Vacant | N86: 45609 | Q86: 0 | R86: =Q86 -> 0 | T86: 105500 | U86: =T86 -> 105500 | V86: 109100 | W86: =V86 -> 109100 | X86: =V86/H86 -> 60.011001 | Y86: =SUM(V86-T86)/T86 -> 0.034123223 | Z86: E | AC86: No | AD86: LEM marketing. | AE86: 65 | AF86: 4 | AG86: 6
B87: SH | C87: MEL | D87: 550480 | E87: 6-10a Great Portland Street | F87: Third Floor | G87: Office | H87: 1808 | I87: =H87 -> 1808 | J87: 2000 | K87: Vacant | N87: 45609 | Q87: 0 | R87: =Q87 -> 0 | T87: 108800 | U87: =T87 -> 108800 | V87: 108500 | W87: =V87 -> 108500 | X87: =V87/H87 -> 60.011062 | Y87: =SUM(V87-T87)/T87 -> -0.0027573529 | Z87: E | AC87: No | AD87: LEM marketing. | AE87: 65 | AF87: 4 | AG87: 6
B88: SH | C88: MEL | D88: 550480 | E88: 6-10a Great Portland Street | F88: Fourth Floor | G88: Office | H88: 1672 | I88: =H88 -> 1672 | J88: 1500 | K88: Vacant | N88: 45457 | Q88: 0 | R88: =Q88 -> 0 | T88: 94400 | U88: =T88 -> 94400 | V88: 97800 | W88: =V88 -> 97800 | X88: =V88/H88 -> 58.492823 | Y88: =SUM(V88-T88)/T88 -> 0.036016949 | Z88: B | AC88: No | AD88: To be refurbished. | AE88: 65 | AF88: 1 | AG88: 2 | AH88: LEM
B89: SH | C89: MEL | D89: 550480 | E89: 6-10a Great Portland Street | F89: Fifth Floor | G89: Office | H89: 995 | I89: =H89 -> 995 | J89: 1000 | K89: Racoon Media Services Limited | L89: 45609 | M89: 47434 | P89: 46703 | Q89: 61928 | R89: =Q89 -> 61928 | T89: 61200 | U89: =T89 -> 61200 | V89: 57200 | W89: =V89 -> 57200 | X89: =V89/H89 -> 57.487437 | Y89: =SUM(V89-T89)/T89 -> -0.065359477 | Z89: E | AC89: No | AD89: Tenant break on 6 months notice.
B90: SH | C90: MEL | D90: 550480 | E90: 6-10a Great Portland Street | F90: Basement | G90: Sub-Station | H90: 0 | I90: =H90 -> 0 | K90: London Power Networks Plc | L90: 39295 | M90: 46599 | O90: 45870 | Q90: 903 | R90: =Q90 -> 903 | T90: 625 | U90: =T90 -> 625 | V90: 625 | W90: =V90 -> 625 | AC90: No | AD90: Landlords redevelopment break on 6 months notice. Rent review is RPI indexation (every 2 years. Rent review completed. Backdated rent increased £737 wef 01/08/21 & £903 wef 01/08/23.
C91: MEL
C92: MEL | F92: 6/10a Great Portland Street | H92: =SUM(H84:H90) -> 13113 | Q92: =SUM(Q84:Q90) -> 358501 | S92: =SUM(R83:R90) -> 358501 | T92: =SUM(T84:T90) -> 814825 | V92: =SUM(V84:V90) -> 867725 | AB92: 13775000
C93: MEL
C94: MEL | G94: 15-17 Great Portland Street & 6-7 Great Castle Street
C95: MEL
B96: SH | C96: MEL | D96: 550530 | E96: 15-17 Great Portland Street & 6-7 Great Castle Street | F96: Whole Building | G96: Office/Bank | H96: 9884 | I96: =H96 -> 9884 | J96: 10000 | K96: Barclays Bank UK Plc | L96: 44856 | M96: 47411 | O96: 46682 | Q96: 580000 | R96: =Q96 -> 580000 | S96: =R96 -> 580000 | T96: 580000 | U96: =T96 -> 580000 | V96: 607100 | W96: =V96 -> 607100 | X96: =V96/H96 -> 61.422501 | Y96: =SUM(V96-T96)/T96 -> 0.046724138 | Z96: B | AB96: 10650000 | AC96: Yes
C97: MEL | F97: 15/17 Great Portland Street | H97: =SUM(H96) -> 9884 | Q97: =SUM(Q96) -> 580000 | T97: =SUM(T96) -> 580000 | V97: =SUM(V96) -> 607100
C98: MEL
C99: MEL | G99: 19-21 Great Portland Street
C100: MEL
B101: CD | C101: MEL | D101: 550410 | E101: 19-21 Great Portland Street . | F101: Basement, Ground & First Floors | G101: Restaurant | H101: 11225 | I101: =H101 -> 11225 | J101: 10000 | K101: UK VAP GPS | L101: 44729 | M101: 50207 | O101: 46555 | P101: 48381 | Q101: 625000 | R101: =Q101 -> 625000 | T101: 750000 | U101: =T101 -> 750000 | V101: 650000 | W101: =V101 -> 650000 | X101: =V101/H101 -> 57.906459 | Y101: =SUM(V101-T101)/T101 -> -0.13333333 | Z101: B | AC101: No | AD101: Rent increasing to £650,000 wef 25/03/26. Mutual break @ 16/06/32 on 6 months notice.
...

Sheet Voids Tab
B3: Surveyor | C3: Client | D3: Property Number | E3: Property | F3: Unit Demise | G3: Unit Type | H3: Net Area | I3: . | J3: Agency Area | K3: Tenant Name | L3: Start Date | M3: Expiry Date | N3: Vacant Since? | O3: RRs | P3: Break Date | Q3: Rent PA (£) | R3: check 1 | S3: check 2 | T3: 2023 ERV (£) | U3: check 3 | V3: 2024 ERV (£) | W3: check 4 | X3: ERV 2024 £.Sq.ft | Z3: EPC | AA3: * | AB3: 2024 Cap Valn. (£) | AC3: 1954 Act Protected | AD3: Remarks | AE3: Agency Quoting Rent £.sq.ft | AF3: Monthly Viewings | AG3: Total Viewings | AH3: Marketing Agent
A4: =IFERROR(INDEX('Bank Schedule'!A:A, SMALL(IF('Bank Schedule'!$K$2:$K$825="Vacant", ROW('Bank Schedule'!$K$2:$K$825)), ROW(1:1))), "") -> 0 | B4: {=IFERROR(INDEX('Bank Schedule'!B:B, SMALL(IF('Bank Schedule'!$K$2:$K$825="Vacant", ROW('Bank Schedule'!$K$2:$K$825)), ROW(1:1))), "")} -> SH | C4: {=IFERROR(INDEX('Bank Schedule'!C:C, SMALL(IF('Bank Schedule'!$K$2:$K$825="Vacant", ROW('Bank Schedule'!$K$2:$K$825)), ROW(1:1))), "")} -> MEL | D4: {=IFERROR(INDEX('Bank Schedule'!D:D, SMALL(IF('Bank Schedule'!$K$2:$K$825="Vacant", ROW('Bank Schedule'!$K$2:$K$825)), ROW(1:1))), "")} -> 550910 | E4: {=IFERROR(INDEX('Bank Schedule'!E:E, SMALL(IF('Bank Schedule'!$K$2:$K$825="Vacant", ROW('Bank Schedule'!$K$2:$K$825)), ROW(1:1))), "")} -> 22 and 23-25 Eastcastle Street | F4: {=IFERROR(INDEX('Bank Schedule'!F:F, SMALL(IF('Bank Schedule'!$K$2:$K$825="Vacant", ROW('Bank Schedule'!$K$2:$K$825)), ROW(1:1))), "")} -> Second Floor (23-25) | G4: {=IFERROR(INDEX('Bank Schedule'!G:G, SMALL(IF('Bank Schedule'!$K$2:$K$825="Vacant", ROW('Bank Schedule'!$K$2:$K$825)), ROW(1:1))), "")} -> Office | H4: {=IFERROR(INDEX('Bank Schedule'!H:H, SMALL(IF('Bank Schedule'!$K$2:$K$825="Vacant", ROW('Bank Schedule'!$K$2:$K$825)), ROW(1:1))), "")} -> 2238 | I4: {=IFERROR(INDEX('Bank Schedule'!I:I, SMALL(IF('Bank Schedule'!$K$2:$K$825="Vacant", ROW('Bank Schedule'!$K$2:$K$825)), ROW(1:1))), "")} -> 2238 | J4: {=IFERROR(INDEX('Bank Schedule'!J:J, SMALL(IF('Bank Schedule'!$K$2:$K$825="Vacant", ROW('Bank Schedule'!$K$2:$K$825)), ROW(1:1))), "")} -> 2000 | K4: {=IFERROR(INDEX('Bank Schedule'!K:K, SMALL(IF('Bank Schedule'!$K$2:$K$825="Vacant", ROW('Bank Schedule'!$K$2:$K$825)), ROW(1:1))), "")} -> Vacant | L4: =IFERROR(INDEX('Bank Schedule'!L:L, SMALL(IF('Bank Schedule'!$K$2:$K$825="Vacant", ROW('Bank Schedule'!$K$2:$K$825)), ROW(1:1))), "") -> 0 | M4: =IFERROR(INDEX('Bank Schedule'!M:M, SMALL(IF('Bank Schedule'!$K$2:$K$825="Vacant", ROW('Bank Schedule'!$K$2:$K$825)), ROW(1:1))), "") -> 0 | N4: {=IFERROR(INDEX('Bank Schedule'!N:N, SMALL(IF('Bank Schedule'!$K$2:$K$825="Vacant", ROW('Bank Schedule'!$K$2:$K$825)), ROW(1:1))), "")} -> 45636 | O4: =IFERROR(INDEX('Bank Schedule'!O:O, SMALL(IF('Bank Schedule'!$K$2:$K$825="Vacant", ROW('Bank Schedule'!$K$2:$K$825)), ROW(1:1))), "") -> 0 | P4: =IFERROR(INDEX('Bank Schedule'!P:P, SMALL(IF('Bank Schedule'!$K$2:$K$825="Vacant", ROW('Bank Schedule'!$K$2:$K$825)), ROW(1:1))), "") -> 0 | Q4: {=IFERROR(INDEX('Bank Schedule'!Q:Q, SMALL(IF('Bank Schedule'!$K$2:$K$825="Vacant", ROW('Bank Schedule'!$K$2:$K$825)), ROW(1:1))), "")} -> 0 | R4: {=IFERROR(INDEX('Bank Schedule'!R:R, SMALL(IF('Bank Schedule'!$K$2:$K$825="Vacant", ROW('Bank Schedule'!$K$2:$K$825)), ROW(1:1))), "")} -> 0 | S4: =IFERROR(INDEX('Bank Schedule'!S:S, SMALL(IF('Bank Schedule'!$K$2:$K$825="Vacant", ROW('Bank Schedule'!$K$2:$K$825)), ROW(1:1))), "") -> 0 | T4: {=IFERROR(INDEX('Bank Schedule'!T:T, SMALL(IF('Bank Schedule'!$K$2:$K$825="Vacant", ROW('Bank Schedule'!$K$2:$K$825)), ROW(1:1))), "")} -> 134300 | U4: {=IFERROR(INDEX('Bank Schedule'!U:U, SMALL(IF('Bank Schedule'!$K$2:$K$825="Vacant", ROW('Bank Schedule'!$K$2:$K$825)), ROW(1:1))), "")} -> 134300 | V4: {=IFERROR(INDEX('Bank Schedule'!V:V, SMALL(IF('Bank Schedule'!$K$2:$K$825="Vacant", ROW('Bank Schedule'!$K$2:$K$825)), ROW(1:1))), "")} -> 134300 | W4: {=IFERROR(INDEX('Bank Schedule'!W:W, SMALL(IF('Bank Schedule'!$K$2:$K$825="Vacant", ROW('Bank Schedule'!$K$2:$K$825)), ROW(1:1))), "")} -> 134300 | X4: {=IFERROR(INDEX('Bank Schedule'!X:X, SMALL(IF('Bank Schedule'!$K$2:$K$825="Vacant", ROW('Bank Schedule'!$K$2:$K$825)), ROW(1:1))), "")} -> 60.008937 | Y4: {=IFERROR(INDEX('Bank Schedule'!Y:Y, SMALL(IF('Bank Schedule'!$K$2:$K$825="Vacant", ROW('Bank Schedule'!$K$2:$K$825)), ROW(1:1))), "")} -> 0 | Z4: {=IFERROR(INDEX('Bank Schedule'!Z:Z, SMALL(IF('Bank Schedule'!$K$2:$K$825="Vacant", ROW('Bank Schedule'!$K$2:$K$825)), ROW(1:1))), "")} -> D | AA4: =IFERROR(INDEX('Bank Schedule'!AA:AA, SMALL(IF('Bank Schedule'!$K$2:$K$825="Vacant", ROW('Bank Schedule'!$K$2:$K$825)), ROW(1:1))), "") -> 0 | AB4: =IFERROR(INDEX('Bank Schedule'!AB:AB, SMALL(IF('Bank Schedule'!$K$2:$K$825="Vacant", ROW('Bank Schedule'!$K$2:$K$825)), ROW(1:1))), "") -> 0 | AC4: {=IFERROR(INDEX('Bank Schedule'!AC:AC, SMALL(IF('Bank Schedule'!$K$2:$K$825="Vacant", ROW('Bank Schedule'!$K$2:$K$825)), ROW(1:1))), "")} -> No | AD4: {=IFERROR(INDEX('Bank Schedule'!AD:AD, SMALL(IF('Bank Schedule'!$K$2:$K$825="Vacant", ROW('Bank Schedule'!$K$2:$K$825)), ROW(1:1))), "")} -> LEM marketing. | AE4: =IFERROR(INDEX('Bank Schedule'!AE:AE, SMALL(IF('Bank Schedule'!$K$2:$K$825="Vacant", ROW('Bank Schedule'!$K$2:$K$825)), ROW(1:1))), "") -> 0 | AF4: {=IFERROR(INDEX('Bank Schedule'!AF:AF, SMALL(IF('Bank Schedule'!$K$2:$K$825="Vacant", ROW('Bank Schedule'!$K$2:$K$825)), ROW(1:1))), "")} -> 2 | AG4: {=IFERROR(INDEX('Bank Schedule'!AG:AG, SMALL(IF('Bank Schedule'!$K$2:$K$825="Vacant", ROW('Bank Schedule'!$K$2:$K$825)), ROW(1:1))), "")} -> 2 | AH4: =IFERROR(INDEX('Bank Schedule'!AH:AH, SMALL(IF('Bank Schedule'!$K$2:$K$825="Vacant", ROW('Bank Schedule'!$K$2:$K$825)), ROW(1:1))), "") -> 0
A5: =IFERROR(INDEX('Bank Schedule'!A:A, SMALL(IF('Bank Schedule'!$K$2:$K$825="Vacant", ROW('Bank Schedule'!$K$2:$K$825)), ROW(2:2))), "") | B5: {=IFERROR(INDEX('Bank Schedule'!B:B, SMALL(IF('Bank Schedule'!$K$2:$K$825="Vacant", ROW('Bank Schedule'!$K$2:$K$825)), ROW(2:2))), "")} -> SH | C5: {=IFERROR(INDEX('Bank Schedule'!C:C, SMALL(IF('Bank Schedule'!$K$2:$K$825="Vacant", ROW('Bank Schedule'!$K$2:$K$825)), ROW(2:2))), "")} -> MEL | D5: {=IFERROR(INDEX('Bank Schedule'!D:D, SMALL(IF('Bank Schedule'!$K$2:$K$825="Vacant", ROW('Bank Schedule'!$K$2:$K$825)), ROW(2:2))), "")} -> 550910 | E5: {=IFERROR(INDEX('Bank Schedule'!E:E, SMALL(IF('Bank Schedule'!$K$2:$K$825="Vacant", ROW('Bank Schedule'!$K$2:$K$825)), ROW(2:2))), "")} -> 22 and 23-25 Eastcastle Street | F5: {=IFERROR(INDEX('Bank Schedule'!F:F, SMALL(IF('Bank Schedule'!$K$2:$K$825="Vacant", ROW('Bank Schedule'!$K$2:$K$825)), ROW(2:2))), "")} -> Third Floor (22) | G5: {=IFERROR(INDEX('Bank Schedule'!G:G, SMALL(IF('Bank Schedule'!$K$2:$K$825="Vacant", ROW('Bank Schedule'!$K$2:$K$825)), ROW(2:2))), "")} -> Office | H5: {=IFERROR(INDEX('Bank Schedule'!H:H, SMALL(IF('Bank Schedule'!$K$2:$K$825="Vacant", ROW('Bank Schedule'!$K$2:$K$825)), ROW(2:2))), "")} -> 400 | I5: {=IFERROR(INDEX('Bank Schedule'!I:I, SMALL(IF('Bank Schedule'!$K$2:$K$825="Vacant", ROW('Bank Schedule'!$K$2:$K$825)), ROW(2:2))), "")} -> 400 | J5: {=IFERROR(INDEX('Bank Schedule'!J:J, SMALL(IF('Bank Schedule'!$K$2:$K$825="Vacant", ROW('Bank Schedule'!$K$2:$K$825)), ROW(2:2))), "")} -> 500 | K5: {=IFERROR(INDEX('Bank Schedule'!K:K, SMALL(IF('Bank Schedule'!$K$2:$K$825="Vacant", ROW('Bank Schedule'!$K$2:$K$825)), ROW(2:2))), "")} -> Vacant | L5: =IFERROR(INDEX('Bank Schedule'!L:L, SMALL(IF('Bank Schedule'!$K$2:$K$825="Vacant", ROW('Bank Schedule'!$K$2:$K$825)), ROW(2:2))), "") | M5: =IFERROR(INDEX('Bank Schedule'!M:M, SMALL(IF('Bank Schedule'!$K$2:$K$825="Vacant", ROW('Bank Schedule'!$K$2:$K$825)), ROW(2:2))), "") | N5: {=IFERROR(INDEX('Bank Schedule'!N:N, SMALL(IF('Bank Schedule'!$K$2:$K$825="Vacant", ROW('Bank Schedule'!$K$2:$K$825)), ROW(2:2))), "")} -> 45771 | O5: =IFERROR(INDEX('Bank Schedule'!O:O, SMALL(IF('Bank Schedule'!$K$2:$K$825="Vacant", ROW('Bank Schedule'!$K$2:$K$825)), ROW(2:2))), "") | P5: =IFERROR(INDEX('Bank Schedule'!P:P, SMALL(IF('Bank Schedule'!$K$2:$K$825="Vacant", ROW('Bank Schedule'!$K$2:$K$825)), ROW(2:2))), "") | Q5: {=IFERROR(INDEX('Bank Schedule'!Q:Q, SMALL(IF('Bank Schedule'!$K$2:$K$825="Vacant", ROW('Bank Schedule'!$K$2:$K$825)), ROW(2:2))), "")} -> 0 | R5: {=IFERROR(INDEX('Bank Schedule'!R:R, SMALL(IF('Bank Schedule'!$K$2:$K$825="Vacant", ROW('Bank Schedule'!$K$2:$K$825)), ROW(2:2))), "")} -> 0 | S5: =IFERROR(INDEX('Bank Schedule'!S:S, SMALL(IF('Bank Schedule'!$K$2:$K$825="Vacant", ROW('Bank Schedule'!$K$2:$K$825)), ROW(2:2))), "") | T5: {=IFERROR(INDEX('Bank Schedule'!T:T, SMALL(IF('Bank Schedule'!$K$2:$K$825="Vacant", ROW('Bank Schedule'!$K$2:$K$825)), ROW(2:2))), "")} -> 20600 | U5: {=IFERROR(INDEX('Bank Schedule'!U:U, SMALL(IF('Bank Schedule'!$K$2:$K$825="Vacant", ROW('Bank Schedule'!$K$2:$K$825)), ROW(2:2))), "")} -> 20600 | V5: {=IFERROR(INDEX('Bank Schedule'!V:V, SMALL(IF('Bank Schedule'!$K$2:$K$825="Vacant", ROW('Bank Schedule'!$K$2:$K$825)), ROW(2:2))), "")} -> 23000 | W5: {=IFERROR(INDEX('Bank Schedule'!W:W, SMALL(IF('Bank Schedule'!$K$2:$K$825="Vacant", ROW('Bank Schedule'!$K$2:$K$825)), ROW(2:2))), "")} -> 23000 | X5: {=IFERROR(INDEX('Bank Schedule'!X:X, SMALL(IF('Bank Schedule'!$K$2:$K$825="Vacant", ROW('Bank Schedule'!$K$2:$K$825)), ROW(2:2))), "")} -> 57.5 | Y5: {=IFERROR(INDEX('Bank Schedule'!Y:Y, SMALL(IF('Bank Schedule'!$K$2:$K$825="Vacant", ROW('Bank Schedule'!$K$2:$K$825)), ROW(2:2))), "")} -> 0.11650485 | Z5: {=IFERROR(INDEX('Bank Schedule'!Z:Z, SMALL(IF('Bank Schedule'!$K$2:$K$825="Vacant", ROW('Bank Schedule'!$K$2:$K$825)), ROW(2:2))), "")} -> D | AA5: =IFERROR(INDEX('Bank Schedule'!AA:AA, SMALL(IF('Bank Schedule'!$K$2:$K$825="Vacant", ROW('Bank Schedule'!$K$2:$K$825)), ROW(2:2))), "") | AB5: =IFERROR(INDEX('Bank Schedule'!AB:AB, SMALL(IF('Bank Schedule'!$K$2:$K$825="Vacant", ROW('Bank Schedule'!$K$2:$K$825)), ROW(2:2))), "") | AC5: {=IFERROR(INDEX('Bank Schedule'!AC:AC, SMALL(IF('Bank Schedule'!$K$2:$K$825="Vacant", ROW('Bank Schedule'!$K$2:$K$825)), ROW(2:2))), "")} -> No | AD5: {=IFERROR(INDEX('Bank Schedule'!AD:AD, SMALL(IF('Bank Schedule'!$K$2:$K$825="Vacant", ROW('Bank Schedule'!$K$2:$K$825)), ROW(2:2))), "")} -> LEM marketing. | AE5: =IFERROR(INDEX('Bank Schedule'!AE:AE, SMALL(IF('Bank Schedule'!$K$2:$K$825="Vacant", ROW('Bank Schedule'!$K$2:$K$825)), ROW(2:2))), "") | AF5: {=IFERROR(INDEX('Bank Schedule'!AF:AF, SMALL(IF('Bank Schedule'!$K$2:$K$825="Vacant", ROW('Bank Schedule'!$K$2:$K$825)), ROW(2:2))), "")} -> 1 | AG5: {=IFERROR(INDEX('Bank Schedule'!AG:AG, SMALL(IF('Bank Schedule'!$K$2:$K$825="Vacant", ROW('Bank Schedule'!$K$2:$K$825)), ROW(2:2))), "")} -> 1 | AH5: =IFERROR(INDEX('Bank Schedule'!AH:AH, SMALL(IF('Bank Schedule'!$K$2:$K$825="Vacant", ROW('Bank Schedule'!$K$2:$K$825)), ROW(2:2))), "")
A6: =IFERROR(INDEX('Bank Schedule'!A:A, SMALL(IF('Bank Schedule'!$K$2:$K$825="Vacant", ROW('Bank Schedule'!$K$2:$K$825)), ROW(3:3))), "") | B6: {=IFERROR(INDEX('Bank Schedule'!B:B, SMALL(IF('Bank Schedule'!$K$2:$K$825="Vacant", ROW('Bank Schedule'!$K$2:$K$825)), ROW(3:3))), "")} -> SH | C6: {=IFERROR(INDEX('Bank Schedule'!C:C, SMALL(IF('Bank Schedule'!$K$2:$K$825="Vacant", ROW('Bank Schedule'!$K$2:$K$825)), ROW(3:3))), "")} -> MEL | D6: {=IFERROR(INDEX('Bank Schedule'!D:D, SMALL(IF('Bank Schedule'!$K$2:$K$825="Vacant", ROW('Bank Schedule'!$K$2:$K$825)), ROW(3:3))), "")} -> 550910 | E6: {=IFERROR(INDEX('Bank Schedule'!E:E, SMALL(IF('Bank Schedule'!$K$2:$K$825="Vacant", ROW('Bank Schedule'!$K$2:$K$825)), ROW(3:3))), "")} -> 22 and 23-25 Eastcastle Street | F6: {=IFERROR(INDEX('Bank Schedule'!F:F, SMALL(IF('Bank Schedule'!$K$2:$K$825="Vacant", ROW('Bank Schedule'!$K$2:$K$825)), ROW(3:3))), "")} -> Third Floor (23-25) | G6: {=IFERROR(INDEX('Bank Schedule'!G:G, SMALL(IF('Bank Schedule'!$K$2:$K$825="Vacant", ROW('Bank Schedule'!$K$2:$K$825)), ROW(3:3))), "")} -> Office | H6: {=IFERROR(INDEX('Bank Schedule'!H:H, SMALL(IF('Bank Schedule'!$K$2:$K$825="Vacant", ROW('Bank Schedule'!$K$2:$K$825)), ROW(3:3))), "")} -> 1938 | I6: {=IFERROR(INDEX('Bank Schedule'!I:I, SMALL(IF('Bank Schedule'!$K$2:$K$825="Vacant", ROW('Bank Schedule'!$K$2:$K$825)), ROW(3:3))), "")} -> 1938 | J6: {=IFERROR(INDEX('Bank Schedule'!J:J, SMALL(IF('Bank Schedule'!$K$2:$K$825="Vacant", ROW('Bank Schedule'!$K$2:$K$825)), ROW(3:3))), "")} -> 2000 | K6: {=IFERROR(INDEX('Bank Schedule'!K:K, SMALL(IF('Bank Schedule'!$K$2:$K$825="Vacant", ROW('Bank Schedule'!$K$2:$K$825)), ROW(3:3))), "")} -> Vacant | L6: =IFERROR(INDEX('Bank Schedule'!L:L, SMALL(IF('Bank Schedule'!$K$2:$K$825="Vacant", ROW('Bank Schedule'!$K$2:$K$825)), ROW(3:3))), "") | M6: =IFERROR(INDEX('Bank Schedule'!M:M, SMALL(IF('Bank Schedule'!$K$2:$K$825="Vacant", ROW('Bank Schedule'!$K$2:$K$825)), ROW(3:3))), "") | N6: {=IFERROR(INDEX('Bank Schedule'!N:N, SMALL(IF('Bank Schedule'!$K$2:$K$825="Vacant", ROW('Bank Schedule'!$K$2:$K$825)), ROW(3:3))), "")} -> 45217 | O6: =IFERROR(INDEX('Bank Schedule'!O:O, SMALL(IF('Bank Schedule'!$K$2:$K$825="Vacant", ROW('Bank Schedule'!$K$2:$K$825)), ROW(3:3))), "") | P6: =IFERROR(INDEX('Bank Schedule'!P:P, SMALL(IF('Bank Schedule'!$K$2:$K$825="Vacant", ROW('Bank Schedule'!$K$2:$K$825)), ROW(3:3))), "") | Q6: {=IFERROR(INDEX('Bank Schedule'!Q:Q, SMALL(IF('Bank Schedule'!$K$2:$K$825="Vacant", ROW('Bank Schedule'!$K$2:$K$825)), ROW(3:3))), "")} -> 0 | R6: {=IFERROR(INDEX('Bank Schedule'!R:R, SMALL(IF('Bank Schedule'!$K$2:$K$825="Vacant", ROW('Bank Schedule'!$K$2:$K$825)), ROW(3:3))), "")} -> 0 | S6: =IFERROR(INDEX('Bank Schedule'!S:S, SMALL(IF('Bank Schedule'!$K$2:$K$825="Vacant", ROW('Bank Schedule'!$K$2:$K$825)), ROW(3:3))), "") | T6: {=IFERROR(INDEX('Bank Schedule'!T:T, SMALL(IF('Bank Schedule'!$K$2:$K$825="Vacant", ROW('Bank Schedule'!$K$2:$K$825)), ROW(3:3))), "")} -> 109000 | U6: {=IFERROR(INDEX('Bank Schedule'!U:U, SMALL(IF('Bank Schedule'!$K$2:$K$825="Vacant", ROW('Bank Schedule'!$K$2:$K$825)), ROW(3:3))), "")} -> 109000 | V6: {=IFERROR(INDEX('Bank Schedule'!V:V, SMALL(IF('Bank Schedule'!$K$2:$K$825="Vacant", ROW('Bank Schedule'!$K$2:$K$825)), ROW(3:3))), "")} -> 111400 | W6: {=IFERROR(INDEX('Bank Schedule'!W:W, SMALL(IF('Bank Schedule'!$K$2:$K$825="Vacant", ROW('Bank Schedule'!$K$2:$K$825)), ROW(3:3))), "")} -> 111400 | X6: {=IFERROR(INDEX('Bank Schedule'!X:X, SMALL(IF('Bank Schedule'!$K$2:$K$825="Vacant", ROW('Bank Schedule'!$K$2:$K$825)), ROW(3:3))), "")} -> 57.48194 | Y6: {=IFERROR(INDEX('Bank Schedule'!Y:Y, SMALL(IF('Bank Schedule'!$K$2:$K$825="Vacant", ROW('Bank Schedule'!$K$2:$K$825)), ROW(3:3))), "")} -> 0.022018349 | Z6: {=IFERROR(INDEX('Bank Schedule'!Z:Z, SMALL(IF('Bank Schedule'!$K$2:$K$825="Vacant", ROW('Bank Schedule'!$K$2:$K$825)), ROW(3:3))), "")} -> D | AA6: =IFERROR(INDEX('Bank Schedule'!AA:AA, SMALL(IF('Bank Schedule'!$K$2:$K$825="Vacant", ROW('Bank Schedule'!$K$2:$K$825)), ROW(3:3))), "") | AB6: =IFERROR(INDEX('Bank Schedule'!AB:AB, SMALL(IF('Bank Schedule'!$K$2:$K$825="Vacant", ROW('Bank Schedule'!$K$2:$K$825)), ROW(3:3))), "") | AC6: {=IFERROR(INDEX('Bank Schedule'!AC:AC, SMALL(IF('Bank Schedule'!$K$2:$K$825="Vacant", ROW('Bank Schedule'!$K$2:$K$825)), ROW(3:3))), "")} -> No | AD6: {=IFERROR(INDEX('Bank Schedule'!AD:AD, SMALL(IF('Bank Schedule'!$K$2:$K$825="Vacant", ROW('Bank Schedule'!$K$2:$K$825)), ROW(3:3))), "")} -> LEM marketing. | AE6: {=IFERROR(INDEX('Bank Schedule'!AE:AE, SMALL(IF('Bank Schedule'!$K$2:$K$825="Vacant", ROW('Bank Schedule'!$K$2:$K$825)), ROW(3:3))), "")} -> 65 | AF6: {=IFERROR(INDEX('Bank Schedule'!AF:AF, SMALL(IF('Bank Schedule'!$K$2:$K$825="Vacant", ROW('Bank Schedule'!$K$2:$K$825)), ROW(3:3))), "")} -> 2 | AG6: {=IFERROR(INDEX('Bank Schedule'!AG:AG, SMALL(IF('Bank Schedule'!$K$2:$K$825="Vacant", ROW('Bank Schedule'!$K$2:$K$825)), ROW(3:3))), "")} -> 4 | AH6: =IFERROR(INDEX('Bank Schedule'!AH:AH, SMALL(IF('Bank Schedule'!$K$2:$K$825="Vacant", ROW('Bank Schedule'!$K$2:$K$825)), ROW(3:3))), "")
A7: =IFERROR(INDEX('Bank Schedule'!A:A, SMALL(IF('Bank Schedule'!$K$2:$K$825="Vacant", ROW('Bank Schedule'!$K$2:$K$825)), ROW(4:4))), "") | B7: {=IFERROR(INDEX('Bank Schedule'!B:B, SMALL(IF('Bank Schedule'!$K$2:$K$825="Vacant", ROW('Bank Schedule'!$K$2:$K$825)), ROW(4:4))), "")} -> SH | C7: {=IFERROR(INDEX('Bank Schedule'!C:C, SMALL(IF('Bank Schedule'!$K$2:$K$825="Vacant", ROW('Bank Schedule'!$K$2:$K$825)), ROW(4:4))), "")} -> MEL | D7: {=IFERROR(INDEX('Bank Schedule'!D:D, SMALL(IF('Bank Schedule'!$K$2:$K$825="Vacant", ROW('Bank Schedule'!$K$2:$K$825)), ROW(4:4))), "")} -> 550910 | E7: {=IFERROR(INDEX('Bank Schedule'!E:E, SMALL(IF('Bank Schedule'!$K$2:$K$825="Vacant", ROW('Bank Schedule'!$K$2:$K$825)), ROW(4:4))), "")} -> 22 and 23-25 Eastcastle Street | F7: {=IFERROR(INDEX('Bank Schedule'!F:F, SMALL(IF('Bank Schedule'!$K$2:$K$825="Vacant", ROW('Bank Schedule'!$K$2:$K$825)), ROW(4:4))), "")} -> Sixth Floor (23-25) | G7: {=IFERROR(INDEX('Bank Schedule'!G:G, SMALL(IF('Bank Schedule'!$K$2:$K$825="Vacant", ROW('Bank Schedule'!$K$2:$K$825)), ROW(4:4))), "")} -> Office | H7: {=IFERROR(INDEX('Bank Schedule'!H:H, SMALL(IF('Bank Schedule'!$K$2:$K$825="Vacant", ROW('Bank Schedule'!$K$2:$K$825)), ROW(4:4))), "")} -> 744 | I7: {=IFERROR(INDEX('Bank Schedule'!I:I, SMALL(IF('Bank Schedule'!$K$2:$K$825="Vacant", ROW('Bank Schedule'!$K$2:$K$825)), ROW(4:4))), "")} -> 744 | J7: {=IFERROR(INDEX('Bank Schedule'!J:J, SMALL(IF('Bank Schedule'!$K$2:$K$825="Vacant", ROW('Bank Schedule'!$K$2:$K$825)), ROW(4:4))), "")} -> 750 | K7: {=IFERROR(INDEX('Bank Schedule'!K:K, SMALL(IF('Bank Schedule'!$K$2:$K$825="Vacant", ROW('Bank Schedule'!$K$2:$K$825)), ROW(4:4))), "")} -> Vacant | L7: =IFERROR(INDEX('Bank Schedule'!L:L, SMALL(IF('Bank Schedule'!$K$2:$K$825="Vacant", ROW('Bank Schedule'!$K$2:$K$825)), ROW(4:4))), "") | M7: =IFERROR(INDEX('Bank Schedule'!M:M, SMALL(IF('Bank Schedule'!$K$2:$K$825="Vacant", ROW('Bank Schedule'!$K$2:$K$825)), ROW(4:4))), "") | N7: {=IFERROR(INDEX('Bank Schedule'!N:N, SMALL(IF('Bank Schedule'!$K$2:$K$825="Vacant", ROW('Bank Schedule'!$K$2:$K$825)), ROW(4:4))), "")} -> 45182 | O7: =IFERROR(INDEX('Bank Schedule'!O:O, SMALL(IF('Bank Schedule'!$K$2:$K$825="Vacant", ROW('Bank Schedule'!$K$2:$K$825)), ROW(4:4))), "") | P7: =IFERROR(INDEX('Bank Schedule'!P:P, SMALL(IF('Bank Schedule'!$K$2:$K$825="Vacant", ROW('Bank Schedule'!$K$2:$K$825)), ROW(4:4))), "") | Q7: {=IFERROR(INDEX('Bank Schedule'!Q:Q, SMALL(IF('Bank Schedule'!$K$2:$K$825="Vacant", ROW('Bank Schedule'!$K$2:$K$825)), ROW(4:4))), "")} -> 0 | R7: {=IFERROR(INDEX('Bank Schedule'!R:R, SMALL(IF('Bank Schedule'!$K$2:$K$825="Vacant", ROW('Bank Schedule'!$K$2:$K$825)), ROW(4:4))), "")} -> 0 | S7: =IFERROR(INDEX('Bank Schedule'!S:S, SMALL(IF('Bank Schedule'!$K$2:$K$825="Vacant", ROW('Bank Schedule'!$K$2:$K$825)), ROW(4:4))), "") | T7: {=IFERROR(INDEX('Bank Schedule'!T:T, SMALL(IF('Bank Schedule'!$K$2:$K$825="Vacant", ROW('Bank Schedule'!$K$2:$K$825)), ROW(4:4))), "")} -> 34400 | U7: {=IFERROR(INDEX('Bank Schedule'!U:U, SMALL(IF('Bank Schedule'!$K$2:$K$825="Vacant", ROW('Bank Schedule'!$K$2:$K$825)), ROW(4:4))), "")} -> 34400 | V7: {=IFERROR(INDEX('Bank Schedule'!V:V, SMALL(IF('Bank Schedule'!$K$2:$K$825="Vacant", ROW('Bank Schedule'!$K$2:$K$825)), ROW(4:4))), "")} -> 47000 | W7: {=IFERROR(INDEX('Bank Schedule'!W:W, SMALL(IF('Bank Schedule'!$K$2:$K$825="Vacant", ROW('Bank Schedule'!$K$2:$K$825)), ROW(4:4))), "")} -> 47000 | X7: {=IFERROR(INDEX('Bank Schedule'!X:X, SMALL(IF('Bank Schedule'!$K$2:$K$825="Vacant", ROW('Bank Schedule'!$K$2:$K$825)), ROW(4:4))), "")} -> 63.172043 | Y7: {=IFERROR(INDEX('Bank Schedule'!Y:Y, SMALL(IF('Bank Schedule'!$K$2:$K$825="Vacant", ROW('Bank Schedule'!$K$2:$K$825)), ROW(4:4))), "")} -> 0.36627907 | Z7: {=IFERROR(INDEX('Bank Schedule'!Z:Z, SMALL(IF('Bank Schedule'!$K$2:$K$825="Vacant", ROW('Bank Schedule'!$K$2:$K$825)), ROW(4:4))), "")} -> D | AA7: =IFERROR(INDEX('Bank Schedule'!AA:AA, SMALL(IF('Bank Schedule'!$K$2:$K$825="Vacant", ROW('Bank Schedule'!$K$2:$K$825)), ROW(4:4))), "") | AB7: =IFERROR(INDEX('Bank Schedule'!AB:AB, SMALL(IF('Bank Schedule'!$K$2:$K$825="Vacant", ROW('Bank Schedule'!$K$2:$K$825)), ROW(4:4))), "") | AC7: {=IFERROR(INDEX('Bank Schedule'!AC:AC, SMALL(IF('Bank Schedule'!$K$2:$K$825="Vacant", ROW('Bank Schedule'!$K$2:$K$825)), ROW(4:4))), "")} -> No | AD7: {=IFERROR(INDEX('Bank Schedule'!AD:AD, SMALL(IF('Bank Schedule'!$K$2:$K$825="Vacant", ROW('Bank Schedule'!$K$2:$K$825)), ROW(4:4))), "")} -> LEM marketing. | AE7: {=IFERROR(INDEX('Bank Schedule'!AE:AE, SMALL(IF('Bank Schedule'!$K$2:$K$825="Vacant", ROW('Bank Schedule'!$K$2:$K$825)), ROW(4:4))), "")} -> 63.5 | AF7: {=IFERROR(INDEX('Bank Schedule'!AF:AF, SMALL(IF('Bank Schedule'!$K$2:$K$825="Vacant", ROW('Bank Schedule'!$K$2:$K$825)), ROW(4:4))), "")} -> 2 | AG7: {=IFERROR(INDEX('Bank Schedule'!AG:AG, SMALL(IF('Bank Schedule'!$K$2:$K$825="Vacant", ROW('Bank Schedule'!$K$2:$K$825)), ROW(4:4))), "")} -> 4 | AH7: {=IFERROR(INDEX('Bank Schedule'!AH:AH, SMALL(IF('Bank Schedule'!$K$2:$K$825="Vacant", ROW('Bank Schedule'!$K$2:$K$825)), ROW(4:4))), "")} -> LEM
A8: =IFERROR(INDEX('Bank Schedule'!A:A, SMALL(IF('Bank Schedule'!$K$2:$K$825="Vacant", ROW('Bank Schedule'!$K$2:$K$825)), ROW(5:5))), "") | B8: {=IFERROR(INDEX('Bank Schedule'!B:B, SMALL(IF('Bank Schedule'!$K$2:$K$825="Vacant", ROW('Bank Schedule'!$K$2:$K$825)), ROW(5:5))), "")} -> SH | C8: {=IFERROR(INDEX('Bank Schedule'!C:C, SMALL(IF('Bank Schedule'!$K$2:$K$825="Vacant", ROW('Bank Schedule'!$K$2:$K$825)), ROW(5:5))), "")} -> MEL | D8: {=IFERROR(INDEX('Bank Schedule'!D:D, SMALL(IF('Bank Schedule'!$K$2:$K$825="Vacant", ROW('Bank Schedule'!$K$2:$K$825)), ROW(5:5))), "")} -> 550920 | E8: {=IFERROR(INDEX('Bank Schedule'!E:E, SMALL(IF('Bank Schedule'!$K$2:$K$825="Vacant", ROW('Bank Schedule'!$K$2:$K$825)), ROW(5:5))), "")} -> 26 Eastcastle Street | F8: {=IFERROR(INDEX('Bank Schedule'!F:F, SMALL(IF('Bank Schedule'!$K$2:$K$825="Vacant", ROW('Bank Schedule'!$K$2:$K$825)), ROW(5:5))), "")} -> Second Floor | G8: {=IFERROR(INDEX('Bank Schedule'!G:G, SMALL(IF('Bank Schedule'!$K$2:$K$825="Vacant", ROW('Bank Schedule'!$K$2:$K$825)), ROW(5:5))), "")} -> Offices | H8: {=IFERROR(INDEX('Bank Schedule'!H:H, SMALL(IF('Bank Schedule'!$K$2:$K$825="Vacant", ROW('Bank Schedule'!$K$2:$K$825)), ROW(5:5))), "")} -> 1110 | I8: {=IFERROR(INDEX('Bank Schedule'!I:I, SMALL(IF('Bank Schedule'!$K$2:$K$825="Vacant", ROW('Bank Schedule'!$K$2:$K$825)), ROW(5:5))), "")} -> 1110 | J8: {=IFERROR(INDEX('Bank Schedule'!J:J, SMALL(IF('Bank Schedule'!$K$2:$K$825="Vacant", ROW('Bank Schedule'!$K$2:$K$825)), ROW(5:5))), "")} -> 1000 | K8: {=IFERROR(INDEX('Bank Schedule'!K:K, SMALL(IF('Bank Schedule'!$K$2:$K$825="Vacant", ROW('Bank Schedule'!$K$2:$K$825)), ROW(5:5))), "")} -> Vacant | L8: =IFERROR(INDEX('Bank Schedule'!L:L, SMALL(IF('Bank Schedule'!$K$2:$K$825="Vacant", ROW('Bank Schedule'!$K$2:$K$825)), ROW(5:5))), "") | M8: =IFERROR(INDEX('Bank Schedule'!M:M, SMALL(IF('Bank Schedule'!$K$2:$K$825="Vacant", ROW('Bank Schedule'!$K$2:$K$825)), ROW(5:5))), "") | N8: {=IFERROR(INDEX('Bank Schedule'!N:N, SMALL(IF('Bank Schedule'!$K$2:$K$825="Vacant", ROW('Bank Schedule'!$K$2:$K$825)), ROW(5:5))), "")} -> 43273 | O8: =IFERROR(INDEX('Bank Schedule'!O:O, SMALL(IF('Bank Schedule'!$K$2:$K$825="Vacant", ROW('Bank Schedule'!$K$2:$K$825)), ROW(5:5))), "") | P8: =IFERROR(INDEX('Bank Schedule'!P:P, SMALL(IF('Bank Schedule'!$K$2:$K$825="Vacant", ROW('Bank Schedule'!$K$2:$K$825)), ROW(5:5))), "") | Q8: {=IFERROR(INDEX('Bank Schedule'!Q:Q, SMALL(IF('Bank Schedule'!$K$2:$K$825="Vacant", ROW('Bank Schedule'!$K$2:$K$825)), ROW(5:5))), "")} -> 0 | R8: {=IFERROR(INDEX('Bank Schedule'!R:R, SMALL(IF('Bank Schedule'!$K$2:$K$825="Vacant", ROW('Bank Schedule'!$K$2:$K$825)), ROW(5:5))), "")} -> 0 | S8: =IFERROR(INDEX('Bank Schedule'!S:S, SMALL(IF('Bank Schedule'!$K$2:$K$825="Vacant", ROW('Bank Schedule'!$K$2:$K$825)), ROW(5:5))), "") | T8: {=IFERROR(INDEX('Bank Schedule'!T:T, SMALL(IF('Bank Schedule'!$K$2:$K$825="Vacant", ROW('Bank Schedule'!$K$2:$K$825)), ROW(5:5))), "")} -> 61100 | U8: {=IFERROR(INDEX('Bank Schedule'!U:U, SMALL(IF('Bank Schedule'!$K$2:$K$825="Vacant", ROW('Bank Schedule'!$K$2:$K$825)), ROW(5:5))), "")} -> 61100 | V8: {=IFERROR(INDEX('Bank Schedule'!V:V, SMALL(IF('Bank Schedule'!$K$2:$K$825="Vacant", ROW('Bank Schedule'!$K$2:$K$825)), ROW(5:5))), "")} -> 69400 | W8: {=IFERROR(INDEX('Bank Schedule'!W:W, SMALL(IF('Bank Schedule'!$K$2:$K$825="Vacant", ROW('Bank Schedule'!$K$2:$K$825)), ROW(5:5))), "")} -> 69400 | X8: {=IFERROR(INDEX('Bank Schedule'!X:X, SMALL(IF('Bank Schedule'!$K$2:$K$825="Vacant", ROW('Bank Schedule'!$K$2:$K$825)), ROW(5:5))), "")} -> 62.522523 | Y8: {=IFERROR(INDEX('Bank Schedule'!Y:Y, SMALL(IF('Bank Schedule'!$K$2:$K$825="Vacant", ROW('Bank Schedule'!$K$2:$K$825)), ROW(5:5))), "")} -> 0.13584288 | Z8: {=IFERROR(INDEX('Bank Schedule'!Z:Z, SMALL(IF('Bank Schedule'!$K$2:$K$825="Vacant", ROW('Bank Schedule'!$K$2:$K$825)), ROW(5:5))), "")} -> C | AA8: =IFERROR(INDEX('Bank Schedule'!AA:AA, SMALL(IF('Bank Schedule'!$K$2:$K$825="Vacant", ROW('Bank Schedule'!$K$2:$K$825)), ROW(5:5))), "") | AB8: =IFERROR(INDEX('Bank Schedule'!AB:AB, SMALL(IF('Bank Schedule'!$K$2:$K$825="Vacant", ROW('Bank Schedule'!$K$2:$K$825)), ROW(5:5))), "") | AC8: {=IFERROR(INDEX('Bank Schedule'!AC:AC, SMALL(IF('Bank Schedule'!$K$2:$K$825="Vacant", ROW('Bank Schedule'!$K$2:$K$825)), ROW(5:5))), "")} -> No | AD8: {=IFERROR(INDEX('Bank Schedule'!AD:AD, SMALL(IF('Bank Schedule'!$K$2:$K$825="Vacant", ROW('Bank Schedule'!$K$2:$K$825)), ROW(5:5))), "")} -> LEM marketing. | AE8: {=IFERROR(INDEX('Bank Schedule'!AE:AE, SMALL(IF('Bank Schedule'!$K$2:$K$825="Vacant", ROW('Bank Schedule'!$K$2:$K$825)), ROW(5:5))), "")} -> 63.5 | AF8: =IFERROR(INDEX('Bank Schedule'!AF:AF, SMALL(IF('Bank Schedule'!$K$2:$K$825="Vacant", ROW('Bank Schedule'!$K$2:$K$825)), ROW(5:5))), "") | AG8: {=IFERROR(INDEX('Bank Schedule'!AG:AG, SMALL(IF('Bank Schedule'!$K$2:$K$825="Vacant", ROW('Bank Schedule'!$K$2:$K$825)), ROW(5:5))), "")} -> 1 | AH8: =IFERROR(INDEX('Bank Schedule'!AH:AH, SMALL(IF('Bank Schedule'!$K$2:$K$825="Vacant", ROW('Bank Schedule'!$K$2:$K$825)), ROW(5:5))), "")
A9: =IFERROR(INDEX('Bank Schedule'!A:A, SMALL(IF('Bank Schedule'!$K$2:$K$825="Vacant", ROW('Bank Schedule'!$K$2:$K$825)), ROW(6:6))), "") | B9: {=IFERROR(INDEX('Bank Schedule'!B:B, SMALL(IF('Bank Schedule'!$K$2:$K$825="Vacant", ROW('Bank Schedule'!$K$2:$K$825)), ROW(6:6))), "")} -> SH | C9: {=IFERROR(INDEX('Bank Schedule'!C:C, SMALL(IF('Bank Schedule'!$K$2:$K$825="Vacant", ROW('Bank Schedule'!$K$2:$K$825)), ROW(6:6))), "")} -> MEL | D9: {=IFERROR(INDEX('Bank Schedule'!D:D, SMALL(IF('Bank Schedule'!$K$2:$K$825="Vacant", ROW('Bank Schedule'!$K$2:$K$825)), ROW(6:6))), "")} -> 550070 | E9: {=IFERROR(INDEX('Bank Schedule'!E:E, SMALL(IF('Bank Schedule'!$K$2:$K$825="Vacant", ROW('Bank Schedule'!$K$2:$K$825)), ROW(6:6))), "")} -> Windsor House, 40-41 Great Castle Street | F9: {=IFERROR(INDEX('Bank Schedule'!F:F, SMALL(IF('Bank Schedule'!$K$2:$K$825="Vacant", ROW('Bank Schedule'!$K$2:$K$825)), ROW(6:6))), "")} -> Basement & Ground Floor | G9: {=IFERROR(INDEX('Bank Schedule'!G:G, SMALL(IF('Bank Schedule'!$K$2:$K$825="Vacant", ROW('Bank Schedule'!$K$2:$K$825)), ROW(6:6))), "")} -> Retail/Café | H9: {=IFERROR(INDEX('Bank Schedule'!H:H, SMALL(IF('Bank Schedule'!$K$2:$K$825="Vacant", ROW('Bank Schedule'!$K$2:$K$825)), ROW(6:6))), "")} -> 2235 | I9: {=IFERROR(INDEX('Bank Schedule'!I:I, SMALL(IF('Bank Schedule'!$K$2:$K$825="Vacant", ROW('Bank Schedule'!$K$2:$K$825)), ROW(6:6))), "")} -> 2235 | J9: {=IFERROR(INDEX('Bank Schedule'!J:J, SMALL(IF('Bank Schedule'!$K$2:$K$825="Vacant", ROW('Bank Schedule'!$K$2:$K$825)), ROW(6:6))), "")} -> 2000 | K9: {=IFERROR(INDEX('Bank Schedule'!K:K, SMALL(IF('Bank Schedule'!$K$2:$K$825="Vacant", ROW('Bank Schedule'!$K$2:$K$825)), ROW(6:6))), "")} -> Vacant | L9: =IFERROR(INDEX('Bank Schedule'!L:L, SMALL(IF('Bank Schedule'!$K$2:$K$825="Vacant", ROW('Bank Schedule'!$K$2:$K$825)), ROW(6:6))), "") | M9: =IFERROR(INDEX('Bank Schedule'!M:M, SMALL(IF('Bank Schedule'!$K$2:$K$825="Vacant", ROW('Bank Schedule'!$K$2:$K$825)), ROW(6:6))), "") | N9: {=IFERROR(INDEX('Bank Schedule'!N:N, SMALL(IF('Bank Schedule'!$K$2:$K$825="Vacant", ROW('Bank Schedule'!$K$2:$K$825)), ROW(6:6))), "")} -> 45754 | O9: =IFERROR(INDEX('Bank Schedule'!O:O, SMALL(IF('Bank Schedule'!$K$2:$K$825="Vacant", ROW('Bank Schedule'!$K$2:$K$825)), ROW(6:6))), "") | P9: =IFERROR(INDEX('Bank Schedule'!P:P, SMALL(IF('Bank Schedule'!$K$2:$K$825="Vacant", ROW('Bank Schedule'!$K$2:$K$825)), ROW(6:6))), "") | Q9: {=IFERROR(INDEX('Bank Schedule'!Q:Q, SMALL(IF('Bank Schedule'!$K$2:$K$825="Vacant", ROW('Bank Schedule'!$K$2:$K$825)), ROW(6:6))), "")} -> 0 | R9: {=IFERROR(INDEX('Bank Schedule'!R:R, SMALL(IF('Bank Schedule'!$K$2:$K$825="Vacant", ROW('Bank Schedule'!$K$2:$K$825)), ROW(6:6))), "")} -> 0 | S9: =IFERROR(INDEX('Bank Schedule'!S:S, SMALL(IF('Bank Schedule'!$K$2:$K$825="Vacant", ROW('Bank Schedule'!$K$2:$K$825)), ROW(6:6))), "") | T9: {=IFERROR(INDEX('Bank Schedule'!T:T, SMALL(IF('Bank Schedule'!$K$2:$K$825="Vacant", ROW('Bank Schedule'!$K$2:$K$825)), ROW(6:6))), "")} -> 143000 | U9: {=IFERROR(INDEX('Bank Schedule'!U:U, SMALL(IF('Bank Schedule'!$K$2:$K$825="Vacant", ROW('Bank Schedule'!$K$2:$K$825)), ROW(6:6))), "")} -> 143000 | V9: {=IFERROR(INDEX('Bank Schedule'!V:V, SMALL(IF('Bank Schedule'!$K$2:$K$825="Vacant", ROW('Bank Schedule'!$K$2:$K$825)), ROW(6:6))), "")} -> 145000 | W9: {=IFERROR(INDEX('Bank Schedule'!W:W, SMALL(IF('Bank Schedule'!$K$2:$K$825="Vacant", ROW('Bank Schedule'!$K$2:$K$825)), ROW(6:6))), "")} -> 145000 | X9: {=IFERROR(INDEX('Bank Schedule'!X:X, SMALL(IF('Bank Schedule'!$K$2:$K$825="Vacant", ROW('Bank Schedule'!$K$2:$K$825)), ROW(6:6))), "")} -> 64.876957 | Y9: {=IFERROR(INDEX('Bank Schedule'!Y:Y, SMALL(IF('Bank Schedule'!$K$2:$K$825="Vacant", ROW('Bank Schedule'!$K$2:$K$825)), ROW(6:6))), "")} -> 0.013986014 | Z9: {=IFERROR(INDEX('Bank Schedule'!Z:Z, SMALL(IF('Bank Schedule'!$K$2:$K$825="Vacant", ROW('Bank Schedule'!$K$2:$K$825)), ROW(6:6))), "")} -> D | AA9: =IFERROR(INDEX('Bank Schedule'!AA:AA, SMALL(IF('Bank Schedule'!$K$2:$K$825="Vacant", ROW('Bank Schedule'!$K$2:$K$825)), ROW(6:6))), "") | AB9: =IFERROR(INDEX('Bank Schedule'!AB:AB, SMALL(IF('Bank Schedule'!$K$2:$K$825="Vacant", ROW('Bank Schedule'!$K$2:$K$825)), ROW(6:6))), "") | AC9: {=IFERROR(INDEX('Bank Schedule'!AC:AC, SMALL(IF('Bank Schedule'!$K$2:$K$825="Vacant", ROW('Bank Schedule'!$K$2:$K$825)), ROW(6:6))), "")} -> No | AD9: {=IFERROR(INDEX('Bank Schedule'!AD:AD, SMALL(IF('Bank Schedule'!$K$2:$K$825="Vacant", ROW('Bank Schedule'!$K$2:$K$825)), ROW(6:6))), "")} -> LEM Marketing. | AE9: =IFERROR(INDEX('Bank Schedule'!AE:AE, SMALL(IF('Bank Schedule'!$K$2:$K$825="Vacant", ROW('Bank Schedule'!$K$2:$K$825)), ROW(6:6))), "") | AF9: {=IFERROR(INDEX('Bank Schedule'!AF:AF, SMALL(IF('Bank Schedule'!$K$2:$K$825="Vacant", ROW('Bank Schedule'!$K$2:$K$825)), ROW(6:6))), "")} -> 15 | AG9: {=IFERROR(INDEX('Bank Schedule'!AG:AG, SMALL(IF('Bank Schedule'!$K$2:$K$825="Vacant", ROW('Bank Schedule'!$K$2:$K$825)), ROW(6:6))), "")} -> 15 | AH9: =IFERROR(INDEX('Bank Schedule'!AH:AH, SMALL(IF('Bank Schedule'!$K$2:$K$825="Vacant", ROW('Bank Schedule'!$K$2:$K$825)), ROW(6:6))), "")
A10: =IFERROR(INDEX('Bank Schedule'!A:A, SMALL(IF('Bank Schedule'!$K$2:$K$825="Vacant", ROW('Bank Schedule'!$K$2:$K$825)), ROW(7:7))), "") | B10: {=IFERROR(INDEX('Bank Schedule'!B:B, SMALL(IF('Bank Schedule'!$K$2:$K$825="Vacant", ROW('Bank Schedule'!$K$2:$K$825)), ROW(7:7))), "")} -> SH | C10: {=IFERROR(INDEX('Bank Schedule'!C:C, SMALL(IF('Bank Schedule'!$K$2:$K$825="Vacant", ROW('Bank Schedule'!$K$2:$K$825)), ROW(7:7))), "")} -> MEL | D10: {=IFERROR(INDEX('Bank Schedule'!D:D, SMALL(IF('Bank Schedule'!$K$2:$K$825="Vacant", ROW('Bank Schedule'!$K$2:$K$825)), ROW(7:7))), "")} -> 550070 | E10: {=IFERROR(INDEX('Bank Schedule'!E:E, SMALL(IF('Bank Schedule'!$K$2:$K$825="Vacant", ROW('Bank Schedule'!$K$2:$K$825)), ROW(7:7))), "")} -> Windsor House, 40-41 Great Castle Street | F10: {=IFERROR(INDEX('Bank Schedule'!F:F, SMALL(IF('Bank Schedule'!$K$2:$K$825="Vacant", ROW('Bank Schedule'!$K$2:$K$825)), ROW(7:7))), "")} -> Fourth Floor | G10: {=IFERROR(INDEX('Bank Schedule'!G:G, SMALL(IF('Bank Schedule'!$K$2:$K$825="Vacant", ROW('Bank Schedule'!$K$2:$K$825)), ROW(7:7))), "")} -> Office | H10: {=IFERROR(INDEX('Bank Schedule'!H:H, SMALL(IF('Bank Schedule'!$K$2:$K$825="Vacant", ROW('Bank Schedule'!$K$2:$K$825)), ROW(7:7))), "")} -> 400 | I10: {=IFERROR(INDEX('Bank Schedule'!I:I, SMALL(IF('Bank Schedule'!$K$2:$K$825="Vacant", ROW('Bank Schedule'!$K$2:$K$825)), ROW(7:7))), "")} -> 400 | J10: {=IFERROR(INDEX('Bank Schedule'!J:J, SMALL(IF('Bank Schedule'!$K$2:$K$825="Vacant", ROW('Bank Schedule'!$K$2:$K$825)), ROW(7:7))), "")} -> 500 | K10: {=IFERROR(INDEX('Bank Schedule'!K:K, SMALL(IF('Bank Schedule'!$K$2:$K$825="Vacant", ROW('Bank Schedule'!$K$2:$K$825)), ROW(7:7))), "")} -> Vacant | L10: =IFERROR(INDEX('Bank Schedule'!L:L, SMALL(IF('Bank Schedule'!$K$2:$K$825="Vacant", ROW('Bank Schedule'!$K$2:$K$825)), ROW(7:7))), "") | M10: =IFERROR(INDEX('Bank Schedule'!M:M, SMALL(IF('Bank Schedule'!$K$2:$K$825="Vacant", ROW('Bank Schedule'!$K$2:$K$825)), ROW(7:7))), "") | N10: {=IFERROR(INDEX('Bank Schedule'!N:N, SMALL(IF('Bank Schedule'!$K$2:$K$825="Vacant", ROW('Bank Schedule'!$K$2:$K$825)), ROW(7:7))), "")} -> 44168 | O10: =IFERROR(INDEX('Bank Schedule'!O:O, SMALL(IF('Bank Schedule'!$K$2:$K$825="Vacant", ROW('Bank Schedule'!$K$2:$K$825)), ROW(7:7))), "") | P10: =IFERROR(INDEX('Bank Schedule'!P:P, SMALL(IF('Bank Schedule'!$K$2:$K$825="Vacant", ROW('Bank Schedule'!$K$2:$K$825)), ROW(7:7))), "") | Q10: {=IFERROR(INDEX('Bank Schedule'!Q:Q, SMALL(IF('Bank Schedule'!$K$2:$K$825="Vacant", ROW('Bank Schedule'!$K$2:$K$825)), ROW(7:7))), "")} -> 0 | R10: {=IFERROR(INDEX('Bank Schedule'!R:R, SMALL(IF('Bank Schedule'!$K$2:$K$825="Vacant", ROW('Bank Schedule'!$K$2:$K$825)), ROW(7:7))), "")} -> 0 | S10: =IFERROR(INDEX('Bank Schedule'!S:S, SMALL(IF('Bank Schedule'!$K$2:$K$825="Vacant", ROW('Bank Schedule'!$K$2:$K$825)), ROW(7:7))), "") | T10: {=IFERROR(INDEX('Bank Schedule'!T:T, SMALL(IF('Bank Schedule'!$K$2:$K$825="Vacant", ROW('Bank Schedule'!$K$2:$K$825)), ROW(7:7))), "")} -> 21600 | U10: {=IFERROR(INDEX('Bank Schedule'!U:U, SMALL(IF('Bank Schedule'!$K$2:$K$825="Vacant", ROW('Bank Schedule'!$K$2:$K$825)), ROW(7:7))), "")} -> 21600 | V10: {=IFERROR(INDEX('Bank Schedule'!V:V, SMALL(IF('Bank Schedule'!$K$2:$K$825="Vacant", ROW('Bank Schedule'!$K$2:$K$825)), ROW(7:7))), "")} -> 22000 | W10: {=IFERROR(INDEX('Bank Schedule'!W:W, SMALL(IF('Bank Schedule'!$K$2:$K$825="Vacant", ROW('Bank Schedule'!$K$2:$K$825)), ROW(7:7))), "")} -> 22000 | X10: {=IFERROR(INDEX('Bank Schedule'!X:X, SMALL(IF('Bank Schedule'!$K$2:$K$825="Vacant", ROW('Bank Schedule'!$K$2:$K$825)), ROW(7:7))), "")} -> 55 | Y10: {=IFERROR(INDEX('Bank Schedule'!Y:Y, SMALL(IF('Bank Schedule'!$K$2:$K$825="Vacant", ROW('Bank Schedule'!$K$2:$K$825)), ROW(7:7))), "")} -> 0.018518519 | Z10: {=IFERROR(INDEX('Bank Schedule'!Z:Z, SMALL(IF('Bank Schedule'!$K$2:$K$825="Vacant", ROW('Bank Schedule'!$K$2:$K$825)), ROW(7:7))), "")} -> D | AA10: =IFERROR(INDEX('Bank Schedule'!AA:AA, SMALL(IF('Bank Schedule'!$K$2:$K$825="Vacant", ROW('Bank Schedule'!$K$2:$K$825)), ROW(7:7))), "") | AB10: =IFERROR(INDEX('Bank Schedule'!AB:AB, SMALL(IF('Bank Schedule'!$K$2:$K$825="Vacant", ROW('Bank Schedule'!$K$2:$K$825)), ROW(7:7))), "") | AC10: {=IFERROR(INDEX('Bank Schedule'!AC:AC, SMALL(IF('Bank Schedule'!$K$2:$K$825="Vacant", ROW('Bank Schedule'!$K$2:$K$825)), ROW(7:7))), "")} -> No | AD10: {=IFERROR(INDEX('Bank Schedule'!AD:AD, SMALL(IF('Bank Schedule'!$K$2:$K$825="Vacant", ROW('Bank Schedule'!$K$2:$K$825)), ROW(7:7))), "")} -> To be refurbished. | AE10: =IFERROR(INDEX('Bank Schedule'!AE:AE, SMALL(IF('Bank Schedule'!$K$2:$K$825="Vacant", ROW('Bank Schedule'!$K$2:$K$825)), ROW(7:7))), "") | AF10: =IFERROR(INDEX('Bank Schedule'!AF:AF, SMALL(IF('Bank Schedule'!$K$2:$K$825="Vacant", ROW('Bank Schedule'!$K$2:$K$825)), ROW(7:7))), "") | AG10: =IFERROR(INDEX('Bank Schedule'!AG:AG, SMALL(IF('Bank Schedule'!$K$2:$K$825="Vacant", ROW('Bank Schedule'!$K$2:$K$825)), ROW(7:7))), "") | AH10: =IFERROR(INDEX('Bank Schedule'!AH:AH, SMALL(IF('Bank Schedule'!$K$2:$K$825="Vacant", ROW('Bank Schedule'!$K$2:$K$825)), ROW(7:7))), "")
A11: =IFERROR(INDEX('Bank Schedule'!A:A, SMALL(IF('Bank Schedule'!$K$2:$K$825="Vacant", ROW('Bank Schedule'!$K$2:$K$825)), ROW(8:8))), "") | B11: {=IFERROR(INDEX('Bank Schedule'!B:B, SMALL(IF('Bank Schedule'!$K$2:$K$825="Vacant", ROW('Bank Schedule'!$K$2:$K$825)), ROW(8:8))), "")} -> SH | C11: {=IFERROR(INDEX('Bank Schedule'!C:C, SMALL(IF('Bank Schedule'!$K$2:$K$825="Vacant", ROW('Bank Schedule'!$K$2:$K$825)), ROW(8:8))), "")} -> MEL | D11: {=IFERROR(INDEX('Bank Schedule'!D:D, SMALL(IF('Bank Schedule'!$K$2:$K$825="Vacant", ROW('Bank Schedule'!$K$2:$K$825)), ROW(8:8))), "")} -> 550470 | E11: {=IFERROR(INDEX('Bank Schedule'!E:E, SMALL(IF('Bank Schedule'!$K$2:$K$825="Vacant", ROW('Bank Schedule'!$K$2:$K$825)), ROW(8:8))), "")} -> Portland House, 4 Great Portland Street | F11: {=IFERROR(INDEX('Bank Schedule'!F:F, SMALL(IF('Bank Schedule'!$K$2:$K$825="Vacant", ROW('Bank Schedule'!$K$2:$K$825)), ROW(8:8))), "")} -> Second Floor (West) | G11: {=IFERROR(INDEX('Bank Schedule'!G:G, SMALL(IF('Bank Schedule'!$K$2:$K$825="Vacant", ROW('Bank Schedule'!$K$2:$K$825)), ROW(8:8))), "")} -> Office | H11: {=IFERROR(INDEX('Bank Schedule'!H:H, SMALL(IF('Bank Schedule'!$K$2:$K$825="Vacant", ROW('Bank Schedule'!$K$2:$K$825)), ROW(8:8))), "")} -> 1796 | I11: {=IFERROR(INDEX('Bank Schedule'!I:I, SMALL(IF('Bank Schedule'!$K$2:$K$825="Vacant", ROW('Bank Schedule'!$K$2:$K$825)), ROW(8:8))), "")} -> 1796 | J11: {=IFERROR(INDEX('Bank Schedule'!J:J, SMALL(IF('Bank Schedule'!$K$2:$K$825="Vacant", ROW('Bank Schedule'!$K$2:$K$825)), ROW(8:8))), "")} -> 1750 | K11: {=IFERROR(INDEX('Bank Schedule'!K:K, SMALL(IF('Bank Schedule'!$K$2:$K$825="Vacant", ROW('Bank Schedule'!$K$2:$K$825)), ROW(8:8))), "")} -> Vacant | L11: =IFERROR(INDEX('Bank Schedule'!L:L, SMALL(IF('Bank Schedule'!$K$2:$K$825="Vacant", ROW('Bank Schedule'!$K$2:$K$825)), ROW(8:8))), "") | M11: =IFERROR(INDEX('Bank Schedule'!M:M, SMALL(IF('Bank Schedule'!$K$2:$K$825="Vacant", ROW('Bank Schedule'!$K$2:$K$825)), ROW(8:8))), "") | N11: {=IFERROR(INDEX('Bank Schedule'!N:N, SMALL(IF('Bank Schedule'!$K$2:$K$825="Vacant", ROW('Bank Schedule'!$K$2:$K$825)), ROW(8:8))), "")} -> 45051 | O11: =IFERROR(INDEX('Bank Schedule'!O:O, SMALL(IF('Bank Schedule'!$K$2:$K$825="Vacant", ROW('Bank Schedule'!$K$2:$K$825)), ROW(8:8))), "") | P11: =IFERROR(INDEX('Bank Schedule'!P:P, SMALL(IF('Bank Schedule'!$K$2:$K$825="Vacant", ROW('Bank Schedule'!$K$2:$K$825)), ROW(8:8))), "") | Q11: {=IFERROR(INDEX('Bank Schedule'!Q:Q, SMALL(IF('Bank Schedule'!$K$2:$K$825="Vacant", ROW('Bank Schedule'!$K$2:$K$825)), ROW(8:8))), "")} -> 0 | R11: {=IFERROR(INDEX('Bank Schedule'!R:R, SMALL(IF('Bank Schedule'!$K$2:$K$825="Vacant", ROW('Bank Schedule'!$K$2:$K$825)), ROW(8:8))), "")} -> 0 | S11: =IFERROR(INDEX('Bank Schedule'!S:S, SMALL(IF('Bank Schedule'!$K$2:$K$825="Vacant", ROW('Bank Schedule'!$K$2:$K$825)), ROW(8:8))), "") | T11: {=IFERROR(INDEX('Bank Schedule'!T:T, SMALL(IF('Bank Schedule'!$K$2:$K$825="Vacant", ROW('Bank Schedule'!$K$2:$K$825)), ROW(8:8))), "")} -> 87300 | U11: {=IFERROR(INDEX('Bank Schedule'!U:U, SMALL(IF('Bank Schedule'!$K$2:$K$825="Vacant", ROW('Bank Schedule'!$K$2:$K$825)), ROW(8:8))), "")} -> 87300 | V11: {=IFERROR(INDEX('Bank Schedule'!V:V, SMALL(IF('Bank Schedule'!$K$2:$K$825="Vacant", ROW('Bank Schedule'!$K$2:$K$825)), ROW(8:8))), "")} -> 121240 | W11: {=IFERROR(INDEX('Bank Schedule'!W:W, SMALL(IF('Bank Schedule'!$K$2:$K$825="Vacant", ROW('Bank Schedule'!$K$2:$K$825)), ROW(8:8))), "")} -> 121240 | X11: {=IFERROR(INDEX('Bank Schedule'!X:X, SMALL(IF('Bank Schedule'!$K$2:$K$825="Vacant", ROW('Bank Schedule'!$K$2:$K$825)), ROW(8:8))), "")} -> 67.505568 | Y11: {=IFERROR(INDEX('Bank Schedule'!Y:Y, SMALL(IF('Bank Schedule'!$K$2:$K$825="Vacant", ROW('Bank Schedule'!$K$2:$K$825)), ROW(8:8))), "")} -> 0.38877434 | Z11: {=IFERROR(INDEX('Bank Schedule'!Z:Z, SMALL(IF('Bank Schedule'!$K$2:$K$825="Vacant", ROW('Bank Schedule'!$K$2:$K$825)), ROW(8:8))), "")} -> B | AA11: =IFERROR(INDEX('Bank Schedule'!AA:AA, SMALL(IF('Bank Schedule'!$K$2:$K$825="Vacant", ROW('Bank Schedule'!$K$2:$K$825)), ROW(8:8))), "") | AB11: =IFERROR(INDEX('Bank Schedule'!AB:AB, SMALL(IF('Bank Schedule'!$K$2:$K$825="Vacant", ROW('Bank Schedule'!$K$2:$K$825)), ROW(8:8))), "") | AC11: {=IFERROR(INDEX('Bank Schedule'!AC:AC, SMALL(IF('Bank Schedule'!$K$2:$K$825="Vacant", ROW('Bank Schedule'!$K$2:$K$825)), ROW(8:8))), "")} -> No | AD11: {=IFERROR(INDEX('Bank Schedule'!AD:AD, SMALL(IF('Bank Schedule'!$K$2:$K$825="Vacant", ROW('Bank Schedule'!$K$2:$K$825)), ROW(8:8))), "")} -> LEM marketing. | AE11: {=IFERROR(INDEX('Bank Schedule'!AE:AE, SMALL(IF('Bank Schedule'!$K$2:$K$825="Vacant", ROW('Bank Schedule'!$K$2:$K$825)), ROW(8:8))), "")} -> 72.5 | AF11: {=IFERROR(INDEX('Bank Schedule'!AF:AF, SMALL(IF('Bank Schedule'!$K$2:$K$825="Vacant", ROW('Bank Schedule'!$K$2:$K$825)), ROW(8:8))), "")} -> 3 | AG11: {=IFERROR(INDEX('Bank Schedule'!AG:AG, SMALL(IF('Bank Schedule'!$K$2:$K$825="Vacant", ROW('Bank Schedule'!$K$2:$K$825)), ROW(8:8))), "")} -> 13 | AH11: {=IFERROR(INDEX('Bank Schedule'!AH:AH, SMALL(IF('Bank Schedule'!$K$2:$K$825="Vacant", ROW('Bank Schedule'!$K$2:$K$825)), ROW(8:8))), "")} -> LEM/LDG
A12: =IFERROR(INDEX('Bank Schedule'!A:A, SMALL(IF('Bank Schedule'!$K$2:$K$825="Vacant", ROW('Bank Schedule'!$K$2:$K$825)), ROW(9:9))), "") | B12: {=IFERROR(INDEX('Bank Schedule'!B:B, SMALL(IF('Bank Schedule'!$K$2:$K$825="Vacant", ROW('Bank Schedule'!$K$2:$K$825)), ROW(9:9))), "")} -> SH | C12: {=IFERROR(INDEX('Bank Schedule'!C:C, SMALL(IF('Bank Schedule'!$K$2:$K$825="Vacant", ROW('Bank Schedule'!$K$2:$K$825)), ROW(9:9))), "")} -> MEL | D12: {=IFERROR(INDEX('Bank Schedule'!D:D, SMALL(IF('Bank Schedule'!$K$2:$K$825="Vacant", ROW('Bank Schedule'!$K$2:$K$825)), ROW(9:9))), "")} -> 550470 | E12: {=IFERROR(INDEX('Bank Schedule'!E:E, SMALL(IF('Bank Schedule'!$K$2:$K$825="Vacant", ROW('Bank Schedule'!$K$2:$K$825)), ROW(9:9))), "")} -> Portland House, 4 Great Portland Street | F12: {=IFERROR(INDEX('Bank Schedule'!F:F, SMALL(IF('Bank Schedule'!$K$2:$K$825="Vacant", ROW('Bank Schedule'!$K$2:$K$825)), ROW(9:9))), "")} -> Sixth Floor (East) | G12: {=IFERROR(INDEX('Bank Schedule'!G:G, SMALL(IF('Bank Schedule'!$K$2:$K$825="Vacant", ROW('Bank Schedule'!$K$2:$K$825)), ROW(9:9))), "")} -> Office | H12: {=IFERROR(INDEX('Bank Schedule'!H:H, SMALL(IF('Bank Schedule'!$K$2:$K$825="Vacant", ROW('Bank Schedule'!$K$2:$K$825)), ROW(9:9))), "")} -> 859 | I12: {=IFERROR(INDEX('Bank Schedule'!I:I, SMALL(IF('Bank Schedule'!$K$2:$K$825="Vacant", ROW('Bank Schedule'!$K$2:$K$825)), ROW(9:9))), "")} -> 859 | J12: {=IFERROR(INDEX('Bank Schedule'!J:J, SMALL(IF('Bank Schedule'!$K$2:$K$825="Vacant", ROW('Bank Schedule'!$K$2:$K$825)), ROW(9:9))), "")} -> 1000 | K12: {=IFERROR(INDEX('Bank Schedule'!K:K, SMALL(IF('Bank Schedule'!$K$2:$K$825="Vacant", ROW('Bank Schedule'!$K$2:$K$825)), ROW(9:9))), "")} -> Vacant | L12: =IFERROR(INDEX('Bank Schedule'!L:L, SMALL(IF('Bank Schedule'!$K$2:$K$825="Vacant", ROW('Bank Schedule'!$K$2:$K$825)), ROW(9:9))), "") | M12: =IFERROR(INDEX('Bank Schedule'!M:M, SMALL(IF('Bank Schedule'!$K$2:$K$825="Vacant", ROW('Bank Schedule'!$K$2:$K$825)), ROW(9:9))), "") | N12: {=IFERROR(INDEX('Bank Schedule'!N:N, SMALL(IF('Bank Schedule'!$K$2:$K$825="Vacant", ROW('Bank Schedule'!$K$2:$K$825)), ROW(9:9))), "")} -> 44609 | O12: =IFERROR(INDEX('Bank Schedule'!O:O, SMALL(IF('Bank Schedule'!$K$2:$K$825="Vacant", ROW('Bank Schedule'!$K$2:$K$825)), ROW(9:9))), "") | P12: =IFERROR(INDEX('Bank Schedule'!P:P, SMALL(IF('Bank Schedule'!$K$2:$K$825="Vacant", ROW('Bank Schedule'!$K$2:$K$825)), ROW(9:9))), "") | Q12: {=IFERROR(INDEX('Bank Schedule'!Q:Q, SMALL(IF('Bank Schedule'!$K$2:$K$825="Vacant", ROW('Bank Schedule'!$K$2:$K$825)), ROW(9:9))), "")} -> 0 | R12: {=IFERROR(INDEX('Bank Schedule'!R:R, SMALL(IF('Bank Schedule'!$K$2:$K$825="Vacant", ROW('Bank Schedule'!$K$2:$K$825)), ROW(9:9))), "")} -> 0 | S12: =IFERROR(INDEX('Bank Schedule'!S:S, SMALL(IF('Bank Schedule'!$K$2:$K$825="Vacant", ROW('Bank Schedule'!$K$2:$K$825)), ROW(9:9))), "") | T12: {=IFERROR(INDEX('Bank Schedule'!T:T, SMALL(IF('Bank Schedule'!$K$2:$K$825="Vacant", ROW('Bank Schedule'!$K$2:$K$825)), ROW(9:9))), "")} -> 65750 | U12: {=IFERROR(INDEX('Bank Schedule'!U:U, SMALL(IF('Bank Schedule'!$K$2:$K$825="Vacant", ROW('Bank Schedule'!$K$2:$K$825)), ROW(9:9))), "")} -> 65750 | V12: {=IFERROR(INDEX('Bank Schedule'!V:V, SMALL(IF('Bank Schedule'!$K$2:$K$825="Vacant", ROW('Bank Schedule'!$K$2:$K$825)), ROW(9:9))), "")} -> 53700 | W12: {=IFERROR(INDEX('Bank Schedule'!W:W, SMALL(IF('Bank Schedule'!$K$2:$K$825="Vacant", ROW('Bank Schedule'!$K$2:$K$825)), ROW(9:9))), "")} -> 53700 | X12: {=IFERROR(INDEX('Bank Schedule'!X:X, SMALL(IF('Bank Schedule'!$K$2:$K$825="Vacant", ROW('Bank Schedule'!$K$2:$K$825)), ROW(9:9))), "")} -> 62.514552 | Y12: {=IFERROR(INDEX('Bank Schedule'!Y:Y, SMALL(IF('Bank Schedule'!$K$2:$K$825="Vacant", ROW('Bank Schedule'!$K$2:$K$825)), ROW(9:9))), "")} -> -0.18326996 | Z12: {=IFERROR(INDEX('Bank Schedule'!Z:Z, SMALL(IF('Bank Schedule'!$K$2:$K$825="Vacant", ROW('Bank Schedule'!$K$2:$K$825)), ROW(9:9))), "")} -> D | AA12: =IFERROR(INDEX('Bank Schedule'!AA:AA, SMALL(IF('Bank Schedule'!$K$2:$K$825="Vacant", ROW('Bank Schedule'!$K$2:$K$825)), ROW(9:9))), "") | AB12: =IFERROR(INDEX('Bank Schedule'!AB:AB, SMALL(IF('Bank Schedule'!$K$2:$K$825="Vacant", ROW('Bank Schedule'!$K$2:$K$825)), ROW(9:9))), "") | AC12: {=IFERROR(INDEX('Bank Schedule'!AC:AC, SMALL(IF('Bank Schedule'!$K$2:$K$825="Vacant", ROW('Bank Schedule'!$K$2:$K$825)), ROW(9:9))), "")} -> No | AD12: {=IFERROR(INDEX('Bank Schedule'!AD:AD, SMALL(IF('Bank Schedule'!$K$2:$K$825="Vacant", ROW('Bank Schedule'!$K$2:$K$825)), ROW(9:9))), "")} -> LEM marketing. | AE12: {=IFERROR(INDEX('Bank Schedule'!AE:AE, SMALL(IF('Bank Schedule'!$K$2:$K$825="Vacant", ROW('Bank Schedule'!$K$2:$K$825)), ROW(9:9))), "")} -> 63 | AF12: =IFERROR(INDEX('Bank Schedule'!AF:AF, SMALL(IF('Bank Schedule'!$K$2:$K$825="Vacant", ROW('Bank Schedule'!$K$2:$K$825)), ROW(9:9))), "") | AG12: {=IFERROR(INDEX('Bank Schedule'!AG:AG, SMALL(IF('Bank Schedule'!$K$2:$K$825="Vacant", ROW('Bank Schedule'!$K$2:$K$825)), ROW(9:9))), "")} -> 2 | AH12: =IFERROR(INDEX('Bank Schedule'!AH:AH, SMALL(IF('Bank Schedule'!$K$2:$K$825="Vacant", ROW('Bank Schedule'!$K$2:$K$825)), ROW(9:9))), "")
A13: =IFERROR(INDEX('Bank Schedule'!A:A, SMALL(IF('Bank Schedule'!$K$2:$K$825="Vacant", ROW('Bank Schedule'!$K$2:$K$825)), ROW(10:10))), "") | B13: {=IFERROR(INDEX('Bank Schedule'!B:B, SMALL(IF('Bank Schedule'!$K$2:$K$825="Vacant", ROW('Bank Schedule'!$K$2:$K$825)), ROW(10:10))), "")} -> SH | C13: {=IFERROR(INDEX('Bank Schedule'!C:C, SMALL(IF('Bank Schedule'!$K$2:$K$825="Vacant", ROW('Bank Schedule'!$K$2:$K$825)), ROW(10:10))), "")} -> MEL | D13: {=IFERROR(INDEX('Bank Schedule'!D:D, SMALL(IF('Bank Schedule'!$K$2:$K$825="Vacant", ROW('Bank Schedule'!$K$2:$K$825)), ROW(10:10))), "")} -> 550480 | E13: {=IFERROR(INDEX('Bank Schedule'!E:E, SMALL(IF('Bank Schedule'!$K$2:$K$825="Vacant", ROW('Bank Schedule'!$K$2:$K$825)), ROW(10:10))), "")} -> 6-10a Great Portland Street | F13: {=IFERROR(INDEX('Bank Schedule'!F:F, SMALL(IF('Bank Schedule'!$K$2:$K$825="Vacant", ROW('Bank Schedule'!$K$2:$K$825)), ROW(10:10))), "")} -> Second Floor | G13: {=IFERROR(INDEX('Bank Schedule'!G:G, SMALL(IF('Bank Schedule'!$K$2:$K$825="Vacant", ROW('Bank Schedule'!$K$2:$K$825)), ROW(10:10))), "")} -> Office | H13: {=IFERROR(INDEX('Bank Schedule'!H:H, SMALL(IF('Bank Schedule'!$K$2:$K$825="Vacant", ROW('Bank Schedule'!$K$2:$K$825)), ROW(10:10))), "")} -> 1818 | I13: {=IFERROR(INDEX('Bank Schedule'!I:I, SMALL(IF('Bank Schedule'!$K$2:$K$825="Vacant", ROW('Bank Schedule'!$K$2:$K$825)), ROW(10:10))), "")} -> 1818 | J13: {=IFERROR(INDEX('Bank Schedule'!J:J, SMALL(IF('Bank Schedule'!$K$2:$K$825="Vacant", ROW('Bank Schedule'!$K$2:$K$825)), ROW(10:10))), "")} -> 2000 | K13: {=IFERROR(INDEX('Bank Schedule'!K:K, SMALL(IF('Bank Schedule'!$K$2:$K$825="Vacant", ROW('Bank Schedule'!$K$2:$K$825)), ROW(10:10))), "")} -> Vacant | L13: =IFERROR(INDEX('Bank Schedule'!L:L, SMALL(IF('Bank Schedule'!$K$2:$K$825="Vacant", ROW('Bank Schedule'!$K$2:$K$825)), ROW(10:10))), "") | M13: =IFERROR(INDEX('Bank Schedule'!M:M, SMALL(IF('Bank Schedule'!$K$2:$K$825="Vacant", ROW('Bank Schedule'!$K$2:$K$825)), ROW(10:10))), "") | N13: {=IFERROR(INDEX('Bank Schedule'!N:N, SMALL(IF('Bank Schedule'!$K$2:$K$825="Vacant", ROW('Bank Schedule'!$K$2:$K$825)), ROW(10:10))), "")} -> 45609 | O13: =IFERROR(INDEX('Bank Schedule'!O:O, SMALL(IF('Bank Schedule'!$K$2:$K$825="Vacant", ROW('Bank Schedule'!$K$2:$K$825)), ROW(10:10))), "") | P13: =IFERROR(INDEX('Bank Schedule'!P:P, SMALL(IF('Bank Schedule'!$K$2:$K$825="Vacant", ROW('Bank Schedule'!$K$2:$K$825)), ROW(10:10))), "") | Q13: {=IFERROR(INDEX('Bank Schedule'!Q:Q, SMALL(IF('Bank Schedule'!$K$2:$K$825="Vacant", ROW('Bank Schedule'!$K$2:$K$825)), ROW(10:10))), "")} -> 0 | R13: {=IFERROR(INDEX('Bank Schedule'!R:R, SMALL(IF('Bank Schedule'!$K$2:$K$825="Vacant", ROW('Bank Schedule'!$K$2:$K$825)), ROW(10:10))), "")} -> 0 | S13: =IFERROR(INDEX('Bank Schedule'!S:S, SMALL(IF('Bank Schedule'!$K$2:$K$825="Vacant", ROW('Bank Schedule'!$K$2:$K$825)), ROW(10:10))), "") | T13: {=IFERROR(INDEX('Bank Schedule'!T:T, SMALL(IF('Bank Schedule'!$K$2:$K$825="Vacant", ROW('Bank Schedule'!$K$2:$K$825)), ROW(10:10))), "")} -> 105500 | U13: {=IFERROR(INDEX('Bank Schedule'!U:U, SMALL(IF('Bank Schedule'!$K$2:$K$825="Vacant", ROW('Bank Schedule'!$K$2:$K$825)), ROW(10:10))), "")} -> 105500 | V13: {=IFERROR(INDEX('Bank Schedule'!V:V, SMALL(IF('Bank Schedule'!$K$2:$K$825="Vacant", ROW('Bank Schedule'!$K$2:$K$825)), ROW(10:10))), "")} -> 109100 | W13: {=IFERROR(INDEX('Bank Schedule'!W:W, SMALL(IF('Bank Schedule'!$K$2:$K$825="Vacant", ROW('Bank Schedule'!$K$2:$K$825)), ROW(10:10))), "")} -> 109100 | X13: {=IFERROR(INDEX('Bank Schedule'!X:X, SMALL(IF('Bank Schedule'!$K$2:$K$825="Vacant", ROW('Bank Schedule'!$K$2:$K$825)), ROW(10:10))), "")} -> 60.011001 | Y13: {=IFERROR(INDEX('Bank Schedule'!Y:Y, SMALL(IF('Bank Schedule'!$K$2:$K$825="Vacant", ROW('Bank Schedule'!$K$2:$K$825)), ROW(10:10))), "")} -> 0.034123223 | Z13: {=IFERROR(INDEX('Bank Schedule'!Z:Z, SMALL(IF('Bank Schedule'!$K$2:$K$825="Vacant", ROW('Bank Schedule'!$K$2:$K$825)), ROW(10:10))), "")} -> E | AA13: =IFERROR(INDEX('Bank Schedule'!AA:AA, SMALL(IF('Bank Schedule'!$K$2:$K$825="Vacant", ROW('Bank Schedule'!$K$2:$K$825)), ROW(10:10))), "") | AB13: =IFERROR(INDEX('Bank Schedule'!AB:AB, SMALL(IF('Bank Schedule'!$K$2:$K$825="Vacant", ROW('Bank Schedule'!$K$2:$K$825)), ROW(10:10))), "") | AC13: {=IFERROR(INDEX('Bank Schedule'!AC:AC, SMALL(IF('Bank Schedule'!$K$2:$K$825="Vacant", ROW('Bank Schedule'!$K$2:$K$825)), ROW(10:10))), "")} -> No | AD13: {=IFERROR(INDEX('Bank Schedule'!AD:AD, SMALL(IF('Bank Schedule'!$K$2:$K$825="Vacant", ROW('Bank Schedule'!$K$2:$K$825)), ROW(10:10))), "")} -> LEM marketing. | AE13: {=IFERROR(INDEX('Bank Schedule'!AE:AE, SMALL(IF('Bank Schedule'!$K$2:$K$825="Vacant", ROW('Bank Schedule'!$K$2:$K$825)), ROW(10:10))), "")} -> 65 | AF13: {=IFERROR(INDEX('Bank Schedule'!AF:AF, SMALL(IF('Bank Schedule'!$K$2:$K$825="Vacant", ROW('Bank Schedule'!$K$2:$K$825)), ROW(10:10))), "")} -> 4 | AG13: {=IFERROR(INDEX('Bank Schedule'!AG:AG, SMALL(IF('Bank Schedule'!$K$2:$K$825="Vacant", ROW('Bank Schedule'!$K$2:$K$825)), ROW(10:10))), "")} -> 6 | AH13: =IFERROR(INDEX('Bank Schedule'!AH:AH, SMALL(IF('Bank Schedule'!$K$2:$K$825="Vacant", ROW('Bank Schedule'!$K$2:$K$825)), ROW(10:10))), "")
A14: =IFERROR(INDEX('Bank Schedule'!A:A, SMALL(IF('Bank Schedule'!$K$2:$K$825="Vacant", ROW('Bank Schedule'!$K$2:$K$825)), ROW(11:11))), "") | B14: {=IFERROR(INDEX('Bank Schedule'!B:B, SMALL(IF('Bank Schedule'!$K$2:$K$825="Vacant", ROW('Bank Schedule'!$K$2:$K$825)), ROW(11:11))), "")} -> SH | C14: {=IFERROR(INDEX('Bank Schedule'!C:C, SMALL(IF('Bank Schedule'!$K$2:$K$825="Vacant", ROW('Bank Schedule'!$K$2:$K$825)), ROW(11:11))), "")} -> MEL | D14: {=IFERROR(INDEX('Bank Schedule'!D:D, SMALL(IF('Bank Schedule'!$K$2:$K$825="Vacant", ROW('Bank Schedule'!$K$2:$K$825)), ROW(11:11))), "")} -> 550480 | E14: {=IFERROR(INDEX('Bank Schedule'!E:E, SMALL(IF('Bank Schedule'!$K$2:$K$825="Vacant", ROW('Bank Schedule'!$K$2:$K$825)), ROW(11:11))), "")} -> 6-10a Great Portland Street | F14: {=IFERROR(INDEX('Bank Schedule'!F:F, SMALL(IF('Bank Schedule'!$K$2:$K$825="Vacant", ROW('Bank Schedule'!$K$2:$K$825)), ROW(11:11))), "")} -> Third Floor | G14: {=IFERROR(INDEX('Bank Schedule'!G:G, SMALL(IF('Bank Schedule'!$K$2:$K$825="Vacant", ROW('Bank Schedule'!$K$2:$K$825)), ROW(11:11))), "")} -> Office | H14: {=IFERROR(INDEX('Bank Schedule'!H:H, SMALL(IF('Bank Schedule'!$K$2:$K$825="Vacant", ROW('Bank Schedule'!$K$2:$K$825)), ROW(11:11))), "")} -> 1808 | I14: {=IFERROR(INDEX('Bank Schedule'!I:I, SMALL(IF('Bank Schedule'!$K$2:$K$825="Vacant", ROW('Bank Schedule'!$K$2:$K$825)), ROW(11:11))), "")} -> 1808 | J14: {=IFERROR(INDEX('Bank Schedule'!J:J, SMALL(IF('Bank Schedule'!$K$2:$K$825="Vacant", ROW('Bank Schedule'!$K$2:$K$825)), ROW(11:11))), "")} -> 2000 | K14: {=IFERROR(INDEX('Bank Schedule'!K:K, SMALL(IF('Bank Schedule'!$K$2:$K$825="Vacant", ROW('Bank Schedule'!$K$2:$K$825)), ROW(11:11))), "")} -> Vacant | L14: =IFERROR(INDEX('Bank Schedule'!L:L, SMALL(IF('Bank Schedule'!$K$2:$K$825="Vacant", ROW('Bank Schedule'!$K$2:$K$825)), ROW(11:11))), "") | M14: =IFERROR(INDEX('Bank Schedule'!M:M, SMALL(IF('Bank Schedule'!$K$2:$K$825="Vacant", ROW('Bank Schedule'!$K$2:$K$825)), ROW(11:11))), "") | N14: {=IFERROR(INDEX('Bank Schedule'!N:N, SMALL(IF('Bank Schedule'!$K$2:$K$825="Vacant", ROW('Bank Schedule'!$K$2:$K$825)), ROW(11:11))), "")} -> 45609 | O14: =IFERROR(INDEX('Bank Schedule'!O:O, SMALL(IF('Bank Schedule'!$K$2:$K$825="Vacant", ROW('Bank Schedule'!$K$2:$K$825)), ROW(11:11))), "") | P14: =IFERROR(INDEX('Bank Schedule'!P:P, SMALL(IF('Bank Schedule'!$K$2:$K$825="Vacant", ROW('Bank Schedule'!$K$2:$K$825)), ROW(11:11))), "") | Q14: {=IFERROR(INDEX('Bank Schedule'!Q:Q, SMALL(IF('Bank Schedule'!$K$2:$K$825="Vacant", ROW('Bank Schedule'!$K$2:$K$825)), ROW(11:11))), "")} -> 0 | R14: {=IFERROR(INDEX('Bank Schedule'!R:R, SMALL(IF('Bank Schedule'!$K$2:$K$825="Vacant", ROW('Bank Schedule'!$K$2:$K$825)), ROW(11:11))), "")} -> 0 | S14: =IFERROR(INDEX('Bank Schedule'!S:S, SMALL(IF('Bank Schedule'!$K$2:$K$825="Vacant", ROW('Bank Schedule'!$K$2:$K$825)), ROW(11:11))), "") | T14: {=IFERROR(INDEX('Bank Schedule'!T:T, SMALL(IF('Bank Schedule'!$K$2:$K$825="Vacant", ROW('Bank Schedule'!$K$2:$K$825)), ROW(11:11))), "")} -> 108800 | U14: {=IFERROR(INDEX('Bank Schedule'!U:U, SMALL(IF('Bank Schedule'!$K$2:$K$825="Vacant", ROW('Bank Schedule'!$K$2:$K$825)), ROW(11:11))), "")} -> 108800 | V14: {=IFERROR(INDEX('Bank Schedule'!V:V, SMALL(IF('Bank Schedule'!$K$2:$K$825="Vacant", ROW('Bank Schedule'!$K$2:$K$825)), ROW(11:11))), "")} -> 108500 | W14: {=IFERROR(INDEX('Bank Schedule'!W:W, SMALL(IF('Bank Schedule'!$K$2:$K$825="Vacant", ROW('Bank Schedule'!$K$2:$K$825)), ROW(11:11))), "")} -> 108500 | X14: {=IFERROR(INDEX('Bank Schedule'!X:X, SMALL(IF('Bank Schedule'!$K$2:$K$825="Vacant", ROW('Bank Schedule'!$K$2:$K$825)), ROW(11:11))), "")} -> 60.011062 | Y14: {=IFERROR(INDEX('Bank Schedule'!Y:Y, SMALL(IF('Bank Schedule'!$K$2:$K$825="Vacant", ROW('Bank Schedule'!$K$2:$K$825)), ROW(11:11))), "")} -> -0.0027573529 | Z14: {=IFERROR(INDEX('Bank Schedule'!Z:Z, SMALL(IF('Bank Schedule'!$K$2:$K$825="Vacant", ROW('Bank Schedule'!$K$2:$K$825)), ROW(11:11))), "")} -> E | AA14: =IFERROR(INDEX('Bank Schedule'!AA:AA, SMALL(IF('Bank Schedule'!$K$2:$K$825="Vacant", ROW('Bank Schedule'!$K$2:$K$825)), ROW(11:11))), "") | AB14: =IFERROR(INDEX('Bank Schedule'!AB:AB, SMALL(IF('Bank Schedule'!$K$2:$K$825="Vacant", ROW('Bank Schedule'!$K$2:$K$825)), ROW(11:11))), "") | AC14: {=IFERROR(INDEX('Bank Schedule'!AC:AC, SMALL(IF('Bank Schedule'!$K$2:$K$825="Vacant", ROW('Bank Schedule'!$K$2:$K$825)), ROW(11:11))), "")} -> No | AD14: {=IFERROR(INDEX('Bank Schedule'!AD:AD, SMALL(IF('Bank Schedule'!$K$2:$K$825="Vacant", ROW('Bank Schedule'!$K$2:$K$825)), ROW(11:11))), "")} -> LEM marketing. | AE14: {=IFERROR(INDEX('Bank Schedule'!AE:AE, SMALL(IF('Bank Schedule'!$K$2:$K$825="Vacant", ROW('Bank Schedule'!$K$2:$K$825)), ROW(11:11))), "")} -> 65 | AF14: {=IFERROR(INDEX('Bank Schedule'!AF:AF, SMALL(IF('Bank Schedule'!$K$2:$K$825="Vacant", ROW('Bank Schedule'!$K$2:$K$825)), ROW(11:11))), "")} -> 4 | AG14: {=IFERROR(INDEX('Bank Schedule'!AG:AG, SMALL(IF('Bank Schedule'!$K$2:$K$825="Vacant", ROW('Bank Schedule'!$K$2:$K$825)), ROW(11:11))), "")} -> 6 | AH14: =IFERROR(INDEX('Bank Schedule'!AH:AH, SMALL(IF('Bank Schedule'!$K$2:$K$825="Vacant", ROW('Bank Schedule'!$K$2:$K$825)), ROW(11:11))), "")
A15: =IFERROR(INDEX('Bank Schedule'!A:A, SMALL(IF('Bank Schedule'!$K$2:$K$825="Vacant", ROW('Bank Schedule'!$K$2:$K$825)), ROW(12:12))), "") | B15: {=IFERROR(INDEX('Bank Schedule'!B:B, SMALL(IF('Bank Schedule'!$K$2:$K$825="Vacant", ROW('Bank Schedule'!$K$2:$K$825)), ROW(12:12))), "")} -> SH | C15: {=IFERROR(INDEX('Bank Schedule'!C:C, SMALL(IF('Bank Schedule'!$K$2:$K$825="Vacant", ROW('Bank Schedule'!$K$2:$K$825)), ROW(12:12))), "")} -> MEL | D15: {=IFERROR(INDEX('Bank Schedule'!D:D, SMALL(IF('Bank Schedule'!$K$2:$K$825="Vacant", ROW('Bank Schedule'!$K$2:$K$825)), ROW(12:12))), "")} -> 550480 | E15: {=IFERROR(INDEX('Bank Schedule'!E:E, SMALL(IF('Bank Schedule'!$K$2:$K$825="Vacant", ROW('Bank Schedule'!$K$2:$K$825)), ROW(12:12))), "")} -> 6-10a Great Portland Street | F15: {=IFERROR(INDEX('Bank Schedule'!F:F, SMALL(IF('Bank Schedule'!$K$2:$K$825="Vacant", ROW('Bank Schedule'!$K$2:$K$825)), ROW(12:12))), "")} -> Fourth Floor | G15: {=IFERROR(INDEX('Bank Schedule'!G:G, SMALL(IF('Bank Schedule'!$K$2:$K$825="Vacant", ROW('Bank Schedule'!$K$2:$K$825)), ROW(12:12))), "")} -> Office | H15: {=IFERROR(INDEX('Bank Schedule'!H:H, SMALL(IF('Bank Schedule'!$K$2:$K$825="Vacant", ROW('Bank Schedule'!$K$2:$K$825)), ROW(12:12))), "")} -> 1672 | I15: {=IFERROR(INDEX('Bank Schedule'!I:I, SMALL(IF('Bank Schedule'!$K$2:$K$825="Vacant", ROW('Bank Schedule'!$K$2:$K$825)), ROW(12:12))), "")} -> 1672 | J15: {=IFERROR(INDEX('Bank Schedule'!J:J, SMALL(IF('Bank Schedule'!$K$2:$K$825="Vacant", ROW('Bank Schedule'!$K$2:$K$825)), ROW(12:12))), "")} -> 1500 | K15: {=IFERROR(INDEX('Bank Schedule'!K:K, SMALL(IF('Bank Schedule'!$K$2:$K$825="Vacant", ROW('Bank Schedule'!$K$2:$K$825)), ROW(12:12))), "")} -> Vacant | L15: =IFERROR(INDEX('Bank Schedule'!L:L, SMALL(IF('Bank Schedule'!$K$2:$K$825="Vacant", ROW('Bank Schedule'!$K$2:$K$825)), ROW(12:12))), "") | M15: =IFERROR(INDEX('Bank Schedule'!M:M, SMALL(IF('Bank Schedule'!$K$2:$K$825="Vacant", ROW('Bank Schedule'!$K$2:$K$825)), ROW(12:12))), "") | N15: {=IFERROR(INDEX('Bank Schedule'!N:N, SMALL(IF('Bank Schedule'!$K$2:$K$825="Vacant", ROW('Bank Schedule'!$K$2:$K$825)), ROW(12:12))), "")} -> 45457 | O15: =IFERROR(INDEX('Bank Schedule'!O:O, SMALL(IF('Bank Schedule'!$K$2:$K$825="Vacant", ROW('Bank Schedule'!$K$2:$K$825)), ROW(12:12))), "") | P15: =IFERROR(INDEX('Bank Schedule'!P:P, SMALL(IF('Bank Schedule'!$K$2:$K$825="Vacant", ROW('Bank Schedule'!$K$2:$K$825)), ROW(12:12))), "") | Q15: {=IFERROR(INDEX('Bank Schedule'!Q:Q, SMALL(IF('Bank Schedule'!$K$2:$K$825="Vacant", ROW('Bank Schedule'!$K$2:$K$825)), ROW(12:12))), "")} -> 0 | R15: {=IFERROR(INDEX('Bank Schedule'!R:R, SMALL(IF('Bank Schedule'!$K$2:$K$825="Vacant", ROW('Bank Schedule'!$K$2:$K$825)), ROW(12:12))), "")} -> 0 | S15: =IFERROR(INDEX('Bank Schedule'!S:S, SMALL(IF('Bank Schedule'!$K$2:$K$825="Vacant", ROW('Bank Schedule'!$K$2:$K$825)), ROW(12:12))), "") | T15: {=IFERROR(INDEX('Bank Schedule'!T:T, SMALL(IF('Bank Schedule'!$K$2:$K$825="Vacant", ROW('Bank Schedule'!$K$2:$K$825)), ROW(12:12))), "")} -> 94400 | U15: {=IFERROR(INDEX('Bank Schedule'!U:U, SMALL(IF('Bank Schedule'!$K$2:$K$825="Vacant", ROW('Bank Schedule'!$K$2:$K$825)), ROW(12:12))), "")} -> 94400 | V15: {=IFERROR(INDEX('Bank Schedule'!V:V, SMALL(IF('Bank Schedule'!$K$2:$K$825="Vacant", ROW('Bank Schedule'!$K$2:$K$825)), ROW(12:12))), "")} -> 97800 | W15: {=IFERROR(INDEX('Bank Schedule'!W:W, SMALL(IF('Bank Schedule'!$K$2:$K$825="Vacant", ROW('Bank Schedule'!$K$2:$K$825)), ROW(12:12))), "")} -> 97800 | X15: {=IFERROR(INDEX('Bank Schedule'!X:X, SMALL(IF('Bank Schedule'!$K$2:$K$825="Vacant", ROW('Bank Schedule'!$K$2:$K$825)), ROW(12:12))), "")} -> 58.492823 | Y15: {=IFERROR(INDEX('Bank Schedule'!Y:Y, SMALL(IF('Bank Schedule'!$K$2:$K$825="Vacant", ROW('Bank Schedule'!$K$2:$K$825)), ROW(12:12))), "")} -> 0.036016949 | Z15: {=IFERROR(INDEX('Bank Schedule'!Z:Z, SMALL(IF('Bank Schedule'!$K$2:$K$825="Vacant", ROW('Bank Schedule'!$K$2:$K$825)), ROW(12:12))), "")} -> B | AA15: =IFERROR(INDEX('Bank Schedule'!AA:AA, SMALL(IF('Bank Schedule'!$K$2:$K$825="Vacant", ROW('Bank Schedule'!$K$2:$K$825)), ROW(12:12))), "") | AB15: =IFERROR(INDEX('Bank Schedule'!AB:AB, SMALL(IF('Bank Schedule'!$K$2:$K$825="Vacant", ROW('Bank Schedule'!$K$2:$K$825)), ROW(12:12))), "") | AC15: {=IFERROR(INDEX('Bank Schedule'!AC:AC, SMALL(IF('Bank Schedule'!$K$2:$K$825="Vacant", ROW('Bank Schedule'!$K$2:$K$825)), ROW(12:12))), "")} -> No | AD15: {=IFERROR(INDEX('Bank Schedule'!AD:AD, SMALL(IF('Bank Schedule'!$K$2:$K$825="Vacant", ROW('Bank Schedule'!$K$2:$K$825)), ROW(12:12))), "")} -> To be refurbished. | AE15: {=IFERROR(INDEX('Bank Schedule'!AE:AE, SMALL(IF('Bank Schedule'!$K$2:$K$825="Vacant", ROW('Bank Schedule'!$K$2:$K$825)), ROW(12:12))), "")} -> 65 | AF15: {=IFERROR(INDEX('Bank Schedule'!AF:AF, SMALL(IF('Bank Schedule'!$K$2:$K$825="Vacant", ROW('Bank Schedule'!$K$2:$K$825)), ROW(12:12))), "")} -> 1 | AG15: {=IFERROR(INDEX('Bank Schedule'!AG:AG, SMALL(IF('Bank Schedule'!$K$2:$K$825="Vacant", ROW('Bank Schedule'!$K$2:$K$825)), ROW(12:12))), "")} -> 2 | AH15: {=IFERROR(INDEX('Bank Schedule'!AH:AH, SMALL(IF('Bank Schedule'!$K$2:$K$825="Vacant", ROW('Bank Schedule'!$K$2:$K$825)), ROW(12:12))), "")} -> LEM
A16: =IFERROR(INDEX('Bank Schedule'!A:A, SMALL(IF('Bank Schedule'!$K$2:$K$825="Vacant", ROW('Bank Schedule'!$K$2:$K$825)), ROW(13:13))), "") -> 0 | B16: {=IFERROR(INDEX('Bank Schedule'!B:B, SMALL(IF('Bank Schedule'!$K$2:$K$825="Vacant", ROW('Bank Schedule'!$K$2:$K$825)), ROW(13:13))), "")} -> CD | C16: {=IFERROR(INDEX('Bank Schedule'!C:C, SMALL(IF('Bank Schedule'!$K$2:$K$825="Vacant", ROW('Bank Schedule'!$K$2:$K$825)), ROW(13:13))), "")} -> MEL | D16: {=IFERROR(INDEX('Bank Schedule'!D:D, SMALL(IF('Bank Schedule'!$K$2:$K$825="Vacant", ROW('Bank Schedule'!$K$2:$K$825)), ROW(13:13))), "")} -> 550410 | E16: {=IFERROR(INDEX('Bank Schedule'!E:E, SMALL(IF('Bank Schedule'!$K$2:$K$825="Vacant", ROW('Bank Schedule'!$K$2:$K$825)), ROW(13:13))), "")} -> 19-21 Great Portland Street . | F16: {=IFERROR(INDEX('Bank Schedule'!F:F, SMALL(IF('Bank Schedule'!$K$2:$K$825="Vacant", ROW('Bank Schedule'!$K$2:$K$825)), ROW(13:13))), "")} -> Second Floor. | G16: {=IFERROR(INDEX('Bank Schedule'!G:G, SMALL(IF('Bank Schedule'!$K$2:$K$825="Vacant", ROW('Bank Schedule'!$K$2:$K$825)), ROW(13:13))), "")} -> Offices | H16: {=IFERROR(INDEX('Bank Schedule'!H:H, SMALL(IF('Bank Schedule'!$K$2:$K$825="Vacant", ROW('Bank Schedule'!$K$2:$K$825)), ROW(13:13))), "")} -> 2847 | I16: {=IFERROR(INDEX('Bank Schedule'!I:I, SMALL(IF('Bank Schedule'!$K$2:$K$825="Vacant", ROW('Bank Schedule'!$K$2:$K$825)), ROW(13:13))), "")} -> 2847 | J16: {=IFERROR(INDEX('Bank Schedule'!J:J, SMALL(IF('Bank Schedule'!$K$2:$K$825="Vacant", ROW('Bank Schedule'!$K$2:$K$825)), ROW(13:13))), "")} -> 3000 | K16: {=IFERROR(INDEX('Bank Schedule'!K:K, SMALL(IF('Bank Schedule'!$K$2:$K$825="Vacant", ROW('Bank Schedule'!$K$2:$K$825)), ROW(13:13))), "")} -> Vacant | L16: =IFERROR(INDEX('Bank Schedule'!L:L, SMALL(IF('Bank Schedule'!$K$2:$K$825="Vacant", ROW('Bank Schedule'!$K$2:$K$825)), ROW(13:13))), "") -> 45086 | M16: =IFERROR(INDEX('Bank Schedule'!M:M, SMALL(IF('Bank Schedule'!$K$2:$K$825="Vacant", ROW('Bank Schedule'!$K$2:$K$825)), ROW(13:13))), "") -> 46181 | N16: {=IFERROR(INDEX('Bank Schedule'!N:N, SMALL(IF('Bank Schedule'!$K$2:$K$825="Vacant", ROW('Bank Schedule'!$K$2:$K$825)), ROW(13:13))), "")} -> 45219 | O16: =IFERROR(INDEX('Bank Schedule'!O:O, SMALL(IF('Bank Schedule'!$K$2:$K$825="Vacant", ROW('Bank Schedule'!$K$2:$K$825)), ROW(13:13))), "") -> 0 | P16: =IFERROR(INDEX('Bank Schedule'!P:P, SMALL(IF('Bank Schedule'!$K$2:$K$825="Vacant", ROW('Bank Schedule'!$K$2:$K$825)), ROW(13:13))), "") -> 0 | Q16: {=IFERROR(INDEX('Bank Schedule'!Q:Q, SMALL(IF('Bank Schedule'!$K$2:$K$825="Vacant", ROW('Bank Schedule'!$K$2:$K$825)), ROW(13:13))), "")} -> 0 | R16: {=IFERROR(INDEX('Bank Schedule'!R:R, SMALL(IF('Bank Schedule'!$K$2:$K$825="Vacant", ROW('Bank Schedule'!$K$2:$K$825)), ROW(13:13))), "")} -> 0 | S16: =IFERROR(INDEX('Bank Schedule'!S:S, SMALL(IF('Bank Schedule'!$K$2:$K$825="Vacant", ROW('Bank Schedule'!$K$2:$K$825)), ROW(13:13))), "") -> 0 | T16: {=IFERROR(INDEX('Bank Schedule'!T:T, SMALL(IF('Bank Schedule'!$K$2:$K$825="Vacant", ROW('Bank Schedule'!$K$2:$K$825)), ROW(13:13))), "")} -> 170000 | U16: {=IFERROR(INDEX('Bank Schedule'!U:U, SMALL(IF('Bank Schedule'!$K$2:$K$825="Vacant", ROW('Bank Schedule'!$K$2:$K$825)), ROW(13:13))), "")} -> 170000 | V16: {=IFERROR(INDEX('Bank Schedule'!V:V, SMALL(IF('Bank Schedule'!$K$2:$K$825="Vacant", ROW('Bank Schedule'!$K$2:$K$825)), ROW(13:13))), "")} -> 185100 | W16: {=IFERROR(INDEX('Bank Schedule'!W:W, SMALL(IF('Bank Schedule'!$K$2:$K$825="Vacant", ROW('Bank Schedule'!$K$2:$K$825)), ROW(13:13))), "")} -> 185100 | X16: {=IFERROR(INDEX('Bank Schedule'!X:X, SMALL(IF('Bank Schedule'!$K$2:$K$825="Vacant", ROW('Bank Schedule'!$K$2:$K$825)), ROW(13:13))), "")} -> 65.015806 | Y16: {=IFERROR(INDEX('Bank Schedule'!Y:Y, SMALL(IF('Bank Schedule'!$K$2:$K$825="Vacant", ROW('Bank Schedule'!$K$2:$K$825)), ROW(13:13))), "")} -> 0.088823529 | Z16: {=IFERROR(INDEX('Bank Schedule'!Z:Z, SMALL(IF('Bank Schedule'!$K$2:$K$825="Vacant", ROW('Bank Schedule'!$K$2:$K$825)), ROW(13:13))), "")} -> B | AA16: =IFERROR(INDEX('Bank Schedule'!AA:AA, SMALL(IF('Bank Schedule'!$K$2:$K$825="Vacant", ROW('Bank Schedule'!$K$2:$K$825)), ROW(13:13))), "") -> 0 | AB16: =IFERROR(INDEX('Bank Schedule'!AB:AB, SMALL(IF('Bank Schedule'!$K$2:$K$825="Vacant", ROW('Bank Schedule'!$K$2:$K$825)), ROW(13:13))), "") -> 0 | AC16: {=IFERROR(INDEX('Bank Schedule'!AC:AC, SMALL(IF('Bank Schedule'!$K$2:$K$825="Vacant", ROW('Bank Schedule'!$K$2:$K$825)), ROW(13:13))), "")} -> No | AD16: {=IFERROR(INDEX('Bank Schedule'!AD:AD, SMALL(IF('Bank Schedule'!$K$2:$K$825="Vacant", ROW('Bank Schedule'!$K$2:$K$825)), ROW(13:13))), "")} -> LEM marketing. | AE16: {=IFERROR(INDEX('Bank Schedule'!AE:AE, SMALL(IF('Bank Schedule'!$K$2:$K$825="Vacant", ROW('Bank Schedule'!$K$2:$K$825)), ROW(13:13))), "")} -> 70 | AF16: {=IFERROR(INDEX('Bank Schedule'!AF:AF, SMALL(IF('Bank Schedule'!$K$2:$K$825="Vacant", ROW('Bank Schedule'!$K$2:$K$825)), ROW(13:13))), "")} -> 6 | AG16: {=IFERROR(INDEX('Bank Schedule'!AG:AG, SMALL(IF('Bank Schedule'!$K$2:$K$825="Vacant", ROW('Bank Schedule'!$K$2:$K$825)), ROW(13:13))), "")} -> 20 | AH16: {=IFERROR(INDEX('Bank Schedule'!AH:AH, SMALL(IF('Bank Schedule'!$K$2:$K$825="Vacant", ROW('Bank Schedule'!$K$2:$K$825)), ROW(13:13))), "")} -> LEM / Savills
A17: =IFERROR(INDEX('Bank Schedule'!A:A, SMALL(IF('Bank Schedule'!$K$2:$K$825="Vacant", ROW('Bank Schedule'!$K$2:$K$825)), ROW(14:14))), "") -> 0 | B17: {=IFERROR(INDEX('Bank Schedule'!B:B, SMALL(IF('Bank Schedule'!$K$2:$K$825="Vacant", ROW('Bank Schedule'!$K$2:$K$825)), ROW(14:14))), "")} -> CD | C17: {=IFERROR(INDEX('Bank Schedule'!C:C, SMALL(IF('Bank Schedule'!$K$2:$K$825="Vacant", ROW('Bank Schedule'!$K$2:$K$825)), ROW(14:14))), "")} -> MEL | D17: {=IFERROR(INDEX('Bank Schedule'!D:D, SMALL(IF('Bank Schedule'!$K$2:$K$825="Vacant", ROW('Bank Schedule'!$K$2:$K$825)), ROW(14:14))), "")} -> 550410 | E17: {=IFERROR(INDEX('Bank Schedule'!E:E, SMALL(IF('Bank Schedule'!$K$2:$K$825="Vacant", ROW('Bank Schedule'!$K$2:$K$825)), ROW(14:14))), "")} -> 19-21 Great Portland Street . | F17: {=IFERROR(INDEX('Bank Schedule'!F:F, SMALL(IF('Bank Schedule'!$K$2:$K$825="Vacant", ROW('Bank Schedule'!$K$2:$K$825)), ROW(14:14))), "")} -> Third Floor | G17: {=IFERROR(INDEX('Bank Schedule'!G:G, SMALL(IF('Bank Schedule'!$K$2:$K$825="Vacant", ROW('Bank Schedule'!$K$2:$K$825)), ROW(14:14))), "")} -> Offices | H17: {=IFERROR(INDEX('Bank Schedule'!H:H, SMALL(IF('Bank Schedule'!$K$2:$K$825="Vacant", ROW('Bank Schedule'!$K$2:$K$825)), ROW(14:14))), "")} -> 2651 | I17: {=IFERROR(INDEX('Bank Schedule'!I:I, SMALL(IF('Bank Schedule'!$K$2:$K$825="Vacant", ROW('Bank Schedule'!$K$2:$K$825)), ROW(14:14))), "")} -> 2651 | J17: {=IFERROR(INDEX('Bank Schedule'!J:J, SMALL(IF('Bank Schedule'!$K$2:$K$825="Vacant", ROW('Bank Schedule'!$K$2:$K$825)), ROW(14:14))), "")} -> 2500 | K17: {=IFERROR(INDEX('Bank Schedule'!K:K, SMALL(IF('Bank Schedule'!$K$2:$K$825="Vacant", ROW('Bank Schedule'!$K$2:$K$825)), ROW(14:14))), "")} -> Vacant | L17: =IFERROR(INDEX('Bank Schedule'!L:L, SMALL(IF('Bank Schedule'!$K$2:$K$825="Vacant", ROW('Bank Schedule'!$K$2:$K$825)), ROW(14:14))), "") -> 45614 | M17: =IFERROR(INDEX('Bank Schedule'!M:M, SMALL(IF('Bank Schedule'!$K$2:$K$825="Vacant", ROW('Bank Schedule'!$K$2:$K$825)), ROW(14:14))), "") -> 46181 | N17: {=IFERROR(INDEX('Bank Schedule'!N:N, SMALL(IF('Bank Schedule'!$K$2:$K$825="Vacant", ROW('Bank Schedule'!$K$2:$K$825)), ROW(14:14))), "")} -> 44124 | O17: =IFERROR(INDEX('Bank Schedule'!O:O, SMALL(IF('Bank Schedule'!$K$2:$K$825="Vacant", ROW('Bank Schedule'!$K$2:$K$825)), ROW(14:14))), "") -> 0 | P17: =IFERROR(INDEX('Bank Schedule'!P:P, SMALL(IF('Bank Schedule'!$K$2:$K$825="Vacant", ROW('Bank Schedule'!$K$2:$K$825)), ROW(14:14))), "") -> 0 | Q17: {=IFERROR(INDEX('Bank Schedule'!Q:Q, SMALL(IF('Bank Schedule'!$K$2:$K$825="Vacant", ROW('Bank Schedule'!$K$2:$K$825)), ROW(14:14))), "")} -> 0 | R17: {=IFERROR(INDEX('Bank Schedule'!R:R, SMALL(IF('Bank Schedule'!$K$2:$K$825="Vacant", ROW('Bank Schedule'!$K$2:$K$825)), ROW(14:14))), "")} -> 0 | S17: =IFERROR(INDEX('Bank Schedule'!S:S, SMALL(IF('Bank Schedule'!$K$2:$K$825="Vacant", ROW('Bank Schedule'!$K$2:$K$825)), ROW(14:14))), "") -> 0 | T17: {=IFERROR(INDEX('Bank Schedule'!T:T, SMALL(IF('Bank Schedule'!$K$2:$K$825="Vacant", ROW('Bank Schedule'!$K$2:$K$825)), ROW(14:14))), "")} -> 172000 | U17: {=IFERROR(INDEX('Bank Schedule'!U:U, SMALL(IF('Bank Schedule'!$K$2:$K$825="Vacant", ROW('Bank Schedule'!$K$2:$K$825)), ROW(14:14))), "")} -> 172000 | V17: {=IFERROR(INDEX('Bank Schedule'!V:V, SMALL(IF('Bank Schedule'!$K$2:$K$825="Vacant", ROW('Bank Schedule'!$K$2:$K$825)), ROW(14:14))), "")} -> 181600 | W17: {=IFERROR(INDEX('Bank Schedule'!W:W, SMALL(IF('Bank Schedule'!$K$2:$K$825="Vacant", ROW('Bank Schedule'!$K$2:$K$825)), ROW(14:14))), "")} -> 181600 | X17: {=IFERROR(INDEX('Bank Schedule'!X:X, SMALL(IF('Bank Schedule'!$K$2:$K$825="Vacant", ROW('Bank Schedule'!$K$2:$K$825)), ROW(14:14))), "")} -> 68.502452 | Y17: {=IFERROR(INDEX('Bank Schedule'!Y:Y, SMALL(IF('Bank Schedule'!$K$2:$K$825="Vacant", ROW('Bank Schedule'!$K$2:$K$825)), ROW(14:14))), "")} -> 0.055813953 | Z17: {=IFERROR(INDEX('Bank Schedule'!Z:Z, SMALL(IF('Bank Schedule'!$K$2:$K$825="Vacant", ROW('Bank Schedule'!$K$2:$K$825)), ROW(14:14))), "")} -> B | AA17: =IFERROR(INDEX('Bank Schedule'!AA:AA, SMALL(IF('Bank Schedule'!$K$2:$K$825="Vacant", ROW('Bank Schedule'!$K$2:$K$825)), ROW(14:14))), "") -> 0 | AB17: =IFERROR(INDEX('Bank Schedule'!AB:AB, SMALL(IF('Bank Schedule'!$K$2:$K$825="Vacant", ROW('Bank Schedule'!$K$2:$K$825)), ROW(14:14))), "") -> 0 | AC17: {=IFERROR(INDEX('Bank Schedule'!AC:AC, SMALL(IF('Bank Schedule'!$K$2:$K$825="Vacant", ROW('Bank Schedule'!$K$2:$K$825)), ROW(14:14))), "")} -> No | AD17: {=IFERROR(INDEX('Bank Schedule'!AD:AD, SMALL(IF('Bank Schedule'!$K$2:$K$825="Vacant", ROW('Bank Schedule'!$K$2:$K$825)), ROW(14:14))), "")} -> LEM marketing. | AE17: {=IFERROR(INDEX('Bank Schedule'!AE:AE, SMALL(IF('Bank Schedule'!$K$2:$K$825="Vacant", ROW('Bank Schedule'!$K$2:$K$825)), ROW(14:14))), "")} -> 72.5 | AF17: {=IFERROR(INDEX('Bank Schedule'!AF:AF, SMALL(IF('Bank Schedule'!$K$2:$K$825="Vacant", ROW('Bank Schedule'!$K$2:$K$825)), ROW(14:14))), "")} -> 6 | AG17: {=IFERROR(INDEX('Bank Schedule'!AG:AG, SMALL(IF('Bank Schedule'!$K$2:$K$825="Vacant", ROW('Bank Schedule'!$K$2:$K$825)), ROW(14:14))), "")} -> 20 | AH17: {=IFERROR(INDEX('Bank Schedule'!AH:AH, SMALL(IF('Bank Schedule'!$K$2:$K$825="Vacant", ROW('Bank Schedule'!$K$2:$K$825)), ROW(14:14))), "")} -> LEM / Savills
A18: =IFERROR(INDEX('Bank Schedule'!A:A, SMALL(IF('Bank Schedule'!$K$2:$K$825="Vacant", ROW('Bank Schedule'!$K$2:$K$825)), ROW(15:15))), "") -> 0 | B18: {=IFERROR(INDEX('Bank Schedule'!B:B, SMALL(IF('Bank Schedule'!$K$2:$K$825="Vacant", ROW('Bank Schedule'!$K$2:$K$825)), ROW(15:15))), "")} -> WS | C18: {=IFERROR(INDEX('Bank Schedule'!C:C, SMALL(IF('Bank Schedule'!$K$2:$K$825="Vacant", ROW('Bank Schedule'!$K$2:$K$825)), ROW(15:15))), "")} -> MEL | D18: {=IFERROR(INDEX('Bank Schedule'!D:D, SMALL(IF('Bank Schedule'!$K$2:$K$825="Vacant", ROW('Bank Schedule'!$K$2:$K$825)), ROW(15:15))), "")} -> 550080 | E18: {=IFERROR(INDEX('Bank Schedule'!E:E, SMALL(IF('Bank Schedule'!$K$2:$K$825="Vacant", ROW('Bank Schedule'!$K$2:$K$825)), ROW(15:15))), "")} -> Highlight House, 22-24 Great Portland Street | F18: {=IFERROR(INDEX('Bank Schedule'!F:F, SMALL(IF('Bank Schedule'!$K$2:$K$825="Vacant", ROW('Bank Schedule'!$K$2:$K$825)), ROW(15:15))), "")} -> First Floor | G18: {=IFERROR(INDEX('Bank Schedule'!G:G, SMALL(IF('Bank Schedule'!$K$2:$K$825="Vacant", ROW('Bank Schedule'!$K$2:$K$825)), ROW(15:15))), "")} -> Office | H18: {=IFERROR(INDEX('Bank Schedule'!H:H, SMALL(IF('Bank Schedule'!$K$2:$K$825="Vacant", ROW('Bank Schedule'!$K$2:$K$825)), ROW(15:15))), "")} -> 1493 | I18: {=IFERROR(INDEX('Bank Schedule'!I:I, SMALL(IF('Bank Schedule'!$K$2:$K$825="Vacant", ROW('Bank Schedule'!$K$2:$K$825)), ROW(15:15))), "")} -> 1493 | J18: {=IFERROR(INDEX('Bank Schedule'!J:J, SMALL(IF('Bank Schedule'!$K$2:$K$825="Vacant", ROW('Bank Schedule'!$K$2:$K$825)), ROW(15:15))), "")} -> 1500 | K18: {=IFERROR(INDEX('Bank Schedule'!K:K, SMALL(IF('Bank Schedule'!$K$2:$K$825="Vacant", ROW('Bank Schedule'!$K$2:$K$825)), ROW(15:15))), "")} -> Vacant | L18: =IFERROR(INDEX('Bank Schedule'!L:L, SMALL(IF('Bank Schedule'!$K$2:$K$825="Vacant", ROW('Bank Schedule'!$K$2:$K$825)), ROW(15:15))), "") -> 0 | M18: =IFERROR(INDEX('Bank Schedule'!M:M, SMALL(IF('Bank Schedule'!$K$2:$K$825="Vacant", ROW('Bank Schedule'!$K$2:$K$825)), ROW(15:15))), "") -> 0 | N18: {=IFERROR(INDEX('Bank Schedule'!N:N, SMALL(IF('Bank Schedule'!$K$2:$K$825="Vacant", ROW('Bank Schedule'!$K$2:$K$825)), ROW(15:15))), "")} -> 43279 | O18: =IFERROR(INDEX('Bank Schedule'!O:O, SMALL(IF('Bank Schedule'!$K$2:$K$825="Vacant", ROW('Bank Schedule'!$K$2:$K$825)), ROW(15:15))), "") -> 0 | P18: =IFERROR(INDEX('Bank Schedule'!P:P, SMALL(IF('Bank Schedule'!$K$2:$K$825="Vacant", ROW('Bank Schedule'!$K$2:$K$825)), ROW(15:15))), "") -> 0 | Q18: {=IFERROR(INDEX('Bank Schedule'!Q:Q, SMALL(IF('Bank Schedule'!$K$2:$K$825="Vacant", ROW('Bank Schedule'!$K$2:$K$825)), ROW(15:15))), "")} -> 0 | R18: {=IFERROR(INDEX('Bank Schedule'!R:R, SMALL(IF('Bank Schedule'!$K$2:$K$825="Vacant", ROW('Bank Schedule'!$K$2:$K$825)), ROW(15:15))), "")} -> 0 | S18: =IFERROR(INDEX('Bank Schedule'!S:S, SMALL(IF('Bank Schedule'!$K$2:$K$825="Vacant", ROW('Bank Schedule'!$K$2:$K$825)), ROW(15:15))), "") -> 0 | T18: {=IFERROR(INDEX('Bank Schedule'!T:T, SMALL(IF('Bank Schedule'!$K$2:$K$825="Vacant", ROW('Bank Schedule'!$K$2:$K$825)), ROW(15:15))), "")} -> 86600 | U18: {=IFERROR(INDEX('Bank Schedule'!U:U, SMALL(IF('Bank Schedule'!$K$2:$K$825="Vacant", ROW('Bank Schedule'!$K$2:$K$825)), ROW(15:15))), "")} -> 86600 | V18: {=IFERROR(INDEX('Bank Schedule'!V:V, SMALL(IF('Bank Schedule'!$K$2:$K$825="Vacant", ROW('Bank Schedule'!$K$2:$K$825)), ROW(15:15))), "")} -> 93300 | W18: {=IFERROR(INDEX('Bank Schedule'!W:W, SMALL(IF('Bank Schedule'!$K$2:$K$825="Vacant", ROW('Bank Schedule'!$K$2:$K$825)), ROW(15:15))), "")} -> 93300 | X18: {=IFERROR(INDEX('Bank Schedule'!X:X, SMALL(IF('Bank Schedule'!$K$2:$K$825="Vacant", ROW('Bank Schedule'!$K$2:$K$825)), ROW(15:15))), "")} -> 62.491628 | Y18: {=IFERROR(INDEX('Bank Schedule'!Y:Y, SMALL(IF('Bank Schedule'!$K$2:$K$825="Vacant", ROW('Bank Schedule'!$K$2:$K$825)), ROW(15:15))), "")} -> 0.077367206 | Z18: {=IFERROR(INDEX('Bank Schedule'!Z:Z, SMALL(IF('Bank Schedule'!$K$2:$K$825="Vacant", ROW('Bank Schedule'!$K$2:$K$825)), ROW(15:15))), "")} -> D | AA18: =IFERROR(INDEX('Bank Schedule'!AA:AA, SMALL(IF('Bank Schedule'!$K$2:$K$825="Vacant", ROW('Bank Schedule'!$K$2:$K$825)), ROW(15:15))), "") -> 0 | AB18: =IFERROR(INDEX('Bank Schedule'!AB:AB, SMALL(IF('Bank Schedule'!$K$2:$K$825="Vacant", ROW('Bank Schedule'!$K$2:$K$825)), ROW(15:15))), "") -> 0 | AC18: {=IFERROR(INDEX('Bank Schedule'!AC:AC, SMALL(IF('Bank Schedule'!$K$2:$K$825="Vacant", ROW('Bank Schedule'!$K$2:$K$825)), ROW(15:15))), "")} -> No | AD18: {=IFERROR(INDEX('Bank Schedule'!AD:AD, SMALL(IF('Bank Schedule'!$K$2:$K$825="Vacant", ROW('Bank Schedule'!$K$2:$K$825)), ROW(15:15))), "")} -> Mothballed. | AE18: =IFERROR(INDEX('Bank Schedule'!AE:AE, SMALL(IF('Bank Schedule'!$K$2:$K$825="Vacant", ROW('Bank Schedule'!$K$2:$K$825)), ROW(15:15))), "") -> 0 | AF18: =IFERROR(INDEX('Bank Schedule'!AF:AF, SMALL(IF('Bank Schedule'!$K$2:$K$825="Vacant", ROW('Bank Schedule'!$K$2:$K$825)), ROW(15:15))), "") -> 2 | AG18: {=IFERROR(INDEX('Bank Schedule'!AG:AG, SMALL(IF('Bank Schedule'!$K$2:$K$825="Vacant", ROW('Bank Schedule'!$K$2:$K$825)), ROW(15:15))), "")} -> 2 | AH18: =IFERROR(INDEX('Bank Schedule'!AH:AH, SMALL(IF('Bank Schedule'!$K$2:$K$825="Vacant", ROW('Bank Schedule'!$K$2:$K$825)), ROW(15:15))), "") -> 0
A19: =IFERROR(INDEX('Bank Schedule'!A:A, SMALL(IF('Bank Schedule'!$K$2:$K$825="Vacant", ROW('Bank Schedule'!$K$2:$K$825)), ROW(16:16))), "") | B19: {=IFERROR(INDEX('Bank Schedule'!B:B, SMALL(IF('Bank Schedule'!$K$2:$K$825="Vacant", ROW('Bank Schedule'!$K$2:$K$825)), ROW(16:16))), "")} -> WS | C19: {=IFERROR(INDEX('Bank Schedule'!C:C, SMALL(IF('Bank Schedule'!$K$2:$K$825="Vacant", ROW('Bank Schedule'!$K$2:$K$825)), ROW(16:16))), "")} -> MEL | D19: {=IFERROR(INDEX('Bank Schedule'!D:D, SMALL(IF('Bank Schedule'!$K$2:$K$825="Vacant", ROW('Bank Schedule'!$K$2:$K$825)), ROW(16:16))), "")} -> 550080 | E19: {=IFERROR(INDEX('Bank Schedule'!E:E, SMALL(IF('Bank Schedule'!$K$2:$K$825="Vacant", ROW('Bank Schedule'!$K$2:$K$825)), ROW(16:16))), "")} -> Highlight House, 22-24 Great Portland Street | F19: {=IFERROR(INDEX('Bank Schedule'!F:F, SMALL(IF('Bank Schedule'!$K$2:$K$825="Vacant", ROW('Bank Schedule'!$K$2:$K$825)), ROW(16:16))), "")} -> Second Floor | G19: {=IFERROR(INDEX('Bank Schedule'!G:G, SMALL(IF('Bank Schedule'!$K$2:$K$825="Vacant", ROW('Bank Schedule'!$K$2:$K$825)), ROW(16:16))), "")} -> Office | H19: {=IFERROR(INDEX('Bank Schedule'!H:H, SMALL(IF('Bank Schedule'!$K$2:$K$825="Vacant", ROW('Bank Schedule'!$K$2:$K$825)), ROW(16:16))), "")} -> 1503 | I19: {=IFERROR(INDEX('Bank Schedule'!I:I, SMALL(IF('Bank Schedule'!$K$2:$K$825="Vacant", ROW('Bank Schedule'!$K$2:$K$825)), ROW(16:16))), "")} -> 1503 | J19: {=IFERROR(INDEX('Bank Schedule'!J:J, SMALL(IF('Bank Schedule'!$K$2:$K$825="Vacant", ROW('Bank Schedule'!$K$2:$K$825)), ROW(16:16))), "")} -> 1500 | K19: {=IFERROR(INDEX('Bank Schedule'!K:K, SMALL(IF('Bank Schedule'!$K$2:$K$825="Vacant", ROW('Bank Schedule'!$K$2:$K$825)), ROW(16:16))), "")} -> Vacant | L19: =IFERROR(INDEX('Bank Schedule'!L:L, SMALL(IF('Bank Schedule'!$K$2:$K$825="Vacant", ROW('Bank Schedule'!$K$2:$K$825)), ROW(16:16))), "") | M19: =IFERROR(INDEX('Bank Schedule'!M:M, SMALL(IF('Bank Schedule'!$K$2:$K$825="Vacant", ROW('Bank Schedule'!$K$2:$K$825)), ROW(16:16))), "") | N19: {=IFERROR(INDEX('Bank Schedule'!N:N, SMALL(IF('Bank Schedule'!$K$2:$K$825="Vacant", ROW('Bank Schedule'!$K$2:$K$825)), ROW(16:16))), "")} -> 43354 | O19: =IFERROR(INDEX('Bank Schedule'!O:O, SMALL(IF('Bank Schedule'!$K$2:$K$825="Vacant", ROW('Bank Schedule'!$K$2:$K$825)), ROW(16:16))), "") | P19: =IFERROR(INDEX('Bank Schedule'!P:P, SMALL(IF('Bank Schedule'!$K$2:$K$825="Vacant", ROW('Bank Schedule'!$K$2:$K$825)), ROW(16:16))), "") | Q19: {=IFERROR(INDEX('Bank Schedule'!Q:Q, SMALL(IF('Bank Schedule'!$K$2:$K$825="Vacant", ROW('Bank Schedule'!$K$2:$K$825)), ROW(16:16))), "")} -> 0 | R19: {=IFERROR(INDEX('Bank Schedule'!R:R, SMALL(IF('Bank Schedule'!$K$2:$K$825="Vacant", ROW('Bank Schedule'!$K$2:$K$825)), ROW(16:16))), "")} -> 0 | S19: =IFERROR(INDEX('Bank Schedule'!S:S, SMALL(IF('Bank Schedule'!$K$2:$K$825="Vacant", ROW('Bank Schedule'!$K$2:$K$825)), ROW(16:16))), "") | T19: {=IFERROR(INDEX('Bank Schedule'!T:T, SMALL(IF('Bank Schedule'!$K$2:$K$825="Vacant", ROW('Bank Schedule'!$K$2:$K$825)), ROW(16:16))), "")} -> 88100 | U19: {=IFERROR(INDEX('Bank Schedule'!U:U, SMALL(IF('Bank Schedule'!$K$2:$K$825="Vacant", ROW('Bank Schedule'!$K$2:$K$825)), ROW(16:16))), "")} -> 88100 | V19: {=IFERROR(INDEX('Bank Schedule'!V:V, SMALL(IF('Bank Schedule'!$K$2:$K$825="Vacant", ROW('Bank Schedule'!$K$2:$K$825)), ROW(16:16))), "")} -> 93900 | W19: {=IFERROR(INDEX('Bank Schedule'!W:W, SMALL(IF('Bank Schedule'!$K$2:$K$825="Vacant", ROW('Bank Schedule'!$K$2:$K$825)), ROW(16:16))), "")} -> 93900 | X19: {=IFERROR(INDEX('Bank Schedule'!X:X, SMALL(IF('Bank Schedule'!$K$2:$K$825="Vacant", ROW('Bank Schedule'!$K$2:$K$825)), ROW(16:16))), "")} -> 62.47505 | Y19: {=IFERROR(INDEX('Bank Schedule'!Y:Y, SMALL(IF('Bank Schedule'!$K$2:$K$825="Vacant", ROW('Bank Schedule'!$K$2:$K$825)), ROW(16:16))), "")} -> 0.065834279 | Z19: {=IFERROR(INDEX('Bank Schedule'!Z:Z, SMALL(IF('Bank Schedule'!$K$2:$K$825="Vacant", ROW('Bank Schedule'!$K$2:$K$825)), ROW(16:16))), "")} -> D | AA19: =IFERROR(INDEX('Bank Schedule'!AA:AA, SMALL(IF('Bank Schedule'!$K$2:$K$825="Vacant", ROW('Bank Schedule'!$K$2:$K$825)), ROW(16:16))), "") | AB19: =IFERROR(INDEX('Bank Schedule'!AB:AB, SMALL(IF('Bank Schedule'!$K$2:$K$825="Vacant", ROW('Bank Schedule'!$K$2:$K$825)), ROW(16:16))), "") | AC19: {=IFERROR(INDEX('Bank Schedule'!AC:AC, SMALL(IF('Bank Schedule'!$K$2:$K$825="Vacant", ROW('Bank Schedule'!$K$2:$K$825)), ROW(16:16))), "")} -> No | AD19: {=IFERROR(INDEX('Bank Schedule'!AD:AD, SMALL(IF('Bank Schedule'!$K$2:$K$825="Vacant", ROW('Bank Schedule'!$K$2:$K$825)), ROW(16:16))), "")} -> Mothballed. | AE19: =IFERROR(INDEX('Bank Schedule'!AE:AE, SMALL(IF('Bank Schedule'!$K$2:$K$825="Vacant", ROW('Bank Schedule'!$K$2:$K$825)), ROW(16:16))), "") | AF19: =IFERROR(INDEX('Bank Schedule'!AF:AF, SMALL(IF('Bank Schedule'!$K$2:$K$825="Vacant", ROW('Bank Schedule'!$K$2:$K$825)), ROW(16:16))), "") | AG19: {=IFERROR(INDEX('Bank Schedule'!AG:AG, SMALL(IF('Bank Schedule'!$K$2:$K$825="Vacant", ROW('Bank Schedule'!$K$2:$K$825)), ROW(16:16))), "")} -> 2 | AH19: =IFERROR(INDEX('Bank Schedule'!AH:AH, SMALL(IF('Bank Schedule'!$K$2:$K$825="Vacant", ROW('Bank Schedule'!$K$2:$K$825)), ROW(16:16))), "")
A20: =IFERROR(INDEX('Bank Schedule'!A:A, SMALL(IF('Bank Schedule'!$K$2:$K$825="Vacant", ROW('Bank Schedule'!$K$2:$K$825)), ROW(17:17))), "") | B20: {=IFERROR(INDEX('Bank Schedule'!B:B, SMALL(IF('Bank Schedule'!$K$2:$K$825="Vacant", ROW('Bank Schedule'!$K$2:$K$825)), ROW(17:17))), "")} -> WS | C20: {=IFERROR(INDEX('Bank Schedule'!C:C, SMALL(IF('Bank Schedule'!$K$2:$K$825="Vacant", ROW('Bank Schedule'!$K$2:$K$825)), ROW(17:17))), "")} -> MEL | D20: {=IFERROR(INDEX('Bank Schedule'!D:D, SMALL(IF('Bank Schedule'!$K$2:$K$825="Vacant", ROW('Bank Schedule'!$K$2:$K$825)), ROW(17:17))), "")} -> 550080 | E20: {=IFERROR(INDEX('Bank Schedule'!E:E, SMALL(IF('Bank Schedule'!$K$2:$K$825="Vacant", ROW('Bank Schedule'!$K$2:$K$825)), ROW(17:17))), "")} -> Highlight House, 22-24 Great Portland Street | F20: {=IFERROR(INDEX('Bank Schedule'!F:F, SMALL(IF('Bank Schedule'!$K$2:$K$825="Vacant", ROW('Bank Schedule'!$K$2:$K$825)), ROW(17:17))), "")} -> Third Floor | G20: {=IFERROR(INDEX('Bank Schedule'!G:G, SMALL(IF('Bank Schedule'!$K$2:$K$825="Vacant", ROW('Bank Schedule'!$K$2:$K$825)), ROW(17:17))), "")} -> Office | H20: {=IFERROR(INDEX('Bank Schedule'!H:H, SMALL(IF('Bank Schedule'!$K$2:$K$825="Vacant", ROW('Bank Schedule'!$K$2:$K$825)), ROW(17:17))), "")} -> 1519 | I20: {=IFERROR(INDEX('Bank Schedule'!I:I, SMALL(IF('Bank Schedule'!$K$2:$K$825="Vacant", ROW('Bank Schedule'!$K$2:$K$825)), ROW(17:17))), "")} -> 1519 | J20: {=IFERROR(INDEX('Bank Schedule'!J:J, SMALL(IF('Bank Schedule'!$K$2:$K$825="Vacant", ROW('Bank Schedule'!$K$2:$K$825)), ROW(17:17))), "")} -> 1500 | K20: {=IFERROR(INDEX('Bank Schedule'!K:K, SMALL(IF('Bank Schedule'!$K$2:$K$825="Vacant", ROW('Bank Schedule'!$K$2:$K$825)), ROW(17:17))), "")} -> Vacant | L20: =IFERROR(INDEX('Bank Schedule'!L:L, SMALL(IF('Bank Schedule'!$K$2:$K$825="Vacant", ROW('Bank Schedule'!$K$2:$K$825)), ROW(17:17))), "") | M20: =IFERROR(INDEX('Bank Schedule'!M:M, SMALL(IF('Bank Schedule'!$K$2:$K$825="Vacant", ROW('Bank Schedule'!$K$2:$K$825)), ROW(17:17))), "") | N20: {=IFERROR(INDEX('Bank Schedule'!N:N, SMALL(IF('Bank Schedule'!$K$2:$K$825="Vacant", ROW('Bank Schedule'!$K$2:$K$825)), ROW(17:17))), "")} -> 43354 | O20: =IFERROR(INDEX('Bank Schedule'!O:O, SMALL(IF('Bank Schedule'!$K$2:$K$825="Vacant", ROW('Bank Schedule'!$K$2:$K$825)), ROW(17:17))), "") | P20: =IFERROR(INDEX('Bank Schedule'!P:P, SMALL(IF('Bank Schedule'!$K$2:$K$825="Vacant", ROW('Bank Schedule'!$K$2:$K$825)), ROW(17:17))), "") | Q20: {=IFERROR(INDEX('Bank Schedule'!Q:Q, SMALL(IF('Bank Schedule'!$K$2:$K$825="Vacant", ROW('Bank Schedule'!$K$2:$K$825)), ROW(17:17))), "")} -> 0 | R20: {=IFERROR(INDEX('Bank Schedule'!R:R, SMALL(IF('Bank Schedule'!$K$2:$K$825="Vacant", ROW('Bank Schedule'!$K$2:$K$825)), ROW(17:17))), "")} -> 0 | S20: =IFERROR(INDEX('Bank Schedule'!S:S, SMALL(IF('Bank Schedule'!$K$2:$K$825="Vacant", ROW('Bank Schedule'!$K$2:$K$825)), ROW(17:17))), "") | T20: {=IFERROR(INDEX('Bank Schedule'!T:T, SMALL(IF('Bank Schedule'!$K$2:$K$825="Vacant", ROW('Bank Schedule'!$K$2:$K$825)), ROW(17:17))), "")} -> 83100 | U20: {=IFERROR(INDEX('Bank Schedule'!U:U, SMALL(IF('Bank Schedule'!$K$2:$K$825="Vacant", ROW('Bank Schedule'!$K$2:$K$825)), ROW(17:17))), "")} -> 83100 | V20: {=IFERROR(INDEX('Bank Schedule'!V:V, SMALL(IF('Bank Schedule'!$K$2:$K$825="Vacant", ROW('Bank Schedule'!$K$2:$K$825)), ROW(17:17))), "")} -> 91100 | W20: {=IFERROR(INDEX('Bank Schedule'!W:W, SMALL(IF('Bank Schedule'!$K$2:$K$825="Vacant", ROW('Bank Schedule'!$K$2:$K$825)), ROW(17:17))), "")} -> 91100 | X20: {=IFERROR(INDEX('Bank Schedule'!X:X, SMALL(IF('Bank Schedule'!$K$2:$K$825="Vacant", ROW('Bank Schedule'!$K$2:$K$825)), ROW(17:17))), "")} -> 59.973667 | Y20: {=IFERROR(INDEX('Bank Schedule'!Y:Y, SMALL(IF('Bank Schedule'!$K$2:$K$825="Vacant", ROW('Bank Schedule'!$K$2:$K$825)), ROW(17:17))), "")} -> 0.096269555 | Z20: {=IFERROR(INDEX('Bank Schedule'!Z:Z, SMALL(IF('Bank Schedule'!$K$2:$K$825="Vacant", ROW('Bank Schedule'!$K$2:$K$825)), ROW(17:17))), "")} -> D | AA20: =IFERROR(INDEX('Bank Schedule'!AA:AA, SMALL(IF('Bank Schedule'!$K$2:$K$825="Vacant", ROW('Bank Schedule'!$K$2:$K$825)), ROW(17:17))), "") | AB20: =IFERROR(INDEX('Bank Schedule'!AB:AB, SMALL(IF('Bank Schedule'!$K$2:$K$825="Vacant", ROW('Bank Schedule'!$K$2:$K$825)), ROW(17:17))), "") | AC20: {=IFERROR(INDEX('Bank Schedule'!AC:AC, SMALL(IF('Bank Schedule'!$K$2:$K$825="Vacant", ROW('Bank Schedule'!$K$2:$K$825)), ROW(17:17))), "")} -> No | AD20: {=IFERROR(INDEX('Bank Schedule'!AD:AD, SMALL(IF('Bank Schedule'!$K$2:$K$825="Vacant", ROW('Bank Schedule'!$K$2:$K$825)), ROW(17:17))), "")} -> Mothballed. | AE20: =IFERROR(INDEX('Bank Schedule'!AE:AE, SMALL(IF('Bank Schedule'!$K$2:$K$825="Vacant", ROW('Bank Schedule'!$K$2:$K$825)), ROW(17:17))), "") | AF20: =IFERROR(INDEX('Bank Schedule'!AF:AF, SMALL(IF('Bank Schedule'!$K$2:$K$825="Vacant", ROW('Bank Schedule'!$K$2:$K$825)), ROW(17:17))), "") | AG20: {=IFERROR(INDEX('Bank Schedule'!AG:AG, SMALL(IF('Bank Schedule'!$K$2:$K$825="Vacant", ROW('Bank Schedule'!$K$2:$K$825)), ROW(17:17))), "")} -> 2 | AH20: =IFERROR(INDEX('Bank Schedule'!AH:AH, SMALL(IF('Bank Schedule'!$K$2:$K$825="Vacant", ROW('Bank Schedule'!$K$2:$K$825)), ROW(17:17))), "")
A21: =IFERROR(INDEX('Bank Schedule'!A:A, SMALL(IF('Bank Schedule'!$K$2:$K$825="Vacant", ROW('Bank Schedule'!$K$2:$K$825)), ROW(18:18))), "") | B21: {=IFERROR(INDEX('Bank Schedule'!B:B, SMALL(IF('Bank Schedule'!$K$2:$K$825="Vacant", ROW('Bank Schedule'!$K$2:$K$825)), ROW(18:18))), "")} -> WS | C21: {=IFERROR(INDEX('Bank Schedule'!C:C, SMALL(IF('Bank Schedule'!$K$2:$K$825="Vacant", ROW('Bank Schedule'!$K$2:$K$825)), ROW(18:18))), "")} -> MEL | D21: {=IFERROR(INDEX('Bank Schedule'!D:D, SMALL(IF('Bank Schedule'!$K$2:$K$825="Vacant", ROW('Bank Schedule'!$K$2:$K$825)), ROW(18:18))), "")} -> 550080 | E21: {=IFERROR(INDEX('Bank Schedule'!E:E, SMALL(IF('Bank Schedule'!$K$2:$K$825="Vacant", ROW('Bank Schedule'!$K$2:$K$825)), ROW(18:18))), "")} -> Highlight House, 22-24 Great Portland Street | F21: {=IFERROR(INDEX('Bank Schedule'!F:F, SMALL(IF('Bank Schedule'!$K$2:$K$825="Vacant", ROW('Bank Schedule'!$K$2:$K$825)), ROW(18:18))), "")} -> Fourth Floor | G21: {=IFERROR(INDEX('Bank Schedule'!G:G, SMALL(IF('Bank Schedule'!$K$2:$K$825="Vacant", ROW('Bank Schedule'!$K$2:$K$825)), ROW(18:18))), "")} -> Office | H21: {=IFERROR(INDEX('Bank Schedule'!H:H, SMALL(IF('Bank Schedule'!$K$2:$K$825="Vacant", ROW('Bank Schedule'!$K$2:$K$825)), ROW(18:18))), "")} -> 1505 | I21: {=IFERROR(INDEX('Bank Schedule'!I:I, SMALL(IF('Bank Schedule'!$K$2:$K$825="Vacant", ROW('Bank Schedule'!$K$2:$K$825)), ROW(18:18))), "")} -> 1505 | J21: {=IFERROR(INDEX('Bank Schedule'!J:J, SMALL(IF('Bank Schedule'!$K$2:$K$825="Vacant", ROW('Bank Schedule'!$K$2:$K$825)), ROW(18:18))), "")} -> 1500 | K21: {=IFERROR(INDEX('Bank Schedule'!K:K, SMALL(IF('Bank Schedule'!$K$2:$K$825="Vacant", ROW('Bank Schedule'!$K$2:$K$825)), ROW(18:18))), "")} -> Vacant | L21: =IFERROR(INDEX('Bank Schedule'!L:L, SMALL(IF('Bank Schedule'!$K$2:$K$825="Vacant", ROW('Bank Schedule'!$K$2:$K$825)), ROW(18:18))), "") | M21: =IFERROR(INDEX('Bank Schedule'!M:M, SMALL(IF('Bank Schedule'!$K$2:$K$825="Vacant", ROW('Bank Schedule'!$K$2:$K$825)), ROW(18:18))), "") | N21: {=IFERROR(INDEX('Bank Schedule'!N:N, SMALL(IF('Bank Schedule'!$K$2:$K$825="Vacant", ROW('Bank Schedule'!$K$2:$K$825)), ROW(18:18))), "")} -> 43354 | O21: =IFERROR(INDEX('Bank Schedule'!O:O, SMALL(IF('Bank Schedule'!$K$2:$K$825="Vacant", ROW('Bank Schedule'!$K$2:$K$825)), ROW(18:18))), "") | P21: =IFERROR(INDEX('Bank Schedule'!P:P, SMALL(IF('Bank Schedule'!$K$2:$K$825="Vacant", ROW('Bank Schedule'!$K$2:$K$825)), ROW(18:18))), "") | Q21: {=IFERROR(INDEX('Bank Schedule'!Q:Q, SMALL(IF('Bank Schedule'!$K$2:$K$825="Vacant", ROW('Bank Schedule'!$K$2:$K$825)), ROW(18:18))), "")} -> 0 | R21: {=IFERROR(INDEX('Bank Schedule'!R:R, SMALL(IF('Bank Schedule'!$K$2:$K$825="Vacant", ROW('Bank Schedule'!$K$2:$K$825)), ROW(18:18))), "")} -> 0 | S21: =IFERROR(INDEX('Bank Schedule'!S:S, SMALL(IF('Bank Schedule'!$K$2:$K$825="Vacant", ROW('Bank Schedule'!$K$2:$K$825)), ROW(18:18))), "") | T21: {=IFERROR(INDEX('Bank Schedule'!T:T, SMALL(IF('Bank Schedule'!$K$2:$K$825="Vacant", ROW('Bank Schedule'!$K$2:$K$825)), ROW(18:18))), "")} -> 83800 | U21: {=IFERROR(INDEX('Bank Schedule'!U:U, SMALL(IF('Bank Schedule'!$K$2:$K$825="Vacant", ROW('Bank Schedule'!$K$2:$K$825)), ROW(18:18))), "")} -> 83800 | V21: {=IFERROR(INDEX('Bank Schedule'!V:V, SMALL(IF('Bank Schedule'!$K$2:$K$825="Vacant", ROW('Bank Schedule'!$K$2:$K$825)), ROW(18:18))), "")} -> 90300 | W21: {=IFERROR(INDEX('Bank Schedule'!W:W, SMALL(IF('Bank Schedule'!$K$2:$K$825="Vacant", ROW('Bank Schedule'!$K$2:$K$825)), ROW(18:18))), "")} -> 90300 | X21: {=IFERROR(INDEX('Bank Schedule'!X:X, SMALL(IF('Bank Schedule'!$K$2:$K$825="Vacant", ROW('Bank Schedule'!$K$2:$K$825)), ROW(18:18))), "")} -> 60 | Y21: {=IFERROR(INDEX('Bank Schedule'!Y:Y, SMALL(IF('Bank Schedule'!$K$2:$K$825="Vacant", ROW('Bank Schedule'!$K$2:$K$825)), ROW(18:18))), "")} -> 0.077565632 | Z21: {=IFERROR(INDEX('Bank Schedule'!Z:Z, SMALL(IF('Bank Schedule'!$K$2:$K$825="Vacant", ROW('Bank Schedule'!$K$2:$K$825)), ROW(18:18))), "")} -> D | AA21: =IFERROR(INDEX('Bank Schedule'!AA:AA, SMALL(IF('Bank Schedule'!$K$2:$K$825="Vacant", ROW('Bank Schedule'!$K$2:$K$825)), ROW(18:18))), "") | AB21: =IFERROR(INDEX('Bank Schedule'!AB:AB, SMALL(IF('Bank Schedule'!$K$2:$K$825="Vacant", ROW('Bank Schedule'!$K$2:$K$825)), ROW(18:18))), "") | AC21: {=IFERROR(INDEX('Bank Schedule'!AC:AC, SMALL(IF('Bank Schedule'!$K$2:$K$825="Vacant", ROW('Bank Schedule'!$K$2:$K$825)), ROW(18:18))), "")} -> No | AD21: {=IFERROR(INDEX('Bank Schedule'!AD:AD, SMALL(IF('Bank Schedule'!$K$2:$K$825="Vacant", ROW('Bank Schedule'!$K$2:$K$825)), ROW(18:18))), "")} -> Mothballed. | AE21: =IFERROR(INDEX('Bank Schedule'!AE:AE, SMALL(IF('Bank Schedule'!$K$2:$K$825="Vacant", ROW('Bank Schedule'!$K$2:$K$825)), ROW(18:18))), "") | AF21: =IFERROR(INDEX('Bank Schedule'!AF:AF, SMALL(IF('Bank Schedule'!$K$2:$K$825="Vacant", ROW('Bank Schedule'!$K$2:$K$825)), ROW(18:18))), "") | AG21: {=IFERROR(INDEX('Bank Schedule'!AG:AG, SMALL(IF('Bank Schedule'!$K$2:$K$825="Vacant", ROW('Bank Schedule'!$K$2:$K$825)), ROW(18:18))), "")} -> 2 | AH21: =IFERROR(INDEX('Bank Schedule'!AH:AH, SMALL(IF('Bank Schedule'!$K$2:$K$825="Vacant", ROW('Bank Schedule'!$K$2:$K$825)), ROW(18:18))), "")
A22: =IFERROR(INDEX('Bank Schedule'!A:A, SMALL(IF('Bank Schedule'!$K$2:$K$825="Vacant", ROW('Bank Schedule'!$K$2:$K$825)), ROW(19:19))), "") -> 0 | B22: {=IFERROR(INDEX('Bank Schedule'!B:B, SMALL(IF('Bank Schedule'!$K$2:$K$825="Vacant", ROW('Bank Schedule'!$K$2:$K$825)), ROW(19:19))), "")} -> CM | C22: {=IFERROR(INDEX('Bank Schedule'!C:C, SMALL(IF('Bank Schedule'!$K$2:$K$825="Vacant", ROW('Bank Schedule'!$K$2:$K$825)), ROW(19:19))), "")} -> MEL | D22: {=IFERROR(INDEX('Bank Schedule'!D:D, SMALL(IF('Bank Schedule'!$K$2:$K$825="Vacant", ROW('Bank Schedule'!$K$2:$K$825)), ROW(19:19))), "")} -> 550830 | E22: {=IFERROR(INDEX('Bank Schedule'!E:E, SMALL(IF('Bank Schedule'!$K$2:$K$825="Vacant", ROW('Bank Schedule'!$K$2:$K$825)), ROW(19:19))), "")} -> 42-48 Great Portland Street | F22: {=IFERROR(INDEX('Bank Schedule'!F:F, SMALL(IF('Bank Schedule'!$K$2:$K$825="Vacant", ROW('Bank Schedule'!$K$2:$K$825)), ROW(19:19))), "")} -> Second Floor | G22: {=IFERROR(INDEX('Bank Schedule'!G:G, SMALL(IF('Bank Schedule'!$K$2:$K$825="Vacant", ROW('Bank Schedule'!$K$2:$K$825)), ROW(19:19))), "")} -> Office | H22: {=IFERROR(INDEX('Bank Schedule'!H:H, SMALL(IF('Bank Schedule'!$K$2:$K$825="Vacant", ROW('Bank Schedule'!$K$2:$K$825)), ROW(19:19))), "")} -> 1440 | I22: {=IFERROR(INDEX('Bank Schedule'!I:I, SMALL(IF('Bank Schedule'!$K$2:$K$825="Vacant", ROW('Bank Schedule'!$K$2:$K$825)), ROW(19:19))), "")} -> 1440 | J22: {=IFERROR(INDEX('Bank Schedule'!J:J, SMALL(IF('Bank Schedule'!$K$2:$K$825="Vacant", ROW('Bank Schedule'!$K$2:$K$825)), ROW(19:19))), "")} -> 1500 | K22: {=IFERROR(INDEX('Bank Schedule'!K:K, SMALL(IF('Bank Schedule'!$K$2:$K$825="Vacant", ROW('Bank Schedule'!$K$2:$K$825)), ROW(19:19))), "")} -> Vacant | L22: =IFERROR(INDEX('Bank Schedule'!L:L, SMALL(IF('Bank Schedule'!$K$2:$K$825="Vacant", ROW('Bank Schedule'!$K$2:$K$825)), ROW(19:19))), "") -> 45100 | M22: =IFERROR(INDEX('Bank Schedule'!M:M, SMALL(IF('Bank Schedule'!$K$2:$K$825="Vacant", ROW('Bank Schedule'!$K$2:$K$825)), ROW(19:19))), "") -> 46926 | N22: {=IFERROR(INDEX('Bank Schedule'!N:N, SMALL(IF('Bank Schedule'!$K$2:$K$825="Vacant", ROW('Bank Schedule'!$K$2:$K$825)), ROW(19:19))), "")} -> 44593 | O22: =IFERROR(INDEX('Bank Schedule'!O:O, SMALL(IF('Bank Schedule'!$K$2:$K$825="Vacant", ROW('Bank Schedule'!$K$2:$K$825)), ROW(19:19))), "") -> 0 | P22: =IFERROR(INDEX('Bank Schedule'!P:P, SMALL(IF('Bank Schedule'!$K$2:$K$825="Vacant", ROW('Bank Schedule'!$K$2:$K$825)), ROW(19:19))), "") -> 46195 | Q22: {=IFERROR(INDEX('Bank Schedule'!Q:Q, SMALL(IF('Bank Schedule'!$K$2:$K$825="Vacant", ROW('Bank Schedule'!$K$2:$K$825)), ROW(19:19))), "")} -> 0 | R22: {=IFERROR(INDEX('Bank Schedule'!R:R, SMALL(IF('Bank Schedule'!$K$2:$K$825="Vacant", ROW('Bank Schedule'!$K$2:$K$825)), ROW(19:19))), "")} -> 0 | S22: =IFERROR(INDEX('Bank Schedule'!S:S, SMALL(IF('Bank Schedule'!$K$2:$K$825="Vacant", ROW('Bank Schedule'!$K$2:$K$825)), ROW(19:19))), "") -> 0 | T22: {=IFERROR(INDEX('Bank Schedule'!T:T, SMALL(IF('Bank Schedule'!$K$2:$K$825="Vacant", ROW('Bank Schedule'!$K$2:$K$825)), ROW(19:19))), "")} -> 79800 | U22: {=IFERROR(INDEX('Bank Schedule'!U:U, SMALL(IF('Bank Schedule'!$K$2:$K$825="Vacant", ROW('Bank Schedule'!$K$2:$K$825)), ROW(19:19))), "")} -> 79800 | V22: {=IFERROR(INDEX('Bank Schedule'!V:V, SMALL(IF('Bank Schedule'!$K$2:$K$825="Vacant", ROW('Bank Schedule'!$K$2:$K$825)), ROW(19:19))), "")} -> 93600 | W22: {=IFERROR(INDEX('Bank Schedule'!W:W, SMALL(IF('Bank Schedule'!$K$2:$K$825="Vacant", ROW('Bank Schedule'!$K$2:$K$825)), ROW(19:19))), "")} -> 93600 | X22: {=IFERROR(INDEX('Bank Schedule'!X:X, SMALL(IF('Bank Schedule'!$K$2:$K$825="Vacant", ROW('Bank Schedule'!$K$2:$K$825)), ROW(19:19))), "")} -> 65 | Y22: {=IFERROR(INDEX('Bank Schedule'!Y:Y, SMALL(IF('Bank Schedule'!$K$2:$K$825="Vacant", ROW('Bank Schedule'!$K$2:$K$825)), ROW(19:19))), "")} -> 0.17293233 | Z22: {=IFERROR(INDEX('Bank Schedule'!Z:Z, SMALL(IF('Bank Schedule'!$K$2:$K$825="Vacant", ROW('Bank Schedule'!$K$2:$K$825)), ROW(19:19))), "")} -> D | AA22: =IFERROR(INDEX('Bank Schedule'!AA:AA, SMALL(IF('Bank Schedule'!$K$2:$K$825="Vacant", ROW('Bank Schedule'!$K$2:$K$825)), ROW(19:19))), "") -> 0 | AB22: =IFERROR(INDEX('Bank Schedule'!AB:AB, SMALL(IF('Bank Schedule'!$K$2:$K$825="Vacant", ROW('Bank Schedule'!$K$2:$K$825)), ROW(19:19))), "") -> 0 | AC22: {=IFERROR(INDEX('Bank Schedule'!AC:AC, SMALL(IF('Bank Schedule'!$K$2:$K$825="Vacant", ROW('Bank Schedule'!$K$2:$K$825)), ROW(19:19))), "")} -> No | AD22: {=IFERROR(INDEX('Bank Schedule'!AD:AD, SMALL(IF('Bank Schedule'!$K$2:$K$825="Vacant", ROW('Bank Schedule'!$K$2:$K$825)), ROW(19:19))), "")} -> To be refurbished. | AE22: =IFERROR(INDEX('Bank Schedule'!AE:AE, SMALL(IF('Bank Schedule'!$K$2:$K$825="Vacant", ROW('Bank Schedule'!$K$2:$K$825)), ROW(19:19))), "") -> 0 | AF22: =IFERROR(INDEX('Bank Schedule'!AF:AF, SMALL(IF('Bank Schedule'!$K$2:$K$825="Vacant", ROW('Bank Schedule'!$K$2:$K$825)), ROW(19:19))), "") -> 0 | AG22: =IFERROR(INDEX('Bank Schedule'!AG:AG, SMALL(IF('Bank Schedule'!$K$2:$K$825="Vacant", ROW('Bank Schedule'!$K$2:$K$825)), ROW(19:19))), "") -> 0 | AH22: =IFERROR(INDEX('Bank Schedule'!AH:AH, SMALL(IF('Bank Schedule'!$K$2:$K$825="Vacant", ROW('Bank Schedule'!$K$2:$K$825)), ROW(19:19))), "") -> 0
A23: =IFERROR(INDEX('Bank Schedule'!A:A, SMALL(IF('Bank Schedule'!$K$2:$K$825="Vacant", ROW('Bank Schedule'!$K$2:$K$825)), ROW(20:20))), "") | B23: {=IFERROR(INDEX('Bank Schedule'!B:B, SMALL(IF('Bank Schedule'!$K$2:$K$825="Vacant", ROW('Bank Schedule'!$K$2:$K$825)), ROW(20:20))), "")} -> CM | C23: {=IFERROR(INDEX('Bank Schedule'!C:C, SMALL(IF('Bank Schedule'!$K$2:$K$825="Vacant", ROW('Bank Schedule'!$K$2:$K$825)), ROW(20:20))), "")} -> MEL | D23: {=IFERROR(INDEX('Bank Schedule'!D:D, SMALL(IF('Bank Schedule'!$K$2:$K$825="Vacant", ROW('Bank Schedule'!$K$2:$K$825)), ROW(20:20))), "")} -> 550830 | E23: {=IFERROR(INDEX('Bank Schedule'!E:E, SMALL(IF('Bank Schedule'!$K$2:$K$825="Vacant", ROW('Bank Schedule'!$K$2:$K$825)), ROW(20:20))), "")} -> 42-48 Great Portland Street | F23: {=IFERROR(INDEX('Bank Schedule'!F:F, SMALL(IF('Bank Schedule'!$K$2:$K$825="Vacant", ROW('Bank Schedule'!$K$2:$K$825)), ROW(20:20))), "")} -> Third Floor | G23: {=IFERROR(INDEX('Bank Schedule'!G:G, SMALL(IF('Bank Schedule'!$K$2:$K$825="Vacant", ROW('Bank Schedule'!$K$2:$K$825)), ROW(20:20))), "")} -> Office | H23: {=IFERROR(INDEX('Bank Schedule'!H:H, SMALL(IF('Bank Schedule'!$K$2:$K$825="Vacant", ROW('Bank Schedule'!$K$2:$K$825)), ROW(20:20))), "")} -> 1433 | I23: {=IFERROR(INDEX('Bank Schedule'!I:I, SMALL(IF('Bank Schedule'!$K$2:$K$825="Vacant", ROW('Bank Schedule'!$K$2:$K$825)), ROW(20:20))), "")} -> 1433 | J23: {=IFERROR(INDEX('Bank Schedule'!J:J, SMALL(IF('Bank Schedule'!$K$2:$K$825="Vacant", ROW('Bank Schedule'!$K$2:$K$825)), ROW(20:20))), "")} -> 1500 | K23: {=IFERROR(INDEX('Bank Schedule'!K:K, SMALL(IF('Bank Schedule'!$K$2:$K$825="Vacant", ROW('Bank Schedule'!$K$2:$K$825)), ROW(20:20))), "")} -> Vacant | L23: =IFERROR(INDEX('Bank Schedule'!L:L, SMALL(IF('Bank Schedule'!$K$2:$K$825="Vacant", ROW('Bank Schedule'!$K$2:$K$825)), ROW(20:20))), "") | M23: =IFERROR(INDEX('Bank Schedule'!M:M, SMALL(IF('Bank Schedule'!$K$2:$K$825="Vacant", ROW('Bank Schedule'!$K$2:$K$825)), ROW(20:20))), "") | N23: {=IFERROR(INDEX('Bank Schedule'!N:N, SMALL(IF('Bank Schedule'!$K$2:$K$825="Vacant", ROW('Bank Schedule'!$K$2:$K$825)), ROW(20:20))), "")} -> 43313 | O23: =IFERROR(INDEX('Bank Schedule'!O:O, SMALL(IF('Bank Schedule'!$K$2:$K$825="Vacant", ROW('Bank Schedule'!$K$2:$K$825)), ROW(20:20))), "") | P23: =IFERROR(INDEX('Bank Schedule'!P:P, SMALL(IF('Bank Schedule'!$K$2:$K$825="Vacant", ROW('Bank Schedule'!$K$2:$K$825)), ROW(20:20))), "") | Q23: {=IFERROR(INDEX('Bank Schedule'!Q:Q, SMALL(IF('Bank Schedule'!$K$2:$K$825="Vacant", ROW('Bank Schedule'!$K$2:$K$825)), ROW(20:20))), "")} -> 0 | R23: {=IFERROR(INDEX('Bank Schedule'!R:R, SMALL(IF('Bank Schedule'!$K$2:$K$825="Vacant", ROW('Bank Schedule'!$K$2:$K$825)), ROW(20:20))), "")} -> 0 | S23: =IFERROR(INDEX('Bank Schedule'!S:S, SMALL(IF('Bank Schedule'!$K$2:$K$825="Vacant", ROW('Bank Schedule'!$K$2:$K$825)), ROW(20:20))), "") | T23: {=IFERROR(INDEX('Bank Schedule'!T:T, SMALL(IF('Bank Schedule'!$K$2:$K$825="Vacant", ROW('Bank Schedule'!$K$2:$K$825)), ROW(20:20))), "")} -> 79750 | U23: {=IFERROR(INDEX('Bank Schedule'!U:U, SMALL(IF('Bank Schedule'!$K$2:$K$825="Vacant", ROW('Bank Schedule'!$K$2:$K$825)), ROW(20:20))), "")} -> 79750 | V23: {=IFERROR(INDEX('Bank Schedule'!V:V, SMALL(IF('Bank Schedule'!$K$2:$K$825="Vacant", ROW('Bank Schedule'!$K$2:$K$825)), ROW(20:20))), "")} -> 93100 | W23: {=IFERROR(INDEX('Bank Schedule'!W:W, SMALL(IF('Bank Schedule'!$K$2:$K$825="Vacant", ROW('Bank Schedule'!$K$2:$K$825)), ROW(20:20))), "")} -> 93100 | X23: {=IFERROR(INDEX('Bank Schedule'!X:X, SMALL(IF('Bank Schedule'!$K$2:$K$825="Vacant", ROW('Bank Schedule'!$K$2:$K$825)), ROW(20:20))), "")} -> 64.968597 | Y23: {=IFERROR(INDEX('Bank Schedule'!Y:Y, SMALL(IF('Bank Schedule'!$K$2:$K$825="Vacant", ROW('Bank Schedule'!$K$2:$K$825)), ROW(20:20))), "")} -> 0.16739812 | Z23: {=IFERROR(INDEX('Bank Schedule'!Z:Z, SMALL(IF('Bank Schedule'!$K$2:$K$825="Vacant", ROW('Bank Schedule'!$K$2:$K$825)), ROW(20:20))), "")} -> D | AA23: =IFERROR(INDEX('Bank Schedule'!AA:AA, SMALL(IF('Bank Schedule'!$K$2:$K$825="Vacant", ROW('Bank Schedule'!$K$2:$K$825)), ROW(20:20))), "") | AB23: =IFERROR(INDEX('Bank Schedule'!AB:AB, SMALL(IF('Bank Schedule'!$K$2:$K$825="Vacant", ROW('Bank Schedule'!$K$2:$K$825)), ROW(20:20))), "") | AC23: {=IFERROR(INDEX('Bank Schedule'!AC:AC, SMALL(IF('Bank Schedule'!$K$2:$K$825="Vacant", ROW('Bank Schedule'!$K$2:$K$825)), ROW(20:20))), "")} -> No | AD23: {=IFERROR(INDEX('Bank Schedule'!AD:AD, SMALL(IF('Bank Schedule'!$K$2:$K$825="Vacant", ROW('Bank Schedule'!$K$2:$K$825)), ROW(20:20))), "")} -> To be refurbished. | AE23: =IFERROR(INDEX('Bank Schedule'!AE:AE, SMALL(IF('Bank Schedule'!$K$2:$K$825="Vacant", ROW('Bank Schedule'!$K$2:$K$825)), ROW(20:20))), "") | AF23: =IFERROR(INDEX('Bank Schedule'!AF:AF, SMALL(IF('Bank Schedule'!$K$2:$K$825="Vacant", ROW('Bank Schedule'!$K$2:$K$825)), ROW(20:20))), "") | AG23: =IFERROR(INDEX('Bank Schedule'!AG:AG, SMALL(IF('Bank Schedule'!$K$2:$K$825="Vacant", ROW('Bank Schedule'!$K$2:$K$825)), ROW(20:20))), "") | AH23: =IFERROR(INDEX('Bank Schedule'!AH:AH, SMALL(IF('Bank Schedule'!$K$2:$K$825="Vacant", ROW('Bank Schedule'!$K$2:$K$825)), ROW(20:20))), "")
A24: =IFERROR(INDEX('Bank Schedule'!A:A, SMALL(IF('Bank Schedule'!$K$2:$K$825="Vacant", ROW('Bank Schedule'!$K$2:$K$825)), ROW(21:21))), "") | B24: {=IFERROR(INDEX('Bank Schedule'!B:B, SMALL(IF('Bank Schedule'!$K$2:$K$825="Vacant", ROW('Bank Schedule'!$K$2:$K$825)), ROW(21:21))), "")} -> CM | C24: {=IFERROR(INDEX('Bank Schedule'!C:C, SMALL(IF('Bank Schedule'!$K$2:$K$825="Vacant", ROW('Bank Schedule'!$K$2:$K$825)), ROW(21:21))), "")} -> MEL | D24: {=IFERROR(INDEX('Bank Schedule'!D:D, SMALL(IF('Bank Schedule'!$K$2:$K$825="Vacant", ROW('Bank Schedule'!$K$2:$K$825)), ROW(21:21))), "")} -> 550830 | E24: {=IFERROR(INDEX('Bank Schedule'!E:E, SMALL(IF('Bank Schedule'!$K$2:$K$825="Vacant", ROW('Bank Schedule'!$K$2:$K$825)), ROW(21:21))), "")} -> 42-48 Great Portland Street | F24: {=IFERROR(INDEX('Bank Schedule'!F:F, SMALL(IF('Bank Schedule'!$K$2:$K$825="Vacant", ROW('Bank Schedule'!$K$2:$K$825)), ROW(21:21))), "")} -> Fourth Floor | G24: {=IFERROR(INDEX('Bank Schedule'!G:G, SMALL(IF('Bank Schedule'!$K$2:$K$825="Vacant", ROW('Bank Schedule'!$K$2:$K$825)), ROW(21:21))), "")} -> Office | H24: {=IFERROR(INDEX('Bank Schedule'!H:H, SMALL(IF('Bank Schedule'!$K$2:$K$825="Vacant", ROW('Bank Schedule'!$K$2:$K$825)), ROW(21:21))), "")} -> 1480 | I24: {=IFERROR(INDEX('Bank Schedule'!I:I, SMALL(IF('Bank Schedule'!$K$2:$K$825="Vacant", ROW('Bank Schedule'!$K$2:$K$825)), ROW(21:21))), "")} -> 1480 | J24: {=IFERROR(INDEX('Bank Schedule'!J:J, SMALL(IF('Bank Schedule'!$K$2:$K$825="Vacant", ROW('Bank Schedule'!$K$2:$K$825)), ROW(21:21))), "")} -> 1500 | K24: {=IFERROR(INDEX('Bank Schedule'!K:K, SMALL(IF('Bank Schedule'!$K$2:$K$825="Vacant", ROW('Bank Schedule'!$K$2:$K$825)), ROW(21:21))), "")} -> Vacant | L24: =IFERROR(INDEX('Bank Schedule'!L:L, SMALL(IF('Bank Schedule'!$K$2:$K$825="Vacant", ROW('Bank Schedule'!$K$2:$K$825)), ROW(21:21))), "") | M24: =IFERROR(INDEX('Bank Schedule'!M:M, SMALL(IF('Bank Schedule'!$K$2:$K$825="Vacant", ROW('Bank Schedule'!$K$2:$K$825)), ROW(21:21))), "") | N24: {=IFERROR(INDEX('Bank Schedule'!N:N, SMALL(IF('Bank Schedule'!$K$2:$K$825="Vacant", ROW('Bank Schedule'!$K$2:$K$825)), ROW(21:21))), "")} -> 44409 | O24: =IFERROR(INDEX('Bank Schedule'!O:O, SMALL(IF('Bank Schedule'!$K$2:$K$825="Vacant", ROW('Bank Schedule'!$K$2:$K$825)), ROW(21:21))), "") | P24: =IFERROR(INDEX('Bank Schedule'!P:P, SMALL(IF('Bank Schedule'!$K$2:$K$825="Vacant", ROW('Bank Schedule'!$K$2:$K$825)), ROW(21:21))), "") | Q24: {=IFERROR(INDEX('Bank Schedule'!Q:Q, SMALL(IF('Bank Schedule'!$K$2:$K$825="Vacant", ROW('Bank Schedule'!$K$2:$K$825)), ROW(21:21))), "")} -> 0 | R24: {=IFERROR(INDEX('Bank Schedule'!R:R, SMALL(IF('Bank Schedule'!$K$2:$K$825="Vacant", ROW('Bank Schedule'!$K$2:$K$825)), ROW(21:21))), "")} -> 0 | S24: =IFERROR(INDEX('Bank Schedule'!S:S, SMALL(IF('Bank Schedule'!$K$2:$K$825="Vacant", ROW('Bank Schedule'!$K$2:$K$825)), ROW(21:21))), "") | T24: {=IFERROR(INDEX('Bank Schedule'!T:T, SMALL(IF('Bank Schedule'!$K$2:$K$825="Vacant", ROW('Bank Schedule'!$K$2:$K$825)), ROW(21:21))), "")} -> 79800 | U24: {=IFERROR(INDEX('Bank Schedule'!U:U, SMALL(IF('Bank Schedule'!$K$2:$K$825="Vacant", ROW('Bank Schedule'!$K$2:$K$825)), ROW(21:21))), "")} -> 79800 | V24: {=IFERROR(INDEX('Bank Schedule'!V:V, SMALL(IF('Bank Schedule'!$K$2:$K$825="Vacant", ROW('Bank Schedule'!$K$2:$K$825)), ROW(21:21))), "")} -> 96200 | W24: {=IFERROR(INDEX('Bank Schedule'!W:W, SMALL(IF('Bank Schedule'!$K$2:$K$825="Vacant", ROW('Bank Schedule'!$K$2:$K$825)), ROW(21:21))), "")} -> 96200 | X24: {=IFERROR(INDEX('Bank Schedule'!X:X, SMALL(IF('Bank Schedule'!$K$2:$K$825="Vacant", ROW('Bank Schedule'!$K$2:$K$825)), ROW(21:21))), "")} -> 65 | Y24: {=IFERROR(INDEX('Bank Schedule'!Y:Y, SMALL(IF('Bank Schedule'!$K$2:$K$825="Vacant", ROW('Bank Schedule'!$K$2:$K$825)), ROW(21:21))), "")} -> 0.20551378 | Z24: {=IFERROR(INDEX('Bank Schedule'!Z:Z, SMALL(IF('Bank Schedule'!$K$2:$K$825="Vacant", ROW('Bank Schedule'!$K$2:$K$825)), ROW(21:21))), "")} -> E | AA24: =IFERROR(INDEX('Bank Schedule'!AA:AA, SMALL(IF('Bank Schedule'!$K$2:$K$825="Vacant", ROW('Bank Schedule'!$K$2:$K$825)), ROW(21:21))), "") | AB24: =IFERROR(INDEX('Bank Schedule'!AB:AB, SMALL(IF('Bank Schedule'!$K$2:$K$825="Vacant", ROW('Bank Schedule'!$K$2:$K$825)), ROW(21:21))), "") | AC24: {=IFERROR(INDEX('Bank Schedule'!AC:AC, SMALL(IF('Bank Schedule'!$K$2:$K$825="Vacant", ROW('Bank Schedule'!$K$2:$K$825)), ROW(21:21))), "")} -> No | AD24: {=IFERROR(INDEX('Bank Schedule'!AD:AD, SMALL(IF('Bank Schedule'!$K$2:$K$825="Vacant", ROW('Bank Schedule'!$K$2:$K$825)), ROW(21:21))), "")} -> To be refurbished. | AE24: =IFERROR(INDEX('Bank Schedule'!AE:AE, SMALL(IF('Bank Schedule'!$K$2:$K$825="Vacant", ROW('Bank Schedule'!$K$2:$K$825)), ROW(21:21))), "") | AF24: =IFERROR(INDEX('Bank Schedule'!AF:AF, SMALL(IF('Bank Schedule'!$K$2:$K$825="Vacant", ROW('Bank Schedule'!$K$2:$K$825)), ROW(21:21))), "") | AG24: =IFERROR(INDEX('Bank Schedule'!AG:AG, SMALL(IF('Bank Schedule'!$K$2:$K$825="Vacant", ROW('Bank Schedule'!$K$2:$K$825)), ROW(21:21))), "") | AH24: =IFERROR(INDEX('Bank Schedule'!AH:AH, SMALL(IF('Bank Schedule'!$K$2:$K$825="Vacant", ROW('Bank Schedule'!$K$2:$K$825)), ROW(21:21))), "")
A25: =IFERROR(INDEX('Bank Schedule'!A:A, SMALL(IF('Bank Schedule'!$K$2:$K$825="Vacant", ROW('Bank Schedule'!$K$2:$K$825)), ROW(22:22))), "") | B25: {=IFERROR(INDEX('Bank Schedule'!B:B, SMALL(IF('Bank Schedule'!$K$2:$K$825="Vacant", ROW('Bank Schedule'!$K$2:$K$825)), ROW(22:22))), "")} -> CM | C25: {=IFERROR(INDEX('Bank Schedule'!C:C, SMALL(IF('Bank Schedule'!$K$2:$K$825="Vacant", ROW('Bank Schedule'!$K$2:$K$825)), ROW(22:22))), "")} -> MEL | D25: {=IFERROR(INDEX('Bank Schedule'!D:D, SMALL(IF('Bank Schedule'!$K$2:$K$825="Vacant", ROW('Bank Schedule'!$K$2:$K$825)), ROW(22:22))), "")} -> 550830 | E25: {=IFERROR(INDEX('Bank Schedule'!E:E, SMALL(IF('Bank Schedule'!$K$2:$K$825="Vacant", ROW('Bank Schedule'!$K$2:$K$825)), ROW(22:22))), "")} -> 42-48 Great Portland Street | F25: {=IFERROR(INDEX('Bank Schedule'!F:F, SMALL(IF('Bank Schedule'!$K$2:$K$825="Vacant", ROW('Bank Schedule'!$K$2:$K$825)), ROW(22:22))), "")} -> Fifth Floor | G25: {=IFERROR(INDEX('Bank Schedule'!G:G, SMALL(IF('Bank Schedule'!$K$2:$K$825="Vacant", ROW('Bank Schedule'!$K$2:$K$825)), ROW(22:22))), "")} -> Office | H25: {=IFERROR(INDEX('Bank Schedule'!H:H, SMALL(IF('Bank Schedule'!$K$2:$K$825="Vacant", ROW('Bank Schedule'!$K$2:$K$825)), ROW(22:22))), "")} -> 784 | I25: {=IFERROR(INDEX('Bank Schedule'!I:I, SMALL(IF('Bank Schedule'!$K$2:$K$825="Vacant", ROW('Bank Schedule'!$K$2:$K$825)), ROW(22:22))), "")} -> 784 | J25: {=IFERROR(INDEX('Bank Schedule'!J:J, SMALL(IF('Bank Schedule'!$K$2:$K$825="Vacant", ROW('Bank Schedule'!$K$2:$K$825)), ROW(22:22))), "")} -> 750 | K25: {=IFERROR(INDEX('Bank Schedule'!K:K, SMALL(IF('Bank Schedule'!$K$2:$K$825="Vacant", ROW('Bank Schedule'!$K$2:$K$825)), ROW(22:22))), "")} -> Vacant | L25: =IFERROR(INDEX('Bank Schedule'!L:L, SMALL(IF('Bank Schedule'!$K$2:$K$825="Vacant", ROW('Bank Schedule'!$K$2:$K$825)), ROW(22:22))), "") | M25: =IFERROR(INDEX('Bank Schedule'!M:M, SMALL(IF('Bank Schedule'!$K$2:$K$825="Vacant", ROW('Bank Schedule'!$K$2:$K$825)), ROW(22:22))), "") | N25: {=IFERROR(INDEX('Bank Schedule'!N:N, SMALL(IF('Bank Schedule'!$K$2:$K$825="Vacant", ROW('Bank Schedule'!$K$2:$K$825)), ROW(22:22))), "")} -> 44734 | O25: =IFERROR(INDEX('Bank Schedule'!O:O, SMALL(IF('Bank Schedule'!$K$2:$K$825="Vacant", ROW('Bank Schedule'!$K$2:$K$825)), ROW(22:22))), "") | P25: =IFERROR(INDEX('Bank Schedule'!P:P, SMALL(IF('Bank Schedule'!$K$2:$K$825="Vacant", ROW('Bank Schedule'!$K$2:$K$825)), ROW(22:22))), "") | Q25: {=IFERROR(INDEX('Bank Schedule'!Q:Q, SMALL(IF('Bank Schedule'!$K$2:$K$825="Vacant", ROW('Bank Schedule'!$K$2:$K$825)), ROW(22:22))), "")} -> 0 | R25: {=IFERROR(INDEX('Bank Schedule'!R:R, SMALL(IF('Bank Schedule'!$K$2:$K$825="Vacant", ROW('Bank Schedule'!$K$2:$K$825)), ROW(22:22))), "")} -> 0 | S25: =IFERROR(INDEX('Bank Schedule'!S:S, SMALL(IF('Bank Schedule'!$K$2:$K$825="Vacant", ROW('Bank Schedule'!$K$2:$K$825)), ROW(22:22))), "") | T25: {=IFERROR(INDEX('Bank Schedule'!T:T, SMALL(IF('Bank Schedule'!$K$2:$K$825="Vacant", ROW('Bank Schedule'!$K$2:$K$825)), ROW(22:22))), "")} -> 39030 | U25: {=IFERROR(INDEX('Bank Schedule'!U:U, SMALL(IF('Bank Schedule'!$K$2:$K$825="Vacant", ROW('Bank Schedule'!$K$2:$K$825)), ROW(22:22))), "")} -> 39030 | V25: {=IFERROR(INDEX('Bank Schedule'!V:V, SMALL(IF('Bank Schedule'!$K$2:$K$825="Vacant", ROW('Bank Schedule'!$K$2:$K$825)), ROW(22:22))), "")} -> 49000 | W25: {=IFERROR(INDEX('Bank Schedule'!W:W, SMALL(IF('Bank Schedule'!$K$2:$K$825="Vacant", ROW('Bank Schedule'!$K$2:$K$825)), ROW(22:22))), "")} -> 49000 | X25: {=IFERROR(INDEX('Bank Schedule'!X:X, SMALL(IF('Bank Schedule'!$K$2:$K$825="Vacant", ROW('Bank Schedule'!$K$2:$K$825)), ROW(22:22))), "")} -> 62.5 | Y25: {=IFERROR(INDEX('Bank Schedule'!Y:Y, SMALL(IF('Bank Schedule'!$K$2:$K$825="Vacant", ROW('Bank Schedule'!$K$2:$K$825)), ROW(22:22))), "")} -> 0.25544453 | Z25: {=IFERROR(INDEX('Bank Schedule'!Z:Z, SMALL(IF('Bank Schedule'!$K$2:$K$825="Vacant", ROW('Bank Schedule'!$K$2:$K$825)), ROW(22:22))), "")} -> D | AA25: =IFERROR(INDEX('Bank Schedule'!AA:AA, SMALL(IF('Bank Schedule'!$K$2:$K$825="Vacant", ROW('Bank Schedule'!$K$2:$K$825)), ROW(22:22))), "") | AB25: =IFERROR(INDEX('Bank Schedule'!AB:AB, SMALL(IF('Bank Schedule'!$K$2:$K$825="Vacant", ROW('Bank Schedule'!$K$2:$K$825)), ROW(22:22))), "") | AC25: {=IFERROR(INDEX('Bank Schedule'!AC:AC, SMALL(IF('Bank Schedule'!$K$2:$K$825="Vacant", ROW('Bank Schedule'!$K$2:$K$825)), ROW(22:22))), "")} -> No | AD25: {=IFERROR(INDEX('Bank Schedule'!AD:AD, SMALL(IF('Bank Schedule'!$K$2:$K$825="Vacant", ROW('Bank Schedule'!$K$2:$K$825)), ROW(22:22))), "")} -> To be refurbished. | AE25: =IFERROR(INDEX('Bank Schedule'!AE:AE, SMALL(IF('Bank Schedule'!$K$2:$K$825="Vacant", ROW('Bank Schedule'!$K$2:$K$825)), ROW(22:22))), "") | AF25: =IFERROR(INDEX('Bank Schedule'!AF:AF, SMALL(IF('Bank Schedule'!$K$2:$K$825="Vacant", ROW('Bank Schedule'!$K$2:$K$825)), ROW(22:22))), "") | AG25: =IFERROR(INDEX('Bank Schedule'!AG:AG, SMALL(IF('Bank Schedule'!$K$2:$K$825="Vacant", ROW('Bank Schedule'!$K$2:$K$825)), ROW(22:22))), "") | AH25: =IFERROR(INDEX('Bank Schedule'!AH:AH, SMALL(IF('Bank Schedule'!$K$2:$K$825="Vacant", ROW('Bank Schedule'!$K$2:$K$825)), ROW(22:22))), "")
A26: =IFERROR(INDEX('Bank Schedule'!A:A, SMALL(IF('Bank Schedule'!$K$2:$K$825="Vacant", ROW('Bank Schedule'!$K$2:$K$825)), ROW(23:23))), "") | B26: {=IFERROR(INDEX('Bank Schedule'!B:B, SMALL(IF('Bank Schedule'!$K$2:$K$825="Vacant", ROW('Bank Schedule'!$K$2:$K$825)), ROW(23:23))), "")} -> CD | C26: {=IFERROR(INDEX('Bank Schedule'!C:C, SMALL(IF('Bank Schedule'!$K$2:$K$825="Vacant", ROW('Bank Schedule'!$K$2:$K$825)), ROW(23:23))), "")} -> MEL | D26: {=IFERROR(INDEX('Bank Schedule'!D:D, SMALL(IF('Bank Schedule'!$K$2:$K$825="Vacant", ROW('Bank Schedule'!$K$2:$K$825)), ROW(23:23))), "")} -> 550990 | E26: {=IFERROR(INDEX('Bank Schedule'!E:E, SMALL(IF('Bank Schedule'!$K$2:$K$825="Vacant", ROW('Bank Schedule'!$K$2:$K$825)), ROW(23:23))), "")} -> 50 Great Portland Street | F26: {=IFERROR(INDEX('Bank Schedule'!F:F, SMALL(IF('Bank Schedule'!$K$2:$K$825="Vacant", ROW('Bank Schedule'!$K$2:$K$825)), ROW(23:23))), "")} -> Second Floor | G26: {=IFERROR(INDEX('Bank Schedule'!G:G, SMALL(IF('Bank Schedule'!$K$2:$K$825="Vacant", ROW('Bank Schedule'!$K$2:$K$825)), ROW(23:23))), "")} -> Office | H26: {=IFERROR(INDEX('Bank Schedule'!H:H, SMALL(IF('Bank Schedule'!$K$2:$K$825="Vacant", ROW('Bank Schedule'!$K$2:$K$825)), ROW(23:23))), "")} -> 304 | I26: {=IFERROR(INDEX('Bank Schedule'!I:I, SMALL(IF('Bank Schedule'!$K$2:$K$825="Vacant", ROW('Bank Schedule'!$K$2:$K$825)), ROW(23:23))), "")} -> 304 | J26: {=IFERROR(INDEX('Bank Schedule'!J:J, SMALL(IF('Bank Schedule'!$K$2:$K$825="Vacant", ROW('Bank Schedule'!$K$2:$K$825)), ROW(23:23))), "")} -> 250 | K26: {=IFERROR(INDEX('Bank Schedule'!K:K, SMALL(IF('Bank Schedule'!$K$2:$K$825="Vacant", ROW('Bank Schedule'!$K$2:$K$825)), ROW(23:23))), "")} -> Vacant | L26: =IFERROR(INDEX('Bank Schedule'!L:L, SMALL(IF('Bank Schedule'!$K$2:$K$825="Vacant", ROW('Bank Schedule'!$K$2:$K$825)), ROW(23:23))), "") | M26: =IFERROR(INDEX('Bank Schedule'!M:M, SMALL(IF('Bank Schedule'!$K$2:$K$825="Vacant", ROW('Bank Schedule'!$K$2:$K$825)), ROW(23:23))), "") | N26: {=IFERROR(INDEX('Bank Schedule'!N:N, SMALL(IF('Bank Schedule'!$K$2:$K$825="Vacant", ROW('Bank Schedule'!$K$2:$K$825)), ROW(23:23))), "")} -> 43256 | O26: =IFERROR(INDEX('Bank Schedule'!O:O, SMALL(IF('Bank Schedule'!$K$2:$K$825="Vacant", ROW('Bank Schedule'!$K$2:$K$825)), ROW(23:23))), "") | P26: =IFERROR(INDEX('Bank Schedule'!P:P, SMALL(IF('Bank Schedule'!$K$2:$K$825="Vacant", ROW('Bank Schedule'!$K$2:$K$825)), ROW(23:23))), "") | Q26: {=IFERROR(INDEX('Bank Schedule'!Q:Q, SMALL(IF('Bank Schedule'!$K$2:$K$825="Vacant", ROW('Bank Schedule'!$K$2:$K$825)), ROW(23:23))), "")} -> 0 | R26: {=IFERROR(INDEX('Bank Schedule'!R:R, SMALL(IF('Bank Schedule'!$K$2:$K$825="Vacant", ROW('Bank Schedule'!$K$2:$K$825)), ROW(23:23))), "")} -> 0 | S26: =IFERROR(INDEX('Bank Schedule'!S:S, SMALL(IF('Bank Schedule'!$K$2:$K$825="Vacant", ROW('Bank Schedule'!$K$2:$K$825)), ROW(23:23))), "") | T26: {=IFERROR(INDEX('Bank Schedule'!T:T, SMALL(IF('Bank Schedule'!$K$2:$K$825="Vacant", ROW('Bank Schedule'!$K$2:$K$825)), ROW(23:23))), "")} -> 15800 | U26: {=IFERROR(INDEX('Bank Schedule'!U:U, SMALL(IF('Bank Schedule'!$K$2:$K$825="Vacant", ROW('Bank Schedule'!$K$2:$K$825)), ROW(23:23))), "")} -> 15800 | V26: {=IFERROR(INDEX('Bank Schedule'!V:V, SMALL(IF('Bank Schedule'!$K$2:$K$825="Vacant", ROW('Bank Schedule'!$K$2:$K$825)), ROW(23:23))), "")} -> 16700 | W26: {=IFERROR(INDEX('Bank Schedule'!W:W, SMALL(IF('Bank Schedule'!$K$2:$K$825="Vacant", ROW('Bank Schedule'!$K$2:$K$825)), ROW(23:23))), "")} -> 16700 | X26: {=IFERROR(INDEX('Bank Schedule'!X:X, SMALL(IF('Bank Schedule'!$K$2:$K$825="Vacant", ROW('Bank Schedule'!$K$2:$K$825)), ROW(23:23))), "")} -> 54.934211 | Y26: {=IFERROR(INDEX('Bank Schedule'!Y:Y, SMALL(IF('Bank Schedule'!$K$2:$K$825="Vacant", ROW('Bank Schedule'!$K$2:$K$825)), ROW(23:23))), "")} -> 0.056962025 | Z26: {=IFERROR(INDEX('Bank Schedule'!Z:Z, SMALL(IF('Bank Schedule'!$K$2:$K$825="Vacant", ROW('Bank Schedule'!$K$2:$K$825)), ROW(23:23))), "")} -> D | AA26: =IFERROR(INDEX('Bank Schedule'!AA:AA, SMALL(IF('Bank Schedule'!$K$2:$K$825="Vacant", ROW('Bank Schedule'!$K$2:$K$825)), ROW(23:23))), "") | AB26: =IFERROR(INDEX('Bank Schedule'!AB:AB, SMALL(IF('Bank Schedule'!$K$2:$K$825="Vacant", ROW('Bank Schedule'!$K$2:$K$825)), ROW(23:23))), "") | AC26: {=IFERROR(INDEX('Bank Schedule'!AC:AC, SMALL(IF('Bank Schedule'!$K$2:$K$825="Vacant", ROW('Bank Schedule'!$K$2:$K$825)), ROW(23:23))), "")} -> No | AD26: {=IFERROR(INDEX('Bank Schedule'!AD:AD, SMALL(IF('Bank Schedule'!$K$2:$K$825="Vacant", ROW('Bank Schedule'!$K$2:$K$825)), ROW(23:23))), "")} -> To be refurbished. | AE26: =IFERROR(INDEX('Bank Schedule'!AE:AE, SMALL(IF('Bank Schedule'!$K$2:$K$825="Vacant", ROW('Bank Schedule'!$K$2:$K$825)), ROW(23:23))), "") | AF26: =IFERROR(INDEX('Bank Schedule'!AF:AF, SMALL(IF('Bank Schedule'!$K$2:$K$825="Vacant", ROW('Bank Schedule'!$K$2:$K$825)), ROW(23:23))), "") | AG26: =IFERROR(INDEX('Bank Schedule'!AG:AG, SMALL(IF('Bank Schedule'!$K$2:$K$825="Vacant", ROW('Bank Schedule'!$K$2:$K$825)), ROW(23:23))), "") | AH26: =IFERROR(INDEX('Bank Schedule'!AH:AH, SMALL(IF('Bank Schedule'!$K$2:$K$825="Vacant", ROW('Bank Schedule'!$K$2:$K$825)), ROW(23:23))), "")
A27: =IFERROR(INDEX('Bank Schedule'!A:A, SMALL(IF('Bank Schedule'!$K$2:$K$825="Vacant", ROW('Bank Schedule'!$K$2:$K$825)), ROW(24:24))), "") | B27: {=IFERROR(INDEX('Bank Schedule'!B:B, SMALL(IF('Bank Schedule'!$K$2:$K$825="Vacant", ROW('Bank Schedule'!$K$2:$K$825)), ROW(24:24))), "")} -> WS | C27: {=IFERROR(INDEX('Bank Schedule'!C:C, SMALL(IF('Bank Schedule'!$K$2:$K$825="Vacant", ROW('Bank Schedule'!$K$2:$K$825)), ROW(24:24))), "")} -> MEL | D27: {=IFERROR(INDEX('Bank Schedule'!D:D, SMALL(IF('Bank Schedule'!$K$2:$K$825="Vacant", ROW('Bank Schedule'!$K$2:$K$825)), ROW(24:24))), "")} -> 550700 | E27: {=IFERROR(INDEX('Bank Schedule'!E:E, SMALL(IF('Bank Schedule'!$K$2:$K$825="Vacant", ROW('Bank Schedule'!$K$2:$K$825)), ROW(24:24))), "")} -> 51 Great Portland Street | F27: {=IFERROR(INDEX('Bank Schedule'!F:F, SMALL(IF('Bank Schedule'!$K$2:$K$825="Vacant", ROW('Bank Schedule'!$K$2:$K$825)), ROW(24:24))), "")} -> First Floor | G27: {=IFERROR(INDEX('Bank Schedule'!G:G, SMALL(IF('Bank Schedule'!$K$2:$K$825="Vacant", ROW('Bank Schedule'!$K$2:$K$825)), ROW(24:24))), "")} -> Office | H27: {=IFERROR(INDEX('Bank Schedule'!H:H, SMALL(IF('Bank Schedule'!$K$2:$K$825="Vacant", ROW('Bank Schedule'!$K$2:$K$825)), ROW(24:24))), "")} -> 325 | I27: {=IFERROR(INDEX('Bank Schedule'!I:I, SMALL(IF('Bank Schedule'!$K$2:$K$825="Vacant", ROW('Bank Schedule'!$K$2:$K$825)), ROW(24:24))), "")} -> 325 | J27: {=IFERROR(INDEX('Bank Schedule'!J:J, SMALL(IF('Bank Schedule'!$K$2:$K$825="Vacant", ROW('Bank Schedule'!$K$2:$K$825)), ROW(24:24))), "")} -> 500 | K27: {=IFERROR(INDEX('Bank Schedule'!K:K, SMALL(IF('Bank Schedule'!$K$2:$K$825="Vacant", ROW('Bank Schedule'!$K$2:$K$825)), ROW(24:24))), "")} -> Vacant | L27: =IFERROR(INDEX('Bank Schedule'!L:L, SMALL(IF('Bank Schedule'!$K$2:$K$825="Vacant", ROW('Bank Schedule'!$K$2:$K$825)), ROW(24:24))), "") | M27: =IFERROR(INDEX('Bank Schedule'!M:M, SMALL(IF('Bank Schedule'!$K$2:$K$825="Vacant", ROW('Bank Schedule'!$K$2:$K$825)), ROW(24:24))), "") | N27: {=IFERROR(INDEX('Bank Schedule'!N:N, SMALL(IF('Bank Schedule'!$K$2:$K$825="Vacant", ROW('Bank Schedule'!$K$2:$K$825)), ROW(24:24))), "")} -> 45282 | O27: =IFERROR(INDEX('Bank Schedule'!O:O, SMALL(IF('Bank Schedule'!$K$2:$K$825="Vacant", ROW('Bank Schedule'!$K$2:$K$825)), ROW(24:24))), "") | P27: =IFERROR(INDEX('Bank Schedule'!P:P, SMALL(IF('Bank Schedule'!$K$2:$K$825="Vacant", ROW('Bank Schedule'!$K$2:$K$825)), ROW(24:24))), "") | Q27: {=IFERROR(INDEX('Bank Schedule'!Q:Q, SMALL(IF('Bank Schedule'!$K$2:$K$825="Vacant", ROW('Bank Schedule'!$K$2:$K$825)), ROW(24:24))), "")} -> 0 | R27: {=IFERROR(INDEX('Bank Schedule'!R:R, SMALL(IF('Bank Schedule'!$K$2:$K$825="Vacant", ROW('Bank Schedule'!$K$2:$K$825)), ROW(24:24))), "")} -> 0 | S27: =IFERROR(INDEX('Bank Schedule'!S:S, SMALL(IF('Bank Schedule'!$K$2:$K$825="Vacant", ROW('Bank Schedule'!$K$2:$K$825)), ROW(24:24))), "") | T27: {=IFERROR(INDEX('Bank Schedule'!T:T, SMALL(IF('Bank Schedule'!$K$2:$K$825="Vacant", ROW('Bank Schedule'!$K$2:$K$825)), ROW(24:24))), "")} -> 17100 | U27: {=IFERROR(INDEX('Bank Schedule'!U:U, SMALL(IF('Bank Schedule'!$K$2:$K$825="Vacant", ROW('Bank Schedule'!$K$2:$K$825)), ROW(24:24))), "")} -> 17100 | V27: {=IFERROR(INDEX('Bank Schedule'!V:V, SMALL(IF('Bank Schedule'!$K$2:$K$825="Vacant", ROW('Bank Schedule'!$K$2:$K$825)), ROW(24:24))), "")} -> 17100 | W27: {=IFERROR(INDEX('Bank Schedule'!W:W, SMALL(IF('Bank Schedule'!$K$2:$K$825="Vacant", ROW('Bank Schedule'!$K$2:$K$825)), ROW(24:24))), "")} -> 17100 | X27: {=IFERROR(INDEX('Bank Schedule'!X:X, SMALL(IF('Bank Schedule'!$K$2:$K$825="Vacant", ROW('Bank Schedule'!$K$2:$K$825)), ROW(24:24))), "")} -> 52.615385 | Y27: {=IFERROR(INDEX('Bank Schedule'!Y:Y, SMALL(IF('Bank Schedule'!$K$2:$K$825="Vacant", ROW('Bank Schedule'!$K$2:$K$825)), ROW(24:24))), "")} -> 0 | Z27: {=IFERROR(INDEX('Bank Schedule'!Z:Z, SMALL(IF('Bank Schedule'!$K$2:$K$825="Vacant", ROW('Bank Schedule'!$K$2:$K$825)), ROW(24:24))), "")} -> E | AA27: =IFERROR(INDEX('Bank Schedule'!AA:AA, SMALL(IF('Bank Schedule'!$K$2:$K$825="Vacant", ROW('Bank Schedule'!$K$2:$K$825)), ROW(24:24))), "") | AB27: =IFERROR(INDEX('Bank Schedule'!AB:AB, SMALL(IF('Bank Schedule'!$K$2:$K$825="Vacant", ROW('Bank Schedule'!$K$2:$K$825)), ROW(24:24))), "") | AC27: {=IFERROR(INDEX('Bank Schedule'!AC:AC, SMALL(IF('Bank Schedule'!$K$2:$K$825="Vacant", ROW('Bank Schedule'!$K$2:$K$825)), ROW(24:24))), "")} -> No | AD27: {=IFERROR(INDEX('Bank Schedule'!AD:AD, SMALL(IF('Bank Schedule'!$K$2:$K$825="Vacant", ROW('Bank Schedule'!$K$2:$K$825)), ROW(24:24))), "")} -> To be refurbished. | AE27: {=IFERROR(INDEX('Bank Schedule'!AE:AE, SMALL(IF('Bank Schedule'!$K$2:$K$825="Vacant", ROW('Bank Schedule'!$K$2:$K$825)), ROW(24:24))), "")} -> 58 | AF27: =IFERROR(INDEX('Bank Schedule'!AF:AF, SMALL(IF('Bank Schedule'!$K$2:$K$825="Vacant", ROW('Bank Schedule'!$K$2:$K$825)), ROW(24:24))), "") | AG27: {=IFERROR(INDEX('Bank Schedule'!AG:AG, SMALL(IF('Bank Schedule'!$K$2:$K$825="Vacant", ROW('Bank Schedule'!$K$2:$K$825)), ROW(24:24))), "")} -> 4 | AH27: =IFERROR(INDEX('Bank Schedule'!AH:AH, SMALL(IF('Bank Schedule'!$K$2:$K$825="Vacant", ROW('Bank Schedule'!$K$2:$K$825)), ROW(24:24))), "")
A28: =IFERROR(INDEX('Bank Schedule'!A:A, SMALL(IF('Bank Schedule'!$K$2:$K$825="Vacant", ROW('Bank Schedule'!$K$2:$K$825)), ROW(25:25))), "") | B28: {=IFERROR(INDEX('Bank Schedule'!B:B, SMALL(IF('Bank Schedule'!$K$2:$K$825="Vacant", ROW('Bank Schedule'!$K$2:$K$825)), ROW(25:25))), "")} -> WS | C28: {=IFERROR(INDEX('Bank Schedule'!C:C, SMALL(IF('Bank Schedule'!$K$2:$K$825="Vacant", ROW('Bank Schedule'!$K$2:$K$825)), ROW(25:25))), "")} -> MEL | D28: {=IFERROR(INDEX('Bank Schedule'!D:D, SMALL(IF('Bank Schedule'!$K$2:$K$825="Vacant", ROW('Bank Schedule'!$K$2:$K$825)), ROW(25:25))), "")} -> 550700 | E28: {=IFERROR(INDEX('Bank Schedule'!E:E, SMALL(IF('Bank Schedule'!$K$2:$K$825="Vacant", ROW('Bank Schedule'!$K$2:$K$825)), ROW(25:25))), "")} -> 51 Great Portland Street | F28: {=IFERROR(INDEX('Bank Schedule'!F:F, SMALL(IF('Bank Schedule'!$K$2:$K$825="Vacant", ROW('Bank Schedule'!$K$2:$K$825)), ROW(25:25))), "")} -> Third Floor | G28: {=IFERROR(INDEX('Bank Schedule'!G:G, SMALL(IF('Bank Schedule'!$K$2:$K$825="Vacant", ROW('Bank Schedule'!$K$2:$K$825)), ROW(25:25))), "")} -> Office | H28: {=IFERROR(INDEX('Bank Schedule'!H:H, SMALL(IF('Bank Schedule'!$K$2:$K$825="Vacant", ROW('Bank Schedule'!$K$2:$K$825)), ROW(25:25))), "")} -> 325 | I28: {=IFERROR(INDEX('Bank Schedule'!I:I, SMALL(IF('Bank Schedule'!$K$2:$K$825="Vacant", ROW('Bank Schedule'!$K$2:$K$825)), ROW(25:25))), "")} -> 325 | J28: {=IFERROR(INDEX('Bank Schedule'!J:J, SMALL(IF('Bank Schedule'!$K$2:$K$825="Vacant", ROW('Bank Schedule'!$K$2:$K$825)), ROW(25:25))), "")} -> 500 | K28: {=IFERROR(INDEX('Bank Schedule'!K:K, SMALL(IF('Bank Schedule'!$K$2:$K$825="Vacant", ROW('Bank Schedule'!$K$2:$K$825)), ROW(25:25))), "")} -> Vacant | L28: =IFERROR(INDEX('Bank Schedule'!L:L, SMALL(IF('Bank Schedule'!$K$2:$K$825="Vacant", ROW('Bank Schedule'!$K$2:$K$825)), ROW(25:25))), "") | M28: =IFERROR(INDEX('Bank Schedule'!M:M, SMALL(IF('Bank Schedule'!$K$2:$K$825="Vacant", ROW('Bank Schedule'!$K$2:$K$825)), ROW(25:25))), "") | N28: {=IFERROR(INDEX('Bank Schedule'!N:N, SMALL(IF('Bank Schedule'!$K$2:$K$825="Vacant", ROW('Bank Schedule'!$K$2:$K$825)), ROW(25:25))), "")} -> 44714 | O28: =IFERROR(INDEX('Bank Schedule'!O:O, SMALL(IF('Bank Schedule'!$K$2:$K$825="Vacant", ROW('Bank Schedule'!$K$2:$K$825)), ROW(25:25))), "") | P28: =IFERROR(INDEX('Bank Schedule'!P:P, SMALL(IF('Bank Schedule'!$K$2:$K$825="Vacant", ROW('Bank Schedule'!$K$2:$K$825)), ROW(25:25))), "") | Q28: {=IFERROR(INDEX('Bank Schedule'!Q:Q, SMALL(IF('Bank Schedule'!$K$2:$K$825="Vacant", ROW('Bank Schedule'!$K$2:$K$825)), ROW(25:25))), "")} -> 0 | R28: {=IFERROR(INDEX('Bank Schedule'!R:R, SMALL(IF('Bank Schedule'!$K$2:$K$825="Vacant", ROW('Bank Schedule'!$K$2:$K$825)), ROW(25:25))), "")} -> 0 | S28: =IFERROR(INDEX('Bank Schedule'!S:S, SMALL(IF('Bank Schedule'!$K$2:$K$825="Vacant", ROW('Bank Schedule'!$K$2:$K$825)), ROW(25:25))), "") | T28: {=IFERROR(INDEX('Bank Schedule'!T:T, SMALL(IF('Bank Schedule'!$K$2:$K$825="Vacant", ROW('Bank Schedule'!$K$2:$K$825)), ROW(25:25))), "")} -> 16300 | U28: {=IFERROR(INDEX('Bank Schedule'!U:U, SMALL(IF('Bank Schedule'!$K$2:$K$825="Vacant", ROW('Bank Schedule'!$K$2:$K$825)), ROW(25:25))), "")} -> 16300 | V28: {=IFERROR(INDEX('Bank Schedule'!V:V, SMALL(IF('Bank Schedule'!$K$2:$K$825="Vacant", ROW('Bank Schedule'!$K$2:$K$825)), ROW(25:25))), "")} -> 16300 | W28: {=IFERROR(INDEX('Bank Schedule'!W:W, SMALL(IF('Bank Schedule'!$K$2:$K$825="Vacant", ROW('Bank Schedule'!$K$2:$K$825)), ROW(25:25))), "")} -> 16300 | X28: {=IFERROR(INDEX('Bank Schedule'!X:X, SMALL(IF('Bank Schedule'!$K$2:$K$825="Vacant", ROW('Bank Schedule'!$K$2:$K$825)), ROW(25:25))), "")} -> 50.153846 | Y28: {=IFERROR(INDEX('Bank Schedule'!Y:Y, SMALL(IF('Bank Schedule'!$K$2:$K$825="Vacant", ROW('Bank Schedule'!$K$2:$K$825)), ROW(25:25))), "")} -> 0 | Z28: {=IFERROR(INDEX('Bank Schedule'!Z:Z, SMALL(IF('Bank Schedule'!$K$2:$K$825="Vacant", ROW('Bank Schedule'!$K$2:$K$825)), ROW(25:25))), "")} -> C | AA28: =IFERROR(INDEX('Bank Schedule'!AA:AA, SMALL(IF('Bank Schedule'!$K$2:$K$825="Vacant", ROW('Bank Schedule'!$K$2:$K$825)), ROW(25:25))), "") | AB28: =IFERROR(INDEX('Bank Schedule'!AB:AB, SMALL(IF('Bank Schedule'!$K$2:$K$825="Vacant", ROW('Bank Schedule'!$K$2:$K$825)), ROW(25:25))), "") | AC28: {=IFERROR(INDEX('Bank Schedule'!AC:AC, SMALL(IF('Bank Schedule'!$K$2:$K$825="Vacant", ROW('Bank Schedule'!$K$2:$K$825)), ROW(25:25))), "")} -> No | AD28: {=IFERROR(INDEX('Bank Schedule'!AD:AD, SMALL(IF('Bank Schedule'!$K$2:$K$825="Vacant", ROW('Bank Schedule'!$K$2:$K$825)), ROW(25:25))), "")} -> To be refurbished. | AE28: {=IFERROR(INDEX('Bank Schedule'!AE:AE, SMALL(IF('Bank Schedule'!$K$2:$K$825="Vacant", ROW('Bank Schedule'!$K$2:$K$825)), ROW(25:25))), "")} -> 52.5 | AF28: =IFERROR(INDEX('Bank Schedule'!AF:AF, SMALL(IF('Bank Schedule'!$K$2:$K$825="Vacant", ROW('Bank Schedule'!$K$2:$K$825)), ROW(25:25))), "") | AG28: =IFERROR(INDEX('Bank Schedule'!AG:AG, SMALL(IF('Bank Schedule'!$K$2:$K$825="Vacant", ROW('Bank Schedule'!$K$2:$K$825)), ROW(25:25))), "") | AH28: =IFERROR(INDEX('Bank Schedule'!AH:AH, SMALL(IF('Bank Schedule'!$K$2:$K$825="Vacant", ROW('Bank Schedule'!$K$2:$K$825)), ROW(25:25))), "")
A29: =IFERROR(INDEX('Bank Schedule'!A:A, SMALL(IF('Bank Schedule'!$K$2:$K$825="Vacant", ROW('Bank Schedule'!$K$2:$K$825)), ROW(26:26))), "") | B29: {=IFERROR(INDEX('Bank Schedule'!B:B, SMALL(IF('Bank Schedule'!$K$2:$K$825="Vacant", ROW('Bank Schedule'!$K$2:$K$825)), ROW(26:26))), "")} -> WS | C29: {=IFERROR(INDEX('Bank Schedule'!C:C, SMALL(IF('Bank Schedule'!$K$2:$K$825="Vacant", ROW('Bank Schedule'!$K$2:$K$825)), ROW(26:26))), "")} -> MEL | D29: {=IFERROR(INDEX('Bank Schedule'!D:D, SMALL(IF('Bank Schedule'!$K$2:$K$825="Vacant", ROW('Bank Schedule'!$K$2:$K$825)), ROW(26:26))), "")} -> 550710 | E29: {=IFERROR(INDEX('Bank Schedule'!E:E, SMALL(IF('Bank Schedule'!$K$2:$K$825="Vacant", ROW('Bank Schedule'!$K$2:$K$825)), ROW(26:26))), "")} -> 53 Great Portland Street | F29: {=IFERROR(INDEX('Bank Schedule'!F:F, SMALL(IF('Bank Schedule'!$K$2:$K$825="Vacant", ROW('Bank Schedule'!$K$2:$K$825)), ROW(26:26))), "")} -> First Floor | G29: {=IFERROR(INDEX('Bank Schedule'!G:G, SMALL(IF('Bank Schedule'!$K$2:$K$825="Vacant", ROW('Bank Schedule'!$K$2:$K$825)), ROW(26:26))), "")} -> Office | H29: {=IFERROR(INDEX('Bank Schedule'!H:H, SMALL(IF('Bank Schedule'!$K$2:$K$825="Vacant", ROW('Bank Schedule'!$K$2:$K$825)), ROW(26:26))), "")} -> 370 | I29: {=IFERROR(INDEX('Bank Schedule'!I:I, SMALL(IF('Bank Schedule'!$K$2:$K$825="Vacant", ROW('Bank Schedule'!$K$2:$K$825)), ROW(26:26))), "")} -> 370 | J29: {=IFERROR(INDEX('Bank Schedule'!J:J, SMALL(IF('Bank Schedule'!$K$2:$K$825="Vacant", ROW('Bank Schedule'!$K$2:$K$825)), ROW(26:26))), "")} -> 500 | K29: {=IFERROR(INDEX('Bank Schedule'!K:K, SMALL(IF('Bank Schedule'!$K$2:$K$825="Vacant", ROW('Bank Schedule'!$K$2:$K$825)), ROW(26:26))), "")} -> Vacant | L29: =IFERROR(INDEX('Bank Schedule'!L:L, SMALL(IF('Bank Schedule'!$K$2:$K$825="Vacant", ROW('Bank Schedule'!$K$2:$K$825)), ROW(26:26))), "") | M29: =IFERROR(INDEX('Bank Schedule'!M:M, SMALL(IF('Bank Schedule'!$K$2:$K$825="Vacant", ROW('Bank Schedule'!$K$2:$K$825)), ROW(26:26))), "") | N29: {=IFERROR(INDEX('Bank Schedule'!N:N, SMALL(IF('Bank Schedule'!$K$2:$K$825="Vacant", ROW('Bank Schedule'!$K$2:$K$825)), ROW(26:26))), "")} -> 43738 | O29: =IFERROR(INDEX('Bank Schedule'!O:O, SMALL(IF('Bank Schedule'!$K$2:$K$825="Vacant", ROW('Bank Schedule'!$K$2:$K$825)), ROW(26:26))), "") | P29: =IFERROR(INDEX('Bank Schedule'!P:P, SMALL(IF('Bank Schedule'!$K$2:$K$825="Vacant", ROW('Bank Schedule'!$K$2:$K$825)), ROW(26:26))), "") | Q29: {=IFERROR(INDEX('Bank Schedule'!Q:Q, SMALL(IF('Bank Schedule'!$K$2:$K$825="Vacant", ROW('Bank Schedule'!$K$2:$K$825)), ROW(26:26))), "")} -> 0 | R29: {=IFERROR(INDEX('Bank Schedule'!R:R, SMALL(IF('Bank Schedule'!$K$2:$K$825="Vacant", ROW('Bank Schedule'!$K$2:$K$825)), ROW(26:26))), "")} -> 0 | S29: =IFERROR(INDEX('Bank Schedule'!S:S, SMALL(IF('Bank Schedule'!$K$2:$K$825="Vacant", ROW('Bank Schedule'!$K$2:$K$825)), ROW(26:26))), "") | T29: {=IFERROR(INDEX('Bank Schedule'!T:T, SMALL(IF('Bank Schedule'!$K$2:$K$825="Vacant", ROW('Bank Schedule'!$K$2:$K$825)), ROW(26:26))), "")} -> 18500 | U29: {=IFERROR(INDEX('Bank Schedule'!U:U, SMALL(IF('Bank Schedule'!$K$2:$K$825="Vacant", ROW('Bank Schedule'!$K$2:$K$825)), ROW(26:26))), "")} -> 18500 | V29: {=IFERROR(INDEX('Bank Schedule'!V:V, SMALL(IF('Bank Schedule'!$K$2:$K$825="Vacant", ROW('Bank Schedule'!$K$2:$K$825)), ROW(26:26))), "")} -> 18500 | W29: {=IFERROR(INDEX('Bank Schedule'!W:W, SMALL(IF('Bank Schedule'!$K$2:$K$825="Vacant", ROW('Bank Schedule'!$K$2:$K$825)), ROW(26:26))), "")} -> 18500 | X29: {=IFERROR(INDEX('Bank Schedule'!X:X, SMALL(IF('Bank Schedule'!$K$2:$K$825="Vacant", ROW('Bank Schedule'!$K$2:$K$825)), ROW(26:26))), "")} -> 50 | Y29: {=IFERROR(INDEX('Bank Schedule'!Y:Y, SMALL(IF('Bank Schedule'!$K$2:$K$825="Vacant", ROW('Bank Schedule'!$K$2:$K$825)), ROW(26:26))), "")} -> 0 | Z29: {=IFERROR(INDEX('Bank Schedule'!Z:Z, SMALL(IF('Bank Schedule'!$K$2:$K$825="Vacant", ROW('Bank Schedule'!$K$2:$K$825)), ROW(26:26))), "")} -> E | AA29: =IFERROR(INDEX('Bank Schedule'!AA:AA, SMALL(IF('Bank Schedule'!$K$2:$K$825="Vacant", ROW('Bank Schedule'!$K$2:$K$825)), ROW(26:26))), "") | AB29: =IFERROR(INDEX('Bank Schedule'!AB:AB, SMALL(IF('Bank Schedule'!$K$2:$K$825="Vacant", ROW('Bank Schedule'!$K$2:$K$825)), ROW(26:26))), "") | AC29: {=IFERROR(INDEX('Bank Schedule'!AC:AC, SMALL(IF('Bank Schedule'!$K$2:$K$825="Vacant", ROW('Bank Schedule'!$K$2:$K$825)), ROW(26:26))), "")} -> No | AD29: {=IFERROR(INDEX('Bank Schedule'!AD:AD, SMALL(IF('Bank Schedule'!$K$2:$K$825="Vacant", ROW('Bank Schedule'!$K$2:$K$825)), ROW(26:26))), "")} -> To be refurbished. | AE29: {=IFERROR(INDEX('Bank Schedule'!AE:AE, SMALL(IF('Bank Schedule'!$K$2:$K$825="Vacant", ROW('Bank Schedule'!$K$2:$K$825)), ROW(26:26))), "")} -> 52.5 | AF29: {=IFERROR(INDEX('Bank Schedule'!AF:AF, SMALL(IF('Bank Schedule'!$K$2:$K$825="Vacant", ROW('Bank Schedule'!$K$2:$K$825)), ROW(26:26))), "")} -> 1 | AG29: {=IFERROR(INDEX('Bank Schedule'!AG:AG, SMALL(IF('Bank Schedule'!$K$2:$K$825="Vacant", ROW('Bank Schedule'!$K$2:$K$825)), ROW(26:26))), "")} -> 3 | AH29: =IFERROR(INDEX('Bank Schedule'!AH:AH, SMALL(IF('Bank Schedule'!$K$2:$K$825="Vacant", ROW('Bank Schedule'!$K$2:$K$825)), ROW(26:26))), "")
A30: =IFERROR(INDEX('Bank Schedule'!A:A, SMALL(IF('Bank Schedule'!$K$2:$K$825="Vacant", ROW('Bank Schedule'!$K$2:$K$825)), ROW(27:27))), "") | B30: {=IFERROR(INDEX('Bank Schedule'!B:B, SMALL(IF('Bank Schedule'!$K$2:$K$825="Vacant", ROW('Bank Schedule'!$K$2:$K$825)), ROW(27:27))), "")} -> WS | C30: {=IFERROR(INDEX('Bank Schedule'!C:C, SMALL(IF('Bank Schedule'!$K$2:$K$825="Vacant", ROW('Bank Schedule'!$K$2:$K$825)), ROW(27:27))), "")} -> MEL | D30: {=IFERROR(INDEX('Bank Schedule'!D:D, SMALL(IF('Bank Schedule'!$K$2:$K$825="Vacant", ROW('Bank Schedule'!$K$2:$K$825)), ROW(27:27))), "")} -> 550710 | E30: {=IFERROR(INDEX('Bank Schedule'!E:E, SMALL(IF('Bank Schedule'!$K$2:$K$825="Vacant", ROW('Bank Schedule'!$K$2:$K$825)), ROW(27:27))), "")} -> 53 Great Portland Street | F30: {=IFERROR(INDEX('Bank Schedule'!F:F, SMALL(IF('Bank Schedule'!$K$2:$K$825="Vacant", ROW('Bank Schedule'!$K$2:$K$825)), ROW(27:27))), "")} -> Second Floor | G30: {=IFERROR(INDEX('Bank Schedule'!G:G, SMALL(IF('Bank Schedule'!$K$2:$K$825="Vacant", ROW('Bank Schedule'!$K$2:$K$825)), ROW(27:27))), "")} -> Office | H30: {=IFERROR(INDEX('Bank Schedule'!H:H, SMALL(IF('Bank Schedule'!$K$2:$K$825="Vacant", ROW('Bank Schedule'!$K$2:$K$825)), ROW(27:27))), "")} -> 325 | I30: {=IFERROR(INDEX('Bank Schedule'!I:I, SMALL(IF('Bank Schedule'!$K$2:$K$825="Vacant", ROW('Bank Schedule'!$K$2:$K$825)), ROW(27:27))), "")} -> 325 | J30: {=IFERROR(INDEX('Bank Schedule'!J:J, SMALL(IF('Bank Schedule'!$K$2:$K$825="Vacant", ROW('Bank Schedule'!$K$2:$K$825)), ROW(27:27))), "")} -> 500 | K30: {=IFERROR(INDEX('Bank Schedule'!K:K, SMALL(IF('Bank Schedule'!$K$2:$K$825="Vacant", ROW('Bank Schedule'!$K$2:$K$825)), ROW(27:27))), "")} -> Vacant | L30: =IFERROR(INDEX('Bank Schedule'!L:L, SMALL(IF('Bank Schedule'!$K$2:$K$825="Vacant", ROW('Bank Schedule'!$K$2:$K$825)), ROW(27:27))), "") | M30: =IFERROR(INDEX('Bank Schedule'!M:M, SMALL(IF('Bank Schedule'!$K$2:$K$825="Vacant", ROW('Bank Schedule'!$K$2:$K$825)), ROW(27:27))), "") | N30: {=IFERROR(INDEX('Bank Schedule'!N:N, SMALL(IF('Bank Schedule'!$K$2:$K$825="Vacant", ROW('Bank Schedule'!$K$2:$K$825)), ROW(27:27))), "")} -> 45379 | O30: =IFERROR(INDEX('Bank Schedule'!O:O, SMALL(IF('Bank Schedule'!$K$2:$K$825="Vacant", ROW('Bank Schedule'!$K$2:$K$825)), ROW(27:27))), "") | P30: =IFERROR(INDEX('Bank Schedule'!P:P, SMALL(IF('Bank Schedule'!$K$2:$K$825="Vacant", ROW('Bank Schedule'!$K$2:$K$825)), ROW(27:27))), "") | Q30: {=IFERROR(INDEX('Bank Schedule'!Q:Q, SMALL(IF('Bank Schedule'!$K$2:$K$825="Vacant", ROW('Bank Schedule'!$K$2:$K$825)), ROW(27:27))), "")} -> 0 | R30: {=IFERROR(INDEX('Bank Schedule'!R:R, SMALL(IF('Bank Schedule'!$K$2:$K$825="Vacant", ROW('Bank Schedule'!$K$2:$K$825)), ROW(27:27))), "")} -> 0 | S30: =IFERROR(INDEX('Bank Schedule'!S:S, SMALL(IF('Bank Schedule'!$K$2:$K$825="Vacant", ROW('Bank Schedule'!$K$2:$K$825)), ROW(27:27))), "") | T30: {=IFERROR(INDEX('Bank Schedule'!T:T, SMALL(IF('Bank Schedule'!$K$2:$K$825="Vacant", ROW('Bank Schedule'!$K$2:$K$825)), ROW(27:27))), "")} -> 17000 | U30: {=IFERROR(INDEX('Bank Schedule'!U:U, SMALL(IF('Bank Schedule'!$K$2:$K$825="Vacant", ROW('Bank Schedule'!$K$2:$K$825)), ROW(27:27))), "")} -> 17000 | V30: {=IFERROR(INDEX('Bank Schedule'!V:V, SMALL(IF('Bank Schedule'!$K$2:$K$825="Vacant", ROW('Bank Schedule'!$K$2:$K$825)), ROW(27:27))), "")} -> 17062 | W30: {=IFERROR(INDEX('Bank Schedule'!W:W, SMALL(IF('Bank Schedule'!$K$2:$K$825="Vacant", ROW('Bank Schedule'!$K$2:$K$825)), ROW(27:27))), "")} -> 17062 | X30: {=IFERROR(INDEX('Bank Schedule'!X:X, SMALL(IF('Bank Schedule'!$K$2:$K$825="Vacant", ROW('Bank Schedule'!$K$2:$K$825)), ROW(27:27))), "")} -> 52.498462 | Y30: {=IFERROR(INDEX('Bank Schedule'!Y:Y, SMALL(IF('Bank Schedule'!$K$2:$K$825="Vacant", ROW('Bank Schedule'!$K$2:$K$825)), ROW(27:27))), "")} -> 0.0036470588 | Z30: {=IFERROR(INDEX('Bank Schedule'!Z:Z, SMALL(IF('Bank Schedule'!$K$2:$K$825="Vacant", ROW('Bank Schedule'!$K$2:$K$825)), ROW(27:27))), "")} -> E | AA30: =IFERROR(INDEX('Bank Schedule'!AA:AA, SMALL(IF('Bank Schedule'!$K$2:$K$825="Vacant", ROW('Bank Schedule'!$K$2:$K$825)), ROW(27:27))), "") | AB30: =IFERROR(INDEX('Bank Schedule'!AB:AB, SMALL(IF('Bank Schedule'!$K$2:$K$825="Vacant", ROW('Bank Schedule'!$K$2:$K$825)), ROW(27:27))), "") | AC30: {=IFERROR(INDEX('Bank Schedule'!AC:AC, SMALL(IF('Bank Schedule'!$K$2:$K$825="Vacant", ROW('Bank Schedule'!$K$2:$K$825)), ROW(27:27))), "")} -> No | AD30: {=IFERROR(INDEX('Bank Schedule'!AD:AD, SMALL(IF('Bank Schedule'!$K$2:$K$825="Vacant", ROW('Bank Schedule'!$K$2:$K$825)), ROW(27:27))), "")} -> To be refurbished. | AE30: {=IFERROR(INDEX('Bank Schedule'!AE:AE, SMALL(IF('Bank Schedule'!$K$2:$K$825="Vacant", ROW('Bank Schedule'!$K$2:$K$825)), ROW(27:27))), "")} -> 53 | AF30: =IFERROR(INDEX('Bank Schedule'!AF:AF, SMALL(IF('Bank Schedule'!$K$2:$K$825="Vacant", ROW('Bank Schedule'!$K$2:$K$825)), ROW(27:27))), "") | AG30: =IFERROR(INDEX('Bank Schedule'!AG:AG, SMALL(IF('Bank Schedule'!$K$2:$K$825="Vacant", ROW('Bank Schedule'!$K$2:$K$825)), ROW(27:27))), "") | AH30: =IFERROR(INDEX('Bank Schedule'!AH:AH, SMALL(IF('Bank Schedule'!$K$2:$K$825="Vacant", ROW('Bank Schedule'!$K$2:$K$825)), ROW(27:27))), "")
A31: =IFERROR(INDEX('Bank Schedule'!A:A, SMALL(IF('Bank Schedule'!$K$2:$K$825="Vacant", ROW('Bank Schedule'!$K$2:$K$825)), ROW(28:28))), "") -> 0 | B31: {=IFERROR(INDEX('Bank Schedule'!B:B, SMALL(IF('Bank Schedule'!$K$2:$K$825="Vacant", ROW('Bank Schedule'!$K$2:$K$825)), ROW(28:28))), "")} -> WS | C31: {=IFERROR(INDEX('Bank Schedule'!C:C, SMALL(IF('Bank Schedule'!$K$2:$K$825="Vacant", ROW('Bank Schedule'!$K$2:$K$825)), ROW(28:28))), "")} -> MEL | D31: {=IFERROR(INDEX('Bank Schedule'!D:D, SMALL(IF('Bank Schedule'!$K$2:$K$825="Vacant", ROW('Bank Schedule'!$K$2:$K$825)), ROW(28:28))), "")} -> 550710 | E31: {=IFERROR(INDEX('Bank Schedule'!E:E, SMALL(IF('Bank Schedule'!$K$2:$K$825="Vacant", ROW('Bank Schedule'!$K$2:$K$825)), ROW(28:28))), "")} -> 53 Great Portland Street | F31: {=IFERROR(INDEX('Bank Schedule'!F:F, SMALL(IF('Bank Schedule'!$K$2:$K$825="Vacant", ROW('Bank Schedule'!$K$2:$K$825)), ROW(28:28))), "")} -> Third Floor | G31: {=IFERROR(INDEX('Bank Schedule'!G:G, SMALL(IF('Bank Schedule'!$K$2:$K$825="Vacant", ROW('Bank Schedule'!$K$2:$K$825)), ROW(28:28))), "")} -> Office | H31: {=IFERROR(INDEX('Bank Schedule'!H:H, SMALL(IF('Bank Schedule'!$K$2:$K$825="Vacant", ROW('Bank Schedule'!$K$2:$K$825)), ROW(28:28))), "")} -> 321 | I31: {=IFERROR(INDEX('Bank Schedule'!I:I, SMALL(IF('Bank Schedule'!$K$2:$K$825="Vacant", ROW('Bank Schedule'!$K$2:$K$825)), ROW(28:28))), "")} -> 321 | J31: {=IFERROR(INDEX('Bank Schedule'!J:J, SMALL(IF('Bank Schedule'!$K$2:$K$825="Vacant", ROW('Bank Schedule'!$K$2:$K$825)), ROW(28:28))), "")} -> 500 | K31: {=IFERROR(INDEX('Bank Schedule'!K:K, SMALL(IF('Bank Schedule'!$K$2:$K$825="Vacant", ROW('Bank Schedule'!$K$2:$K$825)), ROW(28:28))), "")} -> Vacant | L31: =IFERROR(INDEX('Bank Schedule'!L:L, SMALL(IF('Bank Schedule'!$K$2:$K$825="Vacant", ROW('Bank Schedule'!$K$2:$K$825)), ROW(28:28))), "") -> 45649 | M31: =IFERROR(INDEX('Bank Schedule'!M:M, SMALL(IF('Bank Schedule'!$K$2:$K$825="Vacant", ROW('Bank Schedule'!$K$2:$K$825)), ROW(28:28))), "") -> 46743 | N31: {=IFERROR(INDEX('Bank Schedule'!N:N, SMALL(IF('Bank Schedule'!$K$2:$K$825="Vacant", ROW('Bank Schedule'!$K$2:$K$825)), ROW(28:28))), "")} -> 45170 | O31: =IFERROR(INDEX('Bank Schedule'!O:O, SMALL(IF('Bank Schedule'!$K$2:$K$825="Vacant", ROW('Bank Schedule'!$K$2:$K$825)), ROW(28:28))), "") -> 0 | P31: =IFERROR(INDEX('Bank Schedule'!P:P, SMALL(IF('Bank Schedule'!$K$2:$K$825="Vacant", ROW('Bank Schedule'!$K$2:$K$825)), ROW(28:28))), "") -> 46013 | Q31: {=IFERROR(INDEX('Bank Schedule'!Q:Q, SMALL(IF('Bank Schedule'!$K$2:$K$825="Vacant", ROW('Bank Schedule'!$K$2:$K$825)), ROW(28:28))), "")} -> 0 | R31: {=IFERROR(INDEX('Bank Schedule'!R:R, SMALL(IF('Bank Schedule'!$K$2:$K$825="Vacant", ROW('Bank Schedule'!$K$2:$K$825)), ROW(28:28))), "")} -> 0 | S31: =IFERROR(INDEX('Bank Schedule'!S:S, SMALL(IF('Bank Schedule'!$K$2:$K$825="Vacant", ROW('Bank Schedule'!$K$2:$K$825)), ROW(28:28))), "") -> 0 | T31: {=IFERROR(INDEX('Bank Schedule'!T:T, SMALL(IF('Bank Schedule'!$K$2:$K$825="Vacant", ROW('Bank Schedule'!$K$2:$K$825)), ROW(28:28))), "")} -> 17000 | U31: {=IFERROR(INDEX('Bank Schedule'!U:U, SMALL(IF('Bank Schedule'!$K$2:$K$825="Vacant", ROW('Bank Schedule'!$K$2:$K$825)), ROW(28:28))), "")} -> 17000 | V31: {=IFERROR(INDEX('Bank Schedule'!V:V, SMALL(IF('Bank Schedule'!$K$2:$K$825="Vacant", ROW('Bank Schedule'!$K$2:$K$825)), ROW(28:28))), "")} -> 16852 | W31: {=IFERROR(INDEX('Bank Schedule'!W:W, SMALL(IF('Bank Schedule'!$K$2:$K$825="Vacant", ROW('Bank Schedule'!$K$2:$K$825)), ROW(28:28))), "")} -> 16852 | X31: {=IFERROR(INDEX('Bank Schedule'!X:X, SMALL(IF('Bank Schedule'!$K$2:$K$825="Vacant", ROW('Bank Schedule'!$K$2:$K$825)), ROW(28:28))), "")} -> 52.498442 | Y31: {=IFERROR(INDEX('Bank Schedule'!Y:Y, SMALL(IF('Bank Schedule'!$K$2:$K$825="Vacant", ROW('Bank Schedule'!$K$2:$K$825)), ROW(28:28))), "")} -> -0.0087058824 | Z31: {=IFERROR(INDEX('Bank Schedule'!Z:Z, SMALL(IF('Bank Schedule'!$K$2:$K$825="Vacant", ROW('Bank Schedule'!$K$2:$K$825)), ROW(28:28))), "")} -> E | AA31: =IFERROR(INDEX('Bank Schedule'!AA:AA, SMALL(IF('Bank Schedule'!$K$2:$K$825="Vacant", ROW('Bank Schedule'!$K$2:$K$825)), ROW(28:28))), "") -> 0 | AB31: =IFERROR(INDEX('Bank Schedule'!AB:AB, SMALL(IF('Bank Schedule'!$K$2:$K$825="Vacant", ROW('Bank Schedule'!$K$2:$K$825)), ROW(28:28))), "") -> 0 | AC31: {=IFERROR(INDEX('Bank Schedule'!AC:AC, SMALL(IF('Bank Schedule'!$K$2:$K$825="Vacant", ROW('Bank Schedule'!$K$2:$K$825)), ROW(28:28))), "")} -> No | AD31: {=IFERROR(INDEX('Bank Schedule'!AD:AD, SMALL(IF('Bank Schedule'!$K$2:$K$825="Vacant", ROW('Bank Schedule'!$K$2:$K$825)), ROW(28:28))), "")} -> To be refurbished. | AE31: {=IFERROR(INDEX('Bank Schedule'!AE:AE, SMALL(IF('Bank Schedule'!$K$2:$K$825="Vacant", ROW('Bank Schedule'!$K$2:$K$825)), ROW(28:28))), "")} -> 53 | AF31: {=IFERROR(INDEX('Bank Schedule'!AF:AF, SMALL(IF('Bank Schedule'!$K$2:$K$825="Vacant", ROW('Bank Schedule'!$K$2:$K$825)), ROW(28:28))), "")} -> 2 | AG31: {=IFERROR(INDEX('Bank Schedule'!AG:AG, SMALL(IF('Bank Schedule'!$K$2:$K$825="Vacant", ROW('Bank Schedule'!$K$2:$K$825)), ROW(28:28))), "")} -> 2 | AH31: =IFERROR(INDEX('Bank Schedule'!AH:AH, SMALL(IF('Bank Schedule'!$K$2:$K$825="Vacant", ROW('Bank Schedule'!$K$2:$K$825)), ROW(28:28))), "") -> 0
A32: =IFERROR(INDEX('Bank Schedule'!A:A, SMALL(IF('Bank Schedule'!$K$2:$K$825="Vacant", ROW('Bank Schedule'!$K$2:$K$825)), ROW(29:29))), "") | B32: {=IFERROR(INDEX('Bank Schedule'!B:B, SMALL(IF('Bank Schedule'!$K$2:$K$825="Vacant", ROW('Bank Schedule'!$K$2:$K$825)), ROW(29:29))), "")} -> CM | C32: {=IFERROR(INDEX('Bank Schedule'!C:C, SMALL(IF('Bank Schedule'!$K$2:$K$825="Vacant", ROW('Bank Schedule'!$K$2:$K$825)), ROW(29:29))), "")} -> MEL | D32: {=IFERROR(INDEX('Bank Schedule'!D:D, SMALL(IF('Bank Schedule'!$K$2:$K$825="Vacant", ROW('Bank Schedule'!$K$2:$K$825)), ROW(29:29))), "")} -> 550090 | E32: {=IFERROR(INDEX('Bank Schedule'!E:E, SMALL(IF('Bank Schedule'!$K$2:$K$825="Vacant", ROW('Bank Schedule'!$K$2:$K$825)), ROW(29:29))), "")} -> 76 Great Portland Street | F32: {=IFERROR(INDEX('Bank Schedule'!F:F, SMALL(IF('Bank Schedule'!$K$2:$K$825="Vacant", ROW('Bank Schedule'!$K$2:$K$825)), ROW(29:29))), "")} -> First to Fourth Floor | G32: {=IFERROR(INDEX('Bank Schedule'!G:G, SMALL(IF('Bank Schedule'!$K$2:$K$825="Vacant", ROW('Bank Schedule'!$K$2:$K$825)), ROW(29:29))), "")} -> Office | H32: {=IFERROR(INDEX('Bank Schedule'!H:H, SMALL(IF('Bank Schedule'!$K$2:$K$825="Vacant", ROW('Bank Schedule'!$K$2:$K$825)), ROW(29:29))), "")} -> 1765 | I32: {=IFERROR(INDEX('Bank Schedule'!I:I, SMALL(IF('Bank Schedule'!$K$2:$K$825="Vacant", ROW('Bank Schedule'!$K$2:$K$825)), ROW(29:29))), "")} -> 1765 | J32: {=IFERROR(INDEX('Bank Schedule'!J:J, SMALL(IF('Bank Schedule'!$K$2:$K$825="Vacant", ROW('Bank Schedule'!$K$2:$K$825)), ROW(29:29))), "")} -> 1750 | K32: {=IFERROR(INDEX('Bank Schedule'!K:K, SMALL(IF('Bank Schedule'!$K$2:$K$825="Vacant", ROW('Bank Schedule'!$K$2:$K$825)), ROW(29:29))), "")} -> Vacant | L32: =IFERROR(INDEX('Bank Schedule'!L:L, SMALL(IF('Bank Schedule'!$K$2:$K$825="Vacant", ROW('Bank Schedule'!$K$2:$K$825)), ROW(29:29))), "") | M32: =IFERROR(INDEX('Bank Schedule'!M:M, SMALL(IF('Bank Schedule'!$K$2:$K$825="Vacant", ROW('Bank Schedule'!$K$2:$K$825)), ROW(29:29))), "") | N32: {=IFERROR(INDEX('Bank Schedule'!N:N, SMALL(IF('Bank Schedule'!$K$2:$K$825="Vacant", ROW('Bank Schedule'!$K$2:$K$825)), ROW(29:29))), "")} -> 43256 | O32: =IFERROR(INDEX('Bank Schedule'!O:O, SMALL(IF('Bank Schedule'!$K$2:$K$825="Vacant", ROW('Bank Schedule'!$K$2:$K$825)), ROW(29:29))), "") | P32: =IFERROR(INDEX('Bank Schedule'!P:P, SMALL(IF('Bank Schedule'!$K$2:$K$825="Vacant", ROW('Bank Schedule'!$K$2:$K$825)), ROW(29:29))), "") | Q32: {=IFERROR(INDEX('Bank Schedule'!Q:Q, SMALL(IF('Bank Schedule'!$K$2:$K$825="Vacant", ROW('Bank Schedule'!$K$2:$K$825)), ROW(29:29))), "")} -> 0 | R32: {=IFERROR(INDEX('Bank Schedule'!R:R, SMALL(IF('Bank Schedule'!$K$2:$K$825="Vacant", ROW('Bank Schedule'!$K$2:$K$825)), ROW(29:29))), "")} -> 0 | S32: =IFERROR(INDEX('Bank Schedule'!S:S, SMALL(IF('Bank Schedule'!$K$2:$K$825="Vacant", ROW('Bank Schedule'!$K$2:$K$825)), ROW(29:29))), "") | T32: {=IFERROR(INDEX('Bank Schedule'!T:T, SMALL(IF('Bank Schedule'!$K$2:$K$825="Vacant", ROW('Bank Schedule'!$K$2:$K$825)), ROW(29:29))), "")} -> 90000 | U32: {=IFERROR(INDEX('Bank Schedule'!U:U, SMALL(IF('Bank Schedule'!$K$2:$K$825="Vacant", ROW('Bank Schedule'!$K$2:$K$825)), ROW(29:29))), "")} -> 90000 | V32: {=IFERROR(INDEX('Bank Schedule'!V:V, SMALL(IF('Bank Schedule'!$K$2:$K$825="Vacant", ROW('Bank Schedule'!$K$2:$K$825)), ROW(29:29))), "")} -> 85000 | W32: {=IFERROR(INDEX('Bank Schedule'!W:W, SMALL(IF('Bank Schedule'!$K$2:$K$825="Vacant", ROW('Bank Schedule'!$K$2:$K$825)), ROW(29:29))), "")} -> 85000 | X32: {=IFERROR(INDEX('Bank Schedule'!X:X, SMALL(IF('Bank Schedule'!$K$2:$K$825="Vacant", ROW('Bank Schedule'!$K$2:$K$825)), ROW(29:29))), "")} -> 48.15864 | Y32: {=IFERROR(INDEX('Bank Schedule'!Y:Y, SMALL(IF('Bank Schedule'!$K$2:$K$825="Vacant", ROW('Bank Schedule'!$K$2:$K$825)), ROW(29:29))), "")} -> -0.055555556 | Z32: {=IFERROR(INDEX('Bank Schedule'!Z:Z, SMALL(IF('Bank Schedule'!$K$2:$K$825="Vacant", ROW('Bank Schedule'!$K$2:$K$825)), ROW(29:29))), "")} -> E | AA32: =IFERROR(INDEX('Bank Schedule'!AA:AA, SMALL(IF('Bank Schedule'!$K$2:$K$825="Vacant", ROW('Bank Schedule'!$K$2:$K$825)), ROW(29:29))), "") | AB32: =IFERROR(INDEX('Bank Schedule'!AB:AB, SMALL(IF('Bank Schedule'!$K$2:$K$825="Vacant", ROW('Bank Schedule'!$K$2:$K$825)), ROW(29:29))), "") | AC32: {=IFERROR(INDEX('Bank Schedule'!AC:AC, SMALL(IF('Bank Schedule'!$K$2:$K$825="Vacant", ROW('Bank Schedule'!$K$2:$K$825)), ROW(29:29))), "")} -> No | AD32: {=IFERROR(INDEX('Bank Schedule'!AD:AD, SMALL(IF('Bank Schedule'!$K$2:$K$825="Vacant", ROW('Bank Schedule'!$K$2:$K$825)), ROW(29:29))), "")} -> Mothballed. | AE32: =IFERROR(INDEX('Bank Schedule'!AE:AE, SMALL(IF('Bank Schedule'!$K$2:$K$825="Vacant", ROW('Bank Schedule'!$K$2:$K$825)), ROW(29:29))), "") | AF32: =IFERROR(INDEX('Bank Schedule'!AF:AF, SMALL(IF('Bank Schedule'!$K$2:$K$825="Vacant", ROW('Bank Schedule'!$K$2:$K$825)), ROW(29:29))), "") | AG32: =IFERROR(INDEX('Bank Schedule'!AG:AG, SMALL(IF('Bank Schedule'!$K$2:$K$825="Vacant", ROW('Bank Schedule'!$K$2:$K$825)), ROW(29:29))), "") | AH32: =IFERROR(INDEX('Bank Schedule'!AH:AH, SMALL(IF('Bank Schedule'!$K$2:$K$825="Vacant", ROW('Bank Schedule'!$K$2:$K$825)), ROW(29:29))), "")
A33: =IFERROR(INDEX('Bank Schedule'!A:A, SMALL(IF('Bank Schedule'!$K$2:$K$825="Vacant", ROW('Bank Schedule'!$K$2:$K$825)), ROW(30:30))), "") | B33: {=IFERROR(INDEX('Bank Schedule'!B:B, SMALL(IF('Bank Schedule'!$K$2:$K$825="Vacant", ROW('Bank Schedule'!$K$2:$K$825)), ROW(30:30))), "")} -> WS | C33: {=IFERROR(INDEX('Bank Schedule'!C:C, SMALL(IF('Bank Schedule'!$K$2:$K$825="Vacant", ROW('Bank Schedule'!$K$2:$K$825)), ROW(30:30))), "")} -> MEL | D33: {=IFERROR(INDEX('Bank Schedule'!D:D, SMALL(IF('Bank Schedule'!$K$2:$K$825="Vacant", ROW('Bank Schedule'!$K$2:$K$825)), ROW(30:30))), "")} -> 550180 | E33: {=IFERROR(INDEX('Bank Schedule'!E:E, SMALL(IF('Bank Schedule'!$K$2:$K$825="Vacant", ROW('Bank Schedule'!$K$2:$K$825)), ROW(30:30))), "")} -> Great Titchfield House, 14-18 Great Titchfield Street | F33: {=IFERROR(INDEX('Bank Schedule'!F:F, SMALL(IF('Bank Schedule'!$K$2:$K$825="Vacant", ROW('Bank Schedule'!$K$2:$K$825)), ROW(30:30))), "")} -> Fourth Floor | G33: {=IFERROR(INDEX('Bank Schedule'!G:G, SMALL(IF('Bank Schedule'!$K$2:$K$825="Vacant", ROW('Bank Schedule'!$K$2:$K$825)), ROW(30:30))), "")} -> Showroom/ Office | H33: {=IFERROR(INDEX('Bank Schedule'!H:H, SMALL(IF('Bank Schedule'!$K$2:$K$825="Vacant", ROW('Bank Schedule'!$K$2:$K$825)), ROW(30:30))), "")} -> 1992 | I33: {=IFERROR(INDEX('Bank Schedule'!I:I, SMALL(IF('Bank Schedule'!$K$2:$K$825="Vacant", ROW('Bank Schedule'!$K$2:$K$825)), ROW(30:30))), "")} -> 1992 | J33: {=IFERROR(INDEX('Bank Schedule'!J:J, SMALL(IF('Bank Schedule'!$K$2:$K$825="Vacant", ROW('Bank Schedule'!$K$2:$K$825)), ROW(30:30))), "")} -> 2000 | K33: {=IFERROR(INDEX('Bank Schedule'!K:K, SMALL(IF('Bank Schedule'!$K$2:$K$825="Vacant", ROW('Bank Schedule'!$K$2:$K$825)), ROW(30:30))), "")} -> Vacant | L33: =IFERROR(INDEX('Bank Schedule'!L:L, SMALL(IF('Bank Schedule'!$K$2:$K$825="Vacant", ROW('Bank Schedule'!$K$2:$K$825)), ROW(30:30))), "") | M33: =IFERROR(INDEX('Bank Schedule'!M:M, SMALL(IF('Bank Schedule'!$K$2:$K$825="Vacant", ROW('Bank Schedule'!$K$2:$K$825)), ROW(30:30))), "") | N33: {=IFERROR(INDEX('Bank Schedule'!N:N, SMALL(IF('Bank Schedule'!$K$2:$K$825="Vacant", ROW('Bank Schedule'!$K$2:$K$825)), ROW(30:30))), "")} -> 45596 | O33: =IFERROR(INDEX('Bank Schedule'!O:O, SMALL(IF('Bank Schedule'!$K$2:$K$825="Vacant", ROW('Bank Schedule'!$K$2:$K$825)), ROW(30:30))), "") | P33: =IFERROR(INDEX('Bank Schedule'!P:P, SMALL(IF('Bank Schedule'!$K$2:$K$825="Vacant", ROW('Bank Schedule'!$K$2:$K$825)), ROW(30:30))), "") | Q33: {=IFERROR(INDEX('Bank Schedule'!Q:Q, SMALL(IF('Bank Schedule'!$K$2:$K$825="Vacant", ROW('Bank Schedule'!$K$2:$K$825)), ROW(30:30))), "")} -> 0 | R33: {=IFERROR(INDEX('Bank Schedule'!R:R, SMALL(IF('Bank Schedule'!$K$2:$K$825="Vacant", ROW('Bank Schedule'!$K$2:$K$825)), ROW(30:30))), "")} -> 0 | S33: =IFERROR(INDEX('Bank Schedule'!S:S, SMALL(IF('Bank Schedule'!$K$2:$K$825="Vacant", ROW('Bank Schedule'!$K$2:$K$825)), ROW(30:30))), "") | T33: {=IFERROR(INDEX('Bank Schedule'!T:T, SMALL(IF('Bank Schedule'!$K$2:$K$825="Vacant", ROW('Bank Schedule'!$K$2:$K$825)), ROW(30:30))), "")} -> 117300 | U33: {=IFERROR(INDEX('Bank Schedule'!U:U, SMALL(IF('Bank Schedule'!$K$2:$K$825="Vacant", ROW('Bank Schedule'!$K$2:$K$825)), ROW(30:30))), "")} -> 117300 | V33: {=IFERROR(INDEX('Bank Schedule'!V:V, SMALL(IF('Bank Schedule'!$K$2:$K$825="Vacant", ROW('Bank Schedule'!$K$2:$K$825)), ROW(30:30))), "")} -> 130325 | W33: {=IFERROR(INDEX('Bank Schedule'!W:W, SMALL(IF('Bank Schedule'!$K$2:$K$825="Vacant", ROW('Bank Schedule'!$K$2:$K$825)), ROW(30:30))), "")} -> 130325 | X33: {=IFERROR(INDEX('Bank Schedule'!X:X, SMALL(IF('Bank Schedule'!$K$2:$K$825="Vacant", ROW('Bank Schedule'!$K$2:$K$825)), ROW(30:30))), "")} -> 65.424197 | Y33: {=IFERROR(INDEX('Bank Schedule'!Y:Y, SMALL(IF('Bank Schedule'!$K$2:$K$825="Vacant", ROW('Bank Schedule'!$K$2:$K$825)), ROW(30:30))), "")} -> 0.11104007 | Z33: {=IFERROR(INDEX('Bank Schedule'!Z:Z, SMALL(IF('Bank Schedule'!$K$2:$K$825="Vacant", ROW('Bank Schedule'!$K$2:$K$825)), ROW(30:30))), "")} -> D | AA33: =IFERROR(INDEX('Bank Schedule'!AA:AA, SMALL(IF('Bank Schedule'!$K$2:$K$825="Vacant", ROW('Bank Schedule'!$K$2:$K$825)), ROW(30:30))), "") | AB33: =IFERROR(INDEX('Bank Schedule'!AB:AB, SMALL(IF('Bank Schedule'!$K$2:$K$825="Vacant", ROW('Bank Schedule'!$K$2:$K$825)), ROW(30:30))), "") | AC33: {=IFERROR(INDEX('Bank Schedule'!AC:AC, SMALL(IF('Bank Schedule'!$K$2:$K$825="Vacant", ROW('Bank Schedule'!$K$2:$K$825)), ROW(30:30))), "")} -> No | AD33: {=IFERROR(INDEX('Bank Schedule'!AD:AD, SMALL(IF('Bank Schedule'!$K$2:$K$825="Vacant", ROW('Bank Schedule'!$K$2:$K$825)), ROW(30:30))), "")} -> To be refurbished. | AE33: {=IFERROR(INDEX('Bank Schedule'!AE:AE, SMALL(IF('Bank Schedule'!$K$2:$K$825="Vacant", ROW('Bank Schedule'!$K$2:$K$825)), ROW(30:30))), "")} -> 72.5 | AF33: {=IFERROR(INDEX('Bank Schedule'!AF:AF, SMALL(IF('Bank Schedule'!$K$2:$K$825="Vacant", ROW('Bank Schedule'!$K$2:$K$825)), ROW(30:30))), "")} -> 4 | AG33: {=IFERROR(INDEX('Bank Schedule'!AG:AG, SMALL(IF('Bank Schedule'!$K$2:$K$825="Vacant", ROW('Bank Schedule'!$K$2:$K$825)), ROW(30:30))), "")} -> 9 | AH33: {=IFERROR(INDEX('Bank Schedule'!AH:AH, SMALL(IF('Bank Schedule'!$K$2:$K$825="Vacant", ROW('Bank Schedule'!$K$2:$K$825)), ROW(30:30))), "")} -> LEM
A34: =IFERROR(INDEX('Bank Schedule'!A:A, SMALL(IF('Bank Schedule'!$K$2:$K$825="Vacant", ROW('Bank Schedule'!$K$2:$K$825)), ROW(31:31))), "") | B34: {=IFERROR(INDEX('Bank Schedule'!B:B, SMALL(IF('Bank Schedule'!$K$2:$K$825="Vacant", ROW('Bank Schedule'!$K$2:$K$825)), ROW(31:31))), "")} -> WS | C34: {=IFERROR(INDEX('Bank Schedule'!C:C, SMALL(IF('Bank Schedule'!$K$2:$K$825="Vacant", ROW('Bank Schedule'!$K$2:$K$825)), ROW(31:31))), "")} -> MEL | D34: {=IFERROR(INDEX('Bank Schedule'!D:D, SMALL(IF('Bank Schedule'!$K$2:$K$825="Vacant", ROW('Bank Schedule'!$K$2:$K$825)), ROW(31:31))), "")} -> 550420 | E34: {=IFERROR(INDEX('Bank Schedule'!E:E, SMALL(IF('Bank Schedule'!$K$2:$K$825="Vacant", ROW('Bank Schedule'!$K$2:$K$825)), ROW(31:31))), "")} -> Golderbrock House, 15-19 Great Titchfield Street | F34: {=IFERROR(INDEX('Bank Schedule'!F:F, SMALL(IF('Bank Schedule'!$K$2:$K$825="Vacant", ROW('Bank Schedule'!$K$2:$K$825)), ROW(31:31))), "")} -> First Floor (Rear) | G34: {=IFERROR(INDEX('Bank Schedule'!G:G, SMALL(IF('Bank Schedule'!$K$2:$K$825="Vacant", ROW('Bank Schedule'!$K$2:$K$825)), ROW(31:31))), "")} -> Office | H34: {=IFERROR(INDEX('Bank Schedule'!H:H, SMALL(IF('Bank Schedule'!$K$2:$K$825="Vacant", ROW('Bank Schedule'!$K$2:$K$825)), ROW(31:31))), "")} -> 533 | I34: {=IFERROR(INDEX('Bank Schedule'!I:I, SMALL(IF('Bank Schedule'!$K$2:$K$825="Vacant", ROW('Bank Schedule'!$K$2:$K$825)), ROW(31:31))), "")} -> 533 | J34: {=IFERROR(INDEX('Bank Schedule'!J:J, SMALL(IF('Bank Schedule'!$K$2:$K$825="Vacant", ROW('Bank Schedule'!$K$2:$K$825)), ROW(31:31))), "")} -> 500 | K34: {=IFERROR(INDEX('Bank Schedule'!K:K, SMALL(IF('Bank Schedule'!$K$2:$K$825="Vacant", ROW('Bank Schedule'!$K$2:$K$825)), ROW(31:31))), "")} -> Vacant | L34: =IFERROR(INDEX('Bank Schedule'!L:L, SMALL(IF('Bank Schedule'!$K$2:$K$825="Vacant", ROW('Bank Schedule'!$K$2:$K$825)), ROW(31:31))), "") | M34: =IFERROR(INDEX('Bank Schedule'!M:M, SMALL(IF('Bank Schedule'!$K$2:$K$825="Vacant", ROW('Bank Schedule'!$K$2:$K$825)), ROW(31:31))), "") | N34: {=IFERROR(INDEX('Bank Schedule'!N:N, SMALL(IF('Bank Schedule'!$K$2:$K$825="Vacant", ROW('Bank Schedule'!$K$2:$K$825)), ROW(31:31))), "")} -> 44536 | O34: =IFERROR(INDEX('Bank Schedule'!O:O, SMALL(IF('Bank Schedule'!$K$2:$K$825="Vacant", ROW('Bank Schedule'!$K$2:$K$825)), ROW(31:31))), "") | P34: =IFERROR(INDEX('Bank Schedule'!P:P, SMALL(IF('Bank Schedule'!$K$2:$K$825="Vacant", ROW('Bank Schedule'!$K$2:$K$825)), ROW(31:31))), "") | Q34: {=IFERROR(INDEX('Bank Schedule'!Q:Q, SMALL(IF('Bank Schedule'!$K$2:$K$825="Vacant", ROW('Bank Schedule'!$K$2:$K$825)), ROW(31:31))), "")} -> 0 | R34: {=IFERROR(INDEX('Bank Schedule'!R:R, SMALL(IF('Bank Schedule'!$K$2:$K$825="Vacant", ROW('Bank Schedule'!$K$2:$K$825)), ROW(31:31))), "")} -> 0 | S34: =IFERROR(INDEX('Bank Schedule'!S:S, SMALL(IF('Bank Schedule'!$K$2:$K$825="Vacant", ROW('Bank Schedule'!$K$2:$K$825)), ROW(31:31))), "") | T34: {=IFERROR(INDEX('Bank Schedule'!T:T, SMALL(IF('Bank Schedule'!$K$2:$K$825="Vacant", ROW('Bank Schedule'!$K$2:$K$825)), ROW(31:31))), "")} -> 28900 | U34: {=IFERROR(INDEX('Bank Schedule'!U:U, SMALL(IF('Bank Schedule'!$K$2:$K$825="Vacant", ROW('Bank Schedule'!$K$2:$K$825)), ROW(31:31))), "")} -> 28900 | V34: {=IFERROR(INDEX('Bank Schedule'!V:V, SMALL(IF('Bank Schedule'!$K$2:$K$825="Vacant", ROW('Bank Schedule'!$K$2:$K$825)), ROW(31:31))), "")} -> 29300 | W34: {=IFERROR(INDEX('Bank Schedule'!W:W, SMALL(IF('Bank Schedule'!$K$2:$K$825="Vacant", ROW('Bank Schedule'!$K$2:$K$825)), ROW(31:31))), "")} -> 29300 | X34: {=IFERROR(INDEX('Bank Schedule'!X:X, SMALL(IF('Bank Schedule'!$K$2:$K$825="Vacant", ROW('Bank Schedule'!$K$2:$K$825)), ROW(31:31))), "")} -> 54.971857 | Y34: {=IFERROR(INDEX('Bank Schedule'!Y:Y, SMALL(IF('Bank Schedule'!$K$2:$K$825="Vacant", ROW('Bank Schedule'!$K$2:$K$825)), ROW(31:31))), "")} -> 0.01384083 | Z34: {=IFERROR(INDEX('Bank Schedule'!Z:Z, SMALL(IF('Bank Schedule'!$K$2:$K$825="Vacant", ROW('Bank Schedule'!$K$2:$K$825)), ROW(31:31))), "")} -> C | AA34: =IFERROR(INDEX('Bank Schedule'!AA:AA, SMALL(IF('Bank Schedule'!$K$2:$K$825="Vacant", ROW('Bank Schedule'!$K$2:$K$825)), ROW(31:31))), "") | AB34: =IFERROR(INDEX('Bank Schedule'!AB:AB, SMALL(IF('Bank Schedule'!$K$2:$K$825="Vacant", ROW('Bank Schedule'!$K$2:$K$825)), ROW(31:31))), "") | AC34: {=IFERROR(INDEX('Bank Schedule'!AC:AC, SMALL(IF('Bank Schedule'!$K$2:$K$825="Vacant", ROW('Bank Schedule'!$K$2:$K$825)), ROW(31:31))), "")} -> No | AD34: {=IFERROR(INDEX('Bank Schedule'!AD:AD, SMALL(IF('Bank Schedule'!$K$2:$K$825="Vacant", ROW('Bank Schedule'!$K$2:$K$825)), ROW(31:31))), "")} -> To be refurbished. | AE34: =IFERROR(INDEX('Bank Schedule'!AE:AE, SMALL(IF('Bank Schedule'!$K$2:$K$825="Vacant", ROW('Bank Schedule'!$K$2:$K$825)), ROW(31:31))), "") | AF34: {=IFERROR(INDEX('Bank Schedule'!AF:AF, SMALL(IF('Bank Schedule'!$K$2:$K$825="Vacant", ROW('Bank Schedule'!$K$2:$K$825)), ROW(31:31))), "")} -> 1 | AG34: {=IFERROR(INDEX('Bank Schedule'!AG:AG, SMALL(IF('Bank Schedule'!$K$2:$K$825="Vacant", ROW('Bank Schedule'!$K$2:$K$825)), ROW(31:31))), "")} -> 1 | AH34: =IFERROR(INDEX('Bank Schedule'!AH:AH, SMALL(IF('Bank Schedule'!$K$2:$K$825="Vacant", ROW('Bank Schedule'!$K$2:$K$825)), ROW(31:31))), "")
A35: =IFERROR(INDEX('Bank Schedule'!A:A, SMALL(IF('Bank Schedule'!$K$2:$K$825="Vacant", ROW('Bank Schedule'!$K$2:$K$825)), ROW(32:32))), "") | B35: {=IFERROR(INDEX('Bank Schedule'!B:B, SMALL(IF('Bank Schedule'!$K$2:$K$825="Vacant", ROW('Bank Schedule'!$K$2:$K$825)), ROW(32:32))), "")} -> SH | C35: {=IFERROR(INDEX('Bank Schedule'!C:C, SMALL(IF('Bank Schedule'!$K$2:$K$825="Vacant", ROW('Bank Schedule'!$K$2:$K$825)), ROW(32:32))), "")} -> MEL | D35: {=IFERROR(INDEX('Bank Schedule'!D:D, SMALL(IF('Bank Schedule'!$K$2:$K$825="Vacant", ROW('Bank Schedule'!$K$2:$K$825)), ROW(32:32))), "")} -> 550190 | E35: {=IFERROR(INDEX('Bank Schedule'!E:E, SMALL(IF('Bank Schedule'!$K$2:$K$825="Vacant", ROW('Bank Schedule'!$K$2:$K$825)), ROW(32:32))), "")} -> Circus House, 21 Great Titchfield Street | F35: {=IFERROR(INDEX('Bank Schedule'!F:F, SMALL(IF('Bank Schedule'!$K$2:$K$825="Vacant", ROW('Bank Schedule'!$K$2:$K$825)), ROW(32:32))), "")} -> Ground Floor (West) | G35: {=IFERROR(INDEX('Bank Schedule'!G:G, SMALL(IF('Bank Schedule'!$K$2:$K$825="Vacant", ROW('Bank Schedule'!$K$2:$K$825)), ROW(32:32))), "")} -> Office | H35: {=IFERROR(INDEX('Bank Schedule'!H:H, SMALL(IF('Bank Schedule'!$K$2:$K$825="Vacant", ROW('Bank Schedule'!$K$2:$K$825)), ROW(32:32))), "")} -> 1946 | I35: {=IFERROR(INDEX('Bank Schedule'!I:I, SMALL(IF('Bank Schedule'!$K$2:$K$825="Vacant", ROW('Bank Schedule'!$K$2:$K$825)), ROW(32:32))), "")} -> 1946 | J35: {=IFERROR(INDEX('Bank Schedule'!J:J, SMALL(IF('Bank Schedule'!$K$2:$K$825="Vacant", ROW('Bank Schedule'!$K$2:$K$825)), ROW(32:32))), "")} -> 2000 | K35: {=IFERROR(INDEX('Bank Schedule'!K:K, SMALL(IF('Bank Schedule'!$K$2:$K$825="Vacant", ROW('Bank Schedule'!$K$2:$K$825)), ROW(32:32))), "")} -> Vacant | L35: =IFERROR(INDEX('Bank Schedule'!L:L, SMALL(IF('Bank Schedule'!$K$2:$K$825="Vacant", ROW('Bank Schedule'!$K$2:$K$825)), ROW(32:32))), "") | M35: =IFERROR(INDEX('Bank Schedule'!M:M, SMALL(IF('Bank Schedule'!$K$2:$K$825="Vacant", ROW('Bank Schedule'!$K$2:$K$825)), ROW(32:32))), "") | N35: {=IFERROR(INDEX('Bank Schedule'!N:N, SMALL(IF('Bank Schedule'!$K$2:$K$825="Vacant", ROW('Bank Schedule'!$K$2:$K$825)), ROW(32:32))), "")} -> 45154 | O35: =IFERROR(INDEX('Bank Schedule'!O:O, SMALL(IF('Bank Schedule'!$K$2:$K$825="Vacant", ROW('Bank Schedule'!$K$2:$K$825)), ROW(32:32))), "") | P35: =IFERROR(INDEX('Bank Schedule'!P:P, SMALL(IF('Bank Schedule'!$K$2:$K$825="Vacant", ROW('Bank Schedule'!$K$2:$K$825)), ROW(32:32))), "") | Q35: {=IFERROR(INDEX('Bank Schedule'!Q:Q, SMALL(IF('Bank Schedule'!$K$2:$K$825="Vacant", ROW('Bank Schedule'!$K$2:$K$825)), ROW(32:32))), "")} -> 0 | R35: {=IFERROR(INDEX('Bank Schedule'!R:R, SMALL(IF('Bank Schedule'!$K$2:$K$825="Vacant", ROW('Bank Schedule'!$K$2:$K$825)), ROW(32:32))), "")} -> 0 | S35: =IFERROR(INDEX('Bank Schedule'!S:S, SMALL(IF('Bank Schedule'!$K$2:$K$825="Vacant", ROW('Bank Schedule'!$K$2:$K$825)), ROW(32:32))), "") | T35: {=IFERROR(INDEX('Bank Schedule'!T:T, SMALL(IF('Bank Schedule'!$K$2:$K$825="Vacant", ROW('Bank Schedule'!$K$2:$K$825)), ROW(32:32))), "")} -> 113900 | U35: {=IFERROR(INDEX('Bank Schedule'!U:U, SMALL(IF('Bank Schedule'!$K$2:$K$825="Vacant", ROW('Bank Schedule'!$K$2:$K$825)), ROW(32:32))), "")} -> 113900 | V35: {=IFERROR(INDEX('Bank Schedule'!V:V, SMALL(IF('Bank Schedule'!$K$2:$K$825="Vacant", ROW('Bank Schedule'!$K$2:$K$825)), ROW(32:32))), "")} -> 116800 | W35: {=IFERROR(INDEX('Bank Schedule'!W:W, SMALL(IF('Bank Schedule'!$K$2:$K$825="Vacant", ROW('Bank Schedule'!$K$2:$K$825)), ROW(32:32))), "")} -> 116800 | X35: {=IFERROR(INDEX('Bank Schedule'!X:X, SMALL(IF('Bank Schedule'!$K$2:$K$825="Vacant", ROW('Bank Schedule'!$K$2:$K$825)), ROW(32:32))), "")} -> 60.020555 | Y35: {=IFERROR(INDEX('Bank Schedule'!Y:Y, SMALL(IF('Bank Schedule'!$K$2:$K$825="Vacant", ROW('Bank Schedule'!$K$2:$K$825)), ROW(32:32))), "")} -> 0.025460931 | Z35: {=IFERROR(INDEX('Bank Schedule'!Z:Z, SMALL(IF('Bank Schedule'!$K$2:$K$825="Vacant", ROW('Bank Schedule'!$K$2:$K$825)), ROW(32:32))), "")} -> E | AA35: =IFERROR(INDEX('Bank Schedule'!AA:AA, SMALL(IF('Bank Schedule'!$K$2:$K$825="Vacant", ROW('Bank Schedule'!$K$2:$K$825)), ROW(32:32))), "") | AB35: =IFERROR(INDEX('Bank Schedule'!AB:AB, SMALL(IF('Bank Schedule'!$K$2:$K$825="Vacant", ROW('Bank Schedule'!$K$2:$K$825)), ROW(32:32))), "") | AC35: {=IFERROR(INDEX('Bank Schedule'!AC:AC, SMALL(IF('Bank Schedule'!$K$2:$K$825="Vacant", ROW('Bank Schedule'!$K$2:$K$825)), ROW(32:32))), "")} -> No | AD35: {=IFERROR(INDEX('Bank Schedule'!AD:AD, SMALL(IF('Bank Schedule'!$K$2:$K$825="Vacant", ROW('Bank Schedule'!$K$2:$K$825)), ROW(32:32))), "")} -> LEM marketing. | AE35: {=IFERROR(INDEX('Bank Schedule'!AE:AE, SMALL(IF('Bank Schedule'!$K$2:$K$825="Vacant", ROW('Bank Schedule'!$K$2:$K$825)), ROW(32:32))), "")} -> 60 | AF35: {=IFERROR(INDEX('Bank Schedule'!AF:AF, SMALL(IF('Bank Schedule'!$K$2:$K$825="Vacant", ROW('Bank Schedule'!$K$2:$K$825)), ROW(32:32))), "")} -> 5 | AG35: {=IFERROR(INDEX('Bank Schedule'!AG:AG, SMALL(IF('Bank Schedule'!$K$2:$K$825="Vacant", ROW('Bank Schedule'!$K$2:$K$825)), ROW(32:32))), "")} -> 11 | AH35: {=IFERROR(INDEX('Bank Schedule'!AH:AH, SMALL(IF('Bank Schedule'!$K$2:$K$825="Vacant", ROW('Bank Schedule'!$K$2:$K$825)), ROW(32:32))), "")} -> LEM
A36: =IFERROR(INDEX('Bank Schedule'!A:A, SMALL(IF('Bank Schedule'!$K$2:$K$825="Vacant", ROW('Bank Schedule'!$K$2:$K$825)), ROW(33:33))), "") | B36: {=IFERROR(INDEX('Bank Schedule'!B:B, SMALL(IF('Bank Schedule'!$K$2:$K$825="Vacant", ROW('Bank Schedule'!$K$2:$K$825)), ROW(33:33))), "")} -> WS | C36: {=IFERROR(INDEX('Bank Schedule'!C:C, SMALL(IF('Bank Schedule'!$K$2:$K$825="Vacant", ROW('Bank Schedule'!$K$2:$K$825)), ROW(33:33))), "")} -> MEL | D36: {=IFERROR(INDEX('Bank Schedule'!D:D, SMALL(IF('Bank Schedule'!$K$2:$K$825="Vacant", ROW('Bank Schedule'!$K$2:$K$825)), ROW(33:33))), "")} -> 550570 | E36: {=IFERROR(INDEX('Bank Schedule'!E:E, SMALL(IF('Bank Schedule'!$K$2:$K$825="Vacant", ROW('Bank Schedule'!$K$2:$K$825)), ROW(33:33))), "")} -> Moray House, 23-35 Great Titchfield Street & 63-65 Mortimer Street | F36: {=IFERROR(INDEX('Bank Schedule'!F:F, SMALL(IF('Bank Schedule'!$K$2:$K$825="Vacant", ROW('Bank Schedule'!$K$2:$K$825)), ROW(33:33))), "")} -> Suite 1.1 First Floor | G36: {=IFERROR(INDEX('Bank Schedule'!G:G, SMALL(IF('Bank Schedule'!$K$2:$K$825="Vacant", ROW('Bank Schedule'!$K$2:$K$825)), ROW(33:33))), "")} -> Office | H36: {=IFERROR(INDEX('Bank Schedule'!H:H, SMALL(IF('Bank Schedule'!$K$2:$K$825="Vacant", ROW('Bank Schedule'!$K$2:$K$825)), ROW(33:33))), "")} -> 1443 | I36: {=IFERROR(INDEX('Bank Schedule'!I:I, SMALL(IF('Bank Schedule'!$K$2:$K$825="Vacant", ROW('Bank Schedule'!$K$2:$K$825)), ROW(33:33))), "")} -> 1443 | J36: {=IFERROR(INDEX('Bank Schedule'!J:J, SMALL(IF('Bank Schedule'!$K$2:$K$825="Vacant", ROW('Bank Schedule'!$K$2:$K$825)), ROW(33:33))), "")} -> 1500 | K36: {=IFERROR(INDEX('Bank Schedule'!K:K, SMALL(IF('Bank Schedule'!$K$2:$K$825="Vacant", ROW('Bank Schedule'!$K$2:$K$825)), ROW(33:33))), "")} -> Vacant | L36: =IFERROR(INDEX('Bank Schedule'!L:L, SMALL(IF('Bank Schedule'!$K$2:$K$825="Vacant", ROW('Bank Schedule'!$K$2:$K$825)), ROW(33:33))), "") | M36: =IFERROR(INDEX('Bank Schedule'!M:M, SMALL(IF('Bank Schedule'!$K$2:$K$825="Vacant", ROW('Bank Schedule'!$K$2:$K$825)), ROW(33:33))), "") | N36: {=IFERROR(INDEX('Bank Schedule'!N:N, SMALL(IF('Bank Schedule'!$K$2:$K$825="Vacant", ROW('Bank Schedule'!$K$2:$K$825)), ROW(33:33))), "")} -> 44121 | O36: =IFERROR(INDEX('Bank Schedule'!O:O, SMALL(IF('Bank Schedule'!$K$2:$K$825="Vacant", ROW('Bank Schedule'!$K$2:$K$825)), ROW(33:33))), "") | P36: =IFERROR(INDEX('Bank Schedule'!P:P, SMALL(IF('Bank Schedule'!$K$2:$K$825="Vacant", ROW('Bank Schedule'!$K$2:$K$825)), ROW(33:33))), "") | Q36: {=IFERROR(INDEX('Bank Schedule'!Q:Q, SMALL(IF('Bank Schedule'!$K$2:$K$825="Vacant", ROW('Bank Schedule'!$K$2:$K$825)), ROW(33:33))), "")} -> 0 | R36: {=IFERROR(INDEX('Bank Schedule'!R:R, SMALL(IF('Bank Schedule'!$K$2:$K$825="Vacant", ROW('Bank Schedule'!$K$2:$K$825)), ROW(33:33))), "")} -> 0 | S36: =IFERROR(INDEX('Bank Schedule'!S:S, SMALL(IF('Bank Schedule'!$K$2:$K$825="Vacant", ROW('Bank Schedule'!$K$2:$K$825)), ROW(33:33))), "") | T36: {=IFERROR(INDEX('Bank Schedule'!T:T, SMALL(IF('Bank Schedule'!$K$2:$K$825="Vacant", ROW('Bank Schedule'!$K$2:$K$825)), ROW(33:33))), "")} -> 87800 | U36: {=IFERROR(INDEX('Bank Schedule'!U:U, SMALL(IF('Bank Schedule'!$K$2:$K$825="Vacant", ROW('Bank Schedule'!$K$2:$K$825)), ROW(33:33))), "")} -> 87800 | V36: {=IFERROR(INDEX('Bank Schedule'!V:V, SMALL(IF('Bank Schedule'!$K$2:$K$825="Vacant", ROW('Bank Schedule'!$K$2:$K$825)), ROW(33:33))), "")} -> 90200 | W36: {=IFERROR(INDEX('Bank Schedule'!W:W, SMALL(IF('Bank Schedule'!$K$2:$K$825="Vacant", ROW('Bank Schedule'!$K$2:$K$825)), ROW(33:33))), "")} -> 90200 | X36: {=IFERROR(INDEX('Bank Schedule'!X:X, SMALL(IF('Bank Schedule'!$K$2:$K$825="Vacant", ROW('Bank Schedule'!$K$2:$K$825)), ROW(33:33))), "")} -> 62.508663 | Y36: {=IFERROR(INDEX('Bank Schedule'!Y:Y, SMALL(IF('Bank Schedule'!$K$2:$K$825="Vacant", ROW('Bank Schedule'!$K$2:$K$825)), ROW(33:33))), "")} -> 0.027334852 | Z36: {=IFERROR(INDEX('Bank Schedule'!Z:Z, SMALL(IF('Bank Schedule'!$K$2:$K$825="Vacant", ROW('Bank Schedule'!$K$2:$K$825)), ROW(33:33))), "")} -> D | AA36: =IFERROR(INDEX('Bank Schedule'!AA:AA, SMALL(IF('Bank Schedule'!$K$2:$K$825="Vacant", ROW('Bank Schedule'!$K$2:$K$825)), ROW(33:33))), "") | AB36: =IFERROR(INDEX('Bank Schedule'!AB:AB, SMALL(IF('Bank Schedule'!$K$2:$K$825="Vacant", ROW('Bank Schedule'!$K$2:$K$825)), ROW(33:33))), "") | AC36: {=IFERROR(INDEX('Bank Schedule'!AC:AC, SMALL(IF('Bank Schedule'!$K$2:$K$825="Vacant", ROW('Bank Schedule'!$K$2:$K$825)), ROW(33:33))), "")} -> No | AD36: {=IFERROR(INDEX('Bank Schedule'!AD:AD, SMALL(IF('Bank Schedule'!$K$2:$K$825="Vacant", ROW('Bank Schedule'!$K$2:$K$825)), ROW(33:33))), "")} -> To be refurbished. | AE36: {=IFERROR(INDEX('Bank Schedule'!AE:AE, SMALL(IF('Bank Schedule'!$K$2:$K$825="Vacant", ROW('Bank Schedule'!$K$2:$K$825)), ROW(33:33))), "")} -> 65 | AF36: =IFERROR(INDEX('Bank Schedule'!AF:AF, SMALL(IF('Bank Schedule'!$K$2:$K$825="Vacant", ROW('Bank Schedule'!$K$2:$K$825)), ROW(33:33))), "") | AG36: {=IFERROR(INDEX('Bank Schedule'!AG:AG, SMALL(IF('Bank Schedule'!$K$2:$K$825="Vacant", ROW('Bank Schedule'!$K$2:$K$825)), ROW(33:33))), "")} -> 3 | AH36: {=IFERROR(INDEX('Bank Schedule'!AH:AH, SMALL(IF('Bank Schedule'!$K$2:$K$825="Vacant", ROW('Bank Schedule'!$K$2:$K$825)), ROW(33:33))), "")} -> LEM
